Workbook

Sheet GDP per capita long
E1: 1960 | F1: =E1+1 -> 1961 | G1: =F1+1 -> 1962 | H1: =G1+1 -> 1963 | I1: =H1+1 -> 1964 | J1: =I1+1 -> 1965 | K1: =J1+1 -> 1966 | L1: =K1+1 -> 1967 | M1: =L1+1 -> 1968 | ... BQ1: =BP1+1 -> 2024
A2: Country Name | B2: Country Code | C2: Series Name | D2: Series Code | E2: 1960 [YR1960] | F2: 1961 [YR1961] | G2: 1962 [YR1962] | H2: 1963 [YR1963] | I2: 1964 [YR1964] | J2: 1965 [YR1965] | K2: 1966 [YR1966] | L2: 1967 [YR1967] | M2: 1968 [YR1968] | N2: 1969 [YR1969] | O2: 1970 [YR1970] | P2: 1971 [YR1971] | Q2: 1972 [YR1972] | R2: 1973 [YR1973] | S2: 1974 [YR1974] | T2: 1975 [YR1975] | U2: 1976 [YR1976] | V2: 1977 [YR1977] | W2: 1978 [YR1978] | X2: 1979 [YR1979] | Y2: 1980 [YR1980] | Z2: 1981 [YR1981] | AA2: 1982 [YR1982] | AB2: 1983 [YR1983] | AC2: 1984 [YR1984] | AD2: 1985 [YR1985] | AE2: 1986 [YR1986] | AF2: 1987 [YR1987] | AG2: 1988 [YR1988] | AH2: 1989 [YR1989] | AI2: 1990 [YR1990] | AJ2: 1991 [YR1991] | AK2: 1992 [YR1992] | AL2: 1993 [YR1993] | AM2: 1994 [YR1994] | AN2: 1995 [YR1995] | AO2: 1996 [YR1996] | AP2: 1997 [YR1997] | AQ2: 1998 [YR1998] | AR2: 1999 [YR1999] | AS2: 2000 [YR2000] | AT2: 2001 [YR2001] | AU2: 2002 [YR2002] | AV2: 2003 [YR2003] | AW2: 2004 [YR2004] | AX2: 2005 [YR2005] | AY2: 2006 [YR2006] | AZ2: 2007 [YR2007] | BA2: 2008 [YR2008] | BB2: 2009 [YR2009] | BC2: 2010 [YR2010] | BD2: 2011 [YR2011] | BE2: 2012 [YR2012] | BF2: 2013 [YR2013] | BG2: 2014 [YR2014] | BH2: 2015 [YR2015] | BI2: 2016 [YR2016] | BJ2: 2017 [YR2017] | BK2: 2018 [YR2018] | BL2: 2019 [YR2019] | BM2: 2020 [YR2020] | BN2: 2021 [YR2021] | BO2: 2022 [YR2022] | BP2: 2023 [YR2023] | BQ2: 2024 [YR2024]
A3: Mexico | B3: MEX | C3: GDP per capita (constant LCU) | D3: NY.GDP.PCAP.KN | E3: 78139.839 | F3: 79523.064 | G3: 80596.678 | H3: 84339.591 | I3: 91334.962 | J3: 94642.285 | K3: 97139.015 | L3: 99481.697 | M3: 105342.35 | N3: 105480.8 | O3: 108842.78 | P3: 109495.45 | Q3: 114957.68 | R3: 120348.09 | S3: 123629.6 | T3: 127047.19 | U3: 129021.44 | V3: 129835.82 | W3: 137771.36 | X3: 147288.5 | Y3: 156255.23 | Z3: 167277.2 | AA3: 163535.87 | AB3: 152640.7 | AC3: 154702.81 | AD3: 154443.44 | AE3: 145386.04 | AF3: 145440.42 | AG3: 144332.72 | AH3: 146709.04 | AI3: 151478.63 | AJ3: 154497.14 | AK3: 157008.68 | AL3: 158545.4 | AM3: 162535.22 | AN3: 150230.5 | AO3: 156827.53 | AP3: 165312.74 | AQ3: 172683.25 | AR3: 174626.14 | AS3: 180600.81 | AT3: 177139.96 | AU3: 174198.32 | AV3: 173816.04 | AW3: 177572.32 | AX3: 178895.96 | AY3: 184970.87 | AZ3: 186174.64 | BA3: 185206.74 | BB3: 171028.84 | BC3: 176964.99 | BD3: 180487.05 | BE3: 184380.73 | BF3: 183555.06 | BG3: 185887.89 | BH3: 188880.14 | BI3: 190374.1 | BJ3: 192132.06 | BK3: 194075.22 | BL3: 191485.05 | BM3: 174054.41 | BN3: 183354.26 | BO3: 188731.77 | BP3: 193258.3 | BQ3: 194388.43
A7: Data from database: World Development Indicators
A8: Last Updated: 07/01/2025 | G8: rho | H8: 0.5748 | J8: drop in 1982 | K8: =E39/E38-1 -> -0.02236604
G9: sigma | H9: 0.0256 | J9: drop in 1983 | K9: =E40/E39-1 -> -0.066622502
J10: drop in 1983 from 1981 | K10: =E40/E38-1 -> -0.08749846
J11: drop in 1982 from linear trend pre default | K11: =J39 -> 0.0069613579
J12: drop in 1983 from linear trend pre default | K12: =J40 -> -0.095455005
I14: intercept | J14: -54.341319
I15: slope | J15: 0.03347081
E16: gdp | F16: log | G16: trend | H16: cycle | I16: log_lin_trend | J16: log deviation from linear trend
D17: 1960 | E17: =HLOOKUP(D17,$E$1:$BQ$3,3,FALSE) -> 78139.839 | F17: =LN(E17) -> 11.266255 | G17: 11.255054 | H17: =F17-G17 -> 0.011201643 | I17: =$J$14+$J$15*D17 -> 11.261468 | J17: =F17-I17 -> 0.004786828
D18: =D17+1 -> 1961 | E18: =HLOOKUP(D18,$E$1:$BQ$3,3,FALSE) -> 79523.064 | F18: =LN(E18) -> 11.283802 | G18: 11.291325 | H18: =F18-G18 -> -0.0075223265 | I18: =$J$14+$J$15*D18 -> 11.294939 | J18: =F18-I18 -> -0.011136918
D19: =D18+1 -> 1962 | E19: =HLOOKUP(D19,$E$1:$BQ$3,3,FALSE) -> 80596.678 | F19: =LN(E19) -> 11.297213 | G19: 11.327708 | H19: =F19-G19 -> -0.030495033 | I19: =$J$14+$J$15*D19 -> 11.32841 | J19: =F19-I19 -> -0.031197385
D20: =D19+1 -> 1963 | E20: =HLOOKUP(D20,$E$1:$BQ$3,3,FALSE) -> 84339.591 | F20: =LN(E20) -> 11.342607 | G20: 11.36424 | H20: =F20-G20 -> -0.021632931 | I20: =$J$14+$J$15*D20 -> 11.361881 | J20: =F20-I20 -> -0.019274234
D21: =D20+1 -> 1964 | E21: =HLOOKUP(D21,$E$1:$BQ$3,3,FALSE) -> 91334.962 | F21: =LN(E21) -> 11.422289 | G21: 11.400652 | H21: =F21-G21 -> 0.021636809 | I21: =$J$14+$J$15*D21 -> 11.395352 | J21: =F21-I21 -> 0.026937207
D22: =D21+1 -> 1965 | E22: =HLOOKUP(D22,$E$1:$BQ$3,3,FALSE) -> 94642.285 | F22: =LN(E22) -> 11.45786 | G22: 11.436461 | H22: =F22-G22 -> 0.021398844 | I22: =$J$14+$J$15*D22 -> 11.428823 | J22: =F22-I22 -> 0.02903711
D23: =D22+1 -> 1966 | E23: =HLOOKUP(D23,$E$1:$BQ$3,3,FALSE) -> 97139.015 | F23: =LN(E23) -> 11.483898 | G23: 11.471398 | H23: =F23-G23 -> 0.012500854 | I23: =$J$14+$J$15*D23 -> 11.462293 | J23: =F23-I23 -> 0.021605035
D24: =D23+1 -> 1967 | E24: =HLOOKUP(D24,$E$1:$BQ$3,3,FALSE) -> 99481.697 | F24: =LN(E24) -> 11.507729 | G24: 11.505408 | H24: =F24-G24 -> 0.0023207962 | I24: =$J$14+$J$15*D24 -> 11.495764 | J24: =F24-I24 -> 0.01196481
D25: =D24+1 -> 1968 | E25: =HLOOKUP(D25,$E$1:$BQ$3,3,FALSE) -> 105342.35 | F25: =LN(E25) -> 11.564971 | G25: 11.538564 | H25: =F25-G25 -> 0.026407155 | I25: =$J$14+$J$15*D25 -> 11.529235 | J25: =F25-I25 -> 0.035735797
D26: =D25+1 -> 1969 | E26: =HLOOKUP(D26,$E$1:$BQ$3,3,FALSE) -> 105480.8 | F26: =LN(E26) -> 11.566284 | G26: 11.570958 | H26: =F26-G26 -> -0.0046737304 | I26: =$J$14+$J$15*D26 -> 11.562706 | J26: =F26-I26 -> 0.0035784236
D27: =D26+1 -> 1970 | E27: =HLOOKUP(D27,$E$1:$BQ$3,3,FALSE) -> 108842.78 | F27: =LN(E27) -> 11.59766 | G27: 11.602949 | H27: =F27-G27 -> -0.0052895608 | I27: =$J$14+$J$15*D27 -> 11.596177 | J27: =F27-I27 -> 0.0014831459
D28: =D27+1 -> 1971 | E28: =HLOOKUP(D28,$E$1:$BQ$3,3,FALSE) -> 109495.45 | F28: =LN(E28) -> 11.603638 | G28: 11.634849 | H28: =F28-G28 -> -0.031210806 | I28: =$J$14+$J$15*D28 -> 11.629647 | J28: =F28-I28 -> -0.026009085
D29: =D28+1 -> 1972 | E29: =HLOOKUP(D29,$E$1:$BQ$3,3,FALSE) -> 114957.68 | F29: =LN(E29) -> 11.652319 | G29: 11.666916 | H29: =F29-G29 -> -0.014596569 | I29: =$J$14+$J$15*D29 -> 11.663118 | J29: =F29-I29 -> -0.010798847
... D40: =D39+1 -> 1983 | E40: =HLOOKUP(D40,$E$1:$BQ$3,3,FALSE) -> 152640.7 | F40: =LN(E40) -> 11.935842 | G40: 11.934364 | H40: =F40-G40 -> 0.0014782486 | I40: =$J$14+$J$15*D40 -> 12.031297 | J40: =F40-I40 -> -0.095455005
D41: =D40+1 -> 1984 | E41: =HLOOKUP(D41,$E$1:$BQ$3,3,FALSE) -> 154702.81 | F41: =LN(E41) -> 11.949261 | G41: 11.936126 | H41: =F41-G41 -> 0.013134948
D42: =D41+1 -> 1985 | E42: =HLOOKUP(D42,$E$1:$BQ$3,3,FALSE) -> 154443.44 | F42: =LN(E42) -> 11.947583 | G42: 11.935283 | H42: =F42-G42 -> 0.012300323
D43: =D42+1 -> 1986 | E43: =HLOOKUP(D43,$E$1:$BQ$3,3,FALSE) -> 145386.04 | F43: =LN(E43) -> 11.887148 | G43: 11.933283 | H43: =F43-G43 -> -0.046135268
D44: =D43+1 -> 1987 | E44: =HLOOKUP(D44,$E$1:$BQ$3,3,FALSE) -> 145440.42 | F44: =LN(E44) -> 11.887522 | G44: 11.931699 | H44: =F44-G44 -> -0.044177111
D45: =D44+1 -> 1988 | E45: =HLOOKUP(D45,$E$1:$BQ$3,3,FALSE) -> 144332.72 | F45: =LN(E45) -> 11.879876 | G45: 11.931641 | H45: =F45-G45 -> -0.051764659
D46: =D45+1 -> 1989 | E46: =HLOOKUP(D46,$E$1:$BQ$3,3,FALSE) -> 146709.04 | F46: =LN(E46) -> 11.896207 | G46: 11.933779 | H46: =F46-G46 -> -0.037572299
D47: =D46+1 -> 1990 | E47: =HLOOKUP(D47,$E$1:$BQ$3,3,FALSE) -> 151478.63 | F47: =LN(E47) -> 11.9282 | G47: 11.938264 | H47: =F47-G47 -> -0.010063765
D48: =D47+1 -> 1991 | E48: =HLOOKUP(D48,$E$1:$BQ$3,3,FALSE) -> 154497.14 | F48: =LN(E48) -> 11.947931 | G48: 11.944871 | H48: =F48-G48 -> 0.0030600617
D49: =D48+1 -> 1992 | E49: =HLOOKUP(D49,$E$1:$BQ$3,3,FALSE) -> 157008.68 | F49: =LN(E49) -> 11.964056 | G49: 11.953276 | H49: =F49-G49 -> 0.010780717
D50: =D49+1 -> 1993 | E50: =HLOOKUP(D50,$E$1:$BQ$3,3,FALSE) -> 158545.4 | F50: =LN(E50) -> 11.973796 | G50: 11.963184 | H50: =F50-G50 -> 0.010612471
D51: =D50+1 -> 1994 | E51: =HLOOKUP(D51,$E$1:$BQ$3,3,FALSE) -> 162535.22 | F51: =LN(E51) -> 11.99865 | G51: 11.974409 | H51: =F51-G51 -> 0.024241418
D52: =D51+1 -> 1995 | E52: =HLOOKUP(D52,$E$1:$BQ$3,3,FALSE) -> 150230.5 | F52: =LN(E52) -> 11.919926 | G52: 11.98687 | H52: =F52-G52 -> -0.066943551
... D76: =D75+1 -> 2019 | E76: =HLOOKUP(D76,$E$1:$BQ$3,3,FALSE) -> 191485.05 | F76: =LN(E76) -> 12.162565 | G76: 12.172056 | H76: =F76-G76 -> -0.0094911844

Sheet M1
A1: Banco de México
A3: Agregados monetarios y activos financieros internos
A4: Agregados monetarios (metodología 2018)
A6: Fecha de consulta: 26/06/2025 08:51:08
A10: Título | B10: Agregados Monetarios, M1
A11: Periodo disponible | B11: Dic 2000 - Abr 2025
A12: Periodicidad | B12: Mensual
A13: Cifra | B13: Saldos
A14: Unidad | B14: Miles de Pesos
A15: Base
A16: Aviso
A17: Tipo de información | B17: Niveles
A18: Fecha | B18: SF311408 | F18: M1
A19: 36861 | B19: 5.7563476e+08 | E19: 36892 | F19: =AVERAGE(B20:B22) -> 5.1724154e+08
A20: 36892 | B20: 5.2483613e+08 | E20: 36982 | F20: =AVERAGE(B23:B25) -> 5.1927853e+08
A21: 36923 | B21: 5.1718661e+08 | E21: 37073 | F21: =AVERAGE(B26:B28) -> 5.5366736e+08
A22: 36951 | B22: 5.0970187e+08 | E22: 37165 | F22: =AVERAGE(B29:B31) -> 6.2268534e+08
A23: 36982 | B23: 5.1195243e+08 | E23: 37257 | F23: =AVERAGE(B32:B34) -> 6.345527e+08
A24: 37012 | B24: 5.1484546e+08 | E24: 37347 | F24: =AVERAGE(B35:B37) -> 6.387434e+08
A25: 37043 | B25: 5.3103769e+08 | E25: 37438 | F25: =AVERAGE(B38:B40) -> 6.5066789e+08
A26: 37073 | B26: 5.3559066e+08 | E26: 37530 | F26: =AVERAGE(B41:B43) -> 6.992638e+08
A27: 37104 | B27: 5.4663748e+08 | E27: 37622 | F27: =AVERAGE(B44:B46) -> 7.1382544e+08
A28: 37135 | B28: 5.7877395e+08 | E28: 37712 | F28: =AVERAGE(B47:B49) -> 7.1408971e+08
A29: 37165 | B29: 5.773955e+08 | E29: 37803 | F29: =AVERAGE(B50:B52) -> 7.2204542e+08
A30: 37196 | B30: 6.1019542e+08 | E30: 37895 | F30: =AVERAGE(B53:B55) -> 7.8481006e+08
A31: 37226 | B31: 6.804651e+08 | E31: 37987 | F31: =AVERAGE(B56:B58) -> 8.0442241e+08
A32: 37257 | B32: 6.3373584e+08 | E32: 38078 | F32: =AVERAGE(B59:B61) -> 8.2198621e+08
A33: 37288 | B33: 6.2735042e+08 | E33: 38169 | F33: =AVERAGE(B62:B64) -> 8.292136e+08
A34: 37316 | B34: 6.4257182e+08 | E34: 38261 | F34: =AVERAGE(B65:B67) -> 8.8573326e+08
A35: 37347 | B35: 6.2981367e+08 | E35: 38353 | F35: =AVERAGE(B68:B70) -> 9.007962e+08
A36: 37377 | B36: 6.3283116e+08 | E36: 38443 | F36: =AVERAGE(B71:B73) -> 9.0428418e+08
A37: 37408 | B37: 6.5358538e+08 | E37: 38534 | F37: =AVERAGE(B74:B76) -> 9.2195332e+08
A38: 37438 | B38: 6.5035931e+08 | E38: 38626 | F38: =AVERAGE(B77:B79) -> 9.8839653e+08
A39: 37469 | B39: 6.4758324e+08 | E39: 38718 | F39: =AVERAGE(B80:B82) -> 1.0218158e+09
A40: 37500 | B40: 6.5406112e+08 | E40: 38808 | F40: =AVERAGE(B83:B85) -> 1.0623253e+09
A41: 37530 | B41: 6.5191183e+08 | E41: 38899 | F41: =AVERAGE(B86:B88) -> 1.0754597e+09
A42: 37561 | B42: 6.7963852e+08 | E42: 38991 | F42: =AVERAGE(B89:B91) -> 1.134491e+09
A43: 37591 | B43: 7.6624106e+08 | E43: 39083 | F43: =AVERAGE(B92:B94) -> 1.1402452e+09
A44: 37622 | B44: 7.1971702e+08 | E44: 39173 | F44: =AVERAGE(B95:B97) -> 1.1440156e+09
A45: 37653 | B45: 7.0737687e+08 | E45: 39264 | F45: =AVERAGE(B98:B100) -> 1.1780381e+09
A46: 37681 | B46: 7.1438242e+08 | E46: 39356 | F46: =AVERAGE(B101:B103) -> 1.2470907e+09
A47: 37712 | B47: 7.0292141e+08 | E47: 39448 | F47: =AVERAGE(B104:B106) -> 1.2507778e+09
A48: 37742 | B48: 7.1185123e+08 | E48: 39539 | F48: =AVERAGE(B107:B109) -> 1.2365153e+09
A49: 37773 | B49: 7.274965e+08 | E49: 39630 | F49: =AVERAGE(B110:B112) -> 1.2362347e+09
A50: 37803 | B50: 7.2253988e+08 | E50: 39722 | F50: =AVERAGE(B113:B115) -> 1.3668051e+09
A51: 37834 | B51: 7.2023774e+08 | E51: 39814 | F51: =AVERAGE(B116:B118) -> 1.4134268e+09
A52: 37865 | B52: 7.2335864e+08 | E52: 39904 | F52: =AVERAGE(B119:B121) -> 1.4041558e+09
A53: 37895 | B53: 7.3131256e+08 | E53: 39995 | F53: =AVERAGE(B122:B124) -> 1.4105307e+09
A54: 37926 | B54: 7.6569925e+08 | E54: 40087 | F54: =AVERAGE(B125:B127) -> 1.5172535e+09
A55: 37956 | B55: 8.5741836e+08 | E55: 40179 | F55: =AVERAGE(B128:B130) -> 1.530091e+09
A56: 37987 | B56: 8.1197592e+08 | E56: 40269 | F56: =AVERAGE(B131:B133) -> 1.5293159e+09
A57: 38018 | B57: 8.0442965e+08 | E57: 40360 | F57: =AVERAGE(B134:B136) -> 1.5667756e+09
A58: 38047 | B58: 7.9686166e+08 | E58: 40452 | F58: =AVERAGE(B137:B139) -> 1.6802811e+09
A59: 38078 | B59: 7.9977481e+08 | E59: 40544 | F59: =AVERAGE(B140:B142) -> 1.7289972e+09
A60: 38108 | B60: 8.1668489e+08 | E60: 40634 | F60: =AVERAGE(B143:B145) -> 1.751474e+09
A61: 38139 | B61: 8.4949893e+08 | E61: 40725 | F61: =AVERAGE(B146:B148) -> 1.8075132e+09
A62: 38169 | B62: 8.3065783e+08 | E62: 40817 | F62: =AVERAGE(B149:B151) -> 1.9460805e+09
A63: 38200 | B63: 8.2450168e+08 | E63: 40909 | F63: =AVERAGE(B152:B154) -> 1.9802544e+09
A64: 38231 | B64: 8.3248129e+08 | E64: 41000 | F64: =AVERAGE(B155:B157) -> 2.0405357e+09
A65: 38261 | B65: 8.4490091e+08 | E65: 41091 | F65: =AVERAGE(B158:B160) -> 2.0624494e+09
A66: 38292 | B66: 8.6598608e+08 | E66: 41183 | F66: =AVERAGE(B161:B163) -> 2.1549849e+09
A67: 38322 | B67: 9.463128e+08 | E67: 41275 | F67: =AVERAGE(B164:B166) -> 2.167392e+09
A68: 38353 | B68: 9.0803509e+08 | E68: 41365 | F68: =AVERAGE(B167:B169) -> 2.1750192e+09
A69: 38384 | B69: 9.0398645e+08 | E69: 41456 | F69: =AVERAGE(B170:B172) -> 2.2309927e+09
A70: 38412 | B70: 8.9036707e+08 | E70: 41548 | F70: =AVERAGE(B173:B175) -> 2.3568004e+09
A71: 38443 | B71: 8.9089422e+08 | E71: 41640 | F71: =AVERAGE(B176:B178) -> 2.4456714e+09
A72: 38473 | B72: 8.9200301e+08 | E72: 41730 | F72: =AVERAGE(B179:B181) -> 2.4849054e+09
A73: 38504 | B73: 9.2995532e+08 | E73: 41821 | F73: =AVERAGE(B182:B184) -> 2.5443342e+09
A74: 38534 | B74: 9.2486679e+08 | E74: 41913 | F74: =AVERAGE(B185:B187) -> 2.7355848e+09
A75: 38565 | B75: 9.1639244e+08 | E75: 42005 | F75: =AVERAGE(B188:B190) -> 2.8802189e+09
A76: 38596 | B76: 9.2460073e+08 | E76: 42095 | F76: =AVERAGE(B191:B193) -> 2.9438803e+09
A77: 38626 | B77: 9.3476186e+08 | E77: 42186 | F77: =AVERAGE(B194:B196) -> 3.0441941e+09
A78: 38657 | B78: 9.6228843e+08 | E78: 42278 | F78: =AVERAGE(B197:B199) -> 3.1940547e+09
A79: 38687 | B79: 1.0681393e+09 | E79: 42370 | F79: =AVERAGE(B200:B202) -> 3.2899212e+09
A80: 38718 | B80: 1.0199178e+09 | E80: 42461 | F80: =AVERAGE(B203:B205) -> 3.3802537e+09
A81: 38749 | B81: 1.0125873e+09 | E81: 42552 | F81: =AVERAGE(B206:B208) -> 3.4714954e+09
A82: 38777 | B82: 1.0329423e+09 | E82: 42644 | F82: =AVERAGE(B209:B211) -> 3.6775476e+09
A83: 38808 | B83: 1.0422845e+09 | E83: 42736 | F83: =AVERAGE(B212:B214) -> 3.7977517e+09
A84: 38838 | B84: 1.0478361e+09 | E84: 42826 | F84: =AVERAGE(B215:B217) -> 3.7859701e+09
A85: 38869 | B85: 1.0968552e+09 | E85: 42917 | F85: =AVERAGE(B218:B220) -> 3.8197463e+09
A86: 38899 | B86: 1091461936 | E86: 43009 | F86: =AVERAGE(B221:B223) -> 4.0597729e+09
A87: 38930 | B87: 1.0607409e+09 | E87: 43101 | F87: =AVERAGE(B224:B226) -> 4.0967233e+09
A88: 38961 | B88: 1.0741762e+09 | E88: 43191 | F88: =AVERAGE(B227:B229) -> 4.1944259e+09
A89: 38991 | B89: 1.0677867e+09 | E89: 43282 | F89: =AVERAGE(B230:B232) -> 4.1767095e+09
A90: 39022 | B90: 1.1174902e+09 | E90: 43374 | F90: =AVERAGE(B233:B235) -> 4.3490777e+09
A91: 39052 | B91: 1.2181962e+09 | E91: 43466 | F91: =AVERAGE(B236:B238) -> 4.3155599e+09
A92: 39083 | B92: 1.1453288e+09 | E92: 43556 | F92: =AVERAGE(B239:B241) -> 4.3267748e+09
A93: 39114 | B93: 1.1307882e+09 | E93: 43647 | F93: =AVERAGE(B242:B244) -> 4.3442356e+09
A94: 39142 | B94: 1.1446185e+09 | E94: 43739 | F94: =AVERAGE(B245:B247) -> 4.517084e+09
A95: 39173 | B95: 1.1263026e+09 | E95: 43831 | F95: =AVERAGE(B248:B250) -> 4.6770048e+09
A96: 39203 | B96: 1.1322306e+09 | E96: 43922 | F96: =AVERAGE(B251:B253) -> 5.1468549e+09
A97: 39234 | B97: 1.1735137e+09 | E97: 44013 | F97: =AVERAGE(B254:B256) -> 5.2378658e+09
A98: 39264 | B98: 1.1626249e+09 | E98: 44105 | F98: =AVERAGE(B257:B259) -> 5.45317e+09
A99: 39295 | B99: 1.1726966e+09 | E99: 44197 | F99: =AVERAGE(B260:B262) -> 5.6211451e+09
A100: 39326 | B100: 1.1987927e+09 | E100: 44287 | F100: =AVERAGE(B263:B265) -> 5.7249759e+09
A101: 39356 | B101: 1.1786073e+09 | E101: 44378 | F101: =AVERAGE(B266:B268) -> 5.8679705e+09
A102: 39387 | B102: 1.2128747e+09 | E102: 44470 | F102: =AVERAGE(B269:B271) -> 6.1395154e+09
A103: 39417 | B103: 1.3497901e+09 | E103: 44562 | F103: =AVERAGE(B272:B274) -> 6.3392876e+09
A104: 39448 | B104: 1.2678597e+09 | E104: 44652 | F104: =AVERAGE(B275:B277) -> 6.4359978e+09
A105: 39479 | B105: 1.2532503e+09 | E105: 44743 | F105: =AVERAGE(B278:B280) -> 6.4649246e+09
...

Sheet GDP quarterly
A1: Banco de México
A3: Producción
A4: Producto Interno Bruto (Precios corrientes)
A6: Fecha de consulta: 26/06/2025 08:52:30
A10: Título | B10: Producto interno bruto, Producto interno bruto, a precios de mercado
A11: Periodo disponible | B11: Ene-Mar 1993 - Ene-Mar 2025
A12: Periodicidad | B12: Trimestral
A13: Cifra | B13: Flujos Constantes
A14: Unidad | B14: Millones de Pesos
A15: Base | B15: 2018
A16: Aviso
A17: Tipo de información | B17: Niveles
A18: Fecha | B18: SR17645
A19: 33970 | B19: 1591205.3
A20: 34060 | B20: 1645078.9
A21: 34151 | B21: 1662210
A22: 34243 | B22: 1708617.4
A23: 34335 | B23: 1750226.2
A24: 34425 | B24: 1864368.8
A25: 34516 | B25: 1878101.8
A26: 34608 | B26: 1981408.6
A27: 34700 | B27: 2126220.5
A28: 34790 | B28: 2356508.4
A29: 34881 | B29: 2504153
A30: 34973 | B30: 2774687.6
... A147: 45658 | B147: 34650228

Sheet Proxy for working capital
B1: Share M1 in firms | C1: =2/3 -> 0.66666667
E3: =AVERAGE(E5:E80) -> 0.080942316
B4: M1 (million pesos) | C4: GDP (million pesos) | D4: M1 in firms' hands | E4: proxy for working capital / GDP
A5: 36892 | B5: =VLOOKUP(A5,'M1'!$E$19:$F$115,2,FALSE)/1000 -> 517241.54 | C5: =VLOOKUP(A5,'GDP quarterly'!$A$19:$B$147,2,FALSE) -> 7320286.3 | D5: =B5*$C$1 -> 344827.69 | E5: =D5/C5 -> 0.047105766
A6: 36982 | B6: =VLOOKUP(A6,'M1'!$E$19:$F$115,2,FALSE)/1000 -> 519278.53 | C6: =VLOOKUP(A6,'GDP quarterly'!$A$19:$B$147,2,FALSE) -> 7459750.4 | D6: =B6*$C$1 -> 346185.68 | E6: =D6/C6 -> 0.04640714
A7: 37073 | B7: =VLOOKUP(A7,'M1'!$E$19:$F$115,2,FALSE)/1000 -> 553667.36 | C7: =VLOOKUP(A7,'GDP quarterly'!$A$19:$B$147,2,FALSE) -> 7502163.6 | D7: =B7*$C$1 -> 369111.58 | E7: =D7/C7 -> 0.049200683
A8: 37165 | B8: =VLOOKUP(A8,'M1'!$E$19:$F$115,2,FALSE)/1000 -> 622685.34 | C8: =VLOOKUP(A8,'GDP quarterly'!$A$19:$B$147,2,FALSE) -> 7466230.3 | D8: =B8*$C$1 -> 415123.56 | E8: =D8/C8 -> 0.055600155
A9: 37257 | B9: =VLOOKUP(A9,'M1'!$E$19:$F$115,2,FALSE)/1000 -> 634552.7 | C9: =VLOOKUP(A9,'GDP quarterly'!$A$19:$B$147,2,FALSE) -> 7309444.3 | D9: =B9*$C$1 -> 423035.13 | E9: =D9/C9 -> 0.057875143
A10: 37347 | B10: =VLOOKUP(A10,'M1'!$E$19:$F$115,2,FALSE)/1000 -> 638743.4 | C10: =VLOOKUP(A10,'GDP quarterly'!$A$19:$B$147,2,FALSE) -> 7941410 | D10: =B10*$C$1 -> 425828.94 | E10: =D10/C10 -> 0.053621326
A11: 37438 | B11: =VLOOKUP(A11,'M1'!$E$19:$F$115,2,FALSE)/1000 -> 650667.89 | C11: =VLOOKUP(A11,'GDP quarterly'!$A$19:$B$147,2,FALSE) -> 7971586 | D11: =B11*$C$1 -> 433778.59 | E11: =D11/C11 -> 0.054415595
A12: 37530 | B12: =VLOOKUP(A12,'M1'!$E$19:$F$115,2,FALSE)/1000 -> 699263.8 | C12: =VLOOKUP(A12,'GDP quarterly'!$A$19:$B$147,2,FALSE) -> 8088591.6 | D12: =B12*$C$1 -> 466175.87 | E12: =D12/C12 -> 0.05763375
A13: 37622 | B13: =VLOOKUP(A13,'M1'!$E$19:$F$115,2,FALSE)/1000 -> 713825.44 | C13: =VLOOKUP(A13,'GDP quarterly'!$A$19:$B$147,2,FALSE) -> 8093632 | D13: =B13*$C$1 -> 475883.62 | E13: =D13/C13 -> 0.05879729
A14: 37712 | B14: =VLOOKUP(A14,'M1'!$E$19:$F$115,2,FALSE)/1000 -> 714089.71 | C14: =VLOOKUP(A14,'GDP quarterly'!$A$19:$B$147,2,FALSE) -> 8253853.5 | D14: =B14*$C$1 -> 476059.81 | E14: =D14/C14 -> 0.057677279
A15: 37803 | B15: =VLOOKUP(A15,'M1'!$E$19:$F$115,2,FALSE)/1000 -> 722045.42 | C15: =VLOOKUP(A15,'GDP quarterly'!$A$19:$B$147,2,FALSE) -> 8210313.4 | D15: =B15*$C$1 -> 481363.62 | E15: =D15/C15 -> 0.05862914
A16: 37895 | B16: =VLOOKUP(A16,'M1'!$E$19:$F$115,2,FALSE)/1000 -> 784810.06 | C16: =VLOOKUP(A16,'GDP quarterly'!$A$19:$B$147,2,FALSE) -> 8480333.7 | D16: =B16*$C$1 -> 523206.7 | E16: =D16/C16 -> 0.061696476
... A101: 45658 | B101: =VLOOKUP(A101,'M1'!$E$19:$F$115,2,FALSE)/1000 -> 8035228.3 | C101: =VLOOKUP(A101,'GDP quarterly'!$A$19:$B$147,2,FALSE) -> 34650228 | D101: =B101*$C$1 -> 5356818.8 | E101: =D101/C101 -> 0.15459693

Sheet EMBI spreads
A1: Date | B1: Ticker | C1: Close | G1: av spread | H1: gdp cycle
A2: 12/31/1997 | B2: EMBPMEXD | C2: 402 | D2: =YEAR(A2) -> 1997 | E2: =MONTH(A2) -> 12 | F2: 1997 | G2: =AVERAGEIF($D$2:$D$7066,F2,$C$2:$C$7066)/100 -> 4.02 | H2: ='Trade balance'!F48 -> 0.1049022 | I2: =CORREL(G2:$G$24,H2:$H$24) -> 0.28533738 | K2: Average | L2: =AVERAGE(C2:C7066)/100 -> 2.924878
A3: 01/02/1998 | B3: EMBPMEXD | C3: 405 | D3: =YEAR(A3) -> 1998 | E3: =MONTH(A3) -> 1 | F3: =F2+1 -> 1998 | G3: =AVERAGEIF($D$2:$D$7066,F3,$C$2:$C$7066)/100 -> 5.775498 | H3: ='Trade balance'!F49 -> 3.001582 | I3: =CORREL(G3:$G$24,H3:$H$24) -> 0.29841837 | K3: Std | L3: =_xlfn.STDEV.P(C2:C7066)/100 -> 1.3573061
A4: 01/05/1998 | B4: EMBPMEXD | C4: 425 | D4: =YEAR(A4) -> 1998 | E4: =MONTH(A4) -> 1 | F4: =F3+1 -> 1999 | G4: =AVERAGEIF($D$2:$D$7066,F4,$C$2:$C$7066)/100 -> 6.0614786 | H4: ='Trade balance'!F50 -> 2.7417396 | I4: =CORREL(G4:$G$24,H4:$H$24) -> 0.19963159 | O4: diferencial de tasas
A5: 01/06/1998 | B5: EMBPMEXD | C5: 434 | D5: =YEAR(A5) -> 1998 | E5: =MONTH(A5) -> 1 | F5: =F4+1 -> 2000 | G5: =AVERAGEIF($D$2:$D$7066,F5,$C$2:$C$7066)/100 -> 3.7051984 | H5: ='Trade balance'!F51 -> 4.8559515 | I5: =CORREL(G5:$G$24,H5:$H$24) -> 0.026998496 | L5: =YEAR(N5) -> 1997 | M5: =MONTH(N5) -> 12 | N5: 35765 | O5: =AVERAGEIFS($C$2:$C$7066,$D$2:$D$7066,L5,$E$2:$E$7066,M5)/10000 -> 0.0402
A6: 01/07/1998 | B6: EMBPMEXD | C6: 419 | D6: =YEAR(A6) -> 1998 | E6: =MONTH(A6) -> 1 | F6: =F5+1 -> 2001 | G6: =AVERAGEIF($D$2:$D$7066,F6,$C$2:$C$7066)/100 -> 3.6644 | H6: ='Trade balance'!F52 -> 1.8267518 | I6: =CORREL(G6:$G$24,H6:$H$24) -> -0.21919493 | L6: =YEAR(N6) -> 1998 | M6: =MONTH(N6) -> 1 | N6: 35796 | O6: =AVERAGEIFS($C$2:$C$7066,$D$2:$D$7066,L6,$E$2:$E$7066,M6)/10000 -> 0.04238
A7: 01/08/1998 | B7: EMBPMEXD | C7: 427 | D7: =YEAR(A7) -> 1998 | E7: =MONTH(A7) -> 1 | F7: =F6+1 -> 2002 | G7: =AVERAGEIF($D$2:$D$7066,F7,$C$2:$C$7066)/100 -> 3.1865873 | H7: ='Trade balance'!F53 -> -0.79021562 | I7: =CORREL(G7:$G$24,H7:$H$24) -> -0.37800786 | L7: =YEAR(N7) -> 1998 | M7: =MONTH(N7) -> 2 | N7: 35827 | O7: =AVERAGEIFS($C$2:$C$7066,$D$2:$D$7066,L7,$E$2:$E$7066,M7)/10000 -> 0.038405263
A8: 01/09/1998 | B8: EMBPMEXD | C8: 444 | D8: =YEAR(A8) -> 1998 | E8: =MONTH(A8) -> 1 | F8: =F7+1 -> 2003 | G8: =AVERAGEIF($D$2:$D$7066,F8,$C$2:$C$7066)/100 -> 2.4419444 | H8: ='Trade balance'!F54 -> -1.8308931 | I8: =CORREL(G8:$G$24,H8:$H$24) -> -0.3797667 | L8: =YEAR(N8) -> 1998 | M8: =MONTH(N8) -> 3 | N8: 35855 | O8: =AVERAGEIFS($C$2:$C$7066,$D$2:$D$7066,L8,$E$2:$E$7066,M8)/10000 -> 0.037322727
A9: 01/12/1998 | B9: EMBPMEXD | C9: 444 | D9: =YEAR(A9) -> 1998 | E9: =MONTH(A9) -> 1 | F9: =F8+1 -> 2004 | G9: =AVERAGEIF($D$2:$D$7066,F9,$C$2:$C$7066)/100 -> 1.9002344 | H9: ='Trade balance'!F55 -> -0.41442742 | I9: =CORREL(G9:$G$24,H9:$H$24) -> -0.36796695 | L9: =YEAR(N9) -> 1998 | M9: =MONTH(N9) -> 4 | N9: 35886 | O9: =AVERAGEIFS($C$2:$C$7066,$D$2:$D$7066,L9,$E$2:$E$7066,M9)/10000 -> 0.038066667
A10: 01/13/1998 | B10: EMBPMEXD | C10: 437 | D10: =YEAR(A10) -> 1998 | E10: =MONTH(A10) -> 1 | F10: =F9+1 -> 2005 | G10: =AVERAGEIF($D$2:$D$7066,F10,$C$2:$C$7066)/100 -> 1.5560618 | H10: ='Trade balance'!F56 -> -0.28789542 | I10: =CORREL(G10:$G$24,H10:$H$24) -> -0.37630597 | L10: =YEAR(N10) -> 1998 | M10: =MONTH(N10) -> 5 | N10: 35916 | O10: =AVERAGEIFS($C$2:$C$7066,$D$2:$D$7066,L10,$E$2:$E$7066,M10)/10000 -> 0.041115
A11: 01/14/1998 | B11: EMBPMEXD | C11: 428 | D11: =YEAR(A11) -> 1998 | E11: =MONTH(A11) -> 1 | F11: =F10+1 -> 2006 | G11: =AVERAGEIF($D$2:$D$7066,F11,$C$2:$C$7066)/100 -> 1.2817969 | H11: ='Trade balance'!F57 -> 2.5567092 | I11: =CORREL(G11:$G$24,H11:$H$24) -> -0.40115193 | L11: =YEAR(N11) -> 1998 | M11: =MONTH(N11) -> 6 | N11: 35947 | O11: =AVERAGEIFS($C$2:$C$7066,$D$2:$D$7066,L11,$E$2:$E$7066,M11)/10000 -> 0.045572727
A12: 01/15/1998 | B12: EMBPMEXD | C12: 438 | D12: =YEAR(A12) -> 1998 | E12: =MONTH(A12) -> 1 | F12: =F11+1 -> 2007 | G12: =AVERAGEIF($D$2:$D$7066,F12,$C$2:$C$7066)/100 -> 1.25868 | H12: ='Trade balance'!F58 -> 2.877748 | I12: =CORREL(G12:$G$24,H12:$H$24) -> -0.30565169 | L12: =YEAR(N12) -> 1998 | M12: =MONTH(N12) -> 7 | N12: 35977 | O12: =AVERAGEIFS($C$2:$C$7066,$D$2:$D$7066,L12,$E$2:$E$7066,M12)/10000 -> 0.046154545
A13: 01/16/1998 | B13: EMBPMEXD | C13: 424 | D13: =YEAR(A13) -> 1998 | E13: =MONTH(A13) -> 1 | F13: =F12+1 -> 2008 | G13: =AVERAGEIF($D$2:$D$7066,F13,$C$2:$C$7066)/100 -> 2.5343825 | H13: ='Trade balance'!F59 -> 2.1654126 | I13: =CORREL(G13:$G$24,H13:$H$24) -> -0.11078636 | L13: =YEAR(N13) -> 1998 | M13: =MONTH(N13) -> 8 | N13: 36008 | O13: =AVERAGEIFS($C$2:$C$7066,$D$2:$D$7066,L13,$E$2:$E$7066,M13)/10000 -> 0.069228571
A14: 01/20/1998 | B14: EMBPMEXD | C14: 423 | D14: =YEAR(A14) -> 1998 | E14: =MONTH(A14) -> 1 | F14: =F13+1 -> 2009 | G14: =AVERAGEIF($D$2:$D$7066,F14,$C$2:$C$7066)/100 -> 3.0032411 | H14: ='Trade balance'!F60 -> -5.9611747 | I14: =CORREL(G14:$G$24,H14:$H$24) -> -0.15291535 | L14: =YEAR(N14) -> 1998 | M14: =MONTH(N14) -> 9 | N14: 36039 | O14: =AVERAGEIFS($C$2:$C$7066,$D$2:$D$7066,L14,$E$2:$E$7066,M14)/10000 -> 0.095042857
A15: 01/21/1998 | B15: EMBPMEXD | C15: 436 | D15: =YEAR(A15) -> 1998 | E15: =MONTH(A15) -> 1 | F15: =F14+1 -> 2010 | G15: =AVERAGEIF($D$2:$D$7066,F15,$C$2:$C$7066)/100 -> 1.8617763 | H15: ='Trade balance'!F61 -> -2.7862803 | I15: =CORREL(G15:$G$24,H15:$H$24) -> 0.29860301 | L15: =YEAR(N15) -> 1998 | M15: =MONTH(N15) -> 10 | N15: 36069 | O15: =AVERAGEIFS($C$2:$C$7066,$D$2:$D$7066,L15,$E$2:$E$7066,M15)/10000 -> 0.089561905
A16: 01/22/1998 | B16: EMBPMEXD | C16: 432 | D16: =YEAR(A16) -> 1998 | E16: =MONTH(A16) -> 1 | F16: =F15+1 -> 2011 | G16: =AVERAGEIF($D$2:$D$7066,F16,$C$2:$C$7066)/100 -> 1.8650485 | H16: ='Trade balance'!F62 -> -1.1489338 | I16: =CORREL(G16:$G$24,H16:$H$24) -> 0.10806808 | L16: =YEAR(N16) -> 1998 | M16: =MONTH(N16) -> 11 | N16: 36100 | O16: =AVERAGEIFS($C$2:$C$7066,$D$2:$D$7066,L16,$E$2:$E$7066,M16)/10000 -> 0.072794737
... A24: 02/03/1998 | B24: EMBPMEXD | C24: 385 | D24: =YEAR(A24) -> 1998 | E24: =MONTH(A24) -> 2 | F24: =F23+1 -> 2019 | G24: =AVERAGEIF($D$2:$D$7066,F24,$C$2:$C$7066)/100 -> 3.181954 | H24: ='Trade balance'!F70 -> -1.3905237 | I24: =CORREL(G24:$G$24,H24:$H$24) -> #DIV/0! | L24: =YEAR(N24) -> 1999 | M24: =MONTH(N24) -> 7 | N24: 36342 | O24: =AVERAGEIFS($C$2:$C$7066,$D$2:$D$7066,L24,$E$2:$E$7066,M24)/10000 -> 0.067
A25: 02/04/1998 | B25: EMBPMEXD | C25: 381 | D25: =YEAR(A25) -> 1998 | E25: =MONTH(A25) -> 2 | L25: =YEAR(N25) -> 1999 | M25: =MONTH(N25) -> 8 | N25: 36373 | O25: =AVERAGEIFS($C$2:$C$7066,$D$2:$D$7066,L25,$E$2:$E$7066,M25)/10000 -> 0.067877273
A26: 02/05/1998 | B26: EMBPMEXD | C26: 377 | D26: =YEAR(A26) -> 1998 | E26: =MONTH(A26) -> 2 | L26: =YEAR(N26) -> 1999 | M26: =MONTH(N26) -> 9 | N26: 36404 | O26: =AVERAGEIFS($C$2:$C$7066,$D$2:$D$7066,L26,$E$2:$E$7066,M26)/10000 -> 0.060377273
A27: 02/06/1998 | B27: EMBPMEXD | C27: 373 | D27: =YEAR(A27) -> 1998 | E27: =MONTH(A27) -> 2 | L27: =YEAR(N27) -> 1999 | M27: =MONTH(N27) -> 10 | N27: 36434 | O27: =AVERAGEIFS($C$2:$C$7066,$D$2:$D$7066,L27,$E$2:$E$7066,M27)/10000 -> 0.05558
A28: 02/09/1998 | B28: EMBPMEXD | C28: 370 | D28: =YEAR(A28) -> 1998 | E28: =MONTH(A28) -> 2 | L28: =YEAR(N28) -> 1999 | M28: =MONTH(N28) -> 11 | N28: 36465 | O28: =AVERAGEIFS($C$2:$C$7066,$D$2:$D$7066,L28,$E$2:$E$7066,M28)/10000 -> 0.047471429
A29: 02/10/1998 | B29: EMBPMEXD | C29: 374 | D29: =YEAR(A29) -> 1998 | E29: =MONTH(A29) -> 2 | L29: =YEAR(N29) -> 1999 | M29: =MONTH(N29) -> 12 | N29: 36495 | O29: =AVERAGEIFS($C$2:$C$7066,$D$2:$D$7066,L29,$E$2:$E$7066,M29)/10000 -> 0.038959091
A30: 02/11/1998 | B30: EMBPMEXD | C30: 378 | D30: =YEAR(A30) -> 1998 | E30: =MONTH(A30) -> 2 | L30: =YEAR(N30) -> 2000 | M30: =MONTH(N30) -> 1 | N30: 36526 | O30: =AVERAGEIFS($C$2:$C$7066,$D$2:$D$7066,L30,$E$2:$E$7066,M30)/10000 -> 0.039875
A31: 02/12/1998 | B31: EMBPMEXD | C31: 384 | D31: =YEAR(A31) -> 1998 | E31: =MONTH(A31) -> 2 | L31: =YEAR(N31) -> 2000 | M31: =MONTH(N31) -> 2 | N31: 36557 | O31: =AVERAGEIFS($C$2:$C$7066,$D$2:$D$7066,L31,$E$2:$E$7066,M31)/10000 -> 0.038045
A32: 02/13/1998 | B32: EMBPMEXD | C32: 387 | D32: =YEAR(A32) -> 1998 | E32: =MONTH(A32) -> 2 | L32: =YEAR(N32) -> 2000 | M32: =MONTH(N32) -> 3 | N32: 36586 | O32: =AVERAGEIFS($C$2:$C$7066,$D$2:$D$7066,L32,$E$2:$E$7066,M32)/10000 -> 0.032669565
A33: 02/17/1998 | B33: EMBPMEXD | C33: 395 | D33: =YEAR(A33) -> 1998 | E33: =MONTH(A33) -> 2 | L33: =YEAR(N33) -> 2000 | M33: =MONTH(N33) -> 4 | N33: 36617 | O33: =AVERAGEIFS($C$2:$C$7066,$D$2:$D$7066,L33,$E$2:$E$7066,M33)/10000 -> 0.040005263
A34: 02/18/1998 | B34: EMBPMEXD | C34: 392 | D34: =YEAR(A34) -> 1998 | E34: =MONTH(A34) -> 2 | L34: =YEAR(N34) -> 2000 | M34: =MONTH(N34) -> 5 | N34: 36647 | O34: =AVERAGEIFS($C$2:$C$7066,$D$2:$D$7066,L34,$E$2:$E$7066,M34)/10000 -> 0.042295455
A35: 02/19/1998 | B35: EMBPMEXD | C35: 398 | D35: =YEAR(A35) -> 1998 | E35: =MONTH(A35) -> 2 | L35: =YEAR(N35) -> 2000 | M35: =MONTH(N35) -> 6 | N35: 36678 | O35: =AVERAGEIFS($C$2:$C$7066,$D$2:$D$7066,L35,$E$2:$E$7066,M35)/10000 -> 0.040004545
A36: 02/20/1998 | B36: EMBPMEXD | C36: 395 | D36: =YEAR(A36) -> 1998 | E36: =MONTH(A36) -> 2 | L36: =YEAR(N36) -> 2000 | M36: =MONTH(N36) -> 7 | N36: 36708 | O36: =AVERAGEIFS($C$2:$C$7066,$D$2:$D$7066,L36,$E$2:$E$7066,M36)/10000 -> 0.03517
... A333: 04/22/1999 | B333: EMBPMEXD | C333: 538 | D333: =YEAR(A333) -> 1999 | E333: =MONTH(A333) -> 4 | L333: =YEAR(N333) -> 2025 | M333: =MONTH(N333) -> 4 | N333: 45748 | O333: =AVERAGEIFS($C$2:$C$7066,$D$2:$D$7066,L333,$E$2:$E$7066,M333)/10000 -> 0.035163636
A334: 04/23/1999 | B334: EMBPMEXD | C334: 550 | D334: =YEAR(A334) -> 1999 | E334: =MONTH(A334) -> 4
A335: 04/26/1999 | B335: EMBPMEXD | C335: 547 | D335: =YEAR(A335) -> 1999 | E335: =MONTH(A335) -> 4
A336: 04/27/1999 | B336: EMBPMEXD | C336: 549 | D336: =YEAR(A336) -> 1999 | E336: =MONTH(A336) -> 4
A337: 04/28/1999 | B337: EMBPMEXD | C337: 540 | D337: =YEAR(A337) -> 1999 | E337: =MONTH(A337) -> 4
A338: 04/29/1999 | B338: EMBPMEXD | C338: 549 | D338: =YEAR(A338) -> 1999 | E338: =MONTH(A338) -> 4
A339: 04/30/1999 | B339: EMBPMEXD | C339: 532 | D339: =YEAR(A339) -> 1999 | E339: =MONTH(A339) -> 4
A340: 05/03/1999 | B340: EMBPMEXD | C340: 523 | D340: =YEAR(A340) -> 1999 | E340: =MONTH(A340) -> 5
A341: 05/04/1999 | B341: EMBPMEXD | C341: 522 | D341: =YEAR(A341) -> 1999 | E341: =MONTH(A341) -> 5
A342: 05/05/1999 | B342: EMBPMEXD | C342: 543 | D342: =YEAR(A342) -> 1999 | E342: =MONTH(A342) -> 5
A343: 05/06/1999 | B343: EMBPMEXD | C343: 538 | D343: =YEAR(A343) -> 1999 | E343: =MONTH(A343) -> 5
A344: 05/07/1999 | B344: EMBPMEXD | C344: 535 | D344: =YEAR(A344) -> 1999 | E344: =MONTH(A344) -> 5
A345: 05/10/1999 | B345: EMBPMEXD | C345: 526 | D345: =YEAR(A345) -> 1999 | E345: =MONTH(A345) -> 5
... A7066: 06/04/2025 | B7066: EMBPMEXD | C7066: 303 | D7066: =YEAR(A7066) -> 2025 | E7066: =MONTH(A7066) -> 6

Sheet DefaultDummys, ReinhartRogoff
A1: SOVEREIGN EXTERNAL DEBT: DEFAULT and RESTRUCTURINGS, 1800-2012--Does not include defaults on WWI debt to United States
B2: Year | C2: 1800 | D2: =C2+1 -> 1801 | E2: =D2+1 -> 1802 | F2: =E2+1 -> 1803 | G2: =F2+1 -> 1804 | H2: =G2+1 -> 1805 | I2: =H2+1 -> 1806 | J2: =I2+1 -> 1807 | K2: =J2+1 -> 1808 | ... Z2: =Y2+1 -> 1823 | AA2: 1824 | AB2: 1825 | AC2: 1826 | AD2: 1827 | AE2: 1828 | AF2: 1829 | AG2: 1830 | AH2: 1831 | AI2: 1832 | AJ2: 1833 | AK2: 1834 | AL2: 1835 | AM2: 1836 | AN2: 1837 | AO2: 1838 | AP2: 1839 | AQ2: 1840 | AR2: 1841 | AS2: 1842 | AT2: 1843 | AU2: 1844 | AV2: 1845 | AW2: 1846 | AX2: 1847 | AY2: 1848 | AZ2: 1849 | BA2: 1850 | BB2: 1851 | BC2: 1852 | BD2: 1853 | BE2: 1854 | BF2: 1855 | BG2: 1856 | BH2: 1857 | BI2: 1858 | BJ2: 1859 | BK2: 1860 | BL2: 1861 | BM2: 1862 | BN2: 1863 | BO2: 1864 | BP2: 1865 | BQ2: 1866 | BR2: 1867 | BS2: 1868 | BT2: 1869 | BU2: 1870 | BV2: 1871 | BW2: 1872 | BX2: 1873 | BY2: 1874 | BZ2: 1875 | CA2: 1876 | CB2: 1877 | CC2: 1878 | CD2: 1879 | CE2: 1880 | CF2: 1881 | CG2: 1882 | CH2: 1883 | CI2: 1884 | CJ2: 1885 | CK2: 1886 | CL2: 1887 | CM2: 1888 | CN2: 1889 | CO2: 1890 | CP2: 1891 | CQ2: 1892 | CR2: 1893 | CS2: 1894 | CT2: 1895 | CU2: 1896 | CV2: 1897 | CW2: 1898 | CX2: 1899 | CY2: 1900 | CZ2: 1901 | DA2: 1902 | DB2: 1903 | DC2: 1904 | DD2: 1905 | DE2: 1906 | DF2: 1907 | DG2: 1908 | DH2: 1909 | DI2: 1910 | DJ2: 1911 | DK2: 1912 | DL2: 1913 | DM2: 1914 | DN2: 1915 | DO2: 1916 | DP2: 1917 | DQ2: 1918 | DR2: 1919 | DS2: 1920 | DT2: 1921 | DU2: 1922 | DV2: 1923 | DW2: 1924 | DX2: 1925 | DY2: 1926 | DZ2: 1927 | EA2: 1928 | EB2: 1929 | EC2: 1930 | ED2: 1931 | EE2: 1932 | EF2: 1933 | EG2: 1934 | EH2: 1935 | EI2: 1936 | EJ2: 1937 | EK2: 1938 | EL2: 1939 | EM2: 1940 | EN2: 1941 | EO2: 1942 | EP2: 1943 | EQ2: 1944 | ER2: 1945 | ES2: 1946 | ET2: 1947 | EU2: 1948 | EV2: 1949 | EW2: 1950 | EX2: 1951 | EY2: 1952 | EZ2: 1953 | FA2: 1954 | FB2: 1955 | FC2: 1956 | FD2: 1957 | FE2: 1958 | FF2: 1959 | FG2: 1960 | FH2: 1961 | FI2: 1962 | FJ2: 1963 | FK2: 1964 | FL2: 1965 | FM2: 1966 | FN2: 1967 | FO2: 1968 | FP2: 1969 | FQ2: 1970 | FR2: 1971 | FS2: 1972 | FT2: 1973 | FU2: 1974 | FV2: 1975 | FW2: 1976 | FX2: 1977 | FY2: 1978 | FZ2: 1979 | GA2: 1980 | GB2: 1981 | GC2: 1982 | GD2: 1983 | GE2: 1984 | GF2: 1985 | GG2: 1986 | GH2: 1987 | GI2: 1988 | GJ2: 1989 | GK2: 1990 | GL2: 1991 | GM2: 1992 | GN2: 1993 | GO2: 1994 | GP2: 1995 | GQ2: 1996 | GR2: 1997 | GS2: 1998 | GT2: 1999 | GU2: 2000 | GV2: 2001 | GW2: 2002 | GX2: 2003 | GY2: 2004 | GZ2: 2005 | HA2: 2006 | HB2: 2007 | HC2: 2008 | HD2: 2009 | HE2: 2010 | HF2: 2011 | HG2: 2012 | HH2: 2013 | HI2: 2014 | HJ2: Year of | HK2: No of years | HL2: No of years in default | HM2: P(default) | HO2: Share of world GDP
B3: Issuer | HJ3: Independence | HK3: since independence or 1800 | HO3: as of 1913 | HP3: as of 1990 | HQ3: as of 2003
C4: 1 | D4: 1 | E4: 1 | F4: 1 | G4: 1 | H4: 1 | I4: 1 | J4: 1 | K4: 1 | L4: 1 | M4: 1 | N4: 1 | O4: 1 | P4: 1 | Q4: 1 | R4: 1 | S4: 1 | T4: 1 | U4: 1 | V4: 1 | W4: 1 | X4: 1 | Y4: 1 | Z4: 1 | AA4: 1 | AB4: 1 | AC4: 1 | AD4: 1 | AE4: 1 | AF4: 1 | AG4: 1 | AH4: 1 | AI4: 1 | AJ4: 1 | AK4: 1 | AL4: 1 | AM4: 1 | AN4: 1 | AO4: 1 | AP4: 1 | AQ4: 1 | AR4: 1 | AS4: 1 | AT4: 1 | AU4: 1 | AV4: 1 | AW4: 1 | AX4: 1 | AY4: 1 | AZ4: 1 | BA4: 1 | BB4: 1 | BC4: 1 | BD4: 1 | BE4: 1 | BF4: 1 | BG4: 1 | BH4: 1 | BI4: 1 | BJ4: 1 | BK4: 1 | BL4: 1 | BM4: 1 | BN4: 1 | BO4: 1 | BP4: 1 | BQ4: 1 | BR4: 1 | BS4: 1 | BT4: 1 | BU4: 1 | BV4: 1 | BW4: 1 | BX4: 1 | BY4: 1 | BZ4: 1 | CA4: 1 | CB4: 1 | CC4: 1 | CD4: 1 | CE4: 1 | CF4: 1 | CG4: 1 | CH4: 1 | CI4: 1 | CJ4: 1 | CK4: 1 | CL4: 1 | CM4: 1 | CN4: 1 | CO4: 1 | CP4: 1 | CQ4: 1 | CR4: 1 | CS4: 1 | CT4: 1 | CU4: 1 | CV4: 1 | CW4: 1 | CX4: 1 | CY4: 1 | CZ4: 1 | DA4: 1 | DB4: 1 | DC4: 1 | DD4: 1 | DE4: 1 | DF4: 1 | DG4: 1 | DH4: 1 | DI4: 1 | DJ4: 1 | DK4: 1 | DL4: 1 | DM4: 1 | DN4: 1 | DO4: 1 | DP4: 1 | DQ4: 1 | DR4: 1 | DS4: 1 | DT4: 1 | DU4: 1 | DV4: 1 | DW4: 1 | DX4: 1 | DY4: 1 | DZ4: 1 | EA4: 1 | EB4: 1 | EC4: 1 | ED4: 1 | EE4: 1 | EF4: 1 | EG4: 1 | EH4: 1 | EI4: 1 | EJ4: 1 | EK4: 1 | EL4: 1 | EM4: 1 | EN4: 1 | EO4: 1 | EP4: 1 | EQ4: 1 | ER4: 1 | ES4: 1 | ET4: 1 | EU4: 1 | EV4: 1 | EW4: 1 | EX4: 1 | EY4: 1 | EZ4: 1 | FA4: 1 | FB4: 1 | FC4: 1 | FD4: 1 | FE4: 1 | FF4: 1 | FG4: 1 | FH4: 1 | FI4: 1 | FJ4: 1 | FK4: 1 | FL4: 1 | FM4: 1 | FN4: 1 | FO4: 1 | FP4: 1 | FQ4: 1 | FR4: 1 | FS4: 1 | FT4: 1 | FU4: 1 | FV4: 1 | FW4: 1 | FX4: 1 | FY4: 1 | FZ4: 1 | GA4: 1 | GB4: 1 | GC4: 1 | GD4: 1 | GE4: 1 | GF4: 1 | GG4: 1 | GH4: 1 | GI4: 1 | GJ4: 1 | GK4: 1 | GL4: 1 | GM4: 1 | GN4: 1 | GO4: 1 | GP4: 1 | GQ4: 1 | GR4: 1 | GS4: 1 | GT4: 1 | GU4: 1 | GV4: 1 | GW4: 1 | GX4: 1 | GY4: 1 | GZ4: 1 | HA4: 1 | HB4: 1 | HC4: 1 | HD4: 1 | HE4: 1 | HF4: 1 | HG4: 1 | HH4: 1 | HI4: 1 | HK4: =SUM(C$4:HI$4) -> 215
A5: Africa | B5: Algeria | C5: 0 | D5: 0 | E5: 0 | F5: 0 | G5: 0 | H5: 0 | I5: 0 | J5: 0 | K5: 0 | L5: 0 | M5: 0 | N5: 0 | O5: 0 | P5: 0 | Q5: 0 | R5: 0 | S5: 0 | T5: 0 | U5: 0 | V5: 0 | W5: 0 | X5: 0 | Y5: 0 | Z5: 0 | AA5: 0 | AB5: 0 | AC5: 0 | AD5: 0 | AE5: 0 | AF5: 0 | AG5: 0 | AH5: 0 | AI5: 0 | AJ5: 0 | AK5: 0 | AL5: 0 | AM5: 0 | AN5: 0 | AO5: 0 | AP5: 0 | AQ5: 0 | AR5: 0 | AS5: 0 | AT5: 0 | AU5: 0 | AV5: 0 | AW5: 0 | AX5: 0 | AY5: 0 | AZ5: 0 | BA5: 0 | BB5: 0 | BC5: 0 | BD5: 0 | BE5: 0 | BF5: 0 | BG5: 0 | BH5: 0 | BI5: 0 | BJ5: 0 | BK5: 0 | BL5: 0 | BM5: 0 | BN5: 0 | BO5: 0 | BP5: 0 | BQ5: 0 | BR5: 0 | BS5: 0 | BT5: 0 | BU5: 0 | BV5: 0 | BW5: 0 | BX5: 0 | BY5: 0 | BZ5: 0 | CA5: 0 | CB5: 0 | CC5: 0 | CD5: 0 | CE5: 0 | CF5: 0 | CG5: 0 | CH5: 0 | CI5: 0 | CJ5: 0 | CK5: 0 | CL5: 0 | CM5: 0 | CN5: 0 | CO5: 0 | CP5: 0 | CQ5: 0 | CR5: 0 | CS5: 0 | CT5: 0 | CU5: 0 | CV5: 0 | CW5: 0 | CX5: 0 | CY5: 0 | CZ5: 0 | DA5: 0 | DB5: 0 | DC5: 0 | DD5: 0 | DE5: 0 | DF5: 0 | DG5: 0 | DH5: 0 | DI5: 0 | DJ5: 0 | DK5: 0 | DL5: 0 | DM5: 0 | DN5: 0 | DO5: 0 | DP5: 0 | DQ5: 0 | DR5: 0 | DS5: 0 | DT5: 0 | DU5: 0 | DV5: 0 | DW5: 0 | DX5: 0 | DY5: 0 | DZ5: 0 | EA5: 0 | EB5: 0 | EC5: 0 | ED5: 0 | EE5: 0 | EF5: 0 | EG5: 0 | EH5: 0 | EI5: 0 | EJ5: 0 | EK5: 0 | EL5: 0 | EM5: 0 | EN5: 0 | EO5: 0 | EP5: 0 | EQ5: 0 | ER5: 0 | ES5: 0 | ET5: 0 | EU5: 0 | EV5: 0 | EW5: 0 | EX5: 0 | EY5: 0 | EZ5: 0 | FA5: 0 | FB5: 0 | FC5: 0 | FD5: 0 | FE5: 0 | FF5: 0 | FG5: 0 | FH5: 0 | FI5: 0 | FJ5: 0 | FK5: 0 | FL5: 0 | FM5: 0 | FN5: 0 | FO5: 0 | FP5: 0 | FQ5: 0 | FR5: 0 | FS5: 0 | FT5: 0 | FU5: 0 | FV5: 0 | FW5: 0 | FX5: 0 | FY5: 0 | FZ5: 0 | GA5: 0 | GB5: 0 | GC5: 0 | GD5: 0 | GE5: 0 | GF5: 0 | GG5: 0 | GH5: 0 | GI5: 0 | GJ5: 0 | GK5: 0 | GL5: 1 | GM5: 1 | GN5: 1 | GO5: 1 | GP5: 1 | GQ5: 1 | GR5: 0 | GS5: 0 | GT5: 0 | GU5: 0 | GV5: 0 | GW5: 0 | GX5: 0 | GY5: 0 | GZ5: 0 | HA5: 0 | HB5: 0 | HC5: 0 | HD5: 0 | HE5: 0 | HF5: 0 | HG5: 0 | HH5: 0 | HI5: 0 | HJ5: 1962 | HK5: =SUM(FI$4:HI$4) -> 53 | HL5: =SUM(FI5:$HI5) -> 6 | HM5: =100*HL5/HK5 -> 11.320755 | HO5: 0.23 | HP5: 0.27 | HQ5: 0.24434716
B6: Angola | C6: 0 | D6: 0 | E6: 0 | F6: 0 | G6: 0 | H6: 0 | I6: 0 | J6: 0 | K6: 0 | L6: 0 | M6: 0 | N6: 0 | O6: 0 | P6: 0 | Q6: 0 | R6: 0 | S6: 0 | T6: 0 | U6: 0 | V6: 0 | W6: 0 | X6: 0 | Y6: 0 | Z6: 0 | AA6: 0 | AB6: 0 | AC6: 0 | AD6: 0 | AE6: 0 | AF6: 0 | AG6: 0 | AH6: 0 | AI6: 0 | AJ6: 0 | AK6: 0 | AL6: 0 | AM6: 0 | AN6: 0 | AO6: 0 | AP6: 0 | AQ6: 0 | AR6: 0 | AS6: 0 | AT6: 0 | AU6: 0 | AV6: 0 | AW6: 0 | AX6: 0 | AY6: 0 | AZ6: 0 | BA6: 0 | BB6: 0 | BC6: 0 | BD6: 0 | BE6: 0 | BF6: 0 | BG6: 0 | BH6: 0 | BI6: 0 | BJ6: 0 | BK6: 0 | BL6: 0 | BM6: 0 | BN6: 0 | BO6: 0 | BP6: 0 | BQ6: 0 | BR6: 0 | BS6: 0 | BT6: 0 | BU6: 0 | BV6: 0 | BW6: 0 | BX6: 0 | BY6: 0 | BZ6: 0 | CA6: 0 | CB6: 0 | CC6: 0 | CD6: 0 | CE6: 0 | CF6: 0 | CG6: 0 | CH6: 0 | CI6: 0 | CJ6: 0 | CK6: 0 | CL6: 0 | CM6: 0 | CN6: 0 | CO6: 0 | CP6: 0 | CQ6: 0 | CR6: 0 | CS6: 0 | CT6: 0 | CU6: 0 | CV6: 0 | CW6: 0 | CX6: 0 | CY6: 0 | CZ6: 0 | DA6: 0 | DB6: 0 | DC6: 0 | DD6: 0 | DE6: 0 | DF6: 0 | DG6: 0 | DH6: 0 | DI6: 0 | DJ6: 0 | DK6: 0 | DL6: 0 | DM6: 0 | DN6: 0 | DO6: 0 | DP6: 0 | DQ6: 0 | DR6: 0 | DS6: 0 | DT6: 0 | DU6: 0 | DV6: 0 | DW6: 0 | DX6: 0 | DY6: 0 | DZ6: 0 | EA6: 0 | EB6: 0 | EC6: 0 | ED6: 0 | EE6: 0 | EF6: 0 | EG6: 0 | EH6: 0 | EI6: 0 | EJ6: 0 | EK6: 0 | EL6: 0 | EM6: 0 | EN6: 0 | EO6: 0 | EP6: 0 | EQ6: 0 | ER6: 0 | ES6: 0 | ET6: 0 | EU6: 0 | EV6: 0 | EW6: 0 | EX6: 0 | EY6: 0 | EZ6: 0 | FA6: 0 | FB6: 0 | FC6: 0 | FD6: 0 | FE6: 0 | FF6: 0 | FG6: 0 | FH6: 0 | FI6: 0 | FJ6: 0 | FK6: 0 | FL6: 0 | FM6: 0 | FN6: 0 | FO6: 0 | FP6: 0 | FQ6: 0 | FR6: 0 | FS6: 0 | FT6: 0 | FU6: 0 | FV6: 0 | FW6: 0 | FX6: 0 | FY6: 0 | FZ6: 0 | GA6: 0 | GB6: 0 | GC6: 0 | GD6: 0 | GE6: 0 | GF6: 1 | GG6: 1 | GH6: 1 | GI6: 1 | GJ6: 1 | GK6: 1 | GL6: 1 | GM6: 1 | GN6: 1 | GO6: 1 | GP6: 1 | GQ6: 1 | GR6: 1 | GS6: 1 | GT6: 1 | GU6: 1 | GV6: 1 | GW6: 1 | GX6: 1 | GY6: 0 | GZ6: 0 | HA6: 0 | HB6: 0 | HC6: 0 | HD6: 0 | HE6: 0 | HF6: 0 | HG6: 0 | HH6: 0 | HI6: 0 | HJ6: 1975 | HK6: =SUM(FV$4:HI$4) -> 40 | HL6: =SUM(FV6:HI6) -> 19 | HM6: =100*HL6/HK6 -> 47.5 | HO6: 0 | HP6: 0.03 | HQ6: 0.023964524
B7: Central African Republic | C7: 0 | D7: 0 | E7: 0 | F7: 0 | G7: 0 | H7: 0 | I7: 0 | J7: 0 | K7: 0 | L7: 0 | M7: 0 | N7: 0 | O7: 0 | P7: 0 | Q7: 0 | R7: 0 | S7: 0 | T7: 0 | U7: 0 | V7: 0 | W7: 0 | X7: 0 | Y7: 0 | Z7: 0 | AA7: 0 | AB7: 0 | AC7: 0 | AD7: 0 | AE7: 0 | AF7: 0 | AG7: 0 | AH7: 0 | AI7: 0 | AJ7: 0 | AK7: 0 | AL7: 0 | AM7: 0 | AN7: 0 | AO7: 0 | AP7: 0 | AQ7: 0 | AR7: 0 | AS7: 0 | AT7: 0 | AU7: 0 | AV7: 0 | AW7: 0 | AX7: 0 | AY7: 0 | AZ7: 0 | BA7: 0 | BB7: 0 | BC7: 0 | BD7: 0 | BE7: 0 | BF7: 0 | BG7: 0 | BH7: 0 | BI7: 0 | BJ7: 0 | BK7: 0 | BL7: 0 | BM7: 0 | BN7: 0 | BO7: 0 | BP7: 0 | BQ7: 0 | BR7: 0 | BS7: 0 | BT7: 0 | BU7: 0 | BV7: 0 | BW7: 0 | BX7: 0 | BY7: 0 | BZ7: 0 | CA7: 0 | CB7: 0 | CC7: 0 | CD7: 0 | CE7: 0 | CF7: 0 | CG7: 0 | CH7: 0 | CI7: 0 | CJ7: 0 | CK7: 0 | CL7: 0 | CM7: 0 | CN7: 0 | CO7: 0 | CP7: 0 | CQ7: 0 | CR7: 0 | CS7: 0 | CT7: 0 | CU7: 0 | CV7: 0 | CW7: 0 | CX7: 0 | CY7: 0 | CZ7: 0 | DA7: 0 | DB7: 0 | DC7: 0 | DD7: 0 | DE7: 0 | DF7: 0 | DG7: 0 | DH7: 0 | DI7: 0 | DJ7: 0 | DK7: 0 | DL7: 0 | DM7: 0 | DN7: 0 | DO7: 0 | DP7: 0 | DQ7: 0 | DR7: 0 | DS7: 0 | DT7: 0 | DU7: 0 | DV7: 0 | DW7: 0 | DX7: 0 | DY7: 0 | DZ7: 0 | EA7: 0 | EB7: 0 | EC7: 0 | ED7: 0 | EE7: 0 | EF7: 0 | EG7: 0 | EH7: 0 | EI7: 0 | EJ7: 0 | EK7: 0 | EL7: 0 | EM7: 0 | EN7: 0 | EO7: 0 | EP7: 0 | EQ7: 0 | ER7: 0 | ES7: 0 | ET7: 0 | EU7: 0 | EV7: 0 | EW7: 0 | EX7: 0 | EY7: 0 | EZ7: 0 | FA7: 0 | FB7: 0 | FC7: 0 | FD7: 0 | FE7: 0 | FF7: 0 | FG7: 0 | FH7: 0 | FI7: 0 | FJ7: 0 | FK7: 0 | FL7: 0 | FM7: 0 | FN7: 0 | FO7: 0 | FP7: 0 | FQ7: 0 | FR7: 0 | FS7: 0 | FT7: 0 | FU7: 0 | FV7: 0 | FW7: 0 | FX7: 0 | FY7: 0 | FZ7: 0 | GA7: 0 | GB7: 1 | GC7: 0 | GD7: 1 | GE7: 1 | GF7: 1 | GG7: 1 | GH7: 1 | GI7: 1 | GJ7: 1 | GK7: 1 | GL7: 1 | GM7: 1 | GN7: 1 | GO7: 1 | GP7: 1 | GQ7: 1 | GR7: 1 | GS7: 1 | GT7: 1 | GU7: 1 | GV7: 1 | GW7: 1 | GX7: 1 | GY7: 1 | GZ7: 1 | HA7: 1 | HB7: 1 | HC7: 1 | HD7: 1 | HE7: 1 | HF7: 1 | HG7: 1 | HH7: 1 | HI7: 1 | HJ7: 1960 | HK7: =SUM(FG$4:HI$4) -> 55 | HL7: =SUM(FG7:HI7) -> 33 | HM7: =100*HL7/HK7 -> 60 | HO7: 0 | HP7: 0.01 | HQ7: 0.01 | HS7: Need to confirm it is ongoing
B8: Cote d'Ivoire | C8: 0 | D8: 0 | E8: 0 | F8: 0 | G8: 0 | H8: 0 | I8: 0 | J8: 0 | K8: 0 | L8: 0 | M8: 0 | N8: 0 | O8: 0 | P8: 0 | Q8: 0 | R8: 0 | S8: 0 | T8: 0 | U8: 0 | V8: 0 | W8: 0 | X8: 0 | Y8: 0 | Z8: 0 | AA8: 0 | AB8: 0 | AC8: 0 | AD8: 0 | AE8: 0 | AF8: 0 | AG8: 0 | AH8: 0 | AI8: 0 | AJ8: 0 | AK8: 0 | AL8: 0 | AM8: 0 | AN8: 0 | AO8: 0 | AP8: 0 | AQ8: 0 | AR8: 0 | AS8: 0 | AT8: 0 | AU8: 0 | AV8: 0 | AW8: 0 | AX8: 0 | AY8: 0 | AZ8: 0 | BA8: 0 | BB8: 0 | BC8: 0 | BD8: 0 | BE8: 0 | BF8: 0 | BG8: 0 | BH8: 0 | BI8: 0 | BJ8: 0 | BK8: 0 | BL8: 0 | BM8: 0 | BN8: 0 | BO8: 0 | BP8: 0 | BQ8: 0 | BR8: 0 | BS8: 0 | BT8: 0 | BU8: 0 | BV8: 0 | BW8: 0 | BX8: 0 | BY8: 0 | BZ8: 0 | CA8: 0 | CB8: 0 | CC8: 0 | CD8: 0 | CE8: 0 | CF8: 0 | CG8: 0 | CH8: 0 | CI8: 0 | CJ8: 0 | CK8: 0 | CL8: 0 | CM8: 0 | CN8: 0 | CO8: 0 | CP8: 0 | CQ8: 0 | CR8: 0 | CS8: 0 | CT8: 0 | CU8: 0 | CV8: 0 | CW8: 0 | CX8: 0 | CY8: 0 | CZ8: 0 | DA8: 0 | DB8: 0 | DC8: 0 | DD8: 0 | DE8: 0 | DF8: 0 | DG8: 0 | DH8: 0 | DI8: 0 | DJ8: 0 | DK8: 0 | DL8: 0 | DM8: 0 | DN8: 0 | DO8: 0 | DP8: 0 | DQ8: 0 | DR8: 0 | DS8: 0 | DT8: 0 | DU8: 0 | DV8: 0 | DW8: 0 | DX8: 0 | DY8: 0 | DZ8: 0 | EA8: 0 | EB8: 0 | EC8: 0 | ED8: 0 | EE8: 0 | EF8: 0 | EG8: 0 | EH8: 0 | EI8: 0 | EJ8: 0 | EK8: 0 | EL8: 0 | EM8: 0 | EN8: 0 | EO8: 0 | EP8: 0 | EQ8: 0 | ER8: 0 | ES8: 0 | ET8: 0 | EU8: 0 | EV8: 0 | EW8: 0 | EX8: 0 | EY8: 0 | EZ8: 0 | FA8: 0 | FB8: 0 | FC8: 0 | FD8: 0 | FE8: 0 | FF8: 0 | FG8: 0 | FH8: 0 | FI8: 0 | FJ8: 0 | FK8: 0 | FL8: 0 | FM8: 0 | FN8: 0 | FO8: 0 | FP8: 0 | FQ8: 0 | FR8: 0 | FS8: 0 | FT8: 0 | FU8: 0 | FV8: 0 | FW8: 0 | FX8: 0 | FY8: 0 | FZ8: 0 | GA8: 0 | GB8: 0 | GC8: 0 | GD8: 1 | GE8: 1 | GF8: 1 | GG8: 1 | GH8: 1 | GI8: 1 | GJ8: 1 | GK8: 1 | GL8: 1 | GM8: 1 | GN8: 1 | GO8: 1 | GP8: 1 | GQ8: 1 | GR8: 1 | GS8: 1 | GT8: 0 | GU8: 1 | GV8: 1 | GW8: 1 | GX8: 1 | GY8: 1 | GZ8: 1 | HA8: 1 | HB8: 1 | HC8: 1 | HD8: 1 | HE8: 1 | HF8: 0 | HG8: 0 | HH8: 0 | HI8: 0 | HJ8: 1960 | HK8: =SUM(FG$4:HI$4) -> 55 | HL8: =SUM(FG8:HI8) -> 27 | HM8: =100*HL8/HK8 -> 49.090909 | HO8: 0 | HP8: 0.06 | HQ8: 0.05 | HS8: Need to check beyond 2010-Moody's documents 2011 default
B9: Egypt | C9: 0 | D9: 0 | E9: 0 | F9: 0 | G9: 0 | H9: 0 | I9: 0 | J9: 0 | K9: 0 | L9: 0 | M9: 0 | N9: 0 | O9: 0 | P9: 0 | Q9: 0 | R9: 0 | S9: 0 | T9: 0 | U9: 0 | V9: 0 | W9: 0 | X9: 0 | Y9: 0 | Z9: 0 | AA9: 0 | AB9: 0 | AC9: 0 | AD9: 0 | AE9: 0 | AF9: 0 | AG9: 0 | AH9: 0 | AI9: 0 | AJ9: 0 | AK9: 0 | AL9: 0 | AM9: 0 | AN9: 0 | AO9: 0 | AP9: 0 | AQ9: 0 | AR9: 0 | AS9: 0 | AT9: 0 | AU9: 0 | AV9: 0 | AW9: 0 | AX9: 0 | AY9: 0 | AZ9: 0 | BA9: 0 | BB9: 0 | BC9: 0 | BD9: 0 | BE9: 0 | BF9: 0 | BG9: 0 | BH9: 0 | BI9: 0 | BJ9: 0 | BK9: 0 | BL9: 0 | BM9: 0 | BN9: 0 | BO9: 0 | BP9: 0 | BQ9: 0 | BR9: 0 | BS9: 0 | BT9: 0 | BU9: 0 | BV9: 0 | BW9: 0 | BX9: 0 | BY9: 0 | BZ9: 0 | CA9: 1 | CB9: 1 | CC9: 1 | CD9: 1 | CE9: 1 | CF9: 0 | CG9: 0 | CH9: 0 | CI9: 0 | CJ9: 0 | CK9: 0 | CL9: 0 | CM9: 0 | CN9: 0 | CO9: 0 | CP9: 0 | CQ9: 0 | CR9: 0 | CS9: 0 | CT9: 0 | CU9: 0 | CV9: 0 | CW9: 0 | CX9: 0 | CY9: 0 | CZ9: 0 | DA9: 0 | DB9: 0 | DC9: 0 | DD9: 0 | DE9: 0 | DF9: 0 | DG9: 0 | DH9: 0 | DI9: 0 | DJ9: 0 | DK9: 0 | DL9: 0 | DM9: 0 | DN9: 0 | DO9: 0 | DP9: 0 | DQ9: 0 | DR9: 0 | DS9: 0 | DT9: 0 | DU9: 0 | DV9: 0 | DW9: 0 | DX9: 0 | DY9: 0 | DZ9: 0 | EA9: 0 | EB9: 0 | EC9: 0 | ED9: 0 | EE9: 0 | EF9: 0 | EG9: 0 | EH9: 0 | EI9: 0 | EJ9: 0 | EK9: 0 | EL9: 0 | EM9: 0 | EN9: 0 | EO9: 0 | EP9: 0 | EQ9: 0 | ER9: 0 | ES9: 0 | ET9: 0 | EU9: 0 | EV9: 0 | EW9: 0 | EX9: 0 | EY9: 0 | EZ9: 0 | FA9: 0 | FB9: 0 | FC9: 0 | FD9: 0 | FE9: 0 | FF9: 0 | FG9: 0 | FH9: 0 | FI9: 0 | FJ9: 0 | FK9: 0 | FL9: 0 | FM9: 0 | FN9: 0 | FO9: 0 | FP9: 0 | FQ9: 0 | FR9: 0 | FS9: 0 | FT9: 0 | FU9: 0 | FV9: 0 | FW9: 0 | FX9: 0 | FY9: 0 | FZ9: 0 | GA9: 0 | GB9: 0 | GC9: 0 | GD9: 0 | GE9: 1 | GF9: 0 | GG9: 0 | GH9: 0 | GI9: 0 | GJ9: 0 | GK9: 0 | GL9: 0 | GM9: 0 | GN9: 0 | GO9: 0 | GP9: 0 | GQ9: 0 | GR9: 0 | GS9: 0 | GT9: 0 | GU9: 0 | GV9: 0 | GW9: 0 | GX9: 0 | GY9: 0 | GZ9: 0 | HA9: 0 | HB9: 0 | HC9: 0 | HD9: 0 | HE9: 0 | HF9: 0 | HG9: 0 | HH9: 0 | HI9: 0 | HJ9: 1831 | HK9: =SUM(AH$4:HI$4) -> 184 | HL9: =SUM(C9:HI9) -> 6 | HM9: =100*HL9/HK9 -> 3.2608696 | HO9: 0.4 | HP9: 0.53 | HQ9: 0.56
B10: Kenya | C10: 0 | D10: 0 | E10: 0 | F10: 0 | G10: 0 | H10: 0 | I10: 0 | J10: 0 | K10: 0 | L10: 0 | M10: 0 | N10: 0 | O10: 0 | P10: 0 | Q10: 0 | R10: 0 | S10: 0 | T10: 0 | U10: 0 | V10: 0 | W10: 0 | X10: 0 | Y10: 0 | Z10: 0 | AA10: 0 | AB10: 0 | AC10: 0 | AD10: 0 | AE10: 0 | AF10: 0 | AG10: 0 | AH10: 0 | AI10: 0 | AJ10: 0 | AK10: 0 | AL10: 0 | AM10: 0 | AN10: 0 | AO10: 0 | AP10: 0 | AQ10: 0 | AR10: 0 | AS10: 0 | AT10: 0 | AU10: 0 | AV10: 0 | AW10: 0 | AX10: 0 | AY10: 0 | AZ10: 0 | BA10: 0 | BB10: 0 | BC10: 0 | BD10: 0 | BE10: 0 | BF10: 0 | BG10: 0 | BH10: 0 | BI10: 0 | BJ10: 0 | BK10: 0 | BL10: 0 | BM10: 0 | BN10: 0 | BO10: 0 | BP10: 0 | BQ10: 0 | BR10: 0 | BS10: 0 | BT10: 0 | BU10: 0 | BV10: 0 | BW10: 0 | BX10: 0 | BY10: 0 | BZ10: 0 | CA10: 0 | CB10: 0 | CC10: 0 | CD10: 0 | CE10: 0 | CF10: 0 | CG10: 0 | CH10: 0 | CI10: 0 | CJ10: 0 | CK10: 0 | CL10: 0 | CM10: 0 | CN10: 0 | CO10: 0 | CP10: 0 | CQ10: 0 | CR10: 0 | CS10: 0 | CT10: 0 | CU10: 0 | CV10: 0 | CW10: 0 | CX10: 0 | CY10: 0 | CZ10: 0 | DA10: 0 | DB10: 0 | DC10: 0 | DD10: 0 | DE10: 0 | DF10: 0 | DG10: 0 | DH10: 0 | DI10: 0 | DJ10: 0 | DK10: 0 | DL10: 0 | DM10: 0 | DN10: 0 | DO10: 0 | DP10: 0 | DQ10: 0 | DR10: 0 | DS10: 0 | DT10: 0 | DU10: 0 | DV10: 0 | DW10: 0 | DX10: 0 | DY10: 0 | DZ10: 0 | EA10: 0 | EB10: 0 | EC10: 0 | ED10: 0 | EE10: 0 | EF10: 0 | EG10: 0 | EH10: 0 | EI10: 0 | EJ10: 0 | EK10: 0 | EL10: 0 | EM10: 0 | EN10: 0 | EO10: 0 | EP10: 0 | EQ10: 0 | ER10: 0 | ES10: 0 | ET10: 0 | EU10: 0 | EV10: 0 | EW10: 0 | EX10: 0 | EY10: 0 | EZ10: 0 | FA10: 0 | FB10: 0 | FC10: 0 | FD10: 0 | FE10: 0 | FF10: 0 | FG10: 0 | FH10: 0 | FI10: 0 | FJ10: 0 | FK10: 0 | FL10: 0 | FM10: 0 | FN10: 0 | FO10: 0 | FP10: 0 | FQ10: 0 | FR10: 0 | FS10: 0 | FT10: 0 | FU10: 0 | FV10: 0 | FW10: 0 | FX10: 0 | FY10: 0 | FZ10: 0 | GA10: 0 | GB10: 0 | GC10: 0 | GD10: 0 | GE10: 0 | GF10: 0 | GG10: 0 | GH10: 0 | GI10: 0 | GJ10: 0 | GK10: 0 | GL10: 0 | GM10: 0 | GN10: 0 | GO10: 1 | GP10: 1 | GQ10: 1 | GR10: 1 | GS10: 1 | GT10: 0 | GU10: 1 | GV10: 0 | GW10: 0 | GX10: 0 | GY10: 0 | GZ10: 0 | HA10: 0 | HB10: 0 | HC10: 0 | HD10: 0 | HE10: 0 | HF10: 0 | HG10: 0 | HH10: 0 | HI10: 0 | HJ10: 1963 | HK10: =SUM(FJ$4:HI$4) -> 52 | HL10: =SUM(FJ10:HI10) -> 6 | HM10: =100*HL10/HK10 -> 11.538462 | HO10: 0 | HP10: 0.1 | HQ10: 0.08
B11: Morocco | C11: 0 | D11: 0 | E11: 0 | F11: 0 | G11: 0 | H11: 0 | I11: 0 | J11: 0 | K11: 0 | L11: 0 | M11: 0 | N11: 0 | O11: 0 | P11: 0 | Q11: 0 | R11: 0 | S11: 0 | T11: 0 | U11: 0 | V11: 0 | W11: 0 | X11: 0 | Y11: 0 | Z11: 0 | AA11: 0 | AB11: 0 | AC11: 0 | AD11: 0 | AE11: 0 | AF11: 0 | AG11: 0 | AH11: 0 | AI11: 0 | AJ11: 0 | AK11: 0 | AL11: 0 | AM11: 0 | AN11: 0 | AO11: 0 | AP11: 0 | AQ11: 0 | AR11: 0 | AS11: 0 | AT11: 0 | AU11: 0 | AV11: 0 | AW11: 0 | AX11: 0 | AY11: 0 | AZ11: 0 | BA11: 0 | BB11: 0 | BC11: 0 | BD11: 0 | BE11: 0 | BF11: 0 | BG11: 0 | BH11: 0 | BI11: 0 | BJ11: 0 | BK11: 0 | BL11: 0 | BM11: 0 | BN11: 0 | BO11: 0 | BP11: 0 | BQ11: 0 | BR11: 0 | BS11: 0 | BT11: 0 | BU11: 0 | BV11: 0 | BW11: 0 | BX11: 0 | BY11: 0 | BZ11: 0 | CA11: 0 | CB11: 0 | CC11: 0 | CD11: 0 | CE11: 0 | CF11: 0 | CG11: 0 | CH11: 0 | CI11: 0 | CJ11: 0 | CK11: 0 | CL11: 0 | CM11: 0 | CN11: 0 | CO11: 0 | CP11: 0 | CQ11: 0 | CR11: 0 | CS11: 0 | CT11: 0 | CU11: 0 | CV11: 0 | CW11: 0 | CX11: 0 | CY11: 0 | CZ11: 0 | DA11: 0 | DB11: 1 | DC11: 1 | DD11: 0 | DE11: 0 | DF11: 0 | DG11: 0 | DH11: 0 | DI11: 0 | DJ11: 0 | DK11: 0 | DL11: 0 | DM11: 0 | DN11: 0 | DO11: 0 | DP11: 0 | DQ11: 0 | DR11: 0 | DS11: 0 | DT11: 0 | DU11: 0 | DV11: 0 | DW11: 0 | DX11: 0 | DY11: 0 | DZ11: 0 | EA11: 0 | EB11: 0 | EC11: 0 | ED11: 0 | EE11: 0 | EF11: 0 | EG11: 0 | EH11: 0 | EI11: 0 | EJ11: 0 | EK11: 0 | EL11: 0 | EM11: 0 | EN11: 0 | EO11: 0 | EP11: 0 | EQ11: 0 | ER11: 0 | ES11: 0 | ET11: 0 | EU11: 0 | EV11: 0 | EW11: 0 | EX11: 0 | EY11: 0 | EZ11: 0 | FA11: 0 | FB11: 0 | FC11: 0 | FD11: 0 | FE11: 0 | FF11: 0 | FG11: 0 | FH11: 0 | FI11: 0 | FJ11: 0 | FK11: 0 | FL11: 0 | FM11: 0 | FN11: 0 | FO11: 0 | FP11: 0 | FQ11: 0 | FR11: 0 | FS11: 0 | FT11: 0 | FU11: 0 | FV11: 0 | FW11: 0 | FX11: 0 | FY11: 0 | FZ11: 0 | GA11: 0 | GB11: 0 | GC11: 0 | GD11: 1 | GE11: 0 | GF11: 0 | GG11: 1 | GH11: 1 | GI11: 1 | GJ11: 1 | GK11: 1 | GL11: 0 | GM11: 0 | GN11: 0 | GO11: 0 | GP11: 0 | GQ11: 0 | GR11: 0 | GS11: 0 | GT11: 0 | GU11: 0 | GV11: 0 | GW11: 0 | GX11: 0 | GY11: 0 | GZ11: 0 | HA11: 0 | HB11: 0 | HC11: 0 | HD11: 0 | HE11: 0 | HF11: 0 | HG11: 0 | HH11: 0 | HI11: 0 | HJ11: 1956 | HK11: =SUM(FC$4:HI$4) -> 59 | HL11: =SUM(FC11:HI11) -> 6 | HM11: =100*HL11/HK11 -> 10.169492 | HO11: 0.13 | HP11: 0.24 | HQ11: 0.23 | HS11: Does not include 1903-1904 default
B12: Mauritius | C12: 0 | D12: 0 | E12: 0 | F12: 0 | G12: 0 | H12: 0 | I12: 0 | J12: 0 | K12: 0 | L12: 0 | M12: 0 | N12: 0 | O12: 0 | P12: 0 | Q12: 0 | R12: 0 | S12: 0 | T12: 0 | U12: 0 | V12: 0 | W12: 0 | X12: 0 | Y12: 0 | Z12: 0 | AA12: 0 | AB12: 0 | AC12: 0 | AD12: 0 | AE12: 0 | AF12: 0 | AG12: 0 | AH12: 0 | AI12: 0 | AJ12: 0 | AK12: 0 | AL12: 0 | AM12: 0 | AN12: 0 | AO12: 0 | AP12: 0 | AQ12: 0 | AR12: 0 | AS12: 0 | AT12: 0 | AU12: 0 | AV12: 0 | AW12: 0 | AX12: 0 | AY12: 0 | AZ12: 0 | BA12: 0 | BB12: 0 | BC12: 0 | BD12: 0 | BE12: 0 | BF12: 0 | BG12: 0 | BH12: 0 | BI12: 0 | BJ12: 0 | BK12: 0 | BL12: 0 | BM12: 0 | BN12: 0 | BO12: 0 | BP12: 0 | BQ12: 0 | BR12: 0 | BS12: 0 | BT12: 0 | BU12: 0 | BV12: 0 | BW12: 0 | BX12: 0 | BY12: 0 | BZ12: 0 | CA12: 0 | CB12: 0 | CC12: 0 | CD12: 0 | CE12: 0 | CF12: 0 | CG12: 0 | CH12: 0 | CI12: 0 | CJ12: 0 | CK12: 0 | CL12: 0 | CM12: 0 | CN12: 0 | CO12: 0 | CP12: 0 | CQ12: 0 | CR12: 0 | CS12: 0 | CT12: 0 | CU12: 0 | CV12: 0 | CW12: 0 | CX12: 0 | CY12: 0 | CZ12: 0 | DA12: 0 | DB12: 0 | DC12: 0 | DD12: 0 | DE12: 0 | DF12: 0 | DG12: 0 | DH12: 0 | DI12: 0 | DJ12: 0 | DK12: 0 | DL12: 0 | DM12: 0 | DN12: 0 | DO12: 0 | DP12: 0 | DQ12: 0 | DR12: 0 | DS12: 0 | DT12: 0 | DU12: 0 | DV12: 0 | DW12: 0 | DX12: 0 | DY12: 0 | DZ12: 0 | EA12: 0 | EB12: 0 | EC12: 0 | ED12: 0 | EE12: 0 | EF12: 0 | EG12: 0 | EH12: 0 | EI12: 0 | EJ12: 0 | EK12: 0 | EL12: 0 | EM12: 0 | EN12: 0 | EO12: 0 | EP12: 0 | EQ12: 0 | ER12: 0 | ES12: 0 | ET12: 0 | EU12: 0 | EV12: 0 | EW12: 0 | EX12: 0 | EY12: 0 | EZ12: 0 | FA12: 0 | FB12: 0 | FC12: 0 | FD12: 0 | FE12: 0 | FF12: 0 | FG12: 0 | FH12: 0 | FI12: 0 | FJ12: 0 | FK12: 0 | FL12: 0 | FM12: 0 | FN12: 0 | FO12: 0 | FP12: 0 | FQ12: 0 | FR12: 0 | FS12: 0 | FT12: 0 | FU12: 0 | FV12: 0 | FW12: 0 | FX12: 0 | FY12: 0 | FZ12: 0 | GA12: 0 | GB12: 0 | GC12: 0 | GD12: 0 | GE12: 0 | GF12: 0 | GG12: 0 | GH12: 0 | GI12: 0 | GJ12: 0 | GK12: 0 | GL12: 0 | GM12: 0 | GN12: 0 | GO12: 0 | GP12: 0 | GQ12: 0 | GR12: 0 | GS12: 0 | GT12: 0 | GU12: 0 | GV12: 0 | GW12: 0 | GX12: 0 | GY12: 0 | GZ12: 0 | HA12: 0 | HB12: 0 | HC12: 0 | HD12: 0 | HE12: 0 | HF12: 0 | HG12: 0 | HH12: 0 | HI12: 0 | HJ12: 1968 | HK12: =SUM(FO$4:HI$4) -> 47 | HL12: =SUM(FO12:HI12) -> 0 | HM12: =100*HL12/HK12 -> 0 | HO12: 0 | HP12: 0.03 | HQ12: 0.04
B13: Nigeria | C13: 0 | D13: 0 | E13: 0 | F13: 0 | G13: 0 | H13: 0 | I13: 0 | J13: 0 | K13: 0 | L13: 0 | M13: 0 | N13: 0 | O13: 0 | P13: 0 | Q13: 0 | R13: 0 | S13: 0 | T13: 0 | U13: 0 | V13: 0 | W13: 0 | X13: 0 | Y13: 0 | Z13: 0 | AA13: 0 | AB13: 0 | AC13: 0 | AD13: 0 | AE13: 0 | AF13: 0 | AG13: 0 | AH13: 0 | AI13: 0 | AJ13: 0 | AK13: 0 | AL13: 0 | AM13: 0 | AN13: 0 | AO13: 0 | AP13: 0 | AQ13: 0 | AR13: 0 | AS13: 0 | AT13: 0 | AU13: 0 | AV13: 0 | AW13: 0 | AX13: 0 | AY13: 0 | AZ13: 0 | BA13: 0 | BB13: 0 | BC13: 0 | BD13: 0 | BE13: 0 | BF13: 0 | BG13: 0 | BH13: 0 | BI13: 0 | BJ13: 0 | BK13: 0 | BL13: 0 | BM13: 0 | BN13: 0 | BO13: 0 | BP13: 0 | BQ13: 0 | BR13: 0 | BS13: 0 | BT13: 0 | BU13: 0 | BV13: 0 | BW13: 0 | BX13: 0 | BY13: 0 | BZ13: 0 | CA13: 0 | CB13: 0 | CC13: 0 | CD13: 0 | CE13: 0 | CF13: 0 | CG13: 0 | CH13: 0 | CI13: 0 | CJ13: 0 | CK13: 0 | CL13: 0 | CM13: 0 | CN13: 0 | CO13: 0 | CP13: 0 | CQ13: 0 | CR13: 0 | CS13: 0 | CT13: 0 | CU13: 0 | CV13: 0 | CW13: 0 | CX13: 0 | CY13: 0 | CZ13: 0 | DA13: 0 | DB13: 0 | DC13: 0 | DD13: 0 | DE13: 0 | DF13: 0 | DG13: 0 | DH13: 0 | DI13: 0 | DJ13: 0 | DK13: 0 | DL13: 0 | DM13: 0 | DN13: 0 | DO13: 0 | DP13: 0 | DQ13: 0 | DR13: 0 | DS13: 0 | DT13: 0 | DU13: 0 | DV13: 0 | DW13: 0 | DX13: 0 | DY13: 0 | DZ13: 0 | EA13: 0 | EB13: 0 | EC13: 0 | ED13: 0 | EE13: 0 | EF13: 0 | EG13: 0 | EH13: 0 | EI13: 0 | EJ13: 0 | EK13: 0 | EL13: 0 | EM13: 0 | EN13: 0 | EO13: 0 | EP13: 0 | EQ13: 0 | ER13: 0 | ES13: 0 | ET13: 0 | EU13: 0 | EV13: 0 | EW13: 0 | EX13: 0 | EY13: 0 | EZ13: 0 | FA13: 0 | FB13: 0 | FC13: 0 | FD13: 0 | FE13: 0 | FF13: 0 | FG13: 0 | FH13: 0 | FI13: 0 | FJ13: 0 | FK13: 0 | FL13: 0 | FM13: 0 | FN13: 0 | FO13: 0 | FP13: 0 | FQ13: 0 | FR13: 0 | FS13: 0 | FT13: 0 | FU13: 0 | FV13: 0 | FW13: 0 | FX13: 0 | FY13: 0 | FZ13: 0 | GA13: 0 | GB13: 0 | GC13: 0 | GD13: 0 | GE13: 0 | GF13: 0 | GG13: 0 | GH13: 1 | GI13: 1 | GJ13: 1 | GK13: 1 | GL13: 1 | GM13: 1 | GN13: 1 | GO13: 1 | GP13: 0 | GQ13: 0 | GR13: 0 | GS13: 0 | GT13: 0 | GU13: 0 | GV13: 0 | GW13: 0 | GX13: 0 | GY13: 1 | GZ13: 1 | HA13: 0 | HB13: 0 | HC13: 0 | HD13: 0 | HE13: 0 | HF13: 0 | HG13: 0 | HJ13: 1960 | HK13: =SUM(FG$4:HI$4) -> 55 | HL13: =SUM(FG13:HI13) -> 10 | HM13: =100*HL13/HK13 -> 18.181818 | HO13: 0 | HP13: 0.4 | HQ13: 0.41
B14: South Africa | C14: 0 | D14: 0 | E14: 0 | F14: 0 | G14: 0 | H14: 0 | I14: 0 | J14: 0 | K14: 0 | L14: 0 | M14: 0 | N14: 0 | O14: 0 | P14: 0 | Q14: 0 | R14: 0 | S14: 0 | T14: 0 | U14: 0 | V14: 0 | W14: 0 | X14: 0 | Y14: 0 | Z14: 0 | AA14: 0 | AB14: 0 | AC14: 0 | AD14: 0 | AE14: 0 | AF14: 0 | AG14: 0 | AH14: 0 | AI14: 0 | AJ14: 0 | AK14: 0 | AL14: 0 | AM14: 0 | AN14: 0 | AO14: 0 | AP14: 0 | AQ14: 0 | AR14: 0 | AS14: 0 | AT14: 0 | AU14: 0 | AV14: 0 | AW14: 0 | AX14: 0 | AY14: 0 | AZ14: 0 | BA14: 0 | BB14: 0 | BC14: 0 | BD14: 0 | BE14: 0 | BF14: 0 | BG14: 0 | BH14: 0 | BI14: 0 | BJ14: 0 | BK14: 0 | BL14: 0 | BM14: 0 | BN14: 0 | BO14: 0 | BP14: 0 | BQ14: 0 | BR14: 0 | BS14: 0 | BT14: 0 | BU14: 0 | BV14: 0 | BW14: 0 | BX14: 0 | BY14: 0 | BZ14: 0 | CA14: 0 | CB14: 0 | CC14: 0 | CD14: 0 | CE14: 0 | CF14: 0 | CG14: 0 | CH14: 0 | CI14: 0 | CJ14: 0 | CK14: 0 | CL14: 0 | CM14: 0 | CN14: 0 | CO14: 0 | CP14: 0 | CQ14: 0 | CR14: 0 | CS14: 0 | CT14: 0 | CU14: 0 | CV14: 0 | CW14: 0 | CX14: 0 | CY14: 0 | CZ14: 0 | DA14: 0 | DB14: 0 | DC14: 0 | DD14: 0 | DE14: 0 | DF14: 0 | DG14: 0 | DH14: 0 | DI14: 0 | DJ14: 0 | DK14: 0 | DL14: 0 | DM14: 0 | DN14: 0 | DO14: 0 | DP14: 0 | DQ14: 0 | DR14: 0 | DS14: 0 | DT14: 0 | DU14: 0 | DV14: 0 | DW14: 0 | DX14: 0 | DY14: 0 | DZ14: 0 | EA14: 0 | EB14: 0 | EC14: 0 | ED14: 0 | EE14: 0 | EF14: 0 | EG14: 0 | EH14: 0 | EI14: 0 | EJ14: 0 | EK14: 0 | EL14: 0 | EM14: 0 | EN14: 0 | EO14: 0 | EP14: 0 | EQ14: 0 | ER14: 0 | ES14: 0 | ET14: 0 | EU14: 0 | EV14: 0 | EW14: 0 | EX14: 0 | EY14: 0 | EZ14: 0 | FA14: 0 | FB14: 0 | FC14: 0 | FD14: 0 | FE14: 0 | FF14: 0 | FG14: 0 | FH14: 0 | FI14: 0 | FJ14: 0 | FK14: 0 | FL14: 0 | FM14: 0 | FN14: 0 | FO14: 0 | FP14: 0 | FQ14: 0 | FR14: 0 | FS14: 0 | FT14: 0 | FU14: 0 | FV14: 0 | FW14: 0 | FX14: 0 | FY14: 0 | FZ14: 0 | GA14: 0 | GB14: 0 | GC14: 0 | GD14: 0 | GE14: 0 | GF14: 1 | GG14: 1 | GH14: 1 | GI14: 0 | GJ14: 1 | GK14: 0 | GL14: 0 | GM14: 0 | GN14: 1 | GO14: 0 | GP14: 0 | GQ14: 0 | GR14: 0 | GS14: 0 | GT14: 0 | GU14: 0 | GV14: 0 | GW14: 0 | GX14: 0 | GY14: 0 | GZ14: 0 | HA14: 0 | HB14: 0 | HC14: 0 | HD14: 0 | HE14: 0 | HF14: 0 | HG14: 0 | HJ14: 1910 | HK14: =SUM(DI$4:HI$4) -> 105 | HL14: =SUM(DI14:HI14) -> 5 | HM14: =100*HL14/HK14 -> 4.7619048 | HO14: 0.36 | HP14: 0.54 | HQ14: 0.47
B15: Tunisia | C15: 0 | D15: 0 | E15: 0 | F15: 0 | G15: 0 | H15: 0 | I15: 0 | J15: 0 | K15: 0 | L15: 0 | M15: 0 | N15: 0 | O15: 0 | P15: 0 | Q15: 0 | R15: 0 | S15: 0 | T15: 0 | U15: 0 | V15: 0 | W15: 0 | X15: 0 | Y15: 0 | Z15: 0 | AA15: 0 | AB15: 0 | AC15: 0 | AD15: 0 | AE15: 0 | AF15: 0 | AG15: 0 | AH15: 0 | AI15: 0 | AJ15: 0 | AK15: 0 | AL15: 0 | AM15: 0 | AN15: 0 | AO15: 0 | AP15: 0 | AQ15: 0 | AR15: 0 | AS15: 0 | AT15: 0 | AU15: 0 | AV15: 0 | AW15: 0 | AX15: 0 | AY15: 0 | AZ15: 0 | BA15: 0 | BB15: 0 | BC15: 0 | BD15: 0 | BE15: 0 | BF15: 0 | BG15: 0 | BH15: 0 | BI15: 0 | BJ15: 0 | BK15: 0 | BL15: 0 | BM15: 0 | BN15: 0 | BO15: 0 | BP15: 0 | BQ15: 0 | BR15: 1 | BS15: 1 | BT15: 1 | BU15: 1 | BV15: 0 | BW15: 0 | BX15: 0 | BY15: 0 | BZ15: 0 | CA15: 0 | CB15: 0 | CC15: 0 | CD15: 0 | CE15: 0 | CF15: 0 | CG15: 0 | CH15: 0 | CI15: 0 | CJ15: 0 | CK15: 0 | CL15: 0 | CM15: 0 | CN15: 0 | CO15: 0 | CP15: 0 | CQ15: 0 | CR15: 0 | CS15: 0 | CT15: 0 | CU15: 0 | CV15: 0 | CW15: 0 | CX15: 0 | CY15: 0 | CZ15: 0 | DA15: 0 | DB15: 0 | DC15: 0 | DD15: 0 | DE15: 0 | DF15: 0 | DG15: 0 | DH15: 0 | DI15: 0 | DJ15: 0 | DK15: 0 | DL15: 0 | DM15: 0 | DN15: 0 | DO15: 0 | DP15: 0 | DQ15: 0 | DR15: 0 | DS15: 0 | DT15: 0 | DU15: 0 | DV15: 0 | DW15: 0 | DX15: 0 | DY15: 0 | DZ15: 0 | EA15: 0 | EB15: 0 | EC15: 0 | ED15: 0 | EE15: 0 | EF15: 0 | EG15: 0 | EH15: 0 | EI15: 0 | EJ15: 0 | EK15: 0 | EL15: 0 | EM15: 0 | EN15: 0 | EO15: 0 | EP15: 0 | EQ15: 0 | ER15: 0 | ES15: 0 | ET15: 0 | EU15: 0 | EV15: 0 | EW15: 0 | EX15: 0 | EY15: 0 | EZ15: 0 | FA15: 0 | FB15: 0 | FC15: 1 | FD15: 0 | FE15: 1 | FF15: 0 | FG15: 0 | FH15: 0 | FI15: 0 | FJ15: 1 | FK15: 0 | FL15: 0 | FM15: 0 | FN15: 0 | FO15: 0 | FP15: 0 | FQ15: 0 | FR15: 0 | FS15: 0 | FT15: 0 | FU15: 0 | FV15: 0 | FW15: 0 | FX15: 0 | FY15: 0 | FZ15: 1 | GA15: 1 | GB15: 1 | GC15: 1 | GD15: 0 | GE15: 0 | GF15: 0 | GG15: 0 | GH15: 0 | GI15: 0 | GJ15: 0 | GK15: 0 | GL15: 0 | GM15: 0 | GN15: 0 | GO15: 0 | GP15: 0 | GQ15: 0 | GR15: 0 | GS15: 0 | GT15: 0 | GU15: 0 | GV15: 0 | GW15: 0 | GX15: 0 | GY15: 0 | GZ15: 0 | HA15: 0 | HB15: 0 | HC15: 0 | HD15: 0 | HE15: 0 | HF15: 0 | HG15: 0 | HJ15: 1591/1957 | HK15: =SUM(C$4:HI$4) -> 215 | HL15: =SUM(C15:HI15) -> 11 | HM15: =100*HL15/HK15 -> 5.1162791 | HO15: 0.06 | HP15: 0.1 | HQ15: 0.12
B16: Zambia | C16: 0 | D16: 0 | E16: 0 | F16: 0 | G16: 0 | H16: 0 | I16: 0 | J16: 0 | K16: 0 | L16: 0 | M16: 0 | N16: 0 | O16: 0 | P16: 0 | Q16: 0 | R16: 0 | S16: 0 | T16: 0 | U16: 0 | V16: 0 | W16: 0 | X16: 0 | Y16: 0 | Z16: 0 | AA16: 0 | AB16: 0 | AC16: 0 | AD16: 0 | AE16: 0 | AF16: 0 | AG16: 0 | AH16: 0 | AI16: 0 | AJ16: 0 | AK16: 0 | AL16: 0 | AM16: 0 | AN16: 0 | AO16: 0 | AP16: 0 | AQ16: 0 | AR16: 0 | AS16: 0 | AT16: 0 | AU16: 0 | AV16: 0 | AW16: 0 | AX16: 0 | AY16: 0 | AZ16: 0 | BA16: 0 | BB16: 0 | BC16: 0 | BD16: 0 | BE16: 0 | BF16: 0 | BG16: 0 | BH16: 0 | BI16: 0 | BJ16: 0 | BK16: 0 | BL16: 0 | BM16: 0 | BN16: 0 | BO16: 0 | BP16: 0 | BQ16: 0 | BR16: 0 | BS16: 0 | BT16: 0 | BU16: 0 | BV16: 0 | BW16: 0 | BX16: 0 | BY16: 0 | BZ16: 0 | CA16: 0 | CB16: 0 | CC16: 0 | CD16: 0 | CE16: 0 | CF16: 0 | CG16: 0 | CH16: 0 | CI16: 0 | CJ16: 0 | CK16: 0 | CL16: 0 | CM16: 0 | CN16: 0 | CO16: 0 | CP16: 0 | CQ16: 0 | CR16: 0 | CS16: 0 | CT16: 0 | CU16: 0 | CV16: 0 | CW16: 0 | CX16: 0 | CY16: 0 | CZ16: 0 | DA16: 0 | DB16: 0 | DC16: 0 | DD16: 0 | DE16: 0 | DF16: 0 | DG16: 0 | DH16: 0 | DI16: 0 | DJ16: 0 | DK16: 0 | DL16: 0 | DM16: 0 | DN16: 0 | DO16: 0 | DP16: 0 | DQ16: 0 | DR16: 0 | DS16: 0 | DT16: 0 | DU16: 0 | DV16: 0 | DW16: 0 | DX16: 0 | DY16: 0 | DZ16: 0 | EA16: 0 | EB16: 0 | EC16: 0 | ED16: 0 | EE16: 0 | EF16: 0 | EG16: 0 | EH16: 0 | EI16: 0 | EJ16: 0 | EK16: 0 | EL16: 0 | EM16: 0 | EN16: 0 | EO16: 0 | EP16: 0 | EQ16: 0 | ER16: 0 | ES16: 0 | ET16: 0 | EU16: 0 | EV16: 0 | EW16: 0 | EX16: 0 | EY16: 0 | EZ16: 0 | FA16: 0 | FB16: 0 | FC16: 0 | FD16: 0 | FE16: 0 | FF16: 0 | FG16: 0 | FH16: 0 | FI16: 0 | FJ16: 0 | FK16: 0 | FL16: 0 | FM16: 0 | FN16: 0 | FO16: 0 | FP16: 0 | FQ16: 0 | FR16: 0 | FS16: 0 | FT16: 0 | FU16: 0 | FV16: 0 | FW16: 0 | FX16: 0 | FY16: 0 | FZ16: 0 | GA16: 0 | GB16: 0 | GC16: 0 | GD16: 1 | GE16: 1 | GF16: 1 | GG16: 1 | GH16: 1 | GI16: 1 | GJ16: 1 | GK16: 1 | GL16: 1 | GM16: 1 | GN16: 1 | GO16: 1 | GP16: 0 | GQ16: 0 | GR16: 0 | GS16: 0 | GT16: 0 | GU16: 0 | GV16: 0 | GW16: 0 | GX16: 0 | GY16: 0 | GZ16: 0 | HA16: 0 | HB16: 0 | HC16: 0 | HD16: 0 | HE16: 0 | HF16: 0 | HG16: 0 | HJ16: 1964 | HK16: =SUM(FK$4:HI$4) -> 51 | HL16: =SUM(FK16:HI16) -> 12 | HM16: =100*HL16/HK16 -> 23.529412 | HO16: 0 | HP16: 0.02 | HQ16: 0.02
B17: Zimbabwe | C17: 0 | D17: 0 | E17: 0 | F17: 0 | G17: 0 | H17: 0 | I17: 0 | J17: 0 | K17: 0 | L17: 0 | M17: 0 | N17: 0 | O17: 0 | P17: 0 | Q17: 0 | R17: 0 | S17: 0 | T17: 0 | U17: 0 | V17: 0 | W17: 0 | X17: 0 | Y17: 0 | Z17: 0 | AA17: 0 | AB17: 0 | AC17: 0 | AD17: 0 | AE17: 0 | AF17: 0 | AG17: 0 | AH17: 0 | AI17: 0 | AJ17: 0 | AK17: 0 | AL17: 0 | AM17: 0 | AN17: 0 | AO17: 0 | AP17: 0 | AQ17: 0 | AR17: 0 | AS17: 0 | AT17: 0 | AU17: 0 | AV17: 0 | AW17: 0 | AX17: 0 | AY17: 0 | AZ17: 0 | BA17: 0 | BB17: 0 | BC17: 0 | BD17: 0 | BE17: 0 | BF17: 0 | BG17: 0 | BH17: 0 | BI17: 0 | BJ17: 0 | BK17: 0 | BL17: 0 | BM17: 0 | BN17: 0 | BO17: 0 | BP17: 0 | BQ17: 0 | BR17: 0 | BS17: 0 | BT17: 0 | BU17: 0 | BV17: 0 | BW17: 0 | BX17: 0 | BY17: 0 | BZ17: 0 | CA17: 0 | CB17: 0 | CC17: 0 | CD17: 0 | CE17: 0 | CF17: 0 | CG17: 0 | CH17: 0 | CI17: 0 | CJ17: 0 | CK17: 0 | CL17: 0 | CM17: 0 | CN17: 0 | CO17: 0 | CP17: 0 | CQ17: 0 | CR17: 0 | CS17: 0 | CT17: 0 | CU17: 0 | CV17: 0 | CW17: 0 | CX17: 0 | CY17: 0 | CZ17: 0 | DA17: 0 | DB17: 0 | DC17: 0 | DD17: 0 | DE17: 0 | DF17: 0 | DG17: 0 | DH17: 0 | DI17: 0 | DJ17: 0 | DK17: 0 | DL17: 0 | DM17: 0 | DN17: 0 | DO17: 0 | DP17: 0 | DQ17: 0 | DR17: 0 | DS17: 0 | DT17: 0 | DU17: 0 | DV17: 0 | DW17: 0 | DX17: 0 | DY17: 0 | DZ17: 0 | EA17: 0 | EB17: 0 | EC17: 0 | ED17: 0 | EE17: 0 | EF17: 0 | EG17: 0 | EH17: 0 | EI17: 0 | EJ17: 0 | EK17: 0 | EL17: 0 | EM17: 0 | EN17: 0 | EO17: 0 | EP17: 0 | EQ17: 0 | ER17: 0 | ES17: 0 | ET17: 0 | EU17: 0 | EV17: 0 | EW17: 0 | EX17: 0 | EY17: 0 | EZ17: 0 | FA17: 0 | FB17: 0 | FC17: 0 | FD17: 0 | FE17: 0 | FF17: 0 | FG17: 0 | FH17: 0 | FI17: 0 | FJ17: 0 | FK17: 0 | FL17: 1 | FM17: 1 | FN17: 1 | FO17: 1 | FP17: 1 | FQ17: 1 | FR17: 1 | FS17: 1 | FT17: 1 | FU17: 1 | FV17: 1 | FW17: 1 | FX17: 1 | FY17: 1 | FZ17: 1 | GA17: 1 | GB17: 0 | GC17: 0 | GD17: 0 | GE17: 0 | GF17: 0 | GG17: 0 | GH17: 0 | GI17: 0 | GJ17: 0 | GK17: 0 | GL17: 0 | GM17: 0 | GN17: 0 | GO17: 0 | GP17: 0 | GQ17: 0 | GR17: 0 | GS17: 0 | GT17: 0 | GU17: 1 | GV17: 1 | GW17: 1 | GX17: 1 | GY17: 1 | GZ17: 1 | HA17: 1 | HB17: 1 | HC17: 1 | HD17: 1 | HE17: 1 | HF17: 1 | HG17: 1 | HJ17: 1965 | HK17: =SUM(FL4:HI$4) -> 50 | HL17: =SUM(FL17:HI17) -> 29 | HM17: =100*HL17/HK17 -> 58 | HO17: 0 | HP17: 0.05 | HQ17: 0.03 | HS17: Need to confirm it is ongoing
A18: Asia | B18: China | C18: 0 | D18: 0 | E18: 0 | F18: 0 | G18: 0 | H18: 0 | I18: 0 | J18: 0 | K18: 0 | L18: 0 | M18: 0 | N18: 0 | O18: 0 | P18: 0 | Q18: 0 | R18: 0 | S18: 0 | T18: 0 | U18: 0 | V18: 0 | W18: 0 | X18: 0 | Y18: 0 | Z18: 0 | AA18: 0 | AB18: 0 | AC18: 0 | AD18: 0 | AE18: 0 | AF18: 0 | AG18: 0 | AH18: 0 | AI18: 0 | AJ18: 0 | AK18: 0 | AL18: 0 | AM18: 0 | AN18: 0 | AO18: 0 | AP18: 0 | AQ18: 0 | AR18: 0 | AS18: 0 | AT18: 0 | AU18: 0 | AV18: 0 | AW18: 0 | AX18: 0 | AY18: 0 | AZ18: 0 | BA18: 0 | BB18: 0 | BC18: 0 | BD18: 0 | BE18: 0 | BF18: 0 | BG18: 0 | BH18: 0 | BI18: 0 | BJ18: 0 | BK18: 0 | BL18: 0 | BM18: 0 | BN18: 0 | BO18: 0 | BP18: 0 | BQ18: 0 | BR18: 0 | BS18: 0 | BT18: 0 | BU18: 0 | BV18: 0 | BW18: 0 | BX18: 0 | BY18: 0 | BZ18: 0 | CA18: 0 | CB18: 0 | CC18: 0 | CD18: 0 | CE18: 0 | CF18: 0 | CG18: 0 | CH18: 0 | CI18: 0 | CJ18: 0 | CK18: 0 | CL18: 0 | CM18: 0 | CN18: 0 | CO18: 0 | CP18: 0 | CQ18: 0 | CR18: 0 | CS18: 0 | CT18: 0 | CU18: 0 | CV18: 0 | CW18: 0 | CX18: 0 | CY18: 0 | CZ18: 0 | DA18: 0 | DB18: 0 | DC18: 0 | DD18: 0 | DE18: 0 | DF18: 0 | DG18: 0 | DH18: 0 | DI18: 0 | DJ18: 0 | DK18: 0 | DL18: 0 | DM18: 0 | DN18: 0 | DO18: 0 | DP18: 0 | DQ18: 0 | DR18: 0 | DS18: 0 | DT18: 1 | DU18: 1 | DV18: 1 | DW18: 1 | DX18: 1 | DY18: 1 | DZ18: 1 | EA18: 1 | EB18: 1 | EC18: 1 | ED18: 1 | EE18: 1 | EF18: 1 | EG18: 1 | EH18: 1 | EI18: 1 | EJ18: 0 | EK18: 0 | EL18: 1 | EM18: 1 | EN18: 1 | EO18: 1 | EP18: 1 | EQ18: 1 | ER18: 1 | ES18: 1 | ET18: 1 | EU18: 1 | EV18: 1 | EW18: 0 | EX18: 0 | EY18: 0 | EZ18: 0 | FA18: 0 | FB18: 0 | FC18: 0 | FD18: 0 | FE18: 0 | FF18: 0 | FG18: 0 | FH18: 0 | FI18: 0 | FJ18: 0 | FK18: 0 | FL18: 0 | FM18: 0 | FN18: 0 | FO18: 0 | FP18: 0 | FQ18: 0 | FR18: 0 | FS18: 0 | FT18: 0 | FU18: 0 | FV18: 0 | FW18: 0 | FX18: 0 | FY18: 0 | FZ18: 0 | GA18: 0 | GB18: 0 | GC18: 0 | GD18: 0 | GE18: 0 | GF18: 0 | GG18: 0 | GH18: 0 | GI18: 0 | GJ18: 0 | GK18: 0 | GL18: 0 | GM18: 0 | GN18: 0 | GO18: 0 | GP18: 0 | GQ18: 0 | GR18: 0 | GS18: 0 | GT18: 0 | GU18: 0 | GV18: 0 | GW18: 0 | GX18: 0 | GY18: 0 | GZ18: 0 | HA18: 0 | HB18: 0 | HC18: 0 | HD18: 0 | HE18: 0 | HF18: 0 | HG18: 0 | HH18: 0 | HI18: 0 | HJ18: 1368 | HK18: =SUM(C$4:HI$4) -> 215 | HL18: =SUM(C18:HI18) -> 27 | HM18: =100*HL18/HK18 -> 12.55814 | HO18: 8.83 | HP18: 7.7 | HQ18: 14.6
B19: Japan | C19: 0 | D19: 0 | E19: 0 | F19: 0 | G19: 0 | H19: 0 | I19: 0 | J19: 0 | K19: 0 | L19: 0 | M19: 0 | N19: 0 | O19: 0 | P19: 0 | Q19: 0 | R19: 0 | S19: 0 | T19: 0 | U19: 0 | V19: 0 | W19: 0 | X19: 0 | Y19: 0 | Z19: 0 | AA19: 0 | AB19: 0 | AC19: 0 | AD19: 0 | AE19: 0 | AF19: 0 | AG19: 0 | AH19: 0 | AI19: 0 | AJ19: 0 | AK19: 0 | AL19: 0 | AM19: 0 | AN19: 0 | AO19: 0 | AP19: 0 | AQ19: 0 | AR19: 0 | AS19: 0 | AT19: 0 | AU19: 0 | AV19: 0 | AW19: 0 | AX19: 0 | AY19: 0 | AZ19: 0 | BA19: 0 | BB19: 0 | BC19: 0 | BD19: 0 | BE19: 0 | BF19: 0 | BG19: 0 | BH19: 0 | BI19: 0 | BJ19: 0 | BK19: 0 | BL19: 0 | BM19: 0 | BN19: 0 | BO19: 0 | BP19: 0 | BQ19: 0 | BR19: 0 | BS19: 0 | BT19: 0 | BU19: 0 | BV19: 0 | BW19: 0 | BX19: 0 | BY19: 0 | BZ19: 0 | CA19: 0 | CB19: 0 | CC19: 0 | CD19: 0 | CE19: 0 | CF19: 0 | CG19: 0 | CH19: 0 | CI19: 0 | CJ19: 0 | CK19: 0 | CL19: 0 | CM19: 0 | CN19: 0 | CO19: 0 | CP19: 0 | CQ19: 0 | CR19: 0 | CS19: 0 | CT19: 0 | CU19: 0 | CV19: 0 | CW19: 0 | CX19: 0 | CY19: 0 | CZ19: 0 | DA19: 0 | DB19: 0 | DC19: 0 | DD19: 0 | DE19: 0 | DF19: 0 | DG19: 0 | DH19: 0 | DI19: 0 | DJ19: 0 | DK19: 0 | DL19: 0 | DM19: 0 | DN19: 0 | DO19: 0 | DP19: 0 | DQ19: 0 | DR19: 0 | DS19: 0 | DT19: 0 | DU19: 0 | DV19: 0 | DW19: 0 | DX19: 0 | DY19: 0 | DZ19: 0 | EA19: 0 | EB19: 0 | EC19: 0 | ED19: 0 | EE19: 0 | EF19: 0 | EG19: 0 | EH19: 0 | EI19: 0 | EJ19: 0 | EK19: 0 | EL19: 0 | EM19: 0 | EN19: 0 | EO19: 1 | EP19: 1 | EQ19: 1 | ER19: 1 | ES19: 1 | ET19: 1 | EU19: 1 | EV19: 1 | EW19: 1 | EX19: 1 | EY19: 1 | EZ19: 0 | FA19: 0 | FB19: 0 | FC19: 0 | FD19: 0 | FE19: 0 | FF19: 0 | FG19: 0 | FH19: 0 | FI19: 0 | FJ19: 0 | FK19: 0 | FL19: 0 | FM19: 0 | FN19: 0 | FO19: 0 | FP19: 0 | FQ19: 0 | FR19: 0 | FS19: 0 | FT19: 0 | FU19: 0 | FV19: 0 | FW19: 0 | FX19: 0 | FY19: 0 | FZ19: 0 | GA19: 0 | GB19: 0 | GC19: 0 | GD19: 0 | GE19: 0 | GF19: 0 | GG19: 0 | GH19: 0 | GI19: 0 | GJ19: 0 | GK19: 0 | GL19: 0 | GM19: 0 | GN19: 0 | GO19: 0 | GP19: 0 | GQ19: 0 | GR19: 0 | GS19: 0 | GT19: 0 | GU19: 0 | GV19: 0 | GW19: 0 | GX19: 0 | GY19: 0 | GZ19: 0 | HA19: 0 | HB19: 0 | HC19: 0 | HD19: 0 | HE19: 0 | HF19: 0 | HG19: 0 | HH19: 0 | HI19: 0 | HJ19: 1590 | HK19: =SUM(C$4:HI$4) -> 215 | HL19: =SUM(C19:HI19) -> 11 | HM19: =100*HL19/HK30 -> 5.1162791 | HO19: 2.62 | HP19: 8.57 | HQ19: 6.64
B20: India | C20: 0 | D20: 0 | E20: 0 | F20: 0 | G20: 0 | H20: 0 | I20: 0 | J20: 0 | K20: 0 | L20: 0 | M20: 0 | N20: 0 | O20: 0 | P20: 0 | Q20: 0 | R20: 0 | S20: 0 | T20: 0 | U20: 0 | V20: 0 | W20: 0 | X20: 0 | Y20: 0 | Z20: 0 | AA20: 0 | AB20: 0 | AC20: 0 | AD20: 0 | AE20: 0 | AF20: 0 | AG20: 0 | AH20: 0 | AI20: 0 | AJ20: 0 | AK20: 0 | AL20: 0 | AM20: 0 | AN20: 0 | AO20: 0 | AP20: 0 | AQ20: 0 | AR20: 0 | AS20: 0 | AT20: 0 | AU20: 0 | AV20: 0 | AW20: 0 | AX20: 0 | AY20: 0 | AZ20: 0 | BA20: 0 | BB20: 0 | BC20: 0 | BD20: 0 | BE20: 0 | BF20: 0 | BG20: 0 | BH20: 0 | BI20: 0 | BJ20: 0 | BK20: 0 | BL20: 0 | BM20: 0 | BN20: 0 | BO20: 0 | BP20: 0 | BQ20: 0 | BR20: 0 | BS20: 0 | BT20: 0 | BU20: 0 | BV20: 0 | BW20: 0 | BX20: 0 | BY20: 0 | BZ20: 0 | CA20: 0 | CB20: 0 | CC20: 0 | CD20: 0 | CE20: 0 | CF20: 0 | CG20: 0 | CH20: 0 | CI20: 0 | CJ20: 0 | CK20: 0 | CL20: 0 | CM20: 0 | CN20: 0 | CO20: 0 | CP20: 0 | CQ20: 0 | CR20: 0 | CS20: 0 | CT20: 0 | CU20: 0 | CV20: 0 | CW20: 0 | CX20: 0 | CY20: 0 | CZ20: 0 | DA20: 0 | DB20: 0 | DC20: 0 | DD20: 0 | DE20: 0 | DF20: 0 | DG20: 0 | DH20: 0 | DI20: 0 | DJ20: 0 | DK20: 0 | DL20: 0 | DM20: 0 | DN20: 0 | DO20: 0 | DP20: 0 | DQ20: 0 | DR20: 0 | DS20: 0 | DT20: 0 | DU20: 0 | DV20: 0 | DW20: 0 | DX20: 0 | DY20: 0 | DZ20: 0 | EA20: 0 | EB20: 0 | EC20: 0 | ED20: 0 | EE20: 0 | EF20: 0 | EG20: 0 | EH20: 0 | EI20: 0 | EJ20: 0 | EK20: 0 | EL20: 0 | EM20: 0 | EN20: 0 | EO20: 0 | EP20: 0 | EQ20: 0 | ER20: 0 | ES20: 0 | ET20: 0 | EU20: 0 | EV20: 0 | EW20: 0 | EX20: 0 | EY20: 0 | EZ20: 0 | FA20: 0 | FB20: 0 | FC20: 0 | FD20: 0 | FE20: 1 | FF20: 0 | FG20: 0 | FH20: 0 | FI20: 0 | FJ20: 0 | FK20: 0 | FL20: 0 | FM20: 0 | FN20: 0 | FO20: 0 | FP20: 1 | FQ20: 1 | FR20: 1 | FS20: 1 | FT20: 1 | FU20: 1 | FV20: 1 | FW20: 1 | FX20: 0 | FY20: 0 | FZ20: 0 | GA20: 0 | GB20: 0 | GC20: 0 | GD20: 0 | GE20: 0 | GF20: 0 | GG20: 0 | GH20: 0 | GI20: 0 | GJ20: 0 | GK20: 0 | GL20: 0 | GM20: 0 | GN20: 0 | GO20: 0 | GP20: 0 | GQ20: 0 | GR20: 0 | GS20: 0 | GT20: 0 | GU20: 0 | GV20: 0 | GW20: 0 | GX20: 0 | GY20: 0 | GZ20: 0 | HA20: 0 | HB20: 0 | HC20: 0 | HD20: 0 | HE20: 0 | HF20: 0 | HG20: 0 | HH20: 0 | HI20: 0 | HJ20: 1947 | HK20: =SUM(ET$4:HI$4) -> 68 | HL20: =SUM(ET20:HI20) -> 9 | HM20: =100*HL20/HK20 -> 13.235294 | HO20: 7.47 | HP20: 4.05 | HQ20: 5.58
B21: Indonesia | C21: 0 | D21: 0 | E21: 0 | F21: 0 | G21: 0 | H21: 0 | I21: 0 | J21: 0 | K21: 0 | L21: 0 | M21: 0 | N21: 0 | O21: 0 | P21: 0 | Q21: 0 | R21: 0 | S21: 0 | T21: 0 | U21: 0 | V21: 0 | W21: 0 | X21: 0 | Y21: 0 | Z21: 0 | AA21: 0 | AB21: 0 | AC21: 0 | AD21: 0 | AE21: 0 | AF21: 0 | AG21: 0 | AH21: 0 | AI21: 0 | AJ21: 0 | AK21: 0 | AL21: 0 | AM21: 0 | AN21: 0 | AO21: 0 | AP21: 0 | AQ21: 0 | AR21: 0 | AS21: 0 | AT21: 0 | AU21: 0 | AV21: 0 | AW21: 0 | AX21: 0 | AY21: 0 | AZ21: 0 | BA21: 0 | BB21: 0 | BC21: 0 | BD21: 0 | BE21: 0 | BF21: 0 | BG21: 0 | BH21: 0 | BI21: 0 | BJ21: 0 | BK21: 0 | BL21: 0 | BM21: 0 | BN21: 0 | BO21: 0 | BP21: 0 | BQ21: 0 | BR21: 0 | BS21: 0 | BT21: 0 | BU21: 0 | BV21: 0 | BW21: 0 | BX21: 0 | BY21: 0 | BZ21: 0 | CA21: 0 | CB21: 0 | CC21: 0 | CD21: 0 | CE21: 0 | CF21: 0 | CG21: 0 | CH21: 0 | CI21: 0 | CJ21: 0 | CK21: 0 | CL21: 0 | CM21: 0 | CN21: 0 | CO21: 0 | CP21: 0 | CQ21: 0 | CR21: 0 | CS21: 0 | CT21: 0 | CU21: 0 | CV21: 0 | CW21: 0 | CX21: 0 | CY21: 0 | CZ21: 0 | DA21: 0 | DB21: 0 | DC21: 0 | DD21: 0 | DE21: 0 | DF21: 0 | DG21: 0 | DH21: 0 | DI21: 0 | DJ21: 0 | DK21: 0 | DL21: 0 | DM21: 0 | DN21: 0 | DO21: 0 | DP21: 0 | DQ21: 0 | DR21: 0 | DS21: 0 | DT21: 0 | DU21: 0 | DV21: 0 | DW21: 0 | DX21: 0 | DY21: 0 | DZ21: 0 | EA21: 0 | EB21: 0 | EC21: 0 | ED21: 0 | EE21: 0 | EF21: 0 | EG21: 0 | EH21: 0 | EI21: 0 | EJ21: 0 | EK21: 0 | EL21: 0 | EM21: 0 | EN21: 0 | EO21: 0 | EP21: 0 | EQ21: 0 | ER21: 0 | ES21: 0 | ET21: 0 | EU21: 0 | EV21: 0 | EW21: 0 | EX21: 0 | EY21: 0 | EZ21: 0 | FA21: 0 | FB21: 0 | FC21: 0 | FD21: 0 | FE21: 0 | FF21: 0 | FG21: 0 | FH21: 0 | FI21: 0 | FJ21: 0 | FK21: 0 | FL21: 0 | FM21: 1 | FN21: 1 | FO21: 1 | FP21: 1 | FQ21: 1 | FR21: 0 | FS21: 0 | FT21: 0 | FU21: 0 | FV21: 0 | FW21: 0 | FX21: 0 | FY21: 0 | FZ21: 0 | GA21: 0 | GB21: 0 | GC21: 0 | GD21: 0 | GE21: 0 | GF21: 0 | GG21: 0 | GH21: 0 | GI21: 0 | GJ21: 0 | GK21: 0 | GL21: 0 | GM21: 0 | GN21: 0 | GO21: 0 | GP21: 0 | GQ21: 0 | GR21: 0 | GS21: 0 | GT21: 1 | GU21: 1 | GV21: 0 | GW21: 1 | GX21: 0 | GY21: 0 | GZ21: 0 | HA21: 0 | HB21: 0 | HC21: 0 | HD21: 0 | HE21: 0 | HF21: 0 | HG21: 0 | HH21: 0 | HI21: 0 | HJ21: 1949 | HK21: =SUM(EV$4:HI$4) -> 66 | HL21: =SUM(EV21:HI21) -> 8 | HM21: =100*HL21/HK21 -> 12.121212 | HO21: 1.65 | HP21: 1.66 | HQ21: 1.88 | HS21: Check 1974
B22: Korea | C22: 0 | D22: 0 | E22: 0 | F22: 0 | G22: 0 | H22: 0 | I22: 0 | J22: 0 | K22: 0 | L22: 0 | M22: 0 | N22: 0 | O22: 0 | P22: 0 | Q22: 0 | R22: 0 | S22: 0 | T22: 0 | U22: 0 | V22: 0 | W22: 0 | X22: 0 | Y22: 0 | Z22: 0 | AA22: 0 | AB22: 0 | AC22: 0 | AD22: 0 | AE22: 0 | AF22: 0 | AG22: 0 | AH22: 0 | AI22: 0 | AJ22: 0 | AK22: 0 | AL22: 0 | AM22: 0 | AN22: 0 | AO22: 0 | AP22: 0 | AQ22: 0 | AR22: 0 | AS22: 0 | AT22: 0 | AU22: 0 | AV22: 0 | AW22: 0 | AX22: 0 | AY22: 0 | AZ22: 0 | BA22: 0 | BB22: 0 | BC22: 0 | BD22: 0 | BE22: 0 | BF22: 0 | BG22: 0 | BH22: 0 | BI22: 0 | BJ22: 0 | BK22: 0 | BL22: 0 | BM22: 0 | BN22: 0 | BO22: 0 | BP22: 0 | BQ22: 0 | BR22: 0 | BS22: 0 | BT22: 0 | BU22: 0 | BV22: 0 | BW22: 0 | BX22: 0 | BY22: 0 | BZ22: 0 | CA22: 0 | CB22: 0 | CC22: 0 | CD22: 0 | CE22: 0 | CF22: 0 | CG22: 0 | CH22: 0 | CI22: 0 | CJ22: 0 | CK22: 0 | CL22: 0 | CM22: 0 | CN22: 0 | CO22: 0 | CP22: 0 | CQ22: 0 | CR22: 0 | CS22: 0 | CT22: 0 | CU22: 0 | CV22: 0 | CW22: 0 | CX22: 0 | CY22: 0 | CZ22: 0 | DA22: 0 | DB22: 0 | DC22: 0 | DD22: 0 | DE22: 0 | DF22: 0 | DG22: 0 | DH22: 0 | DI22: 0 | DJ22: 0 | DK22: 0 | DL22: 0 | DM22: 0 | DN22: 0 | DO22: 0 | DP22: 0 | DQ22: 0 | DR22: 0 | DS22: 0 | DT22: 0 | DU22: 0 | DV22: 0 | DW22: 0 | DX22: 0 | DY22: 0 | DZ22: 0 | EA22: 0 | EB22: 0 | EC22: 0 | ED22: 0 | EE22: 0 | EF22: 0 | EG22: 0 | EH22: 0 | EI22: 0 | EJ22: 0 | EK22: 0 | EL22: 0 | EM22: 0 | EN22: 0 | EO22: 0 | EP22: 0 | EQ22: 0 | ER22: 0 | ES22: 0 | ET22: 0 | EU22: 0 | EV22: 0 | EW22: 0 | EX22: 0 | EY22: 0 | EZ22: 0 | FA22: 0 | FB22: 0 | FC22: 0 | FD22: 0 | FE22: 0 | FF22: 0 | FG22: 0 | FH22: 0 | FI22: 0 | FJ22: 0 | FK22: 0 | FL22: 0 | FM22: 0 | FN22: 0 | FO22: 0 | FP22: 0 | FQ22: 0 | FR22: 0 | FS22: 0 | FT22: 0 | FU22: 0 | FV22: 0 | FW22: 0 | FX22: 0 | FY22: 0 | FZ22: 0 | GA22: 0 | GB22: 0 | GC22: 0 | GD22: 0 | GE22: 0 | GF22: 0 | GG22: 0 | GH22: 0 | GI22: 0 | GJ22: 0 | GK22: 0 | GL22: 0 | GM22: 0 | GN22: 0 | GO22: 0 | GP22: 0 | GQ22: 0 | GR22: 0 | GS22: 0 | GT22: 0 | GU22: 0 | GV22: 0 | GW22: 0 | GX22: 0 | GY22: 0 | GZ22: 0 | HA22: 0 | HB22: 0 | HC22: 0 | HD22: 0 | HE22: 0 | HF22: 0 | HG22: 0 | HH22: 0 | HI22: 0 | HJ22: 1945 | HK22: =SUM(ER$4:HI$4) -> 70 | HL22: =SUM(ER22:HI22) -> 0 | HM22: =100*HL22/HK22 -> 0 | HO22: 0.34 | HP22: 1.38 | HQ22: 1.86
B23: Malaysia | C23: 0 | D23: 0 | E23: 0 | F23: 0 | G23: 0 | H23: 0 | I23: 0 | J23: 0 | K23: 0 | L23: 0 | M23: 0 | N23: 0 | O23: 0 | P23: 0 | Q23: 0 | R23: 0 | S23: 0 | T23: 0 | U23: 0 | V23: 0 | W23: 0 | X23: 0 | Y23: 0 | Z23: 0 | AA23: 0 | AB23: 0 | AC23: 0 | AD23: 0 | AE23: 0 | AF23: 0 | AG23: 0 | AH23: 0 | AI23: 0 | AJ23: 0 | AK23: 0 | AL23: 0 | AM23: 0 | AN23: 0 | AO23: 0 | AP23: 0 | AQ23: 0 | AR23: 0 | AS23: 0 | AT23: 0 | AU23: 0 | AV23: 0 | AW23: 0 | AX23: 0 | AY23: 0 | AZ23: 0 | BA23: 0 | BB23: 0 | BC23: 0 | BD23: 0 | BE23: 0 | BF23: 0 | BG23: 0 | BH23: 0 | BI23: 0 | BJ23: 0 | BK23: 0 | BL23: 0 | BM23: 0 | BN23: 0 | BO23: 0 | BP23: 0 | BQ23: 0 | BR23: 0 | BS23: 0 | BT23: 0 | BU23: 0 | BV23: 0 | BW23: 0 | BX23: 0 | BY23: 0 | BZ23: 0 | CA23: 0 | CB23: 0 | CC23: 0 | CD23: 0 | CE23: 0 | CF23: 0 | CG23: 0 | CH23: 0 | CI23: 0 | CJ23: 0 | CK23: 0 | CL23: 0 | CM23: 0 | CN23: 0 | CO23: 0 | CP23: 0 | CQ23: 0 | CR23: 0 | CS23: 0 | CT23: 0 | CU23: 0 | CV23: 0 | CW23: 0 | CX23: 0 | CY23: 0 | CZ23: 0 | DA23: 0 | DB23: 0 | DC23: 0 | DD23: 0 | DE23: 0 | DF23: 0 | DG23: 0 | DH23: 0 | DI23: 0 | DJ23: 0 | DK23: 0 | DL23: 0 | DM23: 0 | DN23: 0 | DO23: 0 | DP23: 0 | DQ23: 0 | DR23: 0 | DS23: 0 | DT23: 0 | DU23: 0 | DV23: 0 | DW23: 0 | DX23: 0 | DY23: 0 | DZ23: 0 | EA23: 0 | EB23: 0 | EC23: 0 | ED23: 0 | EE23: 0 | EF23: 0 | EG23: 0 | EH23: 0 | EI23: 0 | EJ23: 0 | EK23: 0 | EL23: 0 | EM23: 0 | EN23: 0 | EO23: 0 | EP23: 0 | EQ23: 0 | ER23: 0 | ES23: 0 | ET23: 0 | EU23: 0 | EV23: 0 | EW23: 0 | EX23: 0 | EY23: 0 | EZ23: 0 | FA23: 0 | FB23: 0 | FC23: 0 | FD23: 0 | FE23: 0 | FF23: 0 | FG23: 0 | FH23: 0 | FI23: 0 | FJ23: 0 | FK23: 0 | FL23: 0 | FM23: 0 | FN23: 0 | FO23: 0 | FP23: 0 | FQ23: 0 | FR23: 0 | FS23: 0 | FT23: 0 | FU23: 0 | FV23: 0 | FW23: 0 | FX23: 0 | FY23: 0 | FZ23: 0 | GA23: 0 | GB23: 0 | GC23: 0 | GD23: 0 | GE23: 0 | GF23: 0 | GG23: 0 | GH23: 0 | GI23: 0 | GJ23: 0 | GK23: 0 | GL23: 0 | GM23: 0 | GN23: 0 | GO23: 0 | GP23: 0 | GQ23: 0 | GR23: 0 | GS23: 0 | GT23: 0 | GU23: 0 | GV23: 0 | GW23: 0 | GX23: 0 | GY23: 0 | GZ23: 0 | HA23: 0 | HB23: 0 | HC23: 0 | HD23: 0 | HE23: 0 | HF23: 0 | HG23: 0 | HH23: 0 | HI23: 0 | HJ23: 1957 | HK23: =SUM(FD$4:HI$4) -> 58 | HL23: =SUM(FD23:HI23) -> 0 | HM23: =100*HL23/HK23 -> 0 | HO23: 0.1 | HP23: 0.33 | HQ23: 0.48
B24: Myanmar | C24: 0 | D24: 0 | E24: 0 | F24: 0 | G24: 0 | H24: 0 | I24: 0 | J24: 0 | K24: 0 | L24: 0 | M24: 0 | N24: 0 | O24: 0 | P24: 0 | Q24: 0 | R24: 0 | S24: 0 | T24: 0 | U24: 0 | V24: 0 | W24: 0 | X24: 0 | Y24: 0 | Z24: 0 | AA24: 0 | AB24: 0 | AC24: 0 | AD24: 0 | AE24: 0 | AF24: 0 | AG24: 0 | AH24: 0 | AI24: 0 | AJ24: 0 | AK24: 0 | AL24: 0 | AM24: 0 | AN24: 0 | AO24: 0 | AP24: 0 | AQ24: 0 | AR24: 0 | AS24: 0 | AT24: 0 | AU24: 0 | AV24: 0 | AW24: 0 | AX24: 0 | AY24: 0 | AZ24: 0 | BA24: 0 | BB24: 0 | BC24: 0 | BD24: 0 | BE24: 0 | BF24: 0 | BG24: 0 | BH24: 0 | BI24: 0 | BJ24: 0 | BK24: 0 | BL24: 0 | BM24: 0 | BN24: 0 | BO24: 0 | BP24: 0 | BQ24: 0 | BR24: 0 | BS24: 0 | BT24: 0 | BU24: 0 | BV24: 0 | BW24: 0 | BX24: 0 | BY24: 0 | BZ24: 0 | CA24: 0 | CB24: 0 | CC24: 0 | CD24: 0 | CE24: 0 | CF24: 0 | CG24: 0 | CH24: 0 | CI24: 0 | CJ24: 0 | CK24: 0 | CL24: 0 | CM24: 0 | CN24: 0 | CO24: 0 | CP24: 0 | CQ24: 0 | CR24: 0 | CS24: 0 | CT24: 0 | CU24: 0 | CV24: 0 | CW24: 0 | CX24: 0 | CY24: 0 | CZ24: 0 | DA24: 0 | DB24: 0 | DC24: 0 | DD24: 0 | DE24: 0 | DF24: 0 | DG24: 0 | DH24: 0 | DI24: 0 | DJ24: 0 | DK24: 0 | DL24: 0 | DM24: 0 | DN24: 0 | DO24: 0 | DP24: 0 | DQ24: 0 | DR24: 0 | DS24: 0 | DT24: 0 | DU24: 0 | DV24: 0 | DW24: 0 | DX24: 0 | DY24: 0 | DZ24: 0 | EA24: 0 | EB24: 0 | EC24: 0 | ED24: 0 | EE24: 0 | EF24: 0 | EG24: 0 | EH24: 0 | EI24: 0 | EJ24: 0 | EK24: 0 | EL24: 0 | EM24: 0 | EN24: 0 | EO24: 0 | EP24: 0 | EQ24: 0 | ER24: 0 | ES24: 0 | ET24: 0 | EU24: 0 | EV24: 0 | EW24: 0 | EX24: 0 | EY24: 0 | EZ24: 0 | FA24: 0 | FB24: 0 | FC24: 0 | FD24: 0 | FE24: 0 | FF24: 0 | FG24: 0 | FH24: 0 | FI24: 0 | FJ24: 0 | FK24: 0 | FL24: 0 | FM24: 0 | FN24: 0 | FO24: 0 | FP24: 0 | FQ24: 0 | FR24: 0 | FS24: 0 | FT24: 0 | FU24: 0 | FV24: 0 | FW24: 0 | FX24: 0 | FY24: 0 | FZ24: 0 | GA24: 0 | GB24: 0 | GC24: 0 | GD24: 0 | GE24: 0 | GF24: 0 | GG24: 0 | GH24: 0 | GI24: 0 | GJ24: 0 | GK24: 0 | GL24: 0 | GM24: 0 | GN24: 0 | GO24: 0 | GP24: 0 | GQ24: 0 | GR24: 1 | GS24: 1 | GT24: 1 | GU24: 1 | GV24: 1 | GW24: 1 | GX24: 1 | GY24: 1 | GZ24: 1 | HA24: 1 | HB24: 1 | HC24: 1 | HD24: 1 | HE24: 1 | HF24: 1 | HG24: 1 | HH24: 1 | HI24: 1 | HJ24: 1948 | HK24: =SUM(EU$4:HI$4) -> 67 | HL24: =SUM(EU24:HI24) -> 18 | HM24: =100*HL24/HK24 -> 26.865672 | HO24: 0.31 | HP24: 0.11 | HQ24: 0.21 | HS24: Note: Ongoing arrears, see IMF (2012).
B25: Philippines | C25: 0 | D25: 0 | E25: 0 | F25: 0 | G25: 0 | H25: 0 | I25: 0 | J25: 0 | K25: 0 | L25: 0 | M25: 0 | N25: 0 | O25: 0 | P25: 0 | Q25: 0 | R25: 0 | S25: 0 | T25: 0 | U25: 0 | V25: 0 | W25: 0 | X25: 0 | Y25: 0 | Z25: 0 | AA25: 0 | AB25: 0 | AC25: 0 | AD25: 0 | AE25: 0 | AF25: 0 | AG25: 0 | AH25: 0 | AI25: 0 | AJ25: 0 | AK25: 0 | AL25: 0 | AM25: 0 | AN25: 0 | AO25: 0 | AP25: 0 | AQ25: 0 | AR25: 0 | AS25: 0 | AT25: 0 | AU25: 0 | AV25: 0 | AW25: 0 | AX25: 0 | AY25: 0 | AZ25: 0 | BA25: 0 | BB25: 0 | BC25: 0 | BD25: 0 | BE25: 0 | BF25: 0 | BG25: 0 | BH25: 0 | BI25: 0 | BJ25: 0 | BK25: 0 | BL25: 0 | BM25: 0 | BN25: 0 | BO25: 0 | BP25: 0 | BQ25: 0 | BR25: 0 | BS25: 0 | BT25: 0 | BU25: 0 | BV25: 0 | BW25: 0 | BX25: 0 | BY25: 0 | BZ25: 0 | CA25: 0 | CB25: 0 | CC25: 0 | CD25: 0 | CE25: 0 | CF25: 0 | CG25: 0 | CH25: 0 | CI25: 0 | CJ25: 0 | CK25: 0 | CL25: 0 | CM25: 0 | CN25: 0 | CO25: 0 | CP25: 0 | CQ25: 0 | CR25: 0 | CS25: 0 | CT25: 0 | CU25: 0 | CV25: 0 | CW25: 0 | CX25: 0 | CY25: 0 | CZ25: 0 | DA25: 0 | DB25: 0 | DC25: 0 | DD25: 0 | DE25: 0 | DF25: 0 | DG25: 0 | DH25: 0 | DI25: 0 | DJ25: 0 | DK25: 0 | DL25: 0 | DM25: 0 | DN25: 0 | DO25: 0 | DP25: 0 | DQ25: 0 | DR25: 0 | DS25: 0 | DT25: 0 | DU25: 0 | DV25: 0 | DW25: 0 | DX25: 0 | DY25: 0 | DZ25: 0 | EA25: 0 | EB25: 0 | EC25: 0 | ED25: 0 | EE25: 0 | EF25: 0 | EG25: 0 | EH25: 0 | EI25: 0 | EJ25: 0 | EK25: 0 | EL25: 0 | EM25: 0 | EN25: 0 | EO25: 0 | EP25: 0 | EQ25: 0 | ER25: 0 | ES25: 0 | ET25: 0 | EU25: 0 | EV25: 0 | EW25: 0 | EX25: 0 | EY25: 0 | EZ25: 0 | FA25: 0 | FB25: 0 | FC25: 0 | FD25: 0 | FE25: 0 | FF25: 0 | FG25: 0 | FH25: 0 | FI25: 0 | FJ25: 0 | FK25: 0 | FL25: 0 | FM25: 0 | FN25: 0 | FO25: 0 | FP25: 0 | FQ25: 0 | FR25: 0 | FS25: 0 | FT25: 0 | FU25: 0 | FV25: 0 | FW25: 0 | FX25: 0 | FY25: 0 | FZ25: 0 | GA25: 0 | GB25: 0 | GC25: 0 | GD25: 1 | GE25: 1 | GF25: 1 | GG25: 1 | GH25: 1 | GI25: 1 | GJ25: 1 | GK25: 1 | GL25: 1 | GM25: 1 | GN25: 0 | GO25: 0 | GP25: 0 | GQ25: 0 | GR25: 0 | GS25: 0 | GT25: 0 | GU25: 0 | GV25: 0 | GW25: 0 | GX25: 0 | GY25: 0 | GZ25: 0 | HA25: 0 | HB25: 0 | HC25: 0 | HD25: 0 | HE25: 0 | HF25: 0 | HG25: 0 | HJ25: 1946 | HK25: =SUM(ES$4:HI$4) -> 69 | HL25: =SUM(ES25:HI25) -> 10 | HM25: =100*HL25/HK25 -> 14.492754 | HO25: 0.34 | HP25: 0.53 | HQ25: 0.53
B26: Singapore | C26: 0 | D26: 0 | E26: 0 | F26: 0 | G26: 0 | H26: 0 | I26: 0 | J26: 0 | K26: 0 | L26: 0 | M26: 0 | N26: 0 | O26: 0 | P26: 0 | Q26: 0 | R26: 0 | S26: 0 | T26: 0 | U26: 0 | V26: 0 | W26: 0 | X26: 0 | Y26: 0 | Z26: 0 | AA26: 0 | AB26: 0 | AC26: 0 | AD26: 0 | AE26: 0 | AF26: 0 | AG26: 0 | AH26: 0 | AI26: 0 | AJ26: 0 | AK26: 0 | AL26: 0 | AM26: 0 | AN26: 0 | AO26: 0 | AP26: 0 | AQ26: 0 | AR26: 0 | AS26: 0 | AT26: 0 | AU26: 0 | AV26: 0 | AW26: 0 | AX26: 0 | AY26: 0 | AZ26: 0 | BA26: 0 | BB26: 0 | BC26: 0 | BD26: 0 | BE26: 0 | BF26: 0 | BG26: 0 | BH26: 0 | BI26: 0 | BJ26: 0 | BK26: 0 | BL26: 0 | BM26: 0 | BN26: 0 | BO26: 0 | BP26: 0 | BQ26: 0 | BR26: 0 | BS26: 0 | BT26: 0 | BU26: 0 | BV26: 0 | BW26: 0 | BX26: 0 | BY26: 0 | BZ26: 0 | CA26: 0 | CB26: 0 | CC26: 0 | CD26: 0 | CE26: 0 | CF26: 0 | CG26: 0 | CH26: 0 | CI26: 0 | CJ26: 0 | CK26: 0 | CL26: 0 | CM26: 0 | CN26: 0 | CO26: 0 | CP26: 0 | CQ26: 0 | CR26: 0 | CS26: 0 | CT26: 0 | CU26: 0 | CV26: 0 | CW26: 0 | CX26: 0 | CY26: 0 | CZ26: 0 | DA26: 0 | DB26: 0 | DC26: 0 | DD26: 0 | DE26: 0 | DF26: 0 | DG26: 0 | DH26: 0 | DI26: 0 | DJ26: 0 | DK26: 0 | DL26: 0 | DM26: 0 | DN26: 0 | DO26: 0 | DP26: 0 | DQ26: 0 | DR26: 0 | DS26: 0 | DT26: 0 | DU26: 0 | DV26: 0 | DW26: 0 | DX26: 0 | DY26: 0 | DZ26: 0 | EA26: 0 | EB26: 0 | EC26: 0 | ED26: 0 | EE26: 0 | EF26: 0 | EG26: 0 | EH26: 0 | EI26: 0 | EJ26: 0 | EK26: 0 | EL26: 0 | EM26: 0 | EN26: 0 | EO26: 0 | EP26: 0 | EQ26: 0 | ER26: 0 | ES26: 0 | ET26: 0 | EU26: 0 | EV26: 0 | EW26: 0 | EX26: 0 | EY26: 0 | EZ26: 0 | FA26: 0 | FB26: 0 | FC26: 0 | FD26: 0 | FE26: 0 | FF26: 0 | FG26: 0 | FH26: 0 | FI26: 0 | FJ26: 0 | FK26: 0 | FL26: 0 | FM26: 0 | FN26: 0 | FO26: 0 | FP26: 0 | FQ26: 0 | FR26: 0 | FS26: 0 | FT26: 0 | FU26: 0 | FV26: 0 | FW26: 0 | FX26: 0 | FY26: 0 | FZ26: 0 | GA26: 0 | GB26: 0 | GC26: 0 | GD26: 0 | GE26: 0 | GF26: 0 | GG26: 0 | GH26: 0 | GI26: 0 | GJ26: 0 | GK26: 0 | GL26: 0 | GM26: 0 | GN26: 0 | GO26: 0 | GP26: 0 | GQ26: 0 | GR26: 0 | GS26: 0 | GT26: 0 | GU26: 0 | GV26: 0 | GW26: 0 | GX26: 0 | GY26: 0 | GZ26: 0 | HA26: 0 | HB26: 0 | HC26: 0 | HD26: 0 | HE26: 0 | HF26: 0 | HG26: 0 | HJ26: 1965 | HK26: =SUM(FL$4:HI4) -> 50 | HL26: =SUM(FL26:HI26) -> 0 | HM26: =100*HL26/HK26 -> 0 | HO26: 0.02 | HP26: 0.16 | HQ26: 0.23
B27: Sri Lanka | C27: 0 | D27: 0 | E27: 0 | F27: 0 | G27: 0 | H27: 0 | I27: 0 | J27: 0 | K27: 0 | L27: 0 | M27: 0 | N27: 0 | O27: 0 | P27: 0 | Q27: 0 | R27: 0 | S27: 0 | T27: 0 | U27: 0 | V27: 0 | W27: 0 | X27: 0 | Y27: 0 | Z27: 0 | AA27: 0 | AB27: 0 | AC27: 0 | AD27: 0 | AE27: 0 | AF27: 0 | AG27: 0 | AH27: 0 | AI27: 0 | AJ27: 0 | AK27: 0 | AL27: 0 | AM27: 0 | AN27: 0 | AO27: 0 | AP27: 0 | AQ27: 0 | AR27: 0 | AS27: 0 | AT27: 0 | AU27: 0 | AV27: 0 | AW27: 0 | AX27: 0 | AY27: 0 | AZ27: 0 | BA27: 0 | BB27: 0 | BC27: 0 | BD27: 0 | BE27: 0 | BF27: 0 | BG27: 0 | BH27: 0 | BI27: 0 | BJ27: 0 | BK27: 0 | BL27: 0 | BM27: 0 | BN27: 0 | BO27: 0 | BP27: 0 | BQ27: 0 | BR27: 0 | BS27: 0 | BT27: 0 | BU27: 0 | BV27: 0 | BW27: 0 | BX27: 0 | BY27: 0 | BZ27: 0 | CA27: 0 | CB27: 0 | CC27: 0 | CD27: 0 | CE27: 0 | CF27: 0 | CG27: 0 | CH27: 0 | CI27: 0 | CJ27: 0 | CK27: 0 | CL27: 0 | CM27: 0 | CN27: 0 | CO27: 0 | CP27: 0 | CQ27: 0 | CR27: 0 | CS27: 0 | CT27: 0 | CU27: 0 | CV27: 0 | CW27: 0 | CX27: 0 | CY27: 0 | CZ27: 0 | DA27: 0 | DB27: 0 | DC27: 0 | DD27: 0 | DE27: 0 | DF27: 0 | DG27: 0 | DH27: 0 | DI27: 0 | DJ27: 0 | DK27: 0 | DL27: 0 | DM27: 0 | DN27: 0 | DO27: 0 | DP27: 0 | DQ27: 0 | DR27: 0 | DS27: 0 | DT27: 0 | DU27: 0 | DV27: 0 | DW27: 0 | DX27: 0 | DY27: 0 | DZ27: 0 | EA27: 0 | EB27: 0 | EC27: 0 | ED27: 0 | EE27: 0 | EF27: 0 | EG27: 0 | EH27: 0 | EI27: 0 | EJ27: 0 | EK27: 0 | EL27: 0 | EM27: 0 | EN27: 0 | EO27: 0 | EP27: 0 | EQ27: 0 | ER27: 0 | ES27: 0 | ET27: 0 | EU27: 0 | EV27: 0 | EW27: 0 | EX27: 0 | EY27: 0 | EZ27: 0 | FA27: 0 | FB27: 0 | FC27: 0 | FD27: 0 | FE27: 0 | FF27: 0 | FG27: 0 | FH27: 0 | FI27: 0 | FJ27: 0 | FK27: 0 | FL27: 0 | FM27: 0 | FN27: 0 | FO27: 0 | FP27: 0 | FQ27: 0 | FR27: 0 | FS27: 0 | FT27: 0 | FU27: 0 | FV27: 0 | FW27: 0 | FX27: 0 | FY27: 0 | FZ27: 1 | GA27: 0 | GB27: 1 | GC27: 1 | GD27: 1 | GE27: 0 | GF27: 0 | GG27: 0 | GH27: 0 | GI27: 0 | GJ27: 0 | GK27: 0 | GL27: 0 | GM27: 0 | GN27: 0 | GO27: 0 | GP27: 0 | GQ27: 0 | GR27: 0 | GS27: 0 | GT27: 0 | GU27: 0 | GV27: 0 | GW27: 0 | GX27: 0 | GY27: 0 | GZ27: 0 | HA27: 0 | HB27: 0 | HC27: 0 | HD27: 0 | HE27: 0 | HF27: 0 | HG27: 0 | HJ27: 1948 | HK27: =SUM(EU$4:HI$4) -> 67 | HL27: =SUM(EU27:HI27) -> 4 | HM27: =100*HL27/HK27 -> 5.9701493 | HO27: 0.22 | HP27: 0.16 | HQ27: 0.19
B28: Taiwan | C28: 0 | D28: 0 | E28: 0 | F28: 0 | G28: 0 | H28: 0 | I28: 0 | J28: 0 | K28: 0 | L28: 0 | M28: 0 | N28: 0 | O28: 0 | P28: 0 | Q28: 0 | R28: 0 | S28: 0 | T28: 0 | U28: 0 | V28: 0 | W28: 0 | X28: 0 | Y28: 0 | Z28: 0 | AA28: 0 | AB28: 0 | AC28: 0 | AD28: 0 | AE28: 0 | AF28: 0 | AG28: 0 | AH28: 0 | AI28: 0 | AJ28: 0 | AK28: 0 | AL28: 0 | AM28: 0 | AN28: 0 | AO28: 0 | AP28: 0 | AQ28: 0 | AR28: 0 | AS28: 0 | AT28: 0 | AU28: 0 | AV28: 0 | AW28: 0 | AX28: 0 | AY28: 0 | AZ28: 0 | BA28: 0 | BB28: 0 | BC28: 0 | BD28: 0 | BE28: 0 | BF28: 0 | BG28: 0 | BH28: 0 | BI28: 0 | BJ28: 0 | BK28: 0 | BL28: 0 | BM28: 0 | BN28: 0 | BO28: 0 | BP28: 0 | BQ28: 0 | BR28: 0 | BS28: 0 | BT28: 0 | BU28: 0 | BV28: 0 | BW28: 0 | BX28: 0 | BY28: 0 | BZ28: 0 | CA28: 0 | CB28: 0 | CC28: 0 | CD28: 0 | CE28: 0 | CF28: 0 | CG28: 0 | CH28: 0 | CI28: 0 | CJ28: 0 | CK28: 0 | CL28: 0 | CM28: 0 | CN28: 0 | CO28: 0 | CP28: 0 | CQ28: 0 | CR28: 0 | CS28: 0 | CT28: 0 | CU28: 0 | CV28: 0 | CW28: 0 | CX28: 0 | CY28: 0 | CZ28: 0 | DA28: 0 | DB28: 0 | DC28: 0 | DD28: 0 | DE28: 0 | DF28: 0 | DG28: 0 | DH28: 0 | DI28: 0 | DJ28: 0 | DK28: 0 | DL28: 0 | DM28: 0 | DN28: 0 | DO28: 0 | DP28: 0 | DQ28: 0 | DR28: 0 | DS28: 0 | DT28: 0 | DU28: 0 | DV28: 0 | DW28: 0 | DX28: 0 | DY28: 0 | DZ28: 0 | EA28: 0 | EB28: 0 | EC28: 0 | ED28: 0 | EE28: 0 | EF28: 0 | EG28: 0 | EH28: 0 | EI28: 0 | EJ28: 0 | EK28: 0 | EL28: 0 | EM28: 0 | EN28: 0 | EO28: 0 | EP28: 0 | EQ28: 0 | ER28: 0 | ES28: 0 | ET28: 0 | EU28: 0 | EV28: 0 | EW28: 0 | EX28: 0 | EY28: 0 | EZ28: 0 | FA28: 0 | FB28: 0 | FC28: 0 | FD28: 0 | FE28: 0 | FF28: 0 | FG28: 0 | FH28: 0 | FI28: 0 | FJ28: 0 | FK28: 0 | FL28: 0 | FM28: 0 | FN28: 0 | FO28: 0 | FP28: 0 | FQ28: 0 | FR28: 0 | FS28: 0 | FT28: 0 | FU28: 0 | FV28: 0 | FW28: 0 | FX28: 0 | FY28: 0 | FZ28: 0 | GA28: 0 | GB28: 0 | GC28: 0 | GD28: 0 | GE28: 0 | GF28: 0 | GG28: 0 | GH28: 0 | GI28: 0 | GJ28: 0 | GK28: 0 | GL28: 0 | GM28: 0 | GN28: 0 | GO28: 0 | GP28: 0 | GQ28: 0 | GR28: 0 | GS28: 0 | GT28: 0 | GU28: 0 | GV28: 0 | GW28: 0 | GX28: 0 | GY28: 0 | GZ28: 0 | HA28: 0 | HB28: 0 | HC28: 0 | HD28: 0 | HE28: 0 | HF28: 0 | HG28: 0 | HJ28: 1949 | HK28: =SUM(EV$4:HI$4) -> 66 | HL28: =SUM(EV28:HI28) -> 0 | HM28: =100*HL28/HK28 -> 0 | HO28: 0.09 | HP28: 0.74 | HQ28: 0.96
B29: Thailand | C29: 0 | D29: 0 | E29: 0 | F29: 0 | G29: 0 | H29: 0 | I29: 0 | J29: 0 | K29: 0 | L29: 0 | M29: 0 | N29: 0 | O29: 0 | P29: 0 | Q29: 0 | R29: 0 | S29: 0 | T29: 0 | U29: 0 | V29: 0 | W29: 0 | X29: 0 | Y29: 0 | Z29: 0 | AA29: 0 | AB29: 0 | AC29: 0 | AD29: 0 | AE29: 0 | AF29: 0 | AG29: 0 | AH29: 0 | AI29: 0 | AJ29: 0 | AK29: 0 | AL29: 0 | AM29: 0 | AN29: 0 | AO29: 0 | AP29: 0 | AQ29: 0 | AR29: 0 | AS29: 0 | AT29: 0 | AU29: 0 | AV29: 0 | AW29: 0 | AX29: 0 | AY29: 0 | AZ29: 0 | BA29: 0 | BB29: 0 | BC29: 0 | BD29: 0 | BE29: 0 | BF29: 0 | BG29: 0 | BH29: 0 | BI29: 0 | BJ29: 0 | BK29: 0 | BL29: 0 | BM29: 0 | BN29: 0 | BO29: 0 | BP29: 0 | BQ29: 0 | BR29: 0 | BS29: 0 | BT29: 0 | BU29: 0 | BV29: 0 | BW29: 0 | BX29: 0 | BY29: 0 | BZ29: 0 | CA29: 0 | CB29: 0 | CC29: 0 | CD29: 0 | CE29: 0 | CF29: 0 | CG29: 0 | CH29: 0 | CI29: 0 | CJ29: 0 | CK29: 0 | CL29: 0 | CM29: 0 | CN29: 0 | CO29: 0 | CP29: 0 | CQ29: 0 | CR29: 0 | CS29: 0 | CT29: 0 | CU29: 0 | CV29: 0 | CW29: 0 | CX29: 0 | CY29: 0 | CZ29: 0 | DA29: 0 | DB29: 0 | DC29: 0 | DD29: 0 | DE29: 0 | DF29: 0 | DG29: 0 | DH29: 0 | DI29: 0 | DJ29: 0 | DK29: 0 | DL29: 0 | DM29: 0 | DN29: 0 | DO29: 0 | DP29: 0 | DQ29: 0 | DR29: 0 | DS29: 0 | DT29: 0 | DU29: 0 | DV29: 0 | DW29: 0 | DX29: 0 | DY29: 0 | DZ29: 0 | EA29: 0 | EB29: 0 | EC29: 0 | ED29: 0 | EE29: 0 | EF29: 0 | EG29: 0 | EH29: 0 | EI29: 0 | EJ29: 0 | EK29: 0 | EL29: 0 | EM29: 0 | EN29: 0 | EO29: 0 | EP29: 0 | EQ29: 0 | ER29: 0 | ES29: 0 | ET29: 0 | EU29: 0 | EV29: 0 | EW29: 0 | EX29: 0 | EY29: 0 | EZ29: 0 | FA29: 0 | FB29: 0 | FC29: 0 | FD29: 0 | FE29: 0 | FF29: 0 | FG29: 0 | FH29: 0 | FI29: 0 | FJ29: 0 | FK29: 0 | FL29: 0 | FM29: 0 | FN29: 0 | FO29: 0 | FP29: 0 | FQ29: 0 | FR29: 0 | FS29: 0 | FT29: 0 | FU29: 0 | FV29: 0 | FW29: 0 | FX29: 0 | FY29: 0 | FZ29: 0 | GA29: 0 | GB29: 0 | GC29: 0 | GD29: 0 | GE29: 0 | GF29: 0 | GG29: 0 | GH29: 0 | GI29: 0 | GJ29: 0 | GK29: 0 | GL29: 0 | GM29: 0 | GN29: 0 | GO29: 0 | GP29: 0 | GQ29: 0 | GR29: 0 | GS29: 0 | GT29: 0 | GU29: 0 | GV29: 0 | GW29: 0 | GX29: 0 | GY29: 0 | GZ29: 0 | HA29: 0 | HB29: 0 | HC29: 0 | HD29: 0 | HE29: 0 | HF29: 0 | HG29: 0 | HJ29: 1769 | HK29: =SUM(C$4:HI$4) -> 215 | HL29: =SUM(C29:HI29) -> 0 | HM29: =100*HL29/HK29 -> 0 | HO29: 0.27 | HP29: 0.94 | HQ29: 1.12
A30: Europe | B30: Austria | C30: 0 | D30: 0 | E30: 1 | F30: 1 | G30: 1 | H30: 1 | I30: 1 | J30: 1 | K30: 1 | L30: 1 | M30: 1 | N30: 1 | O30: 1 | P30: 1 | Q30: 1 | R30: 1 | S30: 1 | T30: 0 | U30: 0 | V30: 0 | W30: 0 | X30: 0 | Y30: 0 | Z30: 0 | AA30: 0 | AB30: 0 | AC30: 0 | AD30: 0 | AE30: 0 | AF30: 0 | AG30: 0 | AH30: 0 | AI30: 0 | AJ30: 0 | AK30: 0 | AL30: 0 | AM30: 0 | AN30: 0 | AO30: 0 | AP30: 0 | AQ30: 0 | AR30: 0 | AS30: 0 | AT30: 0 | AU30: 0 | AV30: 0 | AW30: 0 | AX30: 0 | AY30: 0 | AZ30: 0 | BA30: 0 | BB30: 0 | BC30: 0 | BD30: 0 | BE30: 0 | BF30: 0 | BG30: 0 | BH30: 0 | BI30: 0 | BJ30: 0 | BK30: 0 | BL30: 0 | BM30: 0 | BN30: 0 | BO30: 0 | BP30: 0 | BQ30: 0 | BR30: 0 | BS30: 1 | BT30: 1 | BU30: 1 | BV30: 0 | BW30: 0 | BX30: 0 | BY30: 0 | BZ30: 0 | CA30: 0 | CB30: 0 | CC30: 0 | CD30: 0 | CE30: 0 | CF30: 0 | CG30: 0 | CH30: 0 | CI30: 0 | CJ30: 0 | CK30: 0 | CL30: 0 | CM30: 0 | CN30: 0 | CO30: 0 | CP30: 0 | CQ30: 0 | CR30: 0 | CS30: 0 | CT30: 0 | CU30: 0 | CV30: 0 | CW30: 0 | CX30: 0 | CY30: 0 | CZ30: 0 | DA30: 0 | DB30: 0 | DC30: 0 | DD30: 0 | DE30: 0 | DF30: 0 | DG30: 0 | DH30: 0 | DI30: 0 | DJ30: 0 | DK30: 0 | DL30: 0 | DM30: 1 | DN30: 1 | DO30: 0 | DP30: 0 | DQ30: 0 | DR30: 0 | DS30: 0 | DT30: 0 | DU30: 0 | DV30: 0 | DW30: 0 | DX30: 0 | DY30: 0 | DZ30: 0 | EA30: 0 | EB30: 0 | EC30: 0 | ED30: 0 | EE30: 1 | EF30: 1 | EG30: 0 | EH30: 0 | EI30: 0 | EJ30: 0 | EK30: 1 | EL30: 0 | EM30: 1 | EN30: 1 | EO30: 1 | EP30: 1 | EQ30: 1 | ER30: 1 | ES30: 1 | ET30: 1 | EU30: 1 | EV30: 1 | EW30: 1 | EX30: 1 | EY30: 1 | EZ30: 0 | FA30: 0 | FB30: 0 | FC30: 0 | FD30: 0 | FE30: 0 | FF30: 0 | FG30: 0 | FH30: 0 | FI30: 0 | FJ30: 0 | FK30: 0 | FL30: 0 | FM30: 0 | FN30: 0 | FO30: 0 | FP30: 0 | FQ30: 0 | FR30: 0 | FS30: 0 | FT30: 0 | FU30: 0 | FV30: 0 | FW30: 0 | FX30: 0 | FY30: 0 | FZ30: 0 | GA30: 0 | GB30: 0 | GC30: 0 | GD30: 0 | GE30: 0 | GF30: 0 | GG30: 0 | GH30: 0 | GI30: 0 | GJ30: 0 | GK30: 0 | GL30: 0 | GM30: 0 | GN30: 0 | GO30: 0 | GP30: 0 | GQ30: 0 | GR30: 0 | GS30: 0 | GT30: 0 | GU30: 0 | GV30: 0 | GW30: 0 | GX30: 0 | GY30: 0 | GZ30: 0 | HA30: 0 | HB30: 0 | HC30: 0 | HD30: 0 | HE30: 0 | HF30: 0 | HG30: 0 | HH30: 0 | HI30: 0 | HJ30: 1282 | HK30: =SUM(C$4:HI$4) -> 215 | HL30: =SUM(C30:HI30) -> 36 | HM30: =100*HL30/HK30 -> 16.744186 | HO30: 0.86 | HP30: 0.48 | HQ30: 0.43
B31: Belgium | C31: 0 | D31: 0 | E31: 0 | F31: 0 | G31: 0 | H31: 0 | I31: 0 | J31: 0 | K31: 0 | L31: 0 | M31: 0 | N31: 0 | O31: 0 | P31: 0 | Q31: 0 | R31: 0 | S31: 0 | T31: 0 | U31: 0 | V31: 0 | W31: 0 | X31: 0 | Y31: 0 | Z31: 0 | AA31: 0 | AB31: 0 | AC31: 0 | AD31: 0 | AE31: 0 | AF31: 0 | AG31: 0 | AH31: 0 | AI31: 0 | AJ31: 0 | AK31: 0 | AL31: 0 | AM31: 0 | AN31: 0 | AO31: 0 | AP31: 0 | AQ31: 0 | AR31: 0 | AS31: 0 | AT31: 0 | AU31: 0 | AV31: 0 | AW31: 0 | AX31: 0 | AY31: 0 | AZ31: 0 | BA31: 0 | BB31: 0 | BC31: 0 | BD31: 0 | BE31: 0 | BF31: 0 | BG31: 0 | BH31: 0 | BI31: 0 | BJ31: 0 | BK31: 0 | BL31: 0 | BM31: 0 | BN31: 0 | BO31: 0 | BP31: 0 | BQ31: 0 | BR31: 0 | BS31: 0 | BT31: 0 | BU31: 0 | BV31: 0 | BW31: 0 | BX31: 0 | BY31: 0 | BZ31: 0 | CA31: 0 | CB31: 0 | CC31: 0 | CD31: 0 | CE31: 0 | CF31: 0 | CG31: 0 | CH31: 0 | CI31: 0 | CJ31: 0 | CK31: 0 | CL31: 0 | CM31: 0 | CN31: 0 | CO31: 0 | CP31: 0 | CQ31: 0 | CR31: 0 | CS31: 0 | CT31: 0 | CU31: 0 | CV31: 0 | CW31: 0 | CX31: 0 | CY31: 0 | CZ31: 0 | DA31: 0 | DB31: 0 | DC31: 0 | DD31: 0 | DE31: 0 | DF31: 0 | DG31: 0 | DH31: 0 | DI31: 0 | DJ31: 0 | DK31: 0 | DL31: 0 | DM31: 0 | DN31: 0 | DO31: 0 | DP31: 0 | DQ31: 0 | DR31: 0 | DS31: 0 | DT31: 0 | DU31: 0 | DV31: 0 | DW31: 0 | DX31: 0 | DY31: 0 | DZ31: 0 | EA31: 0 | EB31: 0 | EC31: 0 | ED31: 0 | EE31: 0 | EF31: 0 | EG31: 0 | EH31: 0 | EI31: 0 | EJ31: 0 | EK31: 0 | EL31: 0 | EM31: 0 | EN31: 0 | EO31: 0 | EP31: 0 | EQ31: 0 | ER31: 0 | ES31: 0 | ET31: 0 | EU31: 0 | EV31: 0 | EW31: 0 | EX31: 0 | EY31: 0 | EZ31: 0 | FA31: 0 | FB31: 0 | FC31: 0 | FD31: 0 | FE31: 0 | FF31: 0 | FG31: 0 | FH31: 0 | FI31: 0 | FJ31: 0 | FK31: 0 | FL31: 0 | FM31: 0 | FN31: 0 | FO31: 0 | FP31: 0 | FQ31: 0 | FR31: 0 | FS31: 0 | FT31: 0 | FU31: 0 | FV31: 0 | FW31: 0 | FX31: 0 | FY31: 0 | FZ31: 0 | GA31: 0 | GB31: 0 | GC31: 0 | GD31: 0 | GE31: 0 | GF31: 0 | GG31: 0 | GH31: 0 | GI31: 0 | GJ31: 0 | GK31: 0 | GL31: 0 | GM31: 0 | GN31: 0 | GO31: 0 | GP31: 0 | GQ31: 0 | GR31: 0 | GS31: 0 | GT31: 0 | GU31: 0 | GV31: 0 | GW31: 0 | GX31: 0 | GY31: 0 | GZ31: 0 | HA31: 0 | HB31: 0 | HC31: 0 | HD31: 0 | HE31: 0 | HF31: 0 | HG31: 0 | HH31: 0 | HI31: 0 | HJ31: 1830 | HK31: =SUM(AG$4:HI$4) -> 185 | HL31: =SUM(AG31:HI31) -> 0 | HM31: =100*HL31/HK31 -> 0 | HO31: 1.18 | HP31: 0.63 | HQ31: 0.54
B32: Denmark | C32: 0 | D32: 0 | E32: 0 | F32: 0 | G32: 0 | H32: 0 | I32: 0 | J32: 0 | K32: 0 | L32: 0 | M32: 0 | N32: 0 | O32: 0 | P32: 0 | Q32: 0 | R32: 0 | S32: 0 | T32: 0 | U32: 0 | V32: 0 | W32: 0 | X32: 0 | Y32: 0 | Z32: 0 | AA32: 0 | AB32: 0 | AC32: 0 | AD32: 0 | AE32: 0 | AF32: 0 | AG32: 0 | AH32: 0 | AI32: 0 | AJ32: 0 | AK32: 0 | AL32: 0 | AM32: 0 | AN32: 0 | AO32: 0 | AP32: 0 | AQ32: 0 | AR32: 0 | AS32: 0 | AT32: 0 | AU32: 0 | AV32: 0 | AW32: 0 | AX32: 0 | AY32: 0 | AZ32: 0 | BA32: 0 | BB32: 0 | BC32: 0 | BD32: 0 | BE32: 0 | BF32: 0 | BG32: 0 | BH32: 0 | BI32: 0 | BJ32: 0 | BK32: 0 | BL32: 0 | BM32: 0 | BN32: 0 | BO32: 0 | BP32: 0 | BQ32: 0 | BR32: 0 | BS32: 0 | BT32: 0 | BU32: 0 | BV32: 0 | BW32: 0 | BX32: 0 | BY32: 0 | BZ32: 0 | CA32: 0 | CB32: 0 | CC32: 0 | CD32: 0 | CE32: 0 | CF32: 0 | CG32: 0 | CH32: 0 | CI32: 0 | CJ32: 0 | CK32: 0 | CL32: 0 | CM32: 0 | CN32: 0 | CO32: 0 | CP32: 0 | CQ32: 0 | CR32: 0 | CS32: 0 | CT32: 0 | CU32: 0 | CV32: 0 | CW32: 0 | CX32: 0 | CY32: 0 | CZ32: 0 | DA32: 0 | DB32: 0 | DC32: 0 | DD32: 0 | DE32: 0 | DF32: 0 | DG32: 0 | DH32: 0 | DI32: 0 | DJ32: 0 | DK32: 0 | DL32: 0 | DM32: 0 | DN32: 0 | DO32: 0 | DP32: 0 | DQ32: 0 | DR32: 0 | DS32: 0 | DT32: 0 | DU32: 0 | DV32: 0 | DW32: 0 | DX32: 0 | DY32: 0 | DZ32: 0 | EA32: 0 | EB32: 0 | EC32: 0 | ED32: 0 | EE32: 0 | EF32: 0 | EG32: 0 | EH32: 0 | EI32: 0 | EJ32: 0 | EK32: 0 | EL32: 0 | EM32: 0 | EN32: 0 | EO32: 0 | EP32: 0 | EQ32: 0 | ER32: 0 | ES32: 0 | ET32: 0 | EU32: 0 | EV32: 0 | EW32: 0 | EX32: 0 | EY32: 0 | EZ32: 0 | FA32: 0 | FB32: 0 | FC32: 0 | FD32: 0 | FE32: 0 | FF32: 0 | FG32: 0 | FH32: 0 | FI32: 0 | FJ32: 0 | FK32: 0 | FL32: 0 | FM32: 0 | FN32: 0 | FO32: 0 | FP32: 0 | FQ32: 0 | FR32: 0 | FS32: 0 | FT32: 0 | FU32: 0 | FV32: 0 | FW32: 0 | FX32: 0 | FY32: 0 | FZ32: 0 | GA32: 0 | GB32: 0 | GC32: 0 | GD32: 0 | GE32: 0 | GF32: 0 | GG32: 0 | GH32: 0 | GI32: 0 | GJ32: 0 | GK32: 0 | GL32: 0 | GM32: 0 | GN32: 0 | GO32: 0 | GP32: 0 | GQ32: 0 | GR32: 0 | GS32: 0 | GT32: 0 | GU32: 0 | GV32: 0 | GW32: 0 | GX32: 0 | GY32: 0 | GZ32: 0 | HA32: 0 | HB32: 0 | HC32: 0 | HD32: 0 | HE32: 0 | HF32: 0 | HG32: 0 | HH32: 0 | HI32: 0 | HJ32: 980 | HK32: =SUM(C$4:HI$4) -> 215 | HL32: =SUM(C32:HI32) -> 0 | HM32: =100*HL32/HK32 -> 0 | HO32: 0.43 | HP32: 0.35 | HQ32: 0.31
B33: Finland | C33: 0 | D33: 0 | E33: 0 | F33: 0 | G33: 0 | H33: 0 | I33: 0 | J33: 0 | K33: 0 | L33: 0 | M33: 0 | N33: 0 | O33: 0 | P33: 0 | Q33: 0 | R33: 0 | S33: 0 | T33: 0 | U33: 0 | V33: 0 | W33: 0 | X33: 0 | Y33: 0 | Z33: 0 | AA33: 0 | AB33: 0 | AC33: 0 | AD33: 0 | AE33: 0 | AF33: 0 | AG33: 0 | AH33: 0 | AI33: 0 | AJ33: 0 | AK33: 0 | AL33: 0 | AM33: 0 | AN33: 0 | AO33: 0 | AP33: 0 | AQ33: 0 | AR33: 0 | AS33: 0 | AT33: 0 | AU33: 0 | AV33: 0 | AW33: 0 | AX33: 0 | AY33: 0 | AZ33: 0 | BA33: 0 | BB33: 0 | BC33: 0 | BD33: 0 | BE33: 0 | BF33: 0 | BG33: 0 | BH33: 0 | BI33: 0 | BJ33: 0 | BK33: 0 | BL33: 0 | BM33: 0 | BN33: 0 | BO33: 0 | BP33: 0 | BQ33: 0 | BR33: 0 | BS33: 0 | BT33: 0 | BU33: 0 | BV33: 0 | BW33: 0 | BX33: 0 | BY33: 0 | BZ33: 0 | CA33: 0 | CB33: 0 | CC33: 0 | CD33: 0 | CE33: 0 | CF33: 0 | CG33: 0 | CH33: 0 | CI33: 0 | CJ33: 0 | CK33: 0 | CL33: 0 | CM33: 0 | CN33: 0 | CO33: 0 | CP33: 0 | CQ33: 0 | CR33: 0 | CS33: 0 | CT33: 0 | CU33: 0 | CV33: 0 | CW33: 0 | CX33: 0 | CY33: 0 | CZ33: 0 | DA33: 0 | DB33: 0 | DC33: 0 | DD33: 0 | DE33: 0 | DF33: 0 | DG33: 0 | DH33: 0 | DI33: 0 | DJ33: 0 | DK33: 0 | DL33: 0 | DM33: 0 | DN33: 0 | DO33: 0 | DP33: 0 | DQ33: 0 | DR33: 0 | DS33: 0 | DT33: 0 | DU33: 0 | DV33: 0 | DW33: 0 | DX33: 0 | DY33: 0 | DZ33: 0 | EA33: 0 | EB33: 0 | EC33: 0 | ED33: 0 | EE33: 0 | EF33: 0 | EG33: 0 | EH33: 0 | EI33: 0 | EJ33: 0 | EK33: 0 | EL33: 0 | EM33: 0 | EN33: 0 | EO33: 0 | EP33: 0 | EQ33: 0 | ER33: 0 | ES33: 0 | ET33: 0 | EU33: 0 | EV33: 0 | EW33: 0 | EX33: 0 | EY33: 0 | EZ33: 0 | FA33: 0 | FB33: 0 | FC33: 0 | FD33: 0 | FE33: 0 | FF33: 0 | FG33: 0 | FH33: 0 | FI33: 0 | FJ33: 0 | FK33: 0 | FL33: 0 | FM33: 0 | FN33: 0 | FO33: 0 | FP33: 0 | FQ33: 0 | FR33: 0 | FS33: 0 | FT33: 0 | FU33: 0 | FV33: 0 | FW33: 0 | FX33: 0 | FY33: 0 | FZ33: 0 | GA33: 0 | GB33: 0 | GC33: 0 | GD33: 0 | GE33: 0 | GF33: 0 | GG33: 0 | GH33: 0 | GI33: 0 | GJ33: 0 | GK33: 0 | GL33: 0 | GM33: 0 | GN33: 0 | GO33: 0 | GP33: 0 | GQ33: 0 | GR33: 0 | GS33: 0 | GT33: 0 | GU33: 0 | GV33: 0 | GW33: 0 | GX33: 0 | GY33: 0 | GZ33: 0 | HA33: 0 | HB33: 0 | HC33: 0 | HD33: 0 | HE33: 0 | HF33: 0 | HG33: 0 | HH33: 0 | HI33: 0 | HJ33: 1917 | HK33: =SUM(DP$4:HI$4) -> 98 | HL33: =SUM(DP33:HI33) -> 0 | HM33: =100*HL33/HK33 -> 0 | HO33: 0.23 | HP33: 0.31 | HQ33: 0.26
B34: France | C34: 0 | D34: 0 | E34: 0 | F34: 0 | G34: 0 | H34: 0 | I34: 0 | J34: 0 | K34: 0 | L34: 0 | M34: 0 | N34: 0 | O34: 1 | P34: 0 | Q34: 0 | R34: 0 | S34: 0 | T34: 0 | U34: 0 | V34: 0 | W34: 0 | X34: 0 | Y34: 0 | Z34: 0 | AA34: 0 | AB34: 0 | AC34: 0 | AD34: 0 | AE34: 0 | AF34: 0 | AG34: 0 | AH34: 0 | AI34: 0 | AJ34: 0 | AK34: 0 | AL34: 0 | AM34: 0 | AN34: 0 | AO34: 0 | AP34: 0 | AQ34: 0 | AR34: 0 | AS34: 0 | AT34: 0 | AU34: 0 | AV34: 0 | AW34: 0 | AX34: 0 | AY34: 0 | AZ34: 0 | BA34: 0 | BB34: 0 | BC34: 0 | BD34: 0 | BE34: 0 | BF34: 0 | BG34: 0 | BH34: 0 | BI34: 0 | BJ34: 0 | BK34: 0 | BL34: 0 | BM34: 0 | BN34: 0 | BO34: 0 | BP34: 0 | BQ34: 0 | BR34: 0 | BS34: 0 | BT34: 0 | BU34: 0 | BV34: 0 | BW34: 0 | BX34: 0 | BY34: 0 | BZ34: 0 | CA34: 0 | CB34: 0 | CC34: 0 | CD34: 0 | CE34: 0 | CF34: 0 | CG34: 0 | CH34: 0 | CI34: 0 | CJ34: 0 | CK34: 0 | CL34: 0 | CM34: 0 | CN34: 0 | CO34: 0 | CP34: 0 | CQ34: 0 | CR34: 0 | CS34: 0 | CT34: 0 | CU34: 0 | CV34: 0 | CW34: 0 | CX34: 0 | CY34: 0 | CZ34: 0 | DA34: 0 | DB34: 0 | DC34: 0 | DD34: 0 | DE34: 0 | DF34: 0 | DG34: 0 | DH34: 0 | DI34: 0 | DJ34: 0 | DK34: 0 | DL34: 0 | DM34: 0 | DN34: 0 | DO34: 0 | DP34: 0 | DQ34: 0 | DR34: 0 | DS34: 0 | DT34: 0 | DU34: 0 | DV34: 0 | DW34: 0 | DX34: 0 | DY34: 0 | DZ34: 0 | EA34: 0 | EB34: 0 | EC34: 0 | ED34: 0 | EE34: 0 | EF34: 0 | EG34: 0 | EH34: 0 | EI34: 0 | EJ34: 0 | EK34: 0 | EL34: 0 | EM34: 0 | EN34: 0 | EO34: 0 | EP34: 0 | EQ34: 0 | ER34: 0 | ES34: 0 | ET34: 0 | EU34: 0 | EV34: 0 | EW34: 0 | EX34: 0 | EY34: 0 | EZ34: 0 | FA34: 0 | FB34: 0 | FC34: 0 | FD34: 0 | FE34: 0 | FF34: 0 | FG34: 0 | FH34: 0 | FI34: 0 | FJ34: 0 | FK34: 0 | FL34: 0 | FM34: 0 | FN34: 0 | FO34: 0 | FP34: 0 | FQ34: 0 | FR34: 0 | FS34: 0 | FT34: 0 | FU34: 0 | FV34: 0 | FW34: 0 | FX34: 0 | FY34: 0 | FZ34: 0 | GA34: 0 | GB34: 0 | GC34: 0 | GD34: 0 | GE34: 0 | GF34: 0 | GG34: 0 | GH34: 0 | GI34: 0 | GJ34: 0 | GK34: 0 | GL34: 0 | GM34: 0 | GN34: 0 | GO34: 0 | GP34: 0 | GQ34: 0 | GR34: 0 | GS34: 0 | GT34: 0 | GU34: 0 | GV34: 0 | GW34: 0 | GX34: 0 | GY34: 0 | GZ34: 0 | HA34: 0 | HB34: 0 | HC34: 0 | HD34: 0 | HE34: 0 | HF34: 0 | HG34: 0 | HH34: 0 | HI34: 0 | HJ34: 943 | HK34: =SUM(C$4:HI$4) -> 215 | HL34: =SUM(C34:HI34) -> 1 | HM34: =100*HL34/HK34 -> 0.46511628 | HO34: 5.29 | HP34: 3.79 | HQ34: 3.24
B35: Germany | C35: 0 | D35: 0 | E35: 0 | F35: 0 | G35: 0 | H35: 0 | I35: 0 | J35: 1 | K35: 0 | L35: 0 | M35: 0 | N35: 0 | O35: 1 | P35: 1 | Q35: 1 | R35: 0 | S35: 0 | T35: 0 | U35: 0 | V35: 0 | W35: 0 | X35: 0 | Y35: 0 | Z35: 0 | AA35: 0 | AB35: 0 | AC35: 0 | AD35: 0 | AE35: 0 | AF35: 0 | AG35: 0 | AH35: 0 | AI35: 0 | AJ35: 0 | AK35: 0 | AL35: 0 | AM35: 0 | AN35: 0 | AO35: 0 | AP35: 0 | AQ35: 0 | AR35: 0 | AS35: 0 | AT35: 0 | AU35: 0 | AV35: 0 | AW35: 0 | AX35: 0 | AY35: 0 | AZ35: 0 | BA35: 1 | BB35: 0 | BC35: 0 | BD35: 0 | BE35: 0 | BF35: 0 | BG35: 0 | BH35: 0 | BI35: 0 | BJ35: 0 | BK35: 0 | BL35: 0 | BM35: 0 | BN35: 0 | BO35: 0 | BP35: 0 | BQ35: 0 | BR35: 0 | BS35: 0 | BT35: 0 | BU35: 0 | BV35: 0 | BW35: 0 | BX35: 0 | BY35: 0 | BZ35: 0 | CA35: 0 | CB35: 0 | CC35: 0 | CD35: 0 | CE35: 0 | CF35: 0 | CG35: 0 | CH35: 0 | CI35: 0 | CJ35: 0 | CK35: 0 | CL35: 0 | CM35: 0 | CN35: 0 | CO35: 0 | CP35: 0 | CQ35: 0 | CR35: 0 | CS35: 0 | CT35: 0 | CU35: 0 | CV35: 0 | CW35: 0 | CX35: 0 | CY35: 0 | CZ35: 0 | DA35: 0 | DB35: 0 | DC35: 0 | DD35: 0 | DE35: 0 | DF35: 0 | DG35: 0 | DH35: 0 | DI35: 0 | DJ35: 0 | DK35: 0 | DL35: 0 | DM35: 0 | DN35: 0 | DO35: 0 | DP35: 0 | DQ35: 0 | DR35: 0 | DS35: 0 | DT35: 0 | DU35: 0 | DV35: 0 | DW35: 0 | DX35: 0 | DY35: 0 | DZ35: 0 | EA35: 0 | EB35: 0 | EC35: 0 | ED35: 0 | EE35: 1 | EF35: 1 | EG35: 1 | EH35: 1 | EI35: 1 | EJ35: 1 | EK35: 1 | EL35: 1 | EM35: 1 | EN35: 1 | EO35: 1 | EP35: 1 | EQ35: 1 | ER35: 1 | ES35: 1 | ET35: 1 | EU35: 1 | EV35: 1 | EW35: 1 | EX35: 1 | EY35: 1 | EZ35: 1 | FA35: 0 | FB35: 0 | FC35: 0 | FD35: 0 | FE35: 0 | FF35: 0 | FG35: 0 | FH35: 0 | FI35: 0 | FJ35: 0 | FK35: 0 | FL35: 0 | FM35: 0 | FN35: 0 | FO35: 0 | FP35: 0 | FQ35: 0 | FR35: 0 | FS35: 0 | FT35: 0 | FU35: 0 | FV35: 0 | FW35: 0 | FX35: 0 | FY35: 0 | FZ35: 0 | GA35: 0 | GB35: 0 | GC35: 0 | GD35: 0 | GE35: 0 | GF35: 0 | GG35: 0 | GH35: 0 | GI35: 0 | GJ35: 0 | GK35: 0 | GL35: 0 | GM35: 0 | GN35: 0 | GO35: 0 | GP35: 0 | GQ35: 0 | GR35: 0 | GS35: 0 | GT35: 0 | GU35: 0 | GV35: 0 | GW35: 0 | GX35: 0 | GY35: 0 | GZ35: 0 | HA35: 0 | HB35: 0 | HC35: 0 | HD35: 0 | HE35: 0 | HF35: 0 | HG35: 0 | HJ35: 1618 | HK35: =SUM(C$4:HI$4) -> 215 | HL35: =SUM(C35:HI35) -> 27 | HM35: =100*HL35/HK35 -> 12.55814 | HO35: 8.68 | HP35: 4.67 | HQ35: 3.88
B36: Greece | C36: 0 | D36: 0 | E36: 0 | F36: 0 | G36: 0 | H36: 0 | I36: 0 | J36: 0 | K36: 0 | L36: 0 | M36: 0 | N36: 0 | O36: 0 | P36: 0 | Q36: 0 | R36: 0 | S36: 0 | T36: 0 | U36: 0 | V36: 0 | W36: 0 | X36: 0 | Y36: 0 | Z36: 0 | AA36: 0 | AB36: 0 | AC36: 1 | AD36: 1 | AE36: 1 | AF36: 1 | AG36: 1 | AH36: 1 | AI36: 1 | AJ36: 1 | AK36: 1 | AL36: 1 | AM36: 1 | AN36: 1 | AO36: 1 | AP36: 1 | AQ36: 1 | AR36: 1 | AS36: 1 | AT36: 1 | AU36: 1 | AV36: 1 | AW36: 1 | AX36: 1 | AY36: 1 | AZ36: 1 | BA36: 1 | BB36: 1 | BC36: 1 | BD36: 1 | BE36: 1 | BF36: 1 | BG36: 1 | BH36: 1 | BI36: 1 | BJ36: 1 | BK36: 1 | BL36: 1 | BM36: 1 | BN36: 1 | BO36: 1 | BP36: 1 | BQ36: 1 | BR36: 1 | BS36: 1 | BT36: 1 | BU36: 1 | BV36: 1 | BW36: 1 | BX36: 1 | BY36: 1 | BZ36: 1 | CA36: 1 | CB36: 1 | CC36: 1 | CD36: 0 | CE36: 0 | CF36: 0 | CG36: 0 | CH36: 0 | CI36: 0 | CJ36: 0 | CK36: 0 | CL36: 0 | CM36: 0 | CN36: 0 | CO36: 0 | CP36: 0 | CQ36: 0 | CR36: 0 | CS36: 1 | CT36: 1 | CU36: 1 | CV36: 1 | CW36: 0 | CX36: 0 | CY36: 0 | CZ36: 0 | DA36: 0 | DB36: 0 | DC36: 0 | DD36: 0 | DE36: 0 | DF36: 0 | DG36: 0 | DH36: 0 | DI36: 0 | DJ36: 0 | DK36: 0 | DL36: 0 | DM36: 0 | DN36: 0 | DO36: 0 | DP36: 0 | DQ36: 0 | DR36: 0 | DS36: 0 | DT36: 0 | DU36: 0 | DV36: 0 | DW36: 0 | DX36: 0 | DY36: 0 | DZ36: 0 | EA36: 0 | EB36: 0 | EC36: 0 | ED36: 0 | EE36: 1 | EF36: 1 | EG36: 1 | EH36: 1 | EI36: 1 | EJ36: 1 | EK36: 1 | EL36: 1 | EM36: 1 | EN36: 1 | EO36: 1 | EP36: 1 | EQ36: 1 | ER36: 1 | ES36: 1 | ET36: 1 | EU36: 1 | EV36: 1 | EW36: 1 | EX36: 1 | EY36: 1 | EZ36: 1 | FA36: 1 | FB36: 1 | FC36: 1 | FD36: 1 | FE36: 1 | FF36: 1 | FG36: 1 | FH36: 1 | FI36: 1 | FJ36: 1 | FK36: 1 | FL36: 0 | FM36: 0 | FN36: 0 | FO36: 0 | FP36: 0 | FQ36: 0 | FR36: 0 | FS36: 0 | FT36: 0 | FU36: 0 | FV36: 0 | FW36: 0 | FX36: 0 | FY36: 0 | FZ36: 0 | GA36: 0 | GB36: 0 | GC36: 0 | GD36: 0 | GE36: 0 | GF36: 0 | GG36: 0 | GH36: 0 | GI36: 0 | GJ36: 0 | GK36: 0 | GL36: 0 | GM36: 0 | GN36: 0 | GO36: 0 | GP36: 0 | GQ36: 0 | GR36: 0 | GS36: 0 | GT36: 0 | GU36: 0 | GV36: 0 | GW36: 0 | GX36: 0 | GY36: 0 | GZ36: 0 | HA36: 0 | HB36: 0 | HC36: 0 | HD36: 0 | HE36: 0 | HF36: 0 | HG36: 1 | HJ36: 1829 | HK36: =SUM(AF$4:HI$4) -> 186 | HL36: =SUM(AF36:HI36) -> 88 | HM36: =100*HL36/HK36 -> 47.311828 | HO36: 0.32 | HP36: 0.37 | HQ36: 0.36 | HS36: Independence bonds were in default since 1826 (not included in calculation)
B37: Italy | C37: 0 | D37: 0 | E37: 0 | F37: 0 | G37: 0 | H37: 0 | I37: 0 | J37: 0 | K37: 0 | L37: 0 | M37: 0 | N37: 0 | O37: 0 | P37: 0 | Q37: 0 | R37: 0 | S37: 0 | T37: 0 | U37: 0 | V37: 0 | W37: 0 | X37: 0 | Y37: 0 | Z37: 0 | AA37: 0 | AB37: 0 | AC37: 0 | AD37: 0 | AE37: 0 | AF37: 0 | AG37: 0 | AH37: 0 | AI37: 0 | AJ37: 0 | AK37: 0 | AL37: 0 | AM37: 0 | AN37: 0 | AO37: 0 | AP37: 0 | AQ37: 0 | AR37: 0 | AS37: 0 | AT37: 0 | AU37: 0 | AV37: 0 | AW37: 0 | AX37: 0 | AY37: 0 | AZ37: 0 | BA37: 0 | BB37: 0 | BC37: 0 | BD37: 0 | BE37: 0 | BF37: 0 | BG37: 0 | BH37: 0 | BI37: 0 | BJ37: 0 | BK37: 0 | BL37: 0 | BM37: 0 | BN37: 0 | BO37: 0 | BP37: 0 | BQ37: 0 | BR37: 0 | BS37: 0 | BT37: 0 | BU37: 0 | BV37: 0 | BW37: 0 | BX37: 0 | BY37: 0 | BZ37: 0 | CA37: 0 | CB37: 0 | CC37: 0 | CD37: 0 | CE37: 0 | CF37: 0 | CG37: 0 | CH37: 0 | CI37: 0 | CJ37: 0 | CK37: 0 | CL37: 0 | CM37: 0 | CN37: 0 | CO37: 0 | CP37: 0 | CQ37: 0 | CR37: 0 | CS37: 0 | CT37: 0 | CU37: 0 | CV37: 0 | CW37: 0 | CX37: 0 | CY37: 0 | CZ37: 0 | DA37: 0 | DB37: 0 | DC37: 0 | DD37: 0 | DE37: 0 | DF37: 0 | DG37: 0 | DH37: 0 | DI37: 0 | DJ37: 0 | DK37: 0 | DL37: 0 | DM37: 0 | DN37: 0 | DO37: 0 | DP37: 0 | DQ37: 0 | DR37: 0 | DS37: 0 | DT37: 0 | DU37: 0 | DV37: 0 | DW37: 0 | DX37: 0 | DY37: 0 | DZ37: 0 | EA37: 0 | EB37: 0 | EC37: 0 | ED37: 0 | EE37: 0 | EF37: 0 | EG37: 0 | EH37: 0 | EI37: 0 | EJ37: 0 | EK37: 0 | EL37: 0 | EM37: 1 | EN37: 1 | EO37: 1 | EP37: 1 | EQ37: 1 | ER37: 1 | ES37: 1 | ET37: 0 | EU37: 0 | EV37: 0 | EW37: 0 | EX37: 0 | EY37: 0 | EZ37: 0 | FA37: 0 | FB37: 0 | FC37: 0 | FD37: 0 | FE37: 0 | FF37: 0 | FG37: 0 | FH37: 0 | FI37: 0 | FJ37: 0 | FK37: 0 | FL37: 0 | FM37: 0 | FN37: 0 | FO37: 0 | FP37: 0 | FQ37: 0 | FR37: 0 | FS37: 0 | FT37: 0 | FU37: 0 | FV37: 0 | FW37: 0 | FX37: 0 | FY37: 0 | FZ37: 0 | GA37: 0 | GB37: 0 | GC37: 0 | GD37: 0 | GE37: 0 | GF37: 0 | GG37: 0 | GH37: 0 | GI37: 0 | GJ37: 0 | GK37: 0 | GL37: 0 | GM37: 0 | GN37: 0 | GO37: 0 | GP37: 0 | GQ37: 0 | GR37: 0 | GS37: 0 | GT37: 0 | GU37: 0 | GV37: 0 | GW37: 0 | GX37: 0 | GY37: 0 | GZ37: 0 | HA37: 0 | HB37: 0 | HC37: 0 | HD37: 0 | HE37: 0 | HF37: 0 | HG37: 0 | HH37: 0 | HI37: 0 | HJ37: 1569 | HK37: =SUM(C$4:HI$4) -> 215 | HL37: =SUM(C37:HI37) -> 7 | HM37: =100*HL37/HK37 -> 3.255814 | HO37: 3.49 | HP37: 3.42 | HQ37: 2.73
B38: Hungary | C38: 0 | D38: 0 | E38: 0 | F38: 0 | G38: 0 | H38: 0 | I38: 0 | J38: 0 | K38: 0 | L38: 0 | M38: 0 | N38: 0 | O38: 0 | P38: 0 | Q38: 0 | R38: 0 | S38: 0 | T38: 0 | U38: 0 | V38: 0 | W38: 0 | X38: 0 | Y38: 0 | Z38: 0 | AA38: 0 | AB38: 0 | AC38: 0 | AD38: 0 | AE38: 0 | AF38: 0 | AG38: 0 | AH38: 0 | AI38: 0 | AJ38: 0 | AK38: 0 | AL38: 0 | AM38: 0 | AN38: 0 | AO38: 0 | AP38: 0 | AQ38: 0 | AR38: 0 | AS38: 0 | AT38: 0 | AU38: 0 | AV38: 0 | AW38: 0 | AX38: 0 | AY38: 0 | AZ38: 0 | BA38: 0 | BB38: 0 | BC38: 0 | BD38: 0 | BE38: 0 | BF38: 0 | BG38: 0 | BH38: 0 | BI38: 0 | BJ38: 0 | BK38: 0 | BL38: 0 | BM38: 0 | BN38: 0 | BO38: 0 | BP38: 0 | BQ38: 0 | BR38: 0 | BS38: 0 | BT38: 0 | BU38: 0 | BV38: 0 | BW38: 0 | BX38: 0 | BY38: 0 | BZ38: 0 | CA38: 0 | CB38: 0 | CC38: 0 | CD38: 0 | CE38: 0 | CF38: 0 | CG38: 0 | CH38: 0 | CI38: 0 | CJ38: 0 | CK38: 0 | CL38: 0 | CM38: 0 | CN38: 0 | CO38: 0 | CP38: 0 | CQ38: 0 | CR38: 0 | CS38: 0 | CT38: 0 | CU38: 0 | CV38: 0 | CW38: 0 | CX38: 0 | CY38: 0 | CZ38: 0 | DA38: 0 | DB38: 0 | DC38: 0 | DD38: 0 | DE38: 0 | DF38: 0 | DG38: 0 | DH38: 0 | DI38: 0 | DJ38: 0 | DK38: 0 | DL38: 0 | DM38: 0 | DN38: 0 | DO38: 0 | DP38: 0 | DQ38: 0 | DR38: 0 | DS38: 0 | DT38: 0 | DU38: 0 | DV38: 0 | DW38: 0 | DX38: 0 | DY38: 0 | DZ38: 0 | EA38: 0 | EB38: 0 | EC38: 0 | ED38: 0 | EE38: 1 | EF38: 1 | EG38: 1 | EH38: 1 | EI38: 1 | EJ38: 1 | EK38: 0 | EL38: 0 | EM38: 0 | EN38: 1 | EO38: 1 | EP38: 1 | EQ38: 1 | ER38: 1 | ES38: 1 | ET38: 1 | EU38: 1 | EV38: 1 | EW38: 1 | EX38: 1 | EY38: 1 | EZ38: 1 | FA38: 1 | FB38: 1 | FC38: 1 | FD38: 1 | FE38: 1 | FF38: 1 | FG38: 1 | FH38: 1 | FI38: 1 | FJ38: 1 | FK38: 1 | FL38: 1 | FM38: 1 | FN38: 1 | FO38: 0 | FP38: 0 | FQ38: 0 | FR38: 0 | FS38: 0 | FT38: 0 | FU38: 0 | FV38: 0 | FW38: 0 | FX38: 0 | FY38: 0 | FZ38: 0 | GA38: 0 | GB38: 0 | GC38: 0 | GD38: 0 | GE38: 0 | GF38: 0 | GG38: 0 | GH38: 0 | GI38: 0 | GJ38: 0 | GK38: 0 | GL38: 0 | GM38: 0 | GN38: 0 | GO38: 0 | GP38: 0 | GQ38: 0 | GR38: 0 | GS38: 0 | GT38: 0 | GU38: 0 | GV38: 0 | GW38: 0 | GX38: 0 | GY38: 0 | GZ38: 0 | HA38: 0 | HB38: 0 | HC38: 0 | HD38: 0 | HE38: 0 | HF38: 0 | HG38: 0 | HJ38: 1918 | HK38: =SUM(DQ$4:HI$4) -> 97 | HL38: =SUM(DQ38:HI38) -> 33 | HM38: =100*HL38/HK38 -> 34.020619 | HO38: 0.6 | HP38: 0.25 | HQ38: 0.2
B39: Netherlands | C39: 0 | D39: 0 | E39: 1 | F39: 1 | G39: 1 | H39: 1 | I39: 1 | J39: 1 | K39: 1 | L39: 1 | M39: 1 | N39: 1 | O39: 1 | P39: 1 | Q39: 1 | R39: 0 | S39: 0 | T39: 0 | U39: 0 | V39: 0 | W39: 0 | X39: 0 | Y39: 0 | Z39: 0 | AA39: 0 | AB39: 0 | AC39: 0 | AD39: 0 | AE39: 0 | AF39: 0 | AG39: 0 | AH39: 0 | AI39: 0 | AJ39: 0 | AK39: 0 | AL39: 0 | AM39: 0 | AN39: 0 | AO39: 0 | AP39: 0 | AQ39: 0 | AR39: 0 | AS39: 0 | AT39: 0 | AU39: 0 | AV39: 0 | AW39: 0 | AX39: 0 | AY39: 0 | AZ39: 0 | BA39: 0 | BB39: 0 | BC39: 0 | BD39: 0 | BE39: 0 | BF39: 0 | BG39: 0 | BH39: 0 | BI39: 0 | BJ39: 0 | BK39: 0 | BL39: 0 | BM39: 0 | BN39: 0 | BO39: 0 | BP39: 0 | BQ39: 0 | BR39: 0 | BS39: 0 | BT39: 0 | BU39: 0 | BV39: 0 | BW39: 0 | BX39: 0 | BY39: 0 | BZ39: 0 | CA39: 0 | CB39: 0 | CC39: 0 | CD39: 0 | CE39: 0 | CF39: 0 | CG39: 0 | CH39: 0 | CI39: 0 | CJ39: 0 | CK39: 0 | CL39: 0 | CM39: 0 | CN39: 0 | CO39: 0 | CP39: 0 | CQ39: 0 | CR39: 0 | CS39: 0 | CT39: 0 | CU39: 0 | CV39: 0 | CW39: 0 | CX39: 0 | CY39: 0 | CZ39: 0 | DA39: 0 | DB39: 0 | DC39: 0 | DD39: 0 | DE39: 0 | DF39: 0 | DG39: 0 | DH39: 0 | DI39: 0 | DJ39: 0 | DK39: 0 | DL39: 0 | DM39: 0 | DN39: 0 | DO39: 0 | DP39: 0 | DQ39: 0 | DR39: 0 | DS39: 0 | DT39: 0 | DU39: 0 | DV39: 0 | DW39: 0 | DX39: 0 | DY39: 0 | DZ39: 0 | EA39: 0 | EB39: 0 | EC39: 0 | ED39: 0 | EE39: 0 | EF39: 0 | EG39: 0 | EH39: 0 | EI39: 0 | EJ39: 0 | EK39: 0 | EL39: 0 | EM39: 0 | EN39: 0 | EO39: 0 | EP39: 0 | EQ39: 0 | ER39: 0 | ES39: 0 | ET39: 0 | EU39: 0 | EV39: 0 | EW39: 0 | EX39: 0 | EY39: 0 | EZ39: 0 | FA39: 0 | FB39: 0 | FC39: 0 | FD39: 0 | FE39: 0 | FF39: 0 | FG39: 0 | FH39: 0 | FI39: 0 | FJ39: 0 | FK39: 0 | FL39: 0 | FM39: 0 | FN39: 0 | FO39: 0 | FP39: 0 | FQ39: 0 | FR39: 0 | FS39: 0 | FT39: 0 | FU39: 0 | FV39: 0 | FW39: 0 | FX39: 0 | FY39: 0 | FZ39: 0 | GA39: 0 | GB39: 0 | GC39: 0 | GD39: 0 | GE39: 0 | GF39: 0 | GG39: 0 | GH39: 0 | GI39: 0 | GJ39: 0 | GK39: 0 | GL39: 0 | GM39: 0 | GN39: 0 | GO39: 0 | GP39: 0 | GQ39: 0 | GR39: 0 | GS39: 0 | GT39: 0 | GU39: 0 | GV39: 0 | GW39: 0 | GX39: 0 | GY39: 0 | GZ39: 0 | HA39: 0 | HB39: 0 | HC39: 0 | HD39: 0 | HE39: 0 | HF39: 0 | HG39: 0 | HJ39: 1581 | HK39: =SUM(C$4:HI$4) -> 215 | HL39: =SUM(C39:HI39) -> 13 | HM39: =100*HL39/HK39 -> 6.0465116 | HO39: 0.91 | HP39: 0.95 | HQ39: 0.86
B40: Norway | C40: 0 | D40: 0 | E40: 0 | F40: 0 | G40: 0 | H40: 0 | I40: 0 | J40: 0 | K40: 0 | L40: 0 | M40: 0 | N40: 0 | O40: 0 | P40: 0 | Q40: 0 | R40: 0 | S40: 0 | T40: 0 | U40: 0 | V40: 0 | W40: 0 | X40: 0 | Y40: 0 | Z40: 0 | AA40: 0 | AB40: 0 | AC40: 0 | AD40: 0 | AE40: 0 | AF40: 0 | AG40: 0 | AH40: 0 | AI40: 0 | AJ40: 0 | AK40: 0 | AL40: 0 | AM40: 0 | AN40: 0 | AO40: 0 | AP40: 0 | AQ40: 0 | AR40: 0 | AS40: 0 | AT40: 0 | AU40: 0 | AV40: 0 | AW40: 0 | AX40: 0 | AY40: 0 | AZ40: 0 | BA40: 0 | BB40: 0 | BC40: 0 | BD40: 0 | BE40: 0 | BF40: 0 | BG40: 0 | BH40: 0 | BI40: 0 | BJ40: 0 | BK40: 0 | BL40: 0 | BM40: 0 | BN40: 0 | BO40: 0 | BP40: 0 | BQ40: 0 | BR40: 0 | BS40: 0 | BT40: 0 | BU40: 0 | BV40: 0 | BW40: 0 | BX40: 0 | BY40: 0 | BZ40: 0 | CA40: 0 | CB40: 0 | CC40: 0 | CD40: 0 | CE40: 0 | CF40: 0 | CG40: 0 | CH40: 0 | CI40: 0 | CJ40: 0 | CK40: 0 | CL40: 0 | CM40: 0 | CN40: 0 | CO40: 0 | CP40: 0 | CQ40: 0 | CR40: 0 | CS40: 0 | CT40: 0 | CU40: 0 | CV40: 0 | CW40: 0 | CX40: 0 | CY40: 0 | CZ40: 0 | DA40: 0 | DB40: 0 | DC40: 0 | DD40: 0 | DE40: 0 | DF40: 0 | DG40: 0 | DH40: 0 | DI40: 0 | DJ40: 0 | DK40: 0 | DL40: 0 | DM40: 0 | DN40: 0 | DO40: 0 | DP40: 0 | DQ40: 0 | DR40: 0 | DS40: 0 | DT40: 0 | DU40: 0 | DV40: 0 | DW40: 0 | DX40: 0 | DY40: 0 | DZ40: 0 | EA40: 0 | EB40: 0 | EC40: 0 | ED40: 0 | EE40: 0 | EF40: 0 | EG40: 0 | EH40: 0 | EI40: 0 | EJ40: 0 | EK40: 0 | EL40: 0 | EM40: 0 | EN40: 0 | EO40: 0 | EP40: 0 | EQ40: 0 | ER40: 0 | ES40: 0 | ET40: 0 | EU40: 0 | EV40: 0 | EW40: 0 | EX40: 0 | EY40: 0 | EZ40: 0 | FA40: 0 | FB40: 0 | FC40: 0 | FD40: 0 | FE40: 0 | FF40: 0 | FG40: 0 | FH40: 0 | FI40: 0 | FJ40: 0 | FK40: 0 | FL40: 0 | FM40: 0 | FN40: 0 | FO40: 0 | FP40: 0 | FQ40: 0 | FR40: 0 | FS40: 0 | FT40: 0 | FU40: 0 | FV40: 0 | FW40: 0 | FX40: 0 | FY40: 0 | FZ40: 0 | GA40: 0 | GB40: 0 | GC40: 0 | GD40: 0 | GE40: 0 | GF40: 0 | GG40: 0 | GH40: 0 | GI40: 0 | GJ40: 0 | GK40: 0 | GL40: 0 | GM40: 0 | GN40: 0 | GO40: 0 | GP40: 0 | GQ40: 0 | GR40: 0 | GS40: 0 | GT40: 0 | GU40: 0 | GV40: 0 | GW40: 0 | GX40: 0 | GY40: 0 | GZ40: 0 | HA40: 0 | HB40: 0 | HC40: 0 | HD40: 0 | HE40: 0 | HF40: 0 | HG40: 0 | HJ40: 1905 | HK40: =SUM(DD$4:HI$4) -> 110 | HL40: =SUM(DD40:HI40) -> 0 | HM40: =100*HL40/HK40 -> 0 | HO40: 0.22 | HP40: 0.29 | HQ40: 0.29
B41: Poland | C41: 0 | D41: 0 | E41: 0 | F41: 0 | G41: 0 | H41: 0 | I41: 0 | J41: 0 | K41: 0 | L41: 0 | M41: 0 | N41: 0 | O41: 0 | P41: 0 | Q41: 0 | R41: 0 | S41: 0 | T41: 0 | U41: 0 | V41: 0 | W41: 0 | X41: 0 | Y41: 0 | Z41: 0 | AA41: 0 | AB41: 0 | AC41: 0 | AD41: 0 | AE41: 0 | AF41: 0 | AG41: 0 | AH41: 0 | AI41: 0 | AJ41: 0 | AK41: 0 | AL41: 0 | AM41: 0 | AN41: 0 | AO41: 0 | AP41: 0 | AQ41: 0 | AR41: 0 | AS41: 0 | AT41: 0 | AU41: 0 | AV41: 0 | AW41: 0 | AX41: 0 | AY41: 0 | AZ41: 0 | BA41: 0 | BB41: 0 | BC41: 0 | BD41: 0 | BE41: 0 | BF41: 0 | BG41: 0 | BH41: 0 | BI41: 0 | BJ41: 0 | BK41: 0 | BL41: 0 | BM41: 0 | BN41: 0 | BO41: 0 | BP41: 0 | BQ41: 0 | BR41: 0 | BS41: 0 | BT41: 0 | BU41: 0 | BV41: 0 | BW41: 0 | BX41: 0 | BY41: 0 | BZ41: 0 | CA41: 0 | CB41: 0 | CC41: 0 | CD41: 0 | CE41: 0 | CF41: 0 | CG41: 0 | CH41: 0 | CI41: 0 | CJ41: 0 | CK41: 0 | CL41: 0 | CM41: 0 | CN41: 0 | CO41: 0 | CP41: 0 | CQ41: 0 | CR41: 0 | CS41: 0 | CT41: 0 | CU41: 0 | CV41: 0 | CW41: 0 | CX41: 0 | CY41: 0 | CZ41: 0 | DA41: 0 | DB41: 0 | DC41: 0 | DD41: 0 | DE41: 0 | DF41: 0 | DG41: 0 | DH41: 0 | DI41: 0 | DJ41: 0 | DK41: 0 | DL41: 0 | DM41: 0 | DN41: 0 | DO41: 0 | DP41: 0 | DQ41: 0 | DR41: 0 | DS41: 0 | DT41: 0 | DU41: 0 | DV41: 0 | DW41: 0 | DX41: 0 | DY41: 0 | DZ41: 0 | EA41: 0 | EB41: 0 | EC41: 0 | ED41: 0 | EE41: 0 | EF41: 0 | EG41: 0 | EH41: 0 | EI41: 1 | EJ41: 1 | EK41: 0 | EL41: 0 | EM41: 1 | EN41: 1 | EO41: 1 | EP41: 1 | EQ41: 1 | ER41: 1 | ES41: 1 | ET41: 1 | EU41: 1 | EV41: 1 | EW41: 1 | EX41: 1 | EY41: 1 | EZ41: 0 | FA41: 0 | FB41: 0 | FC41: 0 | FD41: 0 | FE41: 0 | FF41: 0 | FG41: 0 | FH41: 0 | FI41: 0 | FJ41: 0 | FK41: 0 | FL41: 0 | FM41: 0 | FN41: 0 | FO41: 0 | FP41: 0 | FQ41: 0 | FR41: 0 | FS41: 0 | FT41: 0 | FU41: 0 | FV41: 0 | FW41: 0 | FX41: 0 | FY41: 0 | FZ41: 0 | GA41: 0 | GB41: 1 | GC41: 1 | GD41: 1 | GE41: 1 | GF41: 1 | GG41: 1 | GH41: 1 | GI41: 1 | GJ41: 1 | GK41: 1 | GL41: 1 | GM41: 1 | GN41: 1 | GO41: 1 | GP41: 0 | GQ41: 0 | GR41: 0 | GS41: 0 | GT41: 0 | GU41: 0 | GV41: 0 | GW41: 0 | GX41: 0 | GY41: 0 | GZ41: 0 | HA41: 0 | HB41: 0 | HC41: 0 | HD41: 0 | HE41: 0 | HF41: 0 | HG41: 0 | HJ41: 1918 | HK41: =SUM(DQ$4:HI$4) -> 97 | HL41: =SUM(DQ41:HI41) -> 29 | HM41: =100*HL41/HK41 -> 29.896907 | HO41: 1.7 | HP41: 0.72 | HQ41: 0.73
B42: Portugal | C42: 0 | D42: 0 | E42: 0 | F42: 0 | G42: 0 | H42: 0 | I42: 0 | J42: 0 | K42: 0 | L42: 0 | M42: 0 | N42: 0 | O42: 0 | P42: 0 | Q42: 0 | R42: 0 | S42: 0 | T42: 0 | U42: 0 | V42: 0 | W42: 0 | X42: 0 | Y42: 0 | Z42: 0 | AA42: 0 | AB42: 0 | AC42: 0 | AD42: 0 | AE42: 1 | AF42: 0 | AG42: 0 | AH42: 0 | AI42: 0 | AJ42: 0 | AK42: 0 | AL42: 0 | AM42: 0 | AN42: 1 | AO42: 1 | AP42: 1 | AQ42: 1 | AR42: 1 | AS42: 0 | AT42: 0 | AU42: 0 | AV42: 0 | AW42: 0 | AX42: 0 | AY42: 0 | AZ42: 0 | BA42: 1 | BB42: 1 | BC42: 1 | BD42: 1 | BE42: 1 | BF42: 1 | BG42: 1 | BH42: 0 | BI42: 0 | BJ42: 0 | BK42: 0 | BL42: 0 | BM42: 0 | BN42: 0 | BO42: 0 | BP42: 0 | BQ42: 0 | BR42: 0 | BS42: 0 | BT42: 0 | BU42: 0 | BV42: 0 | BW42: 0 | BX42: 0 | BY42: 0 | BZ42: 0 | CA42: 0 | CB42: 0 | CC42: 0 | CD42: 0 | CE42: 0 | CF42: 0 | CG42: 0 | CH42: 0 | CI42: 0 | CJ42: 0 | CK42: 0 | CL42: 0 | CM42: 0 | CN42: 0 | CO42: 0 | CP42: 0 | CQ42: 1 | CR42: 1 | CS42: 1 | CT42: 1 | CU42: 1 | CV42: 1 | CW42: 1 | CX42: 1 | CY42: 1 | CZ42: 1 | DA42: 0 | DB42: 0 | DC42: 0 | DD42: 0 | DE42: 0 | DF42: 0 | DG42: 0 | DH42: 0 | DI42: 0 | DJ42: 0 | DK42: 0 | DL42: 0 | DM42: 0 | DN42: 0 | DO42: 0 | DP42: 0 | DQ42: 0 | DR42: 0 | DS42: 0 | DT42: 0 | DU42: 0 | DV42: 0 | DW42: 0 | DX42: 0 | DY42: 0 | DZ42: 0 | EA42: 0 | EB42: 0 | EC42: 0 | ED42: 0 | EE42: 0 | EF42: 0 | EG42: 0 | EH42: 0 | EI42: 0 | EJ42: 0 | EK42: 0 | EL42: 0 | EM42: 0 | EN42: 0 | EO42: 0 | EP42: 0 | EQ42: 0 | ER42: 0 | ES42: 0 | ET42: 0 | EU42: 0 | EV42: 0 | EW42: 0 | EX42: 0 | EY42: 0 | EZ42: 0 | FA42: 0 | FB42: 0 | FC42: 0 | FD42: 0 | FE42: 0 | FF42: 0 | FG42: 0 | FH42: 0 | FI42: 0 | FJ42: 0 | FK42: 0 | FL42: 0 | FM42: 0 | FN42: 0 | FO42: 0 | FP42: 0 | FQ42: 0 | FR42: 0 | FS42: 0 | FT42: 0 | FU42: 0 | FV42: 0 | FW42: 0 | FX42: 0 | FY42: 0 | FZ42: 0 | GA42: 0 | GB42: 0 | GC42: 0 | GD42: 0 | GE42: 0 | GF42: 0 | GG42: 0 | GH42: 0 | GI42: 0 | GJ42: 0 | GK42: 0 | GL42: 0 | GM42: 0 | GN42: 0 | GO42: 0 | GP42: 0 | GQ42: 0 | GR42: 0 | GS42: 0 | GT42: 0 | GU42: 0 | GV42: 0 | GW42: 0 | GX42: 0 | GY42: 0 | GZ42: 0 | HA42: 0 | HB42: 0 | HC42: 0 | HD42: 0 | HE42: 0 | HF42: 0 | HG42: 0 | HJ42: 1139 | HK42: =SUM(C$4:HI$4) -> 215 | HL42: =SUM(C42:HI42) -> 23 | HM42: =100*HL42/HK42 -> 10.697674 | HO42: 0.27 | HP42: 0.4 | HQ42: 0.36
B43: Romania | C43: 0 | D43: 0 | E43: 0 | F43: 0 | G43: 0 | H43: 0 | I43: 0 | J43: 0 | K43: 0 | L43: 0 | M43: 0 | N43: 0 | O43: 0 | P43: 0 | Q43: 0 | R43: 0 | S43: 0 | T43: 0 | U43: 0 | V43: 0 | W43: 0 | X43: 0 | Y43: 0 | Z43: 0 | AA43: 0 | AB43: 0 | AC43: 0 | AD43: 0 | AE43: 0 | AF43: 0 | AG43: 0 | AH43: 0 | AI43: 0 | AJ43: 0 | AK43: 0 | AL43: 0 | AM43: 0 | AN43: 0 | AO43: 0 | AP43: 0 | AQ43: 0 | AR43: 0 | AS43: 0 | AT43: 0 | AU43: 0 | AV43: 0 | AW43: 0 | AX43: 0 | AY43: 0 | AZ43: 0 | BA43: 0 | BB43: 0 | BC43: 0 | BD43: 0 | BE43: 0 | BF43: 0 | BG43: 0 | BH43: 0 | BI43: 0 | BJ43: 0 | BK43: 0 | BL43: 0 | BM43: 0 | BN43: 0 | BO43: 0 | BP43: 0 | BQ43: 0 | BR43: 0 | BS43: 0 | BT43: 0 | BU43: 0 | BV43: 0 | BW43: 0 | BX43: 0 | BY43: 0 | BZ43: 0 | CA43: 0 | CB43: 0 | CC43: 0 | CD43: 0 | CE43: 0 | CF43: 0 | CG43: 0 | CH43: 0 | CI43: 0 | CJ43: 0 | CK43: 0 | CL43: 0 | CM43: 0 | CN43: 0 | CO43: 0 | CP43: 0 | CQ43: 0 | CR43: 0 | CS43: 0 | CT43: 0 | CU43: 0 | CV43: 0 | CW43: 0 | CX43: 0 | CY43: 0 | CZ43: 0 | DA43: 0 | DB43: 0 | DC43: 0 | DD43: 0 | DE43: 0 | DF43: 0 | DG43: 0 | DH43: 0 | DI43: 0 | DJ43: 0 | DK43: 0 | DL43: 0 | DM43: 0 | DN43: 0 | DO43: 0 | DP43: 0 | DQ43: 0 | DR43: 0 | DS43: 0 | DT43: 0 | DU43: 0 | DV43: 0 | DW43: 0 | DX43: 0 | DY43: 0 | DZ43: 0 | EA43: 0 | EB43: 0 | EC43: 0 | ED43: 0 | EE43: 0 | EF43: 1 | EG43: 1 | EH43: 1 | EI43: 1 | EJ43: 1 | EK43: 1 | EL43: 1 | EM43: 1 | EN43: 1 | EO43: 1 | EP43: 1 | EQ43: 1 | ER43: 1 | ES43: 1 | ET43: 1 | EU43: 1 | EV43: 1 | EW43: 1 | EX43: 1 | EY43: 1 | EZ43: 1 | FA43: 1 | FB43: 1 | FC43: 1 | FD43: 1 | FE43: 1 | FF43: 0 | FG43: 0 | FH43: 0 | FI43: 0 | FJ43: 0 | FK43: 0 | FL43: 0 | FM43: 0 | FN43: 0 | FO43: 0 | FP43: 0 | FQ43: 0 | FR43: 0 | FS43: 0 | FT43: 0 | FU43: 0 | FV43: 0 | FW43: 0 | FX43: 0 | FY43: 0 | FZ43: 0 | GA43: 0 | GB43: 1 | GC43: 1 | GD43: 1 | GE43: 0 | GF43: 0 | GG43: 1 | GH43: 0 | GI43: 0 | GJ43: 0 | GK43: 0 | GL43: 0 | GM43: 0 | GN43: 0 | GO43: 0 | GP43: 0 | GQ43: 0 | GR43: 0 | GS43: 0 | GT43: 0 | GU43: 0 | GV43: 0 | GW43: 0 | GX43: 0 | GY43: 0 | GZ43: 0 | HA43: 0 | HB43: 0 | HC43: 0 | HD43: 0 | HE43: 0 | HF43: 0 | HG43: 0 | HJ43: 1878 | HK43: =SUM(CC$4:HI$4) -> 137 | HL43: =SUM(CC43:HI43) -> 30 | HM43: =100*HL43/HK43 -> 21.89781 | HO43: 0.8 | HP43: 0.3 | HQ43: 0.19
B44: Russia | C44: 0 | D44: 0 | E44: 0 | F44: 0 | G44: 0 | H44: 0 | I44: 0 | J44: 0 | K44: 0 | L44: 0 | M44: 0 | N44: 0 | O44: 0 | P44: 0 | Q44: 0 | R44: 0 | S44: 0 | T44: 0 | U44: 0 | V44: 0 | W44: 0 | X44: 0 | Y44: 0 | Z44: 0 | AA44: 0 | AB44: 0 | AC44: 0 | AD44: 0 | AE44: 0 | AF44: 0 | AG44: 0 | AH44: 0 | AI44: 0 | AJ44: 0 | AK44: 0 | AL44: 0 | AM44: 0 | AN44: 0 | AO44: 0 | AP44: 1 | AQ44: 0 | AR44: 0 | AS44: 0 | AT44: 0 | AU44: 0 | AV44: 0 | AW44: 0 | AX44: 0 | AY44: 0 | AZ44: 0 | BA44: 0 | BB44: 0 | BC44: 0 | BD44: 0 | BE44: 0 | BF44: 0 | BG44: 0 | BH44: 0 | BI44: 0 | BJ44: 0 | BK44: 0 | BL44: 0 | BM44: 0 | BN44: 0 | BO44: 0 | BP44: 0 | BQ44: 0 | BR44: 0 | BS44: 0 | BT44: 0 | BU44: 0 | BV44: 0 | BW44: 0 | BX44: 0 | BY44: 0 | BZ44: 0 | CA44: 0 | CB44: 0 | CC44: 0 | CD44: 0 | CE44: 0 | CF44: 0 | CG44: 0 | CH44: 0 | CI44: 0 | CJ44: 1 | CK44: 0 | CL44: 0 | CM44: 0 | CN44: 0 | CO44: 0 | CP44: 0 | CQ44: 0 | CR44: 0 | CS44: 0 | CT44: 0 | CU44: 0 | CV44: 0 | CW44: 0 | CX44: 0 | CY44: 0 | CZ44: 0 | DA44: 0 | DB44: 0 | DC44: 0 | DD44: 0 | DE44: 0 | DF44: 0 | DG44: 0 | DH44: 0 | DI44: 0 | DJ44: 0 | DK44: 0 | DL44: 0 | DM44: 0 | DN44: 0 | DO44: 0 | DP44: 0 | DQ44: 1 | DR44: 1 | DS44: 1 | DT44: 1 | DU44: 1 | DV44: 1 | DW44: 1 | DX44: 1 | DY44: 1 | DZ44: 1 | EA44: 1 | EB44: 1 | EC44: 1 | ED44: 1 | EE44: 1 | EF44: 1 | EG44: 1 | EH44: 1 | EI44: 1 | EJ44: 1 | EK44: 1 | EL44: 1 | EM44: 1 | EN44: 1 | EO44: 1 | EP44: 1 | EQ44: 1 | ER44: 1 | ES44: 1 | ET44: 1 | EU44: 1 | EV44: 1 | EW44: 1 | EX44: 1 | EY44: 1 | EZ44: 1 | FA44: 1 | FB44: 1 | FC44: 1 | FD44: 1 | FE44: 1 | FF44: 1 | FG44: 1 | FH44: 1 | FI44: 1 | FJ44: 1 | FK44: 1 | FL44: 1 | FM44: 1 | FN44: 1 | FO44: 1 | FP44: 1 | FQ44: 1 | FR44: 1 | FS44: 1 | FT44: 1 | FU44: 1 | FV44: 1 | FW44: 1 | FX44: 1 | FY44: 1 | FZ44: 1 | GA44: 1 | GB44: 1 | GC44: 1 | GD44: 1 | GE44: 1 | GF44: 1 | GG44: 1 | GH44: 0 | GI44: 0 | GJ44: 0 | GK44: 0 | GL44: 1 | GM44: 1 | GN44: 1 | GO44: 1 | GP44: 1 | GQ44: 1 | GR44: 1 | GS44: 1 | GT44: 1 | GU44: 1 | GV44: 0 | GW44: 0 | GX44: 0 | GY44: 0 | GZ44: 0 | HA44: 0 | HB44: 0 | HC44: 0 | HD44: 0 | HE44: 0 | HF44: 0 | HG44: 0 | HJ44: 1457 | HK44: =SUM(C$4:HI$4) -> 215 | HL44: =SUM(C44:HI44) -> 81 | HM44: =100*HL44/HK44 -> 37.674419 | HO44: 8.5 | HP44: 4.25 | HQ44: 2.25
B45: Spain | C45: 0 | D45: 0 | E45: 0 | F45: 0 | G45: 0 | H45: 0 | I45: 0 | J45: 0 | K45: 0 | L45: 0 | M45: 0 | N45: 0 | O45: 0 | P45: 0 | Q45: 0 | R45: 0 | S45: 0 | T45: 0 | U45: 0 | V45: 0 | W45: 1 | X45: 0 | Y45: 0 | Z45: 0 | AA45: 1 | AB45: 1 | AC45: 1 | AD45: 1 | AE45: 1 | AF45: 1 | AG45: 1 | AH45: 1 | AI45: 1 | AJ45: 1 | AK45: 1 | AL45: 0 | AM45: 0 | AN45: 1 | AO45: 1 | AP45: 1 | AQ45: 1 | AR45: 1 | AS45: 1 | AT45: 1 | AU45: 1 | AV45: 1 | AW45: 1 | AX45: 1 | AY45: 1 | AZ45: 1 | BA45: 1 | BB45: 1 | BC45: 1 | BD45: 1 | BE45: 1 | BF45: 1 | BG45: 1 | BH45: 1 | BI45: 1 | BJ45: 1 | BK45: 1 | BL45: 1 | BM45: 1 | BN45: 1 | BO45: 1 | BP45: 1 | BQ45: 1 | BR45: 1 | BS45: 0 | BT45: 0 | BU45: 0 | BV45: 0 | BW45: 0 | BX45: 0 | BY45: 0 | BZ45: 0 | CA45: 0 | CB45: 1 | CC45: 1 | CD45: 1 | CE45: 1 | CF45: 1 | CG45: 1 | CH45: 0 | CI45: 0 | CJ45: 0 | CK45: 0 | CL45: 0 | CM45: 0 | CN45: 0 | CO45: 0 | CP45: 0 | CQ45: 0 | CR45: 0 | CS45: 0 | CT45: 0 | CU45: 0 | CV45: 0 | CW45: 0 | CX45: 0 | CY45: 0 | CZ45: 0 | DA45: 0 | DB45: 0 | DC45: 0 | DD45: 0 | DE45: 0 | DF45: 0 | DG45: 0 | DH45: 0 | DI45: 0 | DJ45: 0 | DK45: 0 | DL45: 0 | DM45: 0 | DN45: 0 | DO45: 0 | DP45: 0 | DQ45: 0 | DR45: 0 | DS45: 0 | DT45: 0 | DU45: 0 | DV45: 0 | DW45: 0 | DX45: 0 | DY45: 0 | DZ45: 0 | EA45: 0 | EB45: 0 | EC45: 0 | ED45: 0 | EE45: 0 | EF45: 0 | EG45: 0 | EH45: 0 | EI45: 1 | EJ45: 0 | EK45: 0 | EL45: 0 | EM45: 0 | EN45: 0 | EO45: 0 | EP45: 0 | EQ45: 0 | ER45: 0 | ES45: 0 | ET45: 0 | EU45: 0 | EV45: 0 | EW45: 0 | EX45: 0 | EY45: 0 | EZ45: 0 | FA45: 0 | FB45: 0 | FC45: 0 | FD45: 0 | FE45: 0 | FF45: 0 | FG45: 0 | FH45: 0 | FI45: 0 | FJ45: 0 | FK45: 0 | FL45: 0 | FM45: 0 | FN45: 0 | FO45: 0 | FP45: 0 | FQ45: 0 | FR45: 0 | FS45: 0 | FT45: 0 | FU45: 0 | FV45: 0 | FW45: 0 | FX45: 0 | FY45: 0 | FZ45: 0 | GA45: 0 | GB45: 0 | GC45: 0 | GD45: 0 | GE45: 0 | GF45: 0 | GG45: 0 | GH45: 0 | GI45: 0 | GJ45: 0 | GK45: 0 | GL45: 0 | GM45: 0 | GN45: 0 | GO45: 0 | GP45: 0 | GQ45: 0 | GR45: 0 | GS45: 0 | GT45: 0 | GU45: 0 | GV45: 0 | GW45: 0 | GX45: 0 | GY45: 0 | GZ45: 0 | HA45: 0 | HB45: 0 | HC45: 0 | HD45: 0 | HE45: 0 | HF45: 0 | HG45: 0 | HJ45: 1476 | HK45: =SUM(C$4:HI$4) -> 215 | HL45: =SUM(C45:HI45) -> 50 | HM45: =100*HL45/HK45 -> 23.255814 | HO45: 1.52 | HP45: 1.75 | HQ45: 1.68
B46: Sweden | C46: 0 | D46: 0 | E46: 0 | F46: 0 | G46: 0 | H46: 0 | I46: 0 | J46: 0 | K46: 0 | L46: 0 | M46: 0 | N46: 0 | O46: 1 | P46: 0 | Q46: 0 | R46: 0 | S46: 0 | T46: 0 | U46: 0 | V46: 0 | W46: 0 | X46: 0 | Y46: 0 | Z46: 0 | AA46: 0 | AB46: 0 | AC46: 0 | AD46: 0 | AE46: 0 | AF46: 0 | AG46: 0 | AH46: 0 | AI46: 0 | AJ46: 0 | AK46: 0 | AL46: 0 | AM46: 0 | AN46: 0 | AO46: 0 | AP46: 0 | AQ46: 0 | AR46: 0 | AS46: 0 | AT46: 0 | AU46: 0 | AV46: 0 | AW46: 0 | AX46: 0 | AY46: 0 | AZ46: 0 | BA46: 0 | BB46: 0 | BC46: 0 | BD46: 0 | BE46: 0 | BF46: 0 | BG46: 0 | BH46: 0 | BI46: 0 | BJ46: 0 | BK46: 0 | BL46: 0 | BM46: 0 | BN46: 0 | BO46: 0 | BP46: 0 | BQ46: 0 | BR46: 0 | BS46: 0 | BT46: 0 | BU46: 0 | BV46: 0 | BW46: 0 | BX46: 0 | BY46: 0 | BZ46: 0 | CA46: 0 | CB46: 0 | CC46: 0 | CD46: 0 | CE46: 0 | CF46: 0 | CG46: 0 | CH46: 0 | CI46: 0 | CJ46: 0 | CK46: 0 | CL46: 0 | CM46: 0 | CN46: 0 | CO46: 0 | CP46: 0 | CQ46: 0 | CR46: 0 | CS46: 0 | CT46: 0 | CU46: 0 | CV46: 0 | CW46: 0 | CX46: 0 | CY46: 0 | CZ46: 0 | DA46: 0 | DB46: 0 | DC46: 0 | DD46: 0 | DE46: 0 | DF46: 0 | DG46: 0 | DH46: 0 | DI46: 0 | DJ46: 0 | DK46: 0 | DL46: 0 | DM46: 0 | DN46: 0 | DO46: 0 | DP46: 0 | DQ46: 0 | DR46: 0 | DS46: 0 | DT46: 0 | DU46: 0 | DV46: 0 | DW46: 0 | DX46: 0 | DY46: 0 | DZ46: 0 | EA46: 0 | EB46: 0 | EC46: 0 | ED46: 0 | EE46: 0 | EF46: 0 | EG46: 0 | EH46: 0 | EI46: 0 | EJ46: 0 | EK46: 0 | EL46: 0 | EM46: 0 | EN46: 0 | EO46: 0 | EP46: 0 | EQ46: 0 | ER46: 0 | ES46: 0 | ET46: 0 | EU46: 0 | EV46: 0 | EW46: 0 | EX46: 0 | EY46: 0 | EZ46: 0 | FA46: 0 | FB46: 0 | FC46: 0 | FD46: 0 | FE46: 0 | FF46: 0 | FG46: 0 | FH46: 0 | FI46: 0 | FJ46: 0 | FK46: 0 | FL46: 0 | FM46: 0 | FN46: 0 | FO46: 0 | FP46: 0 | FQ46: 0 | FR46: 0 | FS46: 0 | FT46: 0 | FU46: 0 | FV46: 0 | FW46: 0 | FX46: 0 | FY46: 0 | FZ46: 0 | GA46: 0 | GB46: 0 | GC46: 0 | GD46: 0 | GE46: 0 | GF46: 0 | GG46: 0 | GH46: 0 | GI46: 0 | GJ46: 0 | GK46: 0 | GL46: 0 | GM46: 0 | GN46: 0 | GO46: 0 | GP46: 0 | GQ46: 0 | GR46: 0 | GS46: 0 | GT46: 0 | GU46: 0 | GV46: 0 | GW46: 0 | GX46: 0 | GY46: 0 | GZ46: 0 | HA46: 0 | HB46: 0 | HC46: 0 | HD46: 0 | HE46: 0 | HF46: 0 | HG46: 0 | HJ46: 1523 | HK46: =SUM(C$4:HI$4) -> 215 | HL46: =SUM(C46:HI46) -> 1 | HM46: =100*HL46/HK46 -> 0.46511628 | HO46: 0.64 | HP46: 0.56 | HQ46: 0.48
B47: Turkey/Ottoman Empire | C47: 0 | D47: 0 | E47: 0 | F47: 0 | G47: 0 | H47: 0 | I47: 0 | J47: 0 | K47: 0 | L47: 0 | M47: 0 | N47: 0 | O47: 0 | P47: 0 | Q47: 0 | R47: 0 | S47: 0 | T47: 0 | U47: 0 | V47: 0 | W47: 0 | X47: 0 | Y47: 0 | Z47: 0 | AA47: 0 | AB47: 0 | AC47: 0 | AD47: 0 | AE47: 0 | AF47: 0 | AG47: 0 | AH47: 0 | AI47: 0 | AJ47: 0 | AK47: 0 | AL47: 0 | AM47: 0 | AN47: 0 | AO47: 0 | AP47: 0 | AQ47: 0 | AR47: 0 | AS47: 0 | AT47: 0 | AU47: 0 | AV47: 0 | AW47: 0 | AX47: 0 | AY47: 0 | AZ47: 0 | BA47: 0 | BB47: 0 | BC47: 0 | BD47: 0 | BE47: 0 | BF47: 0 | BG47: 0 | BH47: 0 | BI47: 0 | BJ47: 0 | BK47: 0 | BL47: 0 | BM47: 0 | BN47: 0 | BO47: 0 | BP47: 0 | BQ47: 0 | BR47: 0 | BS47: 0 | BT47: 0 | BU47: 0 | BV47: 0 | BW47: 0 | BX47: 0 | BY47: 0 | BZ47: 0 | CA47: 1 | CB47: 1 | CC47: 1 | CD47: 1 | CE47: 1 | CF47: 1 | CG47: 0 | CH47: 0 | CI47: 0 | CJ47: 0 | CK47: 0 | CL47: 0 | CM47: 0 | CN47: 0 | CO47: 0 | CP47: 0 | CQ47: 0 | CR47: 0 | CS47: 0 | CT47: 0 | CU47: 0 | CV47: 0 | CW47: 0 | CX47: 0 | CY47: 0 | CZ47: 0 | DA47: 0 | DB47: 0 | DC47: 0 | DD47: 0 | DE47: 0 | DF47: 0 | DG47: 0 | DH47: 0 | DI47: 0 | DJ47: 0 | DK47: 0 | DL47: 0 | DM47: 0 | DN47: 1 | DO47: 1 | DP47: 1 | DQ47: 1 | DR47: 1 | DS47: 1 | DT47: 1 | DU47: 1 | DV47: 1 | DW47: 1 | DX47: 1 | DY47: 1 | DZ47: 1 | EA47: 1 | EB47: 0 | EC47: 0 | ED47: 1 | EE47: 1 | EF47: 0 | EG47: 0 | EH47: 0 | EI47: 0 | EJ47: 0 | EK47: 0 | EL47: 0 | EM47: 1 | EN47: 1 | EO47: 1 | EP47: 1 | EQ47: 0 | ER47: 0 | ES47: 0 | ET47: 0 | EU47: 0 | EV47: 0 | EW47: 0 | EX47: 0 | EY47: 0 | EZ47: 0 | FA47: 0 | FB47: 0 | FC47: 1 | FD47: 0 | FE47: 1 | FF47: 0 | FG47: 0 | FH47: 0 | FI47: 0 | FJ47: 1 | FK47: 0 | FL47: 0 | FM47: 0 | FN47: 0 | FO47: 0 | FP47: 0 | FQ47: 0 | FR47: 0 | FS47: 0 | FT47: 0 | FU47: 0 | FV47: 0 | FW47: 0 | FX47: 0 | FY47: 1 | FZ47: 1 | GA47: 0 | GB47: 0 | GC47: 1 | GD47: 0 | GE47: 0 | GF47: 0 | GG47: 0 | GH47: 0 | GI47: 0 | GJ47: 0 | GK47: 0 | GL47: 0 | GM47: 0 | GN47: 0 | GO47: 0 | GP47: 0 | GQ47: 0 | GR47: 0 | GS47: 0 | GT47: 0 | GU47: 0 | GV47: 0 | GW47: 0 | GX47: 0 | GY47: 0 | GZ47: 0 | HA47: 0 | HB47: 0 | HC47: 0 | HD47: 0 | HE47: 0 | HF47: 0 | HG47: 0 | HJ47: 1453 | HK47: =SUM(C$4:HI$4) -> 215 | HL47: =SUM(C47:HI47) -> 32 | HM47: =100*HL47/HK47 -> 14.883721 | HO47: 0.67 | HP47: 1.13 | HQ47: 1.13
B48: United Kingdom | C48: 0 | D48: 0 | E48: 0 | F48: 0 | G48: 0 | H48: 0 | I48: 0 | J48: 0 | K48: 0 | L48: 0 | M48: 0 | N48: 0 | O48: 0 | P48: 0 | Q48: 0 | R48: 0 | S48: 0 | T48: 0 | U48: 0 | V48: 0 | W48: 0 | X48: 0 | Y48: 0 | Z48: 0 | AA48: 0 | AB48: 0 | AC48: 0 | AD48: 0 | AE48: 0 | AF48: 0 | AG48: 0 | AH48: 0 | AI48: 0 | AJ48: 0 | AK48: 0 | AL48: 0 | AM48: 0 | AN48: 0 | AO48: 0 | AP48: 0 | AQ48: 0 | AR48: 0 | AS48: 0 | AT48: 0 | AU48: 0 | AV48: 0 | AW48: 0 | AX48: 0 | AY48: 0 | AZ48: 0 | BA48: 0 | BB48: 0 | BC48: 0 | BD48: 0 | BE48: 0 | BF48: 0 | BG48: 0 | BH48: 0 | BI48: 0 | BJ48: 0 | BK48: 0 | BL48: 0 | BM48: 0 | BN48: 0 | BO48: 0 | BP48: 0 | BQ48: 0 | BR48: 0 | BS48: 0 | BT48: 0 | BU48: 0 | BV48: 0 | BW48: 0 | BX48: 0 | BY48: 0 | BZ48: 0 | CA48: 0 | CB48: 0 | CC48: 0 | CD48: 0 | CE48: 0 | CF48: 0 | CG48: 0 | CH48: 0 | CI48: 0 | CJ48: 0 | CK48: 0 | CL48: 0 | CM48: 0 | CN48: 0 | CO48: 0 | CP48: 0 | CQ48: 0 | CR48: 0 | CS48: 0 | CT48: 0 | CU48: 0 | CV48: 0 | CW48: 0 | CX48: 0 | CY48: 0 | CZ48: 0 | DA48: 0 | DB48: 0 | DC48: 0 | DD48: 0 | DE48: 0 | DF48: 0 | DG48: 0 | DH48: 0 | DI48: 0 | DJ48: 0 | DK48: 0 | DL48: 0 | DM48: 0 | DN48: 0 | DO48: 0 | DP48: 0 | DQ48: 0 | DR48: 0 | DS48: 0 | DT48: 0 | DU48: 0 | DV48: 0 | DW48: 0 | DX48: 0 | DY48: 0 | DZ48: 0 | EA48: 0 | EB48: 0 | EC48: 0 | ED48: 0 | EE48: 0 | EF48: 0 | EG48: 0 | EH48: 0 | EI48: 0 | EJ48: 0 | EK48: 0 | EL48: 0 | EM48: 0 | EN48: 0 | EO48: 0 | EP48: 0 | EQ48: 0 | ER48: 0 | ES48: 0 | ET48: 0 | EU48: 0 | EV48: 0 | EW48: 0 | EX48: 0 | EY48: 0 | EZ48: 0 | FA48: 0 | FB48: 0 | FC48: 0 | FD48: 0 | FE48: 0 | FF48: 0 | FG48: 0 | FH48: 0 | FI48: 0 | FJ48: 0 | FK48: 0 | FL48: 0 | FM48: 0 | FN48: 0 | FO48: 0 | FP48: 0 | FQ48: 0 | FR48: 0 | FS48: 0 | FT48: 0 | FU48: 0 | FV48: 0 | FW48: 0 | FX48: 0 | FY48: 0 | FZ48: 0 | GA48: 0 | GB48: 0 | GC48: 0 | GD48: 0 | GE48: 0 | GF48: 0 | GG48: 0 | GH48: 0 | GI48: 0 | GJ48: 0 | GK48: 0 | GL48: 0 | GM48: 0 | GN48: 0 | GO48: 0 | GP48: 0 | GQ48: 0 | GR48: 0 | GS48: 0 | GT48: 0 | GU48: 0 | GV48: 0 | GW48: 0 | GX48: 0 | GY48: 0 | GZ48: 0 | HA48: 0 | HB48: 0 | HC48: 0 | HD48: 0 | HE48: 0 | HF48: 0 | HG48: 0 | HJ48: 1066 | HK48: =SUM(C$4:HI$4) -> 215 | HL48: =SUM(C48:HI48) -> 0 | HM48: =100*HL48/HK48 -> 0 | HO48: 8.22 | HP48: 3.49 | HQ48: 3.15
A49: Latin America | B49: Argentina | C49: 0 | D49: 0 | E49: 0 | F49: 0 | G49: 0 | H49: 0 | I49: 0 | J49: 0 | K49: 0 | L49: 0 | M49: 0 | N49: 0 | O49: 0 | P49: 0 | Q49: 0 | R49: 0 | S49: 0 | T49: 0 | U49: 0 | V49: 0 | W49: 0 | X49: 0 | Y49: 0 | Z49: 0 | AA49: 0 | AB49: 0 | AC49: 0 | AD49: 0 | AE49: 1 | AF49: 1 | AG49: 1 | AH49: 1 | AI49: 1 | AJ49: 1 | AK49: 1 | AL49: 1 | AM49: 1 | AN49: 1 | AO49: 1 | AP49: 1 | AQ49: 1 | AR49: 1 | AS49: 1 | AT49: 1 | AU49: 1 | AV49: 1 | AW49: 1 | AX49: 1 | AY49: 1 | AZ49: 1 | BA49: 1 | BB49: 1 | BC49: 1 | BD49: 1 | BE49: 1 | BF49: 1 | BG49: 1 | BH49: 1 | BI49: 0 | BJ49: 0 | BK49: 0 | BL49: 0 | BM49: 0 | BN49: 0 | BO49: 0 | BP49: 0 | BQ49: 0 | BR49: 0 | BS49: 0 | BT49: 0 | BU49: 0 | BV49: 0 | BW49: 0 | BX49: 0 | BY49: 0 | BZ49: 0 | CA49: 0 | CB49: 0 | CC49: 0 | CD49: 0 | CE49: 0 | CF49: 0 | CG49: 0 | CH49: 0 | CI49: 0 | CJ49: 0 | CK49: 0 | CL49: 0 | CM49: 0 | CN49: 0 | CO49: 1 | CP49: 1 | CQ49: 1 | CR49: 1 | CS49: 0 | CT49: 0 | CU49: 0 | CV49: 0 | CW49: 0 | CX49: 0 | CY49: 0 | CZ49: 0 | DA49: 0 | DB49: 0 | DC49: 0 | DD49: 0 | DE49: 0 | DF49: 0 | DG49: 0 | DH49: 0 | DI49: 0 | DJ49: 0 | DK49: 0 | DL49: 0 | DM49: 0 | DN49: 0 | DO49: 0 | DP49: 0 | DQ49: 0 | DR49: 0 | DS49: 0 | DT49: 0 | DU49: 0 | DV49: 0 | DW49: 0 | DX49: 0 | DY49: 0 | DZ49: 0 | EA49: 0 | EB49: 0 | EC49: 0 | ED49: 0 | EE49: 0 | EF49: 0 | EG49: 0 | EH49: 0 | EI49: 0 | EJ49: 0 | EK49: 0 | EL49: 0 | EM49: 0 | EN49: 0 | EO49: 0 | EP49: 0 | EQ49: 0 | ER49: 0 | ES49: 0 | ET49: 0 | EU49: 0 | EV49: 0 | EW49: 0 | EX49: 1 | EY49: 0 | EZ49: 0 | FA49: 0 | FB49: 0 | FC49: 1 | FD49: 1 | FE49: 1 | FF49: 1 | FG49: 1 | FH49: 1 | FI49: 1 | FJ49: 1 | FK49: 1 | FL49: 1 | FM49: 0 | FN49: 0 | FO49: 0 | FP49: 0 | FQ49: 0 | FR49: 0 | FS49: 0 | FT49: 0 | FU49: 0 | FV49: 0 | FW49: 0 | FX49: 0 | FY49: 0 | FZ49: 0 | GA49: 0 | GB49: 0 | GC49: 1 | GD49: 1 | GE49: 1 | GF49: 1 | GG49: 1 | GH49: 1 | GI49: 1 | GJ49: 1 | GK49: 1 | GL49: 1 | GM49: 1 | GN49: 1 | GO49: 0 | GP49: 0 | GQ49: 0 | GR49: 0 | GS49: 0 | GT49: 0 | GU49: 0 | GV49: 1 | GW49: 1 | GX49: 1 | GY49: 1 | GZ49: 1 | HA49: 0 | HB49: 0 | HC49: 0 | HD49: 0 | HE49: 0 | HF49: 0 | HG49: 0 | HH49: 1 | HI49: 1 | HJ49: 1816 | HK49: =SUM(S$4:HI$4) -> 199 | HL49: =SUM(S49:HI49) -> 64 | HM49: =100*HL49/HK49 -> 32.160804 | HO49: 1.06 | HP49: 0.78 | HQ49: 0.73
B50: Bolivia | C50: 0 | D50: 0 | E50: 0 | F50: 0 | G50: 0 | H50: 0 | I50: 0 | J50: 0 | K50: 0 | L50: 0 | M50: 0 | N50: 0 | O50: 0 | P50: 0 | Q50: 0 | R50: 0 | S50: 0 | T50: 0 | U50: 0 | V50: 0 | W50: 0 | X50: 0 | Y50: 0 | Z50: 0 | AA50: 0 | AB50: 0 | AC50: 0 | AD50: 0 | AE50: 0 | AF50: 0 | AG50: 0 | AH50: 0 | AI50: 0 | AJ50: 0 | AK50: 0 | AL50: 0 | AM50: 0 | AN50: 0 | AO50: 0 | AP50: 0 | AQ50: 0 | AR50: 0 | AS50: 0 | AT50: 0 | AU50: 0 | AV50: 0 | AW50: 0 | AX50: 0 | AY50: 0 | AZ50: 0 | BA50: 0 | BB50: 0 | BC50: 0 | BD50: 0 | BE50: 0 | BF50: 0 | BG50: 0 | BH50: 0 | BI50: 0 | BJ50: 0 | BK50: 0 | BL50: 0 | BM50: 0 | BN50: 0 | BO50: 0 | BP50: 0 | BQ50: 0 | BR50: 0 | BS50: 0 | BT50: 0 | BU50: 0 | BV50: 0 | BW50: 0 | BX50: 0 | BY50: 0 | BZ50: 1 | CA50: 1 | CB50: 1 | CC50: 1 | CD50: 1 | CE50: 0 | CF50: 0 | CG50: 0 | CH50: 0 | CI50: 0 | CJ50: 0 | CK50: 0 | CL50: 0 | CM50: 0 | CN50: 0 | CO50: 0 | CP50: 0 | CQ50: 0 | CR50: 0 | CS50: 0 | CT50: 0 | CU50: 0 | CV50: 0 | CW50: 0 | CX50: 0 | CY50: 0 | CZ50: 0 | DA50: 0 | DB50: 0 | DC50: 0 | DD50: 0 | DE50: 0 | DF50: 0 | DG50: 0 | DH50: 0 | DI50: 0 | DJ50: 0 | DK50: 0 | DL50: 0 | DM50: 0 | DN50: 0 | DO50: 0 | DP50: 0 | DQ50: 0 | DR50: 0 | DS50: 0 | DT50: 0 | DU50: 0 | DV50: 0 | DW50: 0 | DX50: 0 | DY50: 0 | DZ50: 0 | EA50: 0 | EB50: 0 | EC50: 0 | ED50: 1 | EE50: 1 | EF50: 1 | EG50: 1 | EH50: 1 | EI50: 1 | EJ50: 1 | EK50: 1 | EL50: 1 | EM50: 1 | EN50: 1 | EO50: 1 | EP50: 1 | EQ50: 1 | ER50: 1 | ES50: 1 | ET50: 1 | EU50: 1 | EV50: 0 | EW50: 0 | EX50: 0 | EY50: 0 | EZ50: 0 | FA50: 0 | FB50: 0 | FC50: 0 | FD50: 0 | FE50: 0 | FF50: 0 | FG50: 0 | FH50: 0 | FI50: 0 | FJ50: 0 | FK50: 0 | FL50: 0 | FM50: 0 | FN50: 0 | FO50: 0 | FP50: 0 | FQ50: 0 | FR50: 0 | FS50: 0 | FT50: 0 | FU50: 0 | FV50: 0 | FW50: 0 | FX50: 0 | FY50: 0 | FZ50: 0 | GA50: 1 | GB50: 1 | GC50: 1 | GD50: 1 | GE50: 1 | GF50: 0 | GG50: 1 | GH50: 1 | GI50: 1 | GJ50: 1 | GK50: 1 | GL50: 1 | GM50: 1 | GN50: 1 | GO50: 1 | GP50: 1 | GQ50: 1 | GR50: 1 | GS50: 0 | GT50: 0 | GU50: 0 | GV50: 0 | GW50: 0 | GX50: 0 | GY50: 0 | GZ50: 0 | HA50: 0 | HB50: 0 | HC50: 0 | HD50: 0 | HE50: 0 | HF50: 0 | HG50: 0 | HH50: 0 | HI50: 0 | HJ50: 1825 | HK50: =SUM(AB$4:HI$4) -> 190 | HL50: =SUM(AB50:HI50) -> 40 | HM50: =100*HL50/HK50 -> 21.052632 | HO50: 0 | HP50: 0.05 | HQ50: 0.06
B51: Brazil | C51: 0 | D51: 0 | E51: 0 | F51: 0 | G51: 0 | H51: 0 | I51: 0 | J51: 0 | K51: 0 | L51: 0 | M51: 0 | N51: 0 | O51: 0 | P51: 0 | Q51: 0 | R51: 0 | S51: 0 | T51: 0 | U51: 0 | V51: 0 | W51: 0 | X51: 0 | Y51: 0 | Z51: 0 | AA51: 0 | AB51: 0 | AC51: 0 | AD51: 0 | AE51: 0 | AF51: 0 | AG51: 0 | AH51: 0 | AI51: 0 | AJ51: 0 | AK51: 0 | AL51: 0 | AM51: 0 | AN51: 0 | AO51: 0 | AP51: 0 | AQ51: 0 | AR51: 0 | AS51: 0 | AT51: 0 | AU51: 0 | AV51: 0 | AW51: 0 | AX51: 0 | AY51: 0 | AZ51: 0 | BA51: 0 | BB51: 0 | BC51: 0 | BD51: 0 | BE51: 0 | BF51: 0 | BG51: 0 | BH51: 0 | BI51: 0 | BJ51: 0 | BK51: 0 | BL51: 0 | BM51: 0 | BN51: 0 | BO51: 0 | BP51: 0 | BQ51: 0 | BR51: 0 | BS51: 0 | BT51: 0 | BU51: 0 | BV51: 0 | BW51: 0 | BX51: 0 | BY51: 0 | BZ51: 0 | CA51: 0 | CB51: 0 | CC51: 0 | CD51: 0 | CE51: 0 | CF51: 0 | CG51: 0 | CH51: 0 | CI51: 0 | CJ51: 0 | CK51: 0 | CL51: 0 | CM51: 0 | CN51: 0 | CO51: 0 | CP51: 0 | CQ51: 0 | CR51: 0 | CS51: 0 | CT51: 0 | CU51: 0 | CV51: 0 | CW51: 1 | CX51: 1 | CY51: 1 | CZ51: 1 | DA51: 1 | DB51: 1 | DC51: 1 | DD51: 1 | DE51: 1 | DF51: 1 | DG51: 1 | DH51: 1 | DI51: 1 | DJ51: 0 | DK51: 0 | DL51: 0 | DM51: 1 | DN51: 1 | DO51: 1 | DP51: 1 | DQ51: 1 | DR51: 1 | DS51: 0 | DT51: 0 | DU51: 0 | DV51: 0 | DW51: 0 | DX51: 0 | DY51: 0 | DZ51: 0 | EA51: 0 | EB51: 0 | EC51: 0 | ED51: 1 | EE51: 1 | EF51: 1 | EG51: 0 | EH51: 0 | EI51: 0 | EJ51: 1 | EK51: 1 | EL51: 1 | EM51: 1 | EN51: 1 | EO51: 1 | EP51: 1 | EQ51: 0 | ER51: 0 | ES51: 0 | ET51: 0 | EU51: 0 | EV51: 0 | EW51: 0 | EX51: 0 | EY51: 0 | EZ51: 0 | FA51: 0 | FB51: 0 | FC51: 0 | FD51: 0 | FE51: 0 | FF51: 0 | FG51: 0 | FH51: 1 | FI51: 1 | FJ51: 1 | FK51: 1 | FL51: 0 | FM51: 0 | FN51: 0 | FO51: 0 | FP51: 0 | FQ51: 0 | FR51: 0 | FS51: 0 | FT51: 0 | FU51: 0 | FV51: 0 | FW51: 0 | FX51: 0 | FY51: 0 | FZ51: 0 | GA51: 0 | GB51: 0 | GC51: 0 | GD51: 1 | GE51: 1 | GF51: 1 | GG51: 1 | GH51: 1 | GI51: 1 | GJ51: 1 | GK51: 1 | GL51: 1 | GM51: 1 | GN51: 1 | GO51: 1 | GP51: 0 | GQ51: 0 | GR51: 0 | GS51: 0 | GT51: 0 | GU51: 0 | GV51: 0 | GW51: 0 | GX51: 0 | GY51: 0 | GZ51: 0 | HA51: 0 | HB51: 0 | HC51: 0 | HD51: 0 | HE51: 0 | HF51: 0 | HG51: 0 | HH51: 0 | HI51: 0 | HJ51: 1822 | HK51: =SUM(Y$4:HI$4) -> 193 | HL51: =SUM(Y51:HI51) -> 45 | HM51: =100*HL51/HK51 -> 23.316062 | HO51: 0.7 | HP51: 2.74 | HQ51: 2.49
B52: Chile | C52: 0 | D52: 0 | E52: 0 | F52: 0 | G52: 0 | H52: 0 | I52: 0 | J52: 0 | K52: 0 | L52: 0 | M52: 0 | N52: 0 | O52: 0 | P52: 0 | Q52: 0 | R52: 0 | S52: 0 | T52: 0 | U52: 0 | V52: 0 | W52: 0 | X52: 0 | Y52: 0 | Z52: 0 | AA52: 0 | AB52: 0 | AC52: 1 | AD52: 1 | AE52: 1 | AF52: 1 | AG52: 1 | AH52: 1 | AI52: 1 | AJ52: 1 | AK52: 1 | AL52: 1 | AM52: 1 | AN52: 1 | AO52: 1 | AP52: 1 | AQ52: 1 | AR52: 1 | AS52: 1 | AT52: 0 | AU52: 0 | AV52: 0 | AW52: 0 | AX52: 0 | AY52: 0 | AZ52: 0 | BA52: 0 | BB52: 0 | BC52: 0 | BD52: 0 | BE52: 0 | BF52: 0 | BG52: 0 | BH52: 0 | BI52: 0 | BJ52: 0 | BK52: 0 | BL52: 0 | BM52: 0 | BN52: 0 | BO52: 0 | BP52: 0 | BQ52: 0 | BR52: 0 | BS52: 0 | BT52: 0 | BU52: 0 | BV52: 0 | BW52: 0 | BX52: 0 | BY52: 0 | BZ52: 0 | CA52: 0 | CB52: 0 | CC52: 0 | CD52: 0 | CE52: 1 | CF52: 1 | CG52: 1 | CH52: 1 | CI52: 0 | CJ52: 0 | CK52: 0 | CL52: 0 | CM52: 0 | CN52: 0 | CO52: 0 | CP52: 0 | CQ52: 0 | CR52: 0 | CS52: 0 | CT52: 0 | CU52: 0 | CV52: 0 | CW52: 0 | CX52: 0 | CY52: 0 | CZ52: 0 | DA52: 0 | DB52: 0 | DC52: 0 | DD52: 0 | DE52: 0 | DF52: 0 | DG52: 0 | DH52: 0 | DI52: 0 | DJ52: 0 | DK52: 0 | DL52: 0 | DM52: 0 | DN52: 0 | DO52: 0 | DP52: 0 | DQ52: 0 | DR52: 0 | DS52: 0 | DT52: 0 | DU52: 0 | DV52: 0 | DW52: 0 | DX52: 0 | DY52: 0 | DZ52: 0 | EA52: 0 | EB52: 0 | EC52: 0 | ED52: 1 | EE52: 1 | EF52: 1 | EG52: 1 | EH52: 1 | EI52: 1 | EJ52: 1 | EK52: 1 | EL52: 1 | EM52: 1 | EN52: 1 | EO52: 1 | EP52: 1 | EQ52: 1 | ER52: 1 | ES52: 1 | ET52: 1 | EU52: 0 | EV52: 0 | EW52: 0 | EX52: 0 | EY52: 0 | EZ52: 0 | FA52: 0 | FB52: 0 | FC52: 0 | FD52: 0 | FE52: 0 | FF52: 0 | FG52: 0 | FH52: 1 | FI52: 0 | FJ52: 1 | FK52: 0 | FL52: 1 | FM52: 0 | FN52: 0 | FO52: 0 | FP52: 0 | FQ52: 0 | FR52: 0 | FS52: 1 | FT52: 1 | FU52: 1 | FV52: 1 | FW52: 0 | FX52: 0 | FY52: 0 | FZ52: 0 | GA52: 0 | GB52: 0 | GC52: 0 | GD52: 1 | GE52: 1 | GF52: 1 | GG52: 1 | GH52: 1 | GI52: 1 | GJ52: 1 | GK52: 1 | GL52: 0 | GM52: 0 | GN52: 0 | GO52: 0 | GP52: 0 | GQ52: 0 | GR52: 0 | GS52: 0 | GT52: 0 | GU52: 0 | GV52: 0 | GW52: 0 | GX52: 0 | GY52: 0 | GZ52: 0 | HA52: 0 | HB52: 0 | HC52: 0 | HD52: 0 | HE52: 0 | HF52: 0 | HG52: 0 | HH52: 0 | HI52: 0 | HJ52: 1818 | HK52: =SUM(U$4:HI$4) -> 197 | HL52: =SUM(U52:HI52) -> 53 | HM52: =100*HL52/HK52 -> 26.903553 | HO52: 0.38 | HP52: 0.31 | HQ52: 0.42
B53: Colombia | C53: 0 | D53: 0 | E53: 0 | F53: 0 | G53: 0 | H53: 0 | I53: 0 | J53: 0 | K53: 0 | L53: 0 | M53: 0 | N53: 0 | O53: 0 | P53: 0 | Q53: 0 | R53: 0 | S53: 0 | T53: 0 | U53: 0 | V53: 0 | W53: 0 | X53: 0 | Y53: 0 | Z53: 0 | AA53: 0 | AB53: 0 | AC53: 1 | AD53: 1 | AE53: 1 | AF53: 1 | AG53: 1 | AH53: 1 | AI53: 1 | AJ53: 1 | AK53: 1 | AL53: 1 | AM53: 1 | AN53: 1 | AO53: 1 | AP53: 1 | AQ53: 1 | AR53: 1 | AS53: 1 | AT53: 1 | AU53: 1 | AV53: 1 | AW53: 0 | AX53: 0 | AY53: 0 | AZ53: 0 | BA53: 1 | BB53: 1 | BC53: 1 | BD53: 1 | BE53: 1 | BF53: 1 | BG53: 1 | BH53: 1 | BI53: 1 | BJ53: 1 | BK53: 1 | BL53: 1 | BM53: 0 | BN53: 0 | BO53: 0 | BP53: 0 | BQ53: 0 | BR53: 0 | BS53: 0 | BT53: 0 | BU53: 0 | BV53: 0 | BW53: 0 | BX53: 1 | BY53: 0 | BZ53: 0 | CA53: 0 | CB53: 0 | CC53: 0 | CD53: 0 | CE53: 1 | CF53: 1 | CG53: 1 | CH53: 1 | CI53: 1 | CJ53: 1 | CK53: 1 | CL53: 1 | CM53: 1 | CN53: 1 | CO53: 1 | CP53: 1 | CQ53: 1 | CR53: 1 | CS53: 1 | CT53: 1 | CU53: 1 | CV53: 0 | CW53: 0 | CX53: 0 | CY53: 1 | CZ53: 1 | DA53: 1 | DB53: 1 | DC53: 1 | DD53: 0 | DE53: 0 | DF53: 0 | DG53: 0 | DH53: 0 | DI53: 0 | DJ53: 0 | DK53: 0 | DL53: 0 | DM53: 0 | DN53: 0 | DO53: 0 | DP53: 0 | DQ53: 0 | DR53: 0 | DS53: 0 | DT53: 0 | DU53: 0 | DV53: 0 | DW53: 0 | DX53: 0 | DY53: 0 | DZ53: 0 | EA53: 0 | EB53: 0 | EC53: 0 | ED53: 0 | EE53: 1 | EF53: 1 | EG53: 1 | EH53: 1 | EI53: 1 | EJ53: 1 | EK53: 1 | EL53: 1 | EM53: 1 | EN53: 1 | EO53: 1 | EP53: 1 | EQ53: 1 | ER53: 0 | ES53: 0 | ET53: 0 | EU53: 0 | EV53: 0 | EW53: 0 | EX53: 0 | EY53: 0 | EZ53: 0 | FA53: 0 | FB53: 0 | FC53: 0 | FD53: 0 | FE53: 0 | FF53: 0 | FG53: 0 | FH53: 0 | FI53: 0 | FJ53: 0 | FK53: 0 | FL53: 0 | FM53: 0 | FN53: 0 | FO53: 0 | FP53: 0 | FQ53: 0 | FR53: 0 | FS53: 0 | FT53: 0 | FU53: 0 | FV53: 0 | FW53: 0 | FX53: 0 | FY53: 0 | FZ53: 0 | GA53: 0 | GB53: 0 | GC53: 0 | GD53: 0 | GE53: 0 | GF53: 0 | GG53: 0 | GH53: 0 | GI53: 0 | GJ53: 0 | GK53: 0 | GL53: 0 | GM53: 0 | GN53: 0 | GO53: 0 | GP53: 0 | GQ53: 0 | GR53: 0 | GS53: 0 | GT53: 0 | GU53: 0 | GV53: 0 | GW53: 0 | GX53: 0 | GY53: 0 | GZ53: 0 | HA53: 0 | HB53: 0 | HC53: 0 | HD53: 0 | HE53: 0 | HF53: 0 | HG53: 0 | HH53: 0 | HI53: 0 | HJ53: 1819 | HK53: =SUM(V$4:HI$4) -> 196 | HL53: =SUM(V53:HI53) -> 68 | HM53: =100*HL53/HK53 -> 34.693878 | HO53: 0.23 | HP53: 0.59 | HQ53: 0.54
B54: Costa Rica | C54: 0 | D54: 0 | E54: 0 | F54: 0 | G54: 0 | H54: 0 | I54: 0 | J54: 0 | K54: 0 | L54: 0 | M54: 0 | N54: 0 | O54: 0 | P54: 0 | Q54: 0 | R54: 0 | S54: 0 | T54: 0 | U54: 0 | V54: 0 | W54: 0 | X54: 0 | Y54: 0 | Z54: 0 | AA54: 0 | AB54: 0 | AC54: 0 | AD54: 0 | AE54: 1 | AF54: 1 | AG54: 1 | AH54: 1 | AI54: 1 | AJ54: 1 | AK54: 1 | AL54: 1 | AM54: 1 | AN54: 1 | AO54: 1 | AP54: 1 | AQ54: 1 | AR54: 0 | AS54: 0 | AT54: 0 | AU54: 0 | AV54: 0 | AW54: 0 | AX54: 0 | AY54: 0 | AZ54: 0 | BA54: 0 | BB54: 0 | BC54: 0 | BD54: 0 | BE54: 0 | BF54: 0 | BG54: 0 | BH54: 0 | BI54: 0 | BJ54: 0 | BK54: 0 | BL54: 0 | BM54: 0 | BN54: 0 | BO54: 0 | BP54: 0 | BQ54: 0 | BR54: 0 | BS54: 0 | BT54: 0 | BU54: 0 | BV54: 0 | BW54: 0 | BX54: 0 | BY54: 1 | BZ54: 1 | CA54: 1 | CB54: 1 | CC54: 1 | CD54: 1 | CE54: 1 | CF54: 1 | CG54: 1 | CH54: 1 | CI54: 1 | CJ54: 1 | CK54: 0 | CL54: 0 | CM54: 0 | CN54: 0 | CO54: 0 | CP54: 0 | CQ54: 0 | CR54: 0 | CS54: 0 | CT54: 1 | CU54: 1 | CV54: 1 | CW54: 0 | CX54: 0 | CY54: 0 | CZ54: 1 | DA54: 1 | DB54: 1 | DC54: 1 | DD54: 1 | DE54: 1 | DF54: 1 | DG54: 1 | DH54: 1 | DI54: 1 | DJ54: 1 | DK54: 0 | DL54: 0 | DM54: 0 | DN54: 0 | DO54: 0 | DP54: 0 | DQ54: 0 | DR54: 0 | DS54: 0 | DT54: 0 | DU54: 0 | DV54: 0 | DW54: 0 | DX54: 0 | DY54: 0 | DZ54: 0 | EA54: 0 | EB54: 0 | EC54: 0 | ED54: 0 | EE54: 1 | EF54: 1 | EG54: 1 | EH54: 1 | EI54: 1 | EJ54: 1 | EK54: 1 | EL54: 1 | EM54: 1 | EN54: 1 | EO54: 1 | EP54: 1 | EQ54: 1 | ER54: 1 | ES54: 1 | ET54: 1 | EU54: 1 | EV54: 1 | EW54: 1 | EX54: 1 | EY54: 1 | EZ54: 0 | FA54: 0 | FB54: 0 | FC54: 0 | FD54: 0 | FE54: 0 | FF54: 0 | FG54: 0 | FH54: 0 | FI54: 1 | FJ54: 0 | FK54: 0 | FL54: 0 | FM54: 0 | FN54: 0 | FO54: 0 | FP54: 0 | FQ54: 0 | FR54: 0 | FS54: 0 | FT54: 0 | FU54: 0 | FV54: 0 | FW54: 0 | FX54: 0 | FY54: 0 | FZ54: 0 | GA54: 0 | GB54: 1 | GC54: 1 | GD54: 1 | GE54: 1 | GF54: 1 | GG54: 1 | GH54: 1 | GI54: 1 | GJ54: 1 | GK54: 1 | GL54: 0 | GM54: 0 | GN54: 0 | GO54: 0 | GP54: 0 | GQ54: 0 | GR54: 0 | GS54: 0 | GT54: 0 | GU54: 0 | GV54: 0 | GW54: 0 | GX54: 0 | GY54: 0 | GZ54: 0 | HA54: 0 | HB54: 0 | HC54: 0 | HD54: 0 | HE54: 0 | HF54: 0 | HG54: 0 | HH54: 0 | HI54: 0 | HJ54: 1821 | HK54: =SUM(X$4:HI$4) -> 194 | HL54: =SUM(X54:HI54) -> 71 | HM54: =100*HL54/HK54 -> 36.597938 | HO54: 0 | HP54: 0.05 | HQ54: 0.06
B55: Dominican Republic | C55: 0 | D55: 0 | E55: 0 | F55: 0 | G55: 0 | H55: 0 | I55: 0 | J55: 0 | K55: 0 | L55: 0 | M55: 0 | N55: 0 | O55: 0 | P55: 0 | Q55: 0 | R55: 0 | S55: 0 | T55: 0 | U55: 0 | V55: 0 | W55: 0 | X55: 0 | Y55: 0 | Z55: 0 | AA55: 0 | AB55: 0 | AC55: 0 | AD55: 0 | AE55: 0 | AF55: 0 | AG55: 0 | AH55: 0 | AI55: 0 | AJ55: 0 | AK55: 0 | AL55: 0 | AM55: 0 | AN55: 0 | AO55: 0 | AP55: 0 | AQ55: 0 | AR55: 0 | AS55: 0 | AT55: 0 | AU55: 0 | AV55: 0 | AW55: 0 | AX55: 0 | AY55: 0 | AZ55: 0 | BA55: 0 | BB55: 0 | BC55: 0 | BD55: 0 | BE55: 0 | BF55: 0 | BG55: 0 | BH55: 0 | BI55: 0 | BJ55: 0 | BK55: 0 | BL55: 0 | BM55: 0 | BN55: 0 | BO55: 0 | BP55: 0 | BQ55: 0 | BR55: 0 | BS55: 0 | BT55: 0 | BU55: 0 | BV55: 0 | BW55: 1 | BX55: 1 | BY55: 1 | BZ55: 1 | CA55: 1 | CB55: 1 | CC55: 1 | CD55: 1 | CE55: 1 | CF55: 1 | CG55: 1 | CH55: 1 | CI55: 1 | CJ55: 1 | CK55: 1 | CL55: 1 | CM55: 1 | CN55: 0 | CO55: 0 | CP55: 0 | CQ55: 1 | CR55: 1 | CS55: 0 | CT55: 0 | CU55: 0 | CV55: 1 | CW55: 0 | CX55: 1 | CY55: 1 | CZ55: 1 | DA55: 1 | DB55: 1 | DC55: 1 | DD55: 1 | DE55: 1 | DF55: 1 | DG55: 0 | DH55: 0 | DI55: 0 | DJ55: 0 | DK55: 0 | DL55: 0 | DM55: 0 | DN55: 0 | DO55: 0 | DP55: 0 | DQ55: 0 | DR55: 0 | DS55: 0 | DT55: 0 | DU55: 0 | DV55: 0 | DW55: 0 | DX55: 0 | DY55: 0 | DZ55: 0 | EA55: 0 | EB55: 0 | EC55: 0 | ED55: 1 | EE55: 1 | EF55: 1 | EG55: 1 | EH55: 0 | EI55: 0 | EJ55: 0 | EK55: 0 | EL55: 0 | EM55: 0 | EN55: 0 | EO55: 0 | EP55: 0 | EQ55: 0 | ER55: 0 | ES55: 0 | ET55: 0 | EU55: 0 | EV55: 0 | EW55: 0 | EX55: 0 | EY55: 0 | EZ55: 0 | FA55: 0 | FB55: 0 | FC55: 0 | FD55: 0 | FE55: 0 | FF55: 0 | FG55: 0 | FH55: 0 | FI55: 0 | FJ55: 0 | FK55: 0 | FL55: 0 | FM55: 0 | FN55: 0 | FO55: 0 | FP55: 0 | FQ55: 0 | FR55: 0 | FS55: 0 | FT55: 0 | FU55: 0 | FV55: 0 | FW55: 0 | FX55: 0 | FY55: 0 | FZ55: 0 | GA55: 0 | GB55: 0 | GC55: 1 | GD55: 1 | GE55: 1 | GF55: 1 | GG55: 1 | GH55: 1 | GI55: 1 | GJ55: 1 | GK55: 1 | GL55: 1 | GM55: 1 | GN55: 1 | GO55: 1 | GP55: 0 | GQ55: 0 | GR55: 0 | GS55: 0 | GT55: 0 | GU55: 0 | GV55: 0 | GW55: 0 | GX55: 0 | GY55: 0 | GZ55: 1 | HA55: 0 | HB55: 0 | HC55: 0 | HD55: 0 | HE55: 0 | HF55: 0 | HG55: 0 | HH55: 0 | HI55: 0 | HJ55: 1845 | HK55: =SUM(AV$4:HI$4) -> 170 | HL55: =SUM(AV55:HI55) -> 47 | HM55: =100*HL55/HK55 -> 27.647059 | HO55: 0 | HP55: 0.06 | HQ55: 0.08
B56: Ecuador | C56: 0 | D56: 0 | E56: 0 | F56: 0 | G56: 0 | H56: 0 | I56: 0 | J56: 0 | K56: 0 | L56: 0 | M56: 0 | N56: 0 | O56: 0 | P56: 0 | Q56: 0 | R56: 0 | S56: 0 | T56: 0 | U56: 0 | V56: 0 | W56: 0 | X56: 0 | Y56: 0 | Z56: 0 | AA56: 0 | AB56: 0 | AC56: 0 | AD56: 0 | AE56: 0 | AF56: 0 | AG56: 1 | AH56: 1 | AI56: 1 | AJ56: 1 | AK56: 1 | AL56: 1 | AM56: 1 | AN56: 1 | AO56: 1 | AP56: 1 | AQ56: 1 | AR56: 1 | AS56: 1 | AT56: 1 | AU56: 1 | AV56: 1 | AW56: 0 | AX56: 0 | AY56: 0 | AZ56: 0 | BA56: 0 | BB56: 0 | BC56: 0 | BD56: 0 | BE56: 0 | BF56: 0 | BG56: 0 | BH56: 0 | BI56: 0 | BJ56: 0 | BK56: 0 | BL56: 0 | BM56: 0 | BN56: 0 | BO56: 0 | BP56: 0 | BQ56: 0 | BR56: 0 | BS56: 1 | BT56: 1 | BU56: 1 | BV56: 1 | BW56: 1 | BX56: 1 | BY56: 1 | BZ56: 1 | CA56: 1 | CB56: 1 | CC56: 1 | CD56: 1 | CE56: 1 | CF56: 1 | CG56: 1 | CH56: 1 | CI56: 1 | CJ56: 1 | CK56: 1 | CL56: 1 | CM56: 1 | CN56: 1 | CO56: 1 | CP56: 0 | CQ56: 0 | CR56: 0 | CS56: 1 | CT56: 1 | CU56: 1 | CV56: 1 | CW56: 1 | CX56: 0 | CY56: 0 | CZ56: 0 | DA56: 0 | DB56: 0 | DC56: 0 | DD56: 0 | DE56: 1 | DF56: 1 | DG56: 1 | DH56: 1 | DI56: 1 | DJ56: 1 | DK56: 0 | DL56: 0 | DM56: 1 | DN56: 1 | DO56: 1 | DP56: 1 | DQ56: 1 | DR56: 1 | DS56: 1 | DT56: 1 | DU56: 1 | DV56: 1 | DW56: 1 | DX56: 0 | DY56: 0 | DZ56: 0 | EA56: 0 | EB56: 1 | EC56: 1 | ED56: 1 | EE56: 1 | EF56: 1 | EG56: 1 | EH56: 1 | EI56: 1 | EJ56: 1 | EK56: 1 | EL56: 1 | EM56: 1 | EN56: 1 | EO56: 1 | EP56: 1 | EQ56: 1 | ER56: 1 | ES56: 1 | ET56: 1 | EU56: 1 | EV56: 1 | EW56: 1 | EX56: 1 | EY56: 1 | EZ56: 1 | FA56: 1 | FB56: 0 | FC56: 0 | FD56: 0 | FE56: 0 | FF56: 0 | FG56: 0 | FH56: 0 | FI56: 0 | FJ56: 0 | FK56: 0 | FL56: 0 | FM56: 0 | FN56: 0 | FO56: 0 | FP56: 0 | FQ56: 0 | FR56: 0 | FS56: 0 | FT56: 0 | FU56: 0 | FV56: 0 | FW56: 0 | FX56: 0 | FY56: 0 | FZ56: 0 | GA56: 0 | GB56: 0 | GC56: 1 | GD56: 1 | GE56: 1 | GF56: 1 | GG56: 1 | GH56: 1 | GI56: 1 | GJ56: 1 | GK56: 1 | GL56: 1 | GM56: 1 | GN56: 1 | GO56: 1 | GP56: 1 | GQ56: 0 | GR56: 0 | GS56: 0 | GT56: 1 | GU56: 1 | GV56: 0 | GW56: 0 | GX56: 0 | GY56: 0 | GZ56: 0 | HA56: 0 | HB56: 0 | HC56: 1 | HD56: 1 | HE56: 0 | HF56: 0 | HG56: 0 | HH56: 0 | HI56: 0 | HJ56: 1830 | HK56: =SUM(AG$4:HI$4) -> 185 | HL56: =SUM(AG56:HI56) -> 105 | HM56: =100*HL56/HK56 -> 56.756757 | HO56: 0 | HP56: 0.15 | HQ56: 0.11 | HS56: Technically in default since 1826 when Gran Colombia defaulted.
B57: El Salvador | C57: 0 | D57: 0 | E57: 0 | F57: 0 | G57: 0 | H57: 0 | I57: 0 | J57: 0 | K57: 0 | L57: 0 | M57: 0 | N57: 0 | O57: 0 | P57: 0 | Q57: 0 | R57: 0 | S57: 0 | T57: 0 | U57: 0 | V57: 0 | W57: 0 | X57: 0 | Y57: 0 | Z57: 0 | AA57: 0 | AB57: 0 | AC57: 0 | AD57: 0 | AE57: 1 | AF57: 1 | AG57: 1 | AH57: 1 | AI57: 1 | AJ57: 1 | AK57: 1 | AL57: 1 | AM57: 1 | AN57: 1 | AO57: 1 | AP57: 1 | AQ57: 1 | AR57: 1 | AS57: 1 | AT57: 1 | AU57: 1 | AV57: 1 | AW57: 1 | AX57: 1 | AY57: 1 | AZ57: 1 | BA57: 1 | BB57: 1 | BC57: 1 | BD57: 1 | BE57: 1 | BF57: 1 | BG57: 1 | BH57: 1 | BI57: 1 | BJ57: 1 | BK57: 1 | BL57: 0 | BM57: 0 | BN57: 0 | BO57: 0 | BP57: 0 | BQ57: 0 | BR57: 0 | BS57: 0 | BT57: 0 | BU57: 0 | BV57: 0 | BW57: 0 | BX57: 0 | BY57: 0 | BZ57: 0 | CA57: 0 | CB57: 0 | CC57: 0 | CD57: 0 | CE57: 0 | CF57: 0 | CG57: 0 | CH57: 0 | CI57: 0 | CJ57: 0 | CK57: 0 | CL57: 0 | CM57: 0 | CN57: 0 | CO57: 0 | CP57: 0 | CQ57: 0 | CR57: 0 | CS57: 0 | CT57: 0 | CU57: 0 | CV57: 0 | CW57: 1 | CX57: 0 | CY57: 0 | CZ57: 0 | DA57: 0 | DB57: 0 | DC57: 0 | DD57: 0 | DE57: 0 | DF57: 0 | DG57: 0 | DH57: 0 | DI57: 0 | DJ57: 0 | DK57: 0 | DL57: 0 | DM57: 0 | DN57: 0 | DO57: 0 | DP57: 0 | DQ57: 0 | DR57: 0 | DS57: 0 | DT57: 1 | DU57: 1 | DV57: 0 | DW57: 0 | DX57: 0 | DY57: 0 | DZ57: 0 | EA57: 0 | EB57: 0 | EC57: 0 | ED57: 0 | EE57: 1 | EF57: 1 | EG57: 1 | EH57: 1 | EI57: 0 | EJ57: 0 | EK57: 1 | EL57: 1 | EM57: 1 | EN57: 1 | EO57: 1 | EP57: 1 | EQ57: 1 | ER57: 1 | ES57: 1 | ET57: 0 | EU57: 0 | EV57: 0 | EW57: 0 | EX57: 0 | EY57: 0 | EZ57: 0 | FA57: 0 | FB57: 0 | FC57: 0 | FD57: 0 | FE57: 0 | FF57: 0 | FG57: 0 | FH57: 0 | FI57: 0 | FJ57: 0 | FK57: 0 | FL57: 0 | FM57: 0 | FN57: 0 | FO57: 0 | FP57: 0 | FQ57: 0 | FR57: 0 | FS57: 0 | FT57: 0 | FU57: 0 | FV57: 0 | FW57: 0 | FX57: 0 | FY57: 0 | FZ57: 0 | GA57: 0 | GB57: 0 | GC57: 0 | GD57: 0 | GE57: 0 | GF57: 0 | GG57: 0 | GH57: 0 | GI57: 0 | GJ57: 0 | GK57: 0 | GL57: 0 | GM57: 0 | GN57: 0 | GO57: 0 | GP57: 0 | GQ57: 0 | GR57: 0 | GS57: 0 | GT57: 0 | GU57: 0 | GV57: 0 | GW57: 0 | GX57: 0 | GY57: 0 | GZ57: 0 | HA57: 0 | HB57: 0 | HC57: 0 | HD57: 0 | HE57: 0 | HF57: 0 | HG57: 0 | HH57: 0 | HI57: 0 | HJ57: 1821 | HK57: =SUM(X$4:HI$4) -> 194 | HL57: =SUM(X57:HI57) -> 49 | HM57: =100*HL57/HK57 -> 25.257732 | HO57: 0 | HP57: 0.04 | HQ57: 0.04
B58: Guatemala | C58: 0 | D58: 0 | E58: 0 | F58: 0 | G58: 0 | H58: 0 | I58: 0 | J58: 0 | K58: 0 | L58: 0 | M58: 0 | N58: 0 | O58: 0 | P58: 0 | Q58: 0 | R58: 0 | S58: 0 | T58: 0 | U58: 0 | V58: 0 | W58: 0 | X58: 0 | Y58: 0 | Z58: 0 | AA58: 0 | AB58: 0 | AC58: 0 | AD58: 0 | AE58: 1 | AF58: 1 | AG58: 1 | AH58: 1 | AI58: 1 | AJ58: 1 | AK58: 1 | AL58: 1 | AM58: 1 | AN58: 1 | AO58: 1 | AP58: 1 | AQ58: 1 | AR58: 1 | AS58: 1 | AT58: 1 | AU58: 1 | AV58: 1 | AW58: 1 | AX58: 1 | AY58: 1 | AZ58: 1 | BA58: 1 | BB58: 1 | BC58: 1 | BD58: 1 | BE58: 1 | BF58: 1 | BG58: 1 | BH58: 0 | BI58: 0 | BJ58: 0 | BK58: 0 | BL58: 0 | BM58: 0 | BN58: 0 | BO58: 0 | BP58: 0 | BQ58: 0 | BR58: 0 | BS58: 0 | BT58: 0 | BU58: 0 | BV58: 0 | BW58: 0 | BX58: 0 | BY58: 0 | BZ58: 0 | CA58: 1 | CB58: 1 | CC58: 1 | CD58: 1 | CE58: 1 | CF58: 1 | CG58: 1 | CH58: 1 | CI58: 1 | CJ58: 1 | CK58: 1 | CL58: 1 | CM58: 1 | CN58: 0 | CO58: 0 | CP58: 0 | CQ58: 0 | CR58: 0 | CS58: 1 | CT58: 0 | CU58: 0 | CV58: 0 | CW58: 0 | CX58: 1 | CY58: 1 | CZ58: 1 | DA58: 1 | DB58: 1 | DC58: 1 | DD58: 1 | DE58: 1 | DF58: 1 | DG58: 1 | DH58: 1 | DI58: 1 | DJ58: 1 | DK58: 1 | DL58: 1 | DM58: 0 | DN58: 0 | DO58: 0 | DP58: 0 | DQ58: 0 | DR58: 0 | DS58: 0 | DT58: 0 | DU58: 0 | DV58: 0 | DW58: 0 | DX58: 0 | DY58: 0 | DZ58: 0 | EA58: 0 | EB58: 0 | EC58: 0 | ED58: 0 | EE58: 0 | EF58: 1 | EG58: 1 | EH58: 1 | EI58: 1 | EJ58: 0 | EK58: 0 | EL58: 0 | EM58: 0 | EN58: 0 | EO58: 0 | EP58: 0 | EQ58: 0 | ER58: 0 | ES58: 0 | ET58: 0 | EU58: 0 | EV58: 0 | EW58: 0 | EX58: 0 | EY58: 0 | EZ58: 0 | FA58: 0 | FB58: 0 | FC58: 0 | FD58: 0 | FE58: 0 | FF58: 0 | FG58: 0 | FH58: 0 | FI58: 0 | FJ58: 0 | FK58: 0 | FL58: 0 | FM58: 0 | FN58: 0 | FO58: 0 | FP58: 0 | FQ58: 0 | FR58: 0 | FS58: 0 | FT58: 0 | FU58: 0 | FV58: 0 | FW58: 0 | FX58: 0 | FY58: 0 | FZ58: 0 | GA58: 0 | GB58: 0 | GC58: 0 | GD58: 0 | GE58: 0 | GF58: 0 | GG58: 1 | GH58: 0 | GI58: 0 | GJ58: 1 | GK58: 0 | GL58: 0 | GM58: 0 | GN58: 0 | GO58: 0 | GP58: 0 | GQ58: 0 | GR58: 0 | GS58: 0 | GT58: 0 | GU58: 0 | GV58: 0 | GW58: 0 | GX58: 0 | GY58: 0 | GZ58: 0 | HA58: 0 | HB58: 0 | HC58: 0 | HD58: 0 | HE58: 0 | HF58: 0 | HG58: 0 | HJ58: 1821 | HK58: =SUM(X$4:HI$4) -> 194 | HL58: =SUM(X58:HI58) -> 64 | HM58: =100*HL58/HK58 -> 32.989691 | HO58: 0 | HP58: 0.11 | HQ58: 0.11
B59: Honduras | C59: 0 | D59: 0 | E59: 0 | F59: 0 | G59: 0 | H59: 0 | I59: 0 | J59: 0 | K59: 0 | L59: 0 | M59: 0 | N59: 0 | O59: 0 | P59: 0 | Q59: 0 | R59: 0 | S59: 0 | T59: 0 | U59: 0 | V59: 0 | W59: 0 | X59: 0 | Y59: 0 | Z59: 0 | AA59: 0 | AB59: 0 | AC59: 0 | AD59: 0 | AE59: 1 | AF59: 1 | AG59: 1 | AH59: 1 | AI59: 1 | AJ59: 1 | AK59: 1 | AL59: 1 | AM59: 1 | AN59: 1 | AO59: 1 | AP59: 1 | AQ59: 1 | AR59: 1 | AS59: 1 | AT59: 1 | AU59: 1 | AV59: 1 | AW59: 1 | AX59: 1 | AY59: 1 | AZ59: 1 | BA59: 1 | BB59: 1 | BC59: 1 | BD59: 1 | BE59: 1 | BF59: 1 | BG59: 1 | BH59: 1 | BI59: 1 | BJ59: 1 | BK59: 1 | BL59: 1 | BM59: 1 | BN59: 1 | BO59: 1 | BP59: 1 | BQ59: 1 | BR59: 1 | BS59: 0 | BT59: 0 | BU59: 0 | BV59: 0 | BW59: 0 | BX59: 1 | BY59: 1 | BZ59: 1 | CA59: 1 | CB59: 1 | CC59: 1 | CD59: 1 | CE59: 1 | CF59: 1 | CG59: 1 | CH59: 1 | CI59: 1 | CJ59: 1 | CK59: 1 | CL59: 1 | CM59: 1 | CN59: 1 | CO59: 1 | CP59: 1 | CQ59: 1 | CR59: 1 | CS59: 1 | CT59: 1 | CU59: 1 | CV59: 1 | CW59: 1 | CX59: 1 | CY59: 1 | CZ59: 1 | DA59: 1 | DB59: 1 | DC59: 1 | DD59: 1 | DE59: 1 | DF59: 1 | DG59: 1 | DH59: 1 | DI59: 1 | DJ59: 1 | DK59: 1 | DL59: 1 | DM59: 1 | DN59: 1 | DO59: 1 | DP59: 1 | DQ59: 1 | DR59: 1 | DS59: 1 | DT59: 1 | DU59: 1 | DV59: 1 | DW59: 1 | DX59: 1 | DY59: 0 | DZ59: 0 | EA59: 0 | EB59: 0 | EC59: 0 | ED59: 0 | EE59: 0 | EF59: 0 | EG59: 0 | EH59: 0 | EI59: 0 | EJ59: 0 | EK59: 0 | EL59: 0 | EM59: 0 | EN59: 0 | EO59: 0 | EP59: 0 | EQ59: 0 | ER59: 0 | ES59: 0 | ET59: 0 | EU59: 0 | EV59: 0 | EW59: 0 | EX59: 0 | EY59: 0 | EZ59: 0 | FA59: 0 | FB59: 0 | FC59: 0 | FD59: 0 | FE59: 0 | FF59: 0 | FG59: 0 | FH59: 0 | FI59: 0 | FJ59: 0 | FK59: 0 | FL59: 0 | FM59: 0 | FN59: 0 | FO59: 0 | FP59: 0 | FQ59: 0 | FR59: 0 | FS59: 0 | FT59: 0 | FU59: 0 | FV59: 0 | FW59: 0 | FX59: 0 | FY59: 0 | FZ59: 0 | GA59: 0 | GB59: 1 | GC59: 1 | GD59: 1 | GE59: 1 | GF59: 1 | GG59: 1 | GH59: 1 | GI59: 1 | GJ59: 1 | GK59: 1 | GL59: 1 | GM59: 1 | GN59: 1 | GO59: 1 | GP59: 1 | GQ59: 1 | GR59: 1 | GS59: 1 | GT59: 1 | GU59: 1 | GV59: 1 | GW59: 1 | GX59: 1 | GY59: 1 | GZ59: 1 | HA59: 0 | HB59: 0 | HC59: 0 | HD59: 0 | HE59: 0 | HF59: 0 | HG59: 0 | HJ59: 1821 | HK59: =SUM(X$4:HI$4) -> 194 | HL59: =SUM(X59:HI59) -> 118 | HM59: =100*HL59/HK59 -> 60.824742 | HO59: 0 | HP59: 0.03 | HQ59: 0.03 | HS59: Need to check beyond 2005
B60: Mexico | C60: 0 | D60: 0 | E60: 0 | F60: 0 | G60: 0 | H60: 0 | I60: 0 | J60: 0 | K60: 0 | L60: 0 | M60: 0 | N60: 0 | O60: 0 | P60: 0 | Q60: 0 | R60: 0 | S60: 0 | T60: 0 | U60: 0 | V60: 0 | W60: 0 | X60: 0 | Y60: 0 | Z60: 0 | AA60: 0 | AB60: 0 | AC60: 0 | AD60: 1 | AE60: 1 | AF60: 1 | AG60: 1 | AH60: 0 | AI60: 0 | AJ60: 1 | AK60: 1 | AL60: 1 | AM60: 1 | AN60: 1 | AO60: 1 | AP60: 1 | AQ60: 1 | AR60: 1 | AS60: 0 | AT60: 0 | AU60: 1 | AV60: 1 | AW60: 1 | AX60: 1 | AY60: 1 | AZ60: 1 | BA60: 1 | BB60: 0 | BC60: 0 | BD60: 0 | BE60: 1 | BF60: 1 | BG60: 1 | BH60: 1 | BI60: 1 | BJ60: 1 | BK60: 1 | BL60: 1 | BM60: 1 | BN60: 1 | BO60: 1 | BP60: 0 | BQ60: 1 | BR60: 1 | BS60: 1 | BT60: 1 | BU60: 1 | BV60: 1 | BW60: 1 | BX60: 1 | BY60: 1 | BZ60: 1 | CA60: 1 | CB60: 1 | CC60: 1 | CD60: 1 | CE60: 1 | CF60: 1 | CG60: 1 | CH60: 1 | CI60: 1 | CJ60: 1 | CK60: 0 | CL60: 0 | CM60: 0 | CN60: 0 | CO60: 0 | CP60: 0 | CQ60: 0 | CR60: 0 | CS60: 0 | CT60: 0 | CU60: 0 | CV60: 0 | CW60: 0 | CX60: 0 | CY60: 0 | CZ60: 0 | DA60: 0 | DB60: 0 | DC60: 0 | DD60: 0 | DE60: 0 | DF60: 0 | DG60: 0 | DH60: 0 | DI60: 0 | DJ60: 0 | DK60: 0 | DL60: 0 | DM60: 1 | DN60: 1 | DO60: 1 | DP60: 1 | DQ60: 1 | DR60: 1 | DS60: 1 | DT60: 1 | DU60: 1 | DV60: 0 | DW60: 0 | DX60: 0 | DY60: 0 | DZ60: 0 | EA60: 1 | EB60: 1 | EC60: 1 | ED60: 1 | EE60: 1 | EF60: 1 | EG60: 1 | EH60: 1 | EI60: 1 | EJ60: 1 | EK60: 1 | EL60: 1 | EM60: 1 | EN60: 1 | EO60: 1 | EP60: 0 | EQ60: 0 | ER60: 0 | ES60: 0 | ET60: 0 | EU60: 0 | EV60: 0 | EW60: 0 | EX60: 0 | EY60: 0 | EZ60: 0 | FA60: 0 | FB60: 0 | FC60: 0 | FD60: 0 | FE60: 0 | FF60: 0 | FG60: 0 | FH60: 0 | FI60: 0 | FJ60: 0 | FK60: 0 | FL60: 0 | FM60: 0 | FN60: 0 | FO60: 0 | FP60: 0 | FQ60: 0 | FR60: 0 | FS60: 0 | FT60: 0 | FU60: 0 | FV60: 0 | FW60: 0 | FX60: 0 | FY60: 0 | FZ60: 0 | GA60: 0 | GB60: 0 | GC60: 1 | GD60: 1 | GE60: 1 | GF60: 1 | GG60: 1 | GH60: 1 | GI60: 1 | GJ60: 1 | GK60: 1 | GL60: 0 | GM60: 0 | GN60: 0 | GO60: 0 | GP60: 0 | GQ60: 0 | GR60: 0 | GS60: 0 | GT60: 0 | GU60: 0 | GV60: 0 | GW60: 0 | GX60: 0 | GY60: 0 | GZ60: 0 | HA60: 0 | HB60: 0 | HC60: 0 | HD60: 0 | HE60: 0 | HF60: 0 | HG60: 0 | HH60: 0 | HI60: 0 | HJ60: 1821 | HK60: =SUM(X$4:HI$4) -> 194 | HL60: =SUM(X60:HI60) -> 84 | HM60: =100*HL60/HK60 -> 43.298969 | HO60: 0.95 | HP60: 1.91 | HQ60: 1.82
B61: Nicaragua | C61: 0 | D61: 0 | E61: 0 | F61: 0 | G61: 0 | H61: 0 | I61: 0 | J61: 0 | K61: 0 | L61: 0 | M61: 0 | N61: 0 | O61: 0 | P61: 0 | Q61: 0 | R61: 0 | S61: 0 | T61: 0 | U61: 0 | V61: 0 | W61: 0 | X61: 0 | Y61: 0 | Z61: 0 | AA61: 0 | AB61: 0 | AC61: 0 | AD61: 0 | AE61: 1 | AF61: 1 | AG61: 1 | AH61: 1 | AI61: 1 | AJ61: 1 | AK61: 1 | AL61: 1 | AM61: 1 | AN61: 1 | AO61: 1 | AP61: 1 | AQ61: 1 | AR61: 1 | AS61: 1 | AT61: 1 | AU61: 1 | AV61: 1 | AW61: 1 | AX61: 1 | AY61: 1 | AZ61: 1 | BA61: 1 | BB61: 1 | BC61: 1 | BD61: 1 | BE61: 1 | BF61: 1 | BG61: 1 | BH61: 1 | BI61: 1 | BJ61: 1 | BK61: 1 | BL61: 1 | BM61: 1 | BN61: 1 | BO61: 1 | BP61: 1 | BQ61: 1 | BR61: 1 | BS61: 1 | BT61: 1 | BU61: 1 | BV61: 1 | BW61: 1 | BX61: 1 | BY61: 1 | BZ61: 0 | CA61: 0 | CB61: 0 | CC61: 0 | CD61: 0 | CE61: 0 | CF61: 0 | CG61: 0 | CH61: 0 | CI61: 0 | CJ61: 0 | CK61: 0 | CL61: 0 | CM61: 0 | CN61: 0 | CO61: 0 | CP61: 0 | CQ61: 0 | CR61: 0 | CS61: 1 | CT61: 1 | CU61: 0 | CV61: 0 | CW61: 0 | CX61: 0 | CY61: 0 | CZ61: 0 | DA61: 0 | DB61: 0 | DC61: 0 | DD61: 0 | DE61: 0 | DF61: 0 | DG61: 0 | DH61: 0 | DI61: 0 | DJ61: 1 | DK61: 1 | DL61: 0 | DM61: 0 | DN61: 1 | DO61: 1 | DP61: 1 | DQ61: 0 | DR61: 0 | DS61: 0 | DT61: 0 | DU61: 0 | DV61: 0 | DW61: 0 | DX61: 0 | DY61: 0 | DZ61: 0 | EA61: 0 | EB61: 0 | EC61: 0 | ED61: 0 | EE61: 1 | EF61: 1 | EG61: 1 | EH61: 1 | EI61: 1 | EJ61: 1 | EK61: 0 | EL61: 0 | EM61: 0 | EN61: 0 | EO61: 0 | EP61: 0 | EQ61: 0 | ER61: 0 | ES61: 0 | ET61: 0 | EU61: 0 | EV61: 0 | EW61: 0 | EX61: 0 | EY61: 0 | EZ61: 0 | FA61: 0 | FB61: 0 | FC61: 0 | FD61: 0 | FE61: 0 | FF61: 0 | FG61: 0 | FH61: 0 | FI61: 0 | FJ61: 0 | FK61: 0 | FL61: 0 | FM61: 0 | FN61: 0 | FO61: 0 | FP61: 0 | FQ61: 0 | FR61: 0 | FS61: 0 | FT61: 0 | FU61: 0 | FV61: 0 | FW61: 0 | FX61: 0 | FY61: 0 | FZ61: 1 | GA61: 1 | GB61: 1 | GC61: 1 | GD61: 1 | GE61: 1 | GF61: 1 | GG61: 1 | GH61: 1 | GI61: 1 | GJ61: 1 | GK61: 1 | GL61: 1 | GM61: 1 | GN61: 1 | GO61: 1 | GP61: 1 | GQ61: 1 | GR61: 1 | GS61: 1 | GT61: 1 | GU61: 1 | GV61: 1 | GW61: 1 | GX61: 1 | GY61: 1 | GZ61: 1 | HA61: 1 | HB61: 1 | HC61: 1 | HD61: 1 | HE61: 1 | HF61: 1 | HG61: 1 | HJ61: 1821 | HK61: =SUM(X$4:HI$4) -> 194 | HL61: =SUM(X61:HI61) -> 94 | HM61: =100*HL61/HK61 -> 48.453608 | HO61: 0 | HP61: 0.02 | HQ61: 0.02 | HS61: Need to check beyond 2006
B62: Panama | C62: 0 | D62: 0 | E62: 0 | F62: 0 | G62: 0 | H62: 0 | I62: 0 | J62: 0 | K62: 0 | L62: 0 | M62: 0 | N62: 0 | O62: 0 | P62: 0 | Q62: 0 | R62: 0 | S62: 0 | T62: 0 | U62: 0 | V62: 0 | W62: 0 | X62: 0 | Y62: 0 | Z62: 0 | AA62: 0 | AB62: 0 | AC62: 0 | AD62: 0 | AE62: 0 | AF62: 0 | AG62: 0 | AH62: 0 | AI62: 0 | AJ62: 0 | AK62: 0 | AL62: 0 | AM62: 0 | AN62: 0 | AO62: 0 | AP62: 0 | AQ62: 0 | AR62: 0 | AS62: 0 | AT62: 0 | AU62: 0 | AV62: 0 | AW62: 0 | AX62: 0 | AY62: 0 | AZ62: 0 | BA62: 0 | BB62: 0 | BC62: 0 | BD62: 0 | BE62: 0 | BF62: 0 | BG62: 0 | BH62: 0 | BI62: 0 | BJ62: 0 | BK62: 0 | BL62: 0 | BM62: 0 | BN62: 0 | BO62: 0 | BP62: 0 | BQ62: 0 | BR62: 0 | BS62: 0 | BT62: 0 | BU62: 0 | BV62: 0 | BW62: 0 | BX62: 0 | BY62: 0 | BZ62: 0 | CA62: 0 | CB62: 0 | CC62: 0 | CD62: 0 | CE62: 0 | CF62: 0 | CG62: 0 | CH62: 0 | CI62: 0 | CJ62: 0 | CK62: 0 | CL62: 0 | CM62: 0 | CN62: 0 | CO62: 0 | CP62: 0 | CQ62: 0 | CR62: 0 | CS62: 0 | CT62: 0 | CU62: 0 | CV62: 0 | CW62: 0 | CX62: 0 | CY62: 0 | CZ62: 0 | DA62: 0 | DB62: 0 | DC62: 0 | DD62: 0 | DE62: 0 | DF62: 0 | DG62: 0 | DH62: 0 | DI62: 0 | DJ62: 0 | DK62: 0 | DL62: 0 | DM62: 0 | DN62: 0 | DO62: 0 | DP62: 0 | DQ62: 0 | DR62: 0 | DS62: 0 | DT62: 0 | DU62: 0 | DV62: 0 | DW62: 0 | DX62: 0 | DY62: 0 | DZ62: 0 | EA62: 0 | EB62: 0 | EC62: 0 | ED62: 0 | EE62: 1 | EF62: 1 | EG62: 1 | EH62: 1 | EI62: 1 | EJ62: 1 | EK62: 1 | EL62: 1 | EM62: 1 | EN62: 1 | EO62: 1 | EP62: 1 | EQ62: 1 | ER62: 1 | ES62: 1 | ET62: 0 | EU62: 0 | EV62: 0 | EW62: 0 | EX62: 0 | EY62: 0 | EZ62: 0 | FA62: 0 | FB62: 0 | FC62: 0 | FD62: 0 | FE62: 0 | FF62: 0 | FG62: 0 | FH62: 0 | FI62: 0 | FJ62: 0 | FK62: 0 | FL62: 0 | FM62: 0 | FN62: 0 | FO62: 0 | FP62: 0 | FQ62: 0 | FR62: 0 | FS62: 0 | FT62: 0 | FU62: 0 | FV62: 0 | FW62: 0 | FX62: 0 | FY62: 0 | FZ62: 0 | GA62: 0 | GB62: 0 | GC62: 0 | GD62: 1 | GE62: 1 | GF62: 1 | GG62: 1 | GH62: 1 | GI62: 1 | GJ62: 1 | GK62: 1 | GL62: 1 | GM62: 1 | GN62: 1 | GO62: 1 | GP62: 1 | GQ62: 1 | GR62: 0 | GS62: 0 | GT62: 0 | GU62: 0 | GV62: 0 | GW62: 0 | GX62: 0 | GY62: 0 | GZ62: 0 | HA62: 0 | HB62: 0 | HC62: 0 | HD62: 0 | HE62: 0 | HF62: 0 | HG62: 0 | HJ62: 1903 | HK62: =SUM(DB$4:HI$4) -> 112 | HL62: =SUM(DB62:HI62) -> 29 | HM62: =100*HL62/HK62 -> 25.892857 | HO62: 0 | HP62: 0.04 | HQ62: 0.04
B63: Paraguay | C63: 0 | D63: 0 | E63: 0 | F63: 0 | G63: 0 | H63: 0 | I63: 0 | J63: 0 | K63: 0 | L63: 0 | M63: 0 | N63: 0 | O63: 0 | P63: 0 | Q63: 0 | R63: 0 | S63: 0 | T63: 0 | U63: 0 | V63: 0 | W63: 0 | X63: 0 | Y63: 0 | Z63: 0 | AA63: 0 | AB63: 0 | AC63: 0 | AD63: 0 | AE63: 0 | AF63: 0 | AG63: 0 | AH63: 0 | AI63: 0 | AJ63: 0 | AK63: 0 | AL63: 0 | AM63: 0 | AN63: 0 | AO63: 0 | AP63: 0 | AQ63: 0 | AR63: 0 | AS63: 0 | AT63: 0 | AU63: 0 | AV63: 0 | AW63: 0 | AX63: 0 | AY63: 0 | AZ63: 0 | BA63: 0 | BB63: 0 | BC63: 0 | BD63: 0 | BE63: 0 | BF63: 0 | BG63: 0 | BH63: 0 | BI63: 0 | BJ63: 0 | BK63: 0 | BL63: 0 | BM63: 0 | BN63: 0 | BO63: 0 | BP63: 0 | BQ63: 0 | BR63: 0 | BS63: 0 | BT63: 0 | BU63: 0 | BV63: 0 | BW63: 0 | BX63: 0 | BY63: 1 | BZ63: 1 | CA63: 1 | CB63: 1 | CC63: 1 | CD63: 1 | CE63: 1 | CF63: 1 | CG63: 1 | CH63: 1 | CI63: 1 | CJ63: 1 | CK63: 0 | CL63: 0 | CM63: 0 | CN63: 0 | CO63: 0 | CP63: 0 | CQ63: 1 | CR63: 1 | CS63: 1 | CT63: 1 | CU63: 0 | CV63: 0 | CW63: 0 | CX63: 0 | CY63: 0 | CZ63: 0 | DA63: 0 | DB63: 0 | DC63: 0 | DD63: 0 | DE63: 0 | DF63: 0 | DG63: 0 | DH63: 0 | DI63: 0 | DJ63: 0 | DK63: 0 | DL63: 0 | DM63: 0 | DN63: 0 | DO63: 0 | DP63: 0 | DQ63: 0 | DR63: 0 | DS63: 1 | DT63: 1 | DU63: 1 | DV63: 1 | DW63: 1 | DX63: 0 | DY63: 0 | DZ63: 0 | EA63: 0 | EB63: 0 | EC63: 0 | ED63: 0 | EE63: 1 | EF63: 1 | EG63: 1 | EH63: 1 | EI63: 1 | EJ63: 1 | EK63: 1 | EL63: 1 | EM63: 1 | EN63: 1 | EO63: 1 | EP63: 1 | EQ63: 1 | ER63: 0 | ES63: 0 | ET63: 0 | EU63: 0 | EV63: 0 | EW63: 0 | EX63: 0 | EY63: 0 | EZ63: 0 | FA63: 0 | FB63: 0 | FC63: 0 | FD63: 0 | FE63: 0 | FF63: 0 | FG63: 0 | FH63: 0 | FI63: 0 | FJ63: 0 | FK63: 0 | FL63: 0 | FM63: 0 | FN63: 0 | FO63: 1 | FP63: 1 | FQ63: 0 | FR63: 0 | FS63: 0 | FT63: 0 | FU63: 0 | FV63: 0 | FW63: 0 | FX63: 0 | FY63: 0 | FZ63: 0 | GA63: 0 | GB63: 0 | GC63: 0 | GD63: 0 | GE63: 0 | GF63: 0 | GG63: 1 | GH63: 1 | GI63: 1 | GJ63: 1 | GK63: 1 | GL63: 1 | GM63: 1 | GN63: 0 | GO63: 0 | GP63: 0 | GQ63: 0 | GR63: 0 | GS63: 0 | GT63: 0 | GU63: 0 | GV63: 0 | GW63: 0 | GX63: 1 | GY63: 1 | GZ63: 0 | HA63: 0 | HB63: 0 | HC63: 0 | HD63: 0 | HE63: 0 | HF63: 0 | HG63: 0 | HJ63: 1811 | HK63: =SUM(N$4:HI$4) -> 204 | HL63: =SUM(N63:HI63) -> 45 | HM63: =100*HL63/HK63 -> 22.058824 | HO63: 0 | HP63: 0.05 | HQ63: 0.04
B64: Peru | C64: 0 | D64: 0 | E64: 0 | F64: 0 | G64: 0 | H64: 0 | I64: 0 | J64: 0 | K64: 0 | L64: 0 | M64: 0 | N64: 0 | O64: 0 | P64: 0 | Q64: 0 | R64: 0 | S64: 0 | T64: 0 | U64: 0 | V64: 0 | W64: 0 | X64: 0 | Y64: 0 | Z64: 0 | AA64: 0 | AB64: 0 | AC64: 1 | AD64: 1 | AE64: 1 | AF64: 1 | AG64: 1 | AH64: 1 | AI64: 1 | AJ64: 1 | AK64: 1 | AL64: 1 | AM64: 1 | AN64: 1 | AO64: 1 | AP64: 1 | AQ64: 1 | AR64: 1 | AS64: 1 | AT64: 1 | AU64: 1 | AV64: 1 | AW64: 1 | AX64: 1 | AY64: 1 | AZ64: 0 | BA64: 0 | BB64: 0 | BC64: 0 | BD64: 0 | BE64: 0 | BF64: 0 | BG64: 0 | BH64: 0 | BI64: 0 | BJ64: 0 | BK64: 0 | BL64: 0 | BM64: 0 | BN64: 0 | BO64: 0 | BP64: 0 | BQ64: 0 | BR64: 0 | BS64: 0 | BT64: 0 | BU64: 0 | BV64: 0 | BW64: 0 | BX64: 0 | BY64: 0 | BZ64: 0 | CA64: 1 | CB64: 1 | CC64: 1 | CD64: 1 | CE64: 1 | CF64: 1 | CG64: 1 | CH64: 1 | CI64: 1 | CJ64: 1 | CK64: 1 | CL64: 1 | CM64: 1 | CN64: 1 | CO64: 0 | CP64: 0 | CQ64: 0 | CR64: 0 | CS64: 0 | CT64: 0 | CU64: 0 | CV64: 0 | CW64: 0 | CX64: 0 | CY64: 0 | CZ64: 0 | DA64: 0 | DB64: 0 | DC64: 0 | DD64: 0 | DE64: 0 | DF64: 0 | DG64: 0 | DH64: 0 | DI64: 0 | DJ64: 0 | DK64: 0 | DL64: 0 | DM64: 0 | DN64: 0 | DO64: 0 | DP64: 0 | DQ64: 0 | DR64: 0 | DS64: 0 | DT64: 0 | DU64: 0 | DV64: 0 | DW64: 0 | DX64: 0 | DY64: 0 | DZ64: 0 | EA64: 0 | EB64: 0 | EC64: 0 | ED64: 1 | EE64: 1 | EF64: 1 | EG64: 1 | EH64: 1 | EI64: 1 | EJ64: 1 | EK64: 1 | EL64: 1 | EM64: 1 | EN64: 1 | EO64: 1 | EP64: 1 | EQ64: 1 | ER64: 1 | ES64: 1 | ET64: 1 | EU64: 1 | EV64: 1 | EW64: 1 | EX64: 1 | EY64: 0 | EZ64: 0 | FA64: 0 | FB64: 0 | FC64: 0 | FD64: 0 | FE64: 0 | FF64: 0 | FG64: 0 | FH64: 0 | FI64: 0 | FJ64: 0 | FK64: 0 | FL64: 0 | FM64: 0 | FN64: 0 | FO64: 0 | FP64: 1 | FQ64: 0 | FR64: 0 | FS64: 0 | FT64: 0 | FU64: 0 | FV64: 0 | FW64: 1 | FX64: 0 | FY64: 1 | FZ64: 0 | GA64: 1 | GB64: 0 | GC64: 0 | GD64: 1 | GE64: 1 | GF64: 1 | GG64: 1 | GH64: 1 | GI64: 1 | GJ64: 1 | GK64: 1 | GL64: 1 | GM64: 1 | GN64: 1 | GO64: 1 | GP64: 1 | GQ64: 1 | GR64: 1 | GS64: 0 | GT64: 0 | GU64: 0 | GV64: 0 | GW64: 0 | GX64: 0 | GY64: 0 | GZ64: 0 | HA64: 0 | HB64: 0 | HC64: 0 | HD64: 0 | HE64: 0 | HF64: 0 | HG64: 0 | HJ64: 1821 | HK64: =SUM(X$4:HI$4) -> 194 | HL64: =SUM(X64:HI64) -> 77 | HM64: =100*HL64/HK64 -> 39.690722 | HO64: 0.16 | HP64: 0.24 | HQ64: 0.26
B65: Uruguay | C65: 0 | D65: 0 | E65: 0 | F65: 0 | G65: 0 | H65: 0 | I65: 0 | J65: 0 | K65: 0 | L65: 0 | M65: 0 | N65: 0 | O65: 0 | P65: 0 | Q65: 0 | R65: 0 | S65: 0 | T65: 0 | U65: 0 | V65: 0 | W65: 0 | X65: 0 | Y65: 0 | Z65: 0 | AA65: 0 | AB65: 0 | AC65: 0 | AD65: 0 | AE65: 0 | AF65: 0 | AG65: 0 | AH65: 0 | AI65: 0 | AJ65: 0 | AK65: 0 | AL65: 0 | AM65: 0 | AN65: 0 | AO65: 0 | AP65: 0 | AQ65: 0 | AR65: 0 | AS65: 0 | AT65: 0 | AU65: 0 | AV65: 0 | AW65: 0 | AX65: 0 | AY65: 0 | AZ65: 0 | BA65: 0 | BB65: 0 | BC65: 0 | BD65: 0 | BE65: 0 | BF65: 0 | BG65: 0 | BH65: 0 | BI65: 0 | BJ65: 0 | BK65: 0 | BL65: 0 | BM65: 0 | BN65: 0 | BO65: 0 | BP65: 0 | BQ65: 0 | BR65: 0 | BS65: 0 | BT65: 0 | BU65: 0 | BV65: 0 | BW65: 0 | BX65: 0 | BY65: 0 | BZ65: 0 | CA65: 1 | CB65: 1 | CC65: 1 | CD65: 0 | CE65: 0 | CF65: 0 | CG65: 0 | CH65: 0 | CI65: 0 | CJ65: 0 | CK65: 0 | CL65: 0 | CM65: 0 | CN65: 0 | CO65: 0 | CP65: 1 | CQ65: 0 | CR65: 0 | CS65: 0 | CT65: 0 | CU65: 0 | CV65: 0 | CW65: 0 | CX65: 0 | CY65: 0 | CZ65: 0 | DA65: 0 | DB65: 0 | DC65: 0 | DD65: 0 | DE65: 0 | DF65: 0 | DG65: 0 | DH65: 0 | DI65: 0 | DJ65: 0 | DK65: 0 | DL65: 0 | DM65: 0 | DN65: 1 | DO65: 1 | DP65: 1 | DQ65: 1 | DR65: 1 | DS65: 1 | DT65: 1 | DU65: 0 | DV65: 0 | DW65: 0 | DX65: 0 | DY65: 0 | DZ65: 0 | EA65: 0 | EB65: 0 | EC65: 0 | ED65: 0 | EE65: 0 | EF65: 1 | EG65: 1 | EH65: 1 | EI65: 1 | EJ65: 1 | EK65: 1 | EL65: 0 | EM65: 0 | EN65: 0 | EO65: 0 | EP65: 0 | EQ65: 0 | ER65: 0 | ES65: 0 | ET65: 0 | EU65: 0 | EV65: 0 | EW65: 0 | EX65: 0 | EY65: 0 | EZ65: 0 | FA65: 0 | FB65: 0 | FC65: 0 | FD65: 0 | FE65: 0 | FF65: 0 | FG65: 0 | FH65: 0 | FI65: 0 | FJ65: 0 | FK65: 0 | FL65: 1 | FM65: 0 | FN65: 0 | FO65: 0 | FP65: 0 | FQ65: 0 | FR65: 0 | FS65: 0 | FT65: 0 | FU65: 0 | FV65: 0 | FW65: 0 | FX65: 0 | FY65: 0 | FZ65: 0 | GA65: 0 | GB65: 0 | GC65: 0 | GD65: 1 | GE65: 1 | GF65: 1 | GG65: 0 | GH65: 1 | GI65: 0 | GJ65: 0 | GK65: 1 | GL65: 1 | GM65: 0 | GN65: 0 | GO65: 0 | GP65: 0 | GQ65: 0 | GR65: 0 | GS65: 0 | GT65: 0 | GU65: 0 | GV65: 0 | GW65: 0 | GX65: 1 | GY65: 0 | GZ65: 0 | HA65: 0 | HB65: 0 | HC65: 0 | HD65: 0 | HE65: 0 | HF65: 0 | HG65: 0 | HJ65: 1811 | HK65: =SUM(N$4:HI$4) -> 204 | HL65: =SUM(N65:HI65) -> 25 | HM65: =100*HL65/HK65 -> 12.254902 | HO65: 0.14 | HP65: 0.07 | HQ65: 0.07
B66: Venezuela | C66: 0 | D66: 0 | E66: 0 | F66: 0 | G66: 0 | H66: 0 | I66: 0 | J66: 0 | K66: 0 | L66: 0 | M66: 0 | N66: 0 | O66: 0 | P66: 0 | Q66: 0 | R66: 0 | S66: 0 | T66: 0 | U66: 0 | V66: 0 | W66: 0 | X66: 0 | Y66: 0 | Z66: 0 | AA66: 0 | AB66: 0 | AC66: 1 | AD66: 1 | AE66: 1 | AF66: 1 | AG66: 1 | AH66: 1 | AI66: 1 | AJ66: 1 | AK66: 1 | AL66: 1 | AM66: 1 | AN66: 1 | AO66: 1 | AP66: 1 | AQ66: 1 | AR66: 0 | AS66: 0 | AT66: 0 | AU66: 0 | AV66: 0 | AW66: 0 | AX66: 0 | AY66: 1 | AZ66: 1 | BA66: 1 | BB66: 1 | BC66: 1 | BD66: 1 | BE66: 1 | BF66: 1 | BG66: 1 | BH66: 1 | BI66: 1 | BJ66: 1 | BK66: 1 | BL66: 1 | BM66: 1 | BN66: 0 | BO66: 0 | BP66: 1 | BQ66: 1 | BR66: 1 | BS66: 1 | BT66: 1 | BU66: 1 | BV66: 1 | BW66: 1 | BX66: 1 | BY66: 1 | BZ66: 1 | CA66: 1 | CB66: 1 | CC66: 1 | CD66: 1 | CE66: 1 | CF66: 1 | CG66: 0 | CH66: 0 | CI66: 0 | CJ66: 0 | CK66: 0 | CL66: 0 | CM66: 0 | CN66: 0 | CO66: 0 | CP66: 0 | CQ66: 1 | CR66: 0 | CS66: 0 | CT66: 0 | CU66: 0 | CV66: 0 | CW66: 1 | CX66: 1 | CY66: 1 | CZ66: 1 | DA66: 1 | DB66: 1 | DC66: 1 | DD66: 1 | DE66: 0 | DF66: 0 | DG66: 0 | DH66: 0 | DI66: 0 | DJ66: 0 | DK66: 0 | DL66: 0 | DM66: 0 | DN66: 0 | DO66: 0 | DP66: 0 | DQ66: 0 | DR66: 0 | DS66: 0 | DT66: 0 | DU66: 0 | DV66: 0 | DW66: 0 | DX66: 0 | DY66: 0 | DZ66: 0 | EA66: 0 | EB66: 0 | EC66: 0 | ED66: 0 | EE66: 0 | EF66: 0 | EG66: 0 | EH66: 0 | EI66: 0 | EJ66: 0 | EK66: 0 | EL66: 0 | EM66: 0 | EN66: 0 | EO66: 0 | EP66: 0 | EQ66: 0 | ER66: 0 | ES66: 0 | ET66: 0 | EU66: 0 | EV66: 0 | EW66: 0 | EX66: 0 | EY66: 0 | EZ66: 0 | FA66: 0 | FB66: 0 | FC66: 0 | FD66: 0 | FE66: 0 | FF66: 0 | FG66: 0 | FH66: 0 | FI66: 0 | FJ66: 0 | FK66: 0 | FL66: 0 | FM66: 0 | FN66: 0 | FO66: 0 | FP66: 0 | FQ66: 0 | FR66: 0 | FS66: 0 | FT66: 0 | FU66: 0 | FV66: 0 | FW66: 0 | FX66: 0 | FY66: 0 | FZ66: 0 | GA66: 0 | GB66: 0 | GC66: 0 | GD66: 1 | GE66: 1 | GF66: 1 | GG66: 1 | GH66: 1 | GI66: 1 | GJ66: 0 | GK66: 1 | GL66: 0 | GM66: 0 | GN66: 0 | GO66: 0 | GP66: 1 | GQ66: 1 | GR66: 1 | GS66: 0 | GT66: 0 | GU66: 0 | GV66: 0 | GW66: 0 | GX66: 0 | GY66: 1 | GZ66: 1 | HA66: 0 | HB66: 0 | HC66: 0 | HD66: 0 | HE66: 0 | HF66: 0 | HG66: 0 | HJ66: 1830 | HK66: =SUM(AG$4:HI$4) -> 185 | HL66: =SUM(AG66:HI66) -> 64 | HM66: =100*HL66/HK66 -> 34.594595 | HO66: 0.12 | HP66: 0.59 | HQ66: 0.42
A67: North America | B67: Canada | C67: 0 | D67: 0 | E67: 0 | F67: 0 | G67: 0 | H67: 0 | I67: 0 | J67: 0 | K67: 0 | L67: 0 | M67: 0 | N67: 0 | O67: 0 | P67: 0 | Q67: 0 | R67: 0 | S67: 0 | T67: 0 | U67: 0 | V67: 0 | W67: 0 | X67: 0 | Y67: 0 | Z67: 0 | AA67: 0 | AB67: 0 | AC67: 0 | AD67: 0 | AE67: 0 | AF67: 0 | AG67: 0 | AH67: 0 | AI67: 0 | AJ67: 0 | AK67: 0 | AL67: 0 | AM67: 0 | AN67: 0 | AO67: 0 | AP67: 0 | AQ67: 0 | AR67: 0 | AS67: 0 | AT67: 0 | AU67: 0 | AV67: 0 | AW67: 0 | AX67: 0 | AY67: 0 | AZ67: 0 | BA67: 0 | BB67: 0 | BC67: 0 | BD67: 0 | BE67: 0 | BF67: 0 | BG67: 0 | BH67: 0 | BI67: 0 | BJ67: 0 | BK67: 0 | BL67: 0 | BM67: 0 | BN67: 0 | BO67: 0 | BP67: 0 | BQ67: 0 | BR67: 0 | BS67: 0 | BT67: 0 | BU67: 0 | BV67: 0 | BW67: 0 | BX67: 0 | BY67: 0 | BZ67: 0 | CA67: 0 | CB67: 0 | CC67: 0 | CD67: 0 | CE67: 0 | CF67: 0 | CG67: 0 | CH67: 0 | CI67: 0 | CJ67: 0 | CK67: 0 | CL67: 0 | CM67: 0 | CN67: 0 | CO67: 0 | CP67: 0 | CQ67: 0 | CR67: 0 | CS67: 0 | CT67: 0 | CU67: 0 | CV67: 0 | CW67: 0 | CX67: 0 | CY67: 0 | CZ67: 0 | DA67: 0 | DB67: 0 | DC67: 0 | DD67: 0 | DE67: 0 | DF67: 0 | DG67: 0 | DH67: 0 | DI67: 0 | DJ67: 0 | DK67: 0 | DL67: 0 | DM67: 0 | DN67: 0 | DO67: 0 | DP67: 0 | DQ67: 0 | DR67: 0 | DS67: 0 | DT67: 0 | DU67: 0 | DV67: 0 | DW67: 0 | DX67: 0 | DY67: 0 | DZ67: 0 | EA67: 0 | EB67: 0 | EC67: 0 | ED67: 0 | EE67: 0 | EF67: 0 | EG67: 0 | EH67: 0 | EI67: 0 | EJ67: 0 | EK67: 0 | EL67: 0 | EM67: 0 | EN67: 0 | EO67: 0 | EP67: 0 | EQ67: 0 | ER67: 0 | ES67: 0 | ET67: 0 | EU67: 0 | EV67: 0 | EW67: 0 | EX67: 0 | EY67: 0 | EZ67: 0 | FA67: 0 | FB67: 0 | FC67: 0 | FD67: 0 | FE67: 0 | FF67: 0 | FG67: 0 | FH67: 0 | FI67: 0 | FJ67: 0 | FK67: 0 | FL67: 0 | FM67: 0 | FN67: 0 | FO67: 0 | FP67: 0 | FQ67: 0 | FR67: 0 | FS67: 0 | FT67: 0 | FU67: 0 | FV67: 0 | FW67: 0 | FX67: 0 | FY67: 0 | FZ67: 0 | GA67: 0 | GB67: 0 | GC67: 0 | GD67: 0 | GE67: 0 | GF67: 0 | GG67: 0 | GH67: 0 | GI67: 0 | GJ67: 0 | GK67: 0 | GL67: 0 | GM67: 0 | GN67: 0 | GO67: 0 | GP67: 0 | GQ67: 0 | GR67: 0 | GS67: 0 | GT67: 0 | GU67: 0 | GV67: 0 | GW67: 0 | GX67: 0 | GY67: 0 | GZ67: 0 | HA67: 0 | HB67: 0 | HC67: 0 | HD67: 0 | HE67: 0 | HF67: 0 | HG67: 0 | HJ67: 1867 | HK67: =SUM(BR$4:HI$4) -> 148 | HL67: =SUM(BR67:HI67) -> 0 | HM67: =100*HL67/HK67 -> 0 | HO67: 1.28 | HP67: 1.94 | HQ67: 1.84
B68: United States | C68: 0 | D68: 0 | E68: 0 | F68: 0 | G68: 0 | H68: 0 | I68: 0 | J68: 0 | K68: 0 | L68: 0 | M68: 0 | N68: 0 | O68: 0 | P68: 0 | Q68: 0 | R68: 0 | S68: 0 | T68: 0 | U68: 0 | V68: 0 | W68: 0 | X68: 0 | Y68: 0 | Z68: 0 | AA68: 0 | AB68: 0 | AC68: 0 | AD68: 0 | AE68: 0 | AF68: 0 | AG68: 0 | AH68: 0 | AI68: 0 | AJ68: 0 | AK68: 0 | AL68: 0 | AM68: 0 | AN68: 0 | AO68: 0 | AP68: 0 | AQ68: 0 | AR68: 0 | AS68: 0 | AT68: 0 | AU68: 0 | AV68: 0 | AW68: 0 | AX68: 0 | AY68: 0 | AZ68: 0 | BA68: 0 | BB68: 0 | BC68: 0 | BD68: 0 | BE68: 0 | BF68: 0 | BG68: 0 | BH68: 0 | BI68: 0 | BJ68: 0 | BK68: 0 | BL68: 0 | BM68: 0 | BN68: 0 | BO68: 0 | BP68: 0 | BQ68: 0 | BR68: 0 | BS68: 0 | BT68: 0 | BU68: 0 | BV68: 0 | BW68: 0 | BX68: 0 | BY68: 0 | BZ68: 0 | CA68: 0 | CB68: 0 | CC68: 0 | CD68: 0 | CE68: 0 | CF68: 0 | CG68: 0 | CH68: 0 | CI68: 0 | CJ68: 0 | CK68: 0 | CL68: 0 | CM68: 0 | CN68: 0 | CO68: 0 | CP68: 0 | CQ68: 0 | CR68: 0 | CS68: 0 | CT68: 0 | CU68: 0 | CV68: 0 | CW68: 0 | CX68: 0 | CY68: 0 | CZ68: 0 | DA68: 0 | DB68: 0 | DC68: 0 | DD68: 0 | DE68: 0 | DF68: 0 | DG68: 0 | DH68: 0 | DI68: 0 | DJ68: 0 | DK68: 0 | DL68: 0 | DM68: 0 | DN68: 0 | DO68: 0 | DP68: 0 | DQ68: 0 | DR68: 0 | DS68: 0 | DT68: 0 | DU68: 0 | DV68: 0 | DW68: 0 | DX68: 0 | DY68: 0 | DZ68: 0 | EA68: 0 | EB68: 0 | EC68: 0 | ED68: 0 | EE68: 0 | EF68: 1 | EG68: 0 | EH68: 0 | EI68: 0 | EJ68: 0 | EK68: 0 | EL68: 0 | EM68: 0 | EN68: 0 | EO68: 0 | EP68: 0 | EQ68: 0 | ER68: 0 | ES68: 0 | ET68: 0 | EU68: 0 | EV68: 0 | EW68: 0 | EX68: 0 | EY68: 0 | EZ68: 0 | FA68: 0 | FB68: 0 | FC68: 0 | FD68: 0 | FE68: 0 | FF68: 0 | FG68: 0 | FH68: 0 | FI68: 0 | FJ68: 0 | FK68: 0 | FL68: 0 | FM68: 0 | FN68: 0 | FO68: 0 | FP68: 0 | FQ68: 0 | FR68: 0 | FS68: 0 | FT68: 0 | FU68: 0 | FV68: 0 | FW68: 0 | FX68: 0 | FY68: 0 | FZ68: 0 | GA68: 0 | GB68: 0 | GC68: 0 | GD68: 0 | GE68: 0 | GF68: 0 | GG68: 0 | GH68: 0 | GI68: 0 | GJ68: 0 | GK68: 0 | GL68: 0 | GM68: 0 | GN68: 0 | GO68: 0 | GP68: 0 | GQ68: 0 | GR68: 0 | GS68: 0 | GT68: 0 | GU68: 0 | GV68: 0 | GW68: 0 | GX68: 0 | GY68: 0 | GZ68: 0 | HA68: 0 | HB68: 0 | HC68: 0 | HD68: 0 | HE68: 0 | HF68: 0 | HG68: 0 | HJ68: 1776 | HK68: =SUM(C$4:HI$4) -> 215 | HL68: =SUM(C68:HI68) -> 1 | HM68: =100*HL68/HK68 -> 0.46511628 | HO68: 18.93 | HP68: 21.41 | HQ68: 20.73
A69: Oceania | B69: Australia | C69: 0 | D69: 0 | E69: 0 | F69: 0 | G69: 0 | H69: 0 | I69: 0 | J69: 0 | K69: 0 | L69: 0 | M69: 0 | N69: 0 | O69: 0 | P69: 0 | Q69: 0 | R69: 0 | S69: 0 | T69: 0 | U69: 0 | V69: 0 | W69: 0 | X69: 0 | Y69: 0 | Z69: 0 | AA69: 0 | AB69: 0 | AC69: 0 | AD69: 0 | AE69: 0 | AF69: 0 | AG69: 0 | AH69: 0 | AI69: 0 | AJ69: 0 | AK69: 0 | AL69: 0 | AM69: 0 | AN69: 0 | AO69: 0 | AP69: 0 | AQ69: 0 | AR69: 0 | AS69: 0 | AT69: 0 | AU69: 0 | AV69: 0 | AW69: 0 | AX69: 0 | AY69: 0 | AZ69: 0 | BA69: 0 | BB69: 0 | BC69: 0 | BD69: 0 | BE69: 0 | BF69: 0 | BG69: 0 | BH69: 0 | BI69: 0 | BJ69: 0 | BK69: 0 | BL69: 0 | BM69: 0 | BN69: 0 | BO69: 0 | BP69: 0 | BQ69: 0 | BR69: 0 | BS69: 0 | BT69: 0 | BU69: 0 | BV69: 0 | BW69: 0 | BX69: 0 | BY69: 0 | BZ69: 0 | CA69: 0 | CB69: 0 | CC69: 0 | CD69: 0 | CE69: 0 | CF69: 0 | CG69: 0 | CH69: 0 | CI69: 0 | CJ69: 0 | CK69: 0 | CL69: 0 | CM69: 0 | CN69: 0 | CO69: 0 | CP69: 0 | CQ69: 0 | CR69: 0 | CS69: 0 | CT69: 0 | CU69: 0 | CV69: 0 | CW69: 0 | CX69: 0 | CY69: 0 | CZ69: 0 | DA69: 0 | DB69: 0 | DC69: 0 | DD69: 0 | DE69: 0 | DF69: 0 | DG69: 0 | DH69: 0 | DI69: 0 | DJ69: 0 | DK69: 0 | DL69: 0 | DM69: 0 | DN69: 0 | DO69: 0 | DP69: 0 | DQ69: 0 | DR69: 0 | DS69: 0 | DT69: 0 | DU69: 0 | DV69: 0 | DW69: 0 | DX69: 0 | DY69: 0 | DZ69: 0 | EA69: 0 | EB69: 0 | EC69: 0 | ED69: 0 | EE69: 0 | EF69: 0 | EG69: 0 | EH69: 0 | EI69: 0 | EJ69: 0 | EK69: 0 | EL69: 0 | EM69: 0 | EN69: 0 | EO69: 0 | EP69: 0 | EQ69: 0 | ER69: 0 | ES69: 0 | ET69: 0 | EU69: 0 | EV69: 0 | EW69: 0 | EX69: 0 | EY69: 0 | EZ69: 0 | FA69: 0 | FB69: 0 | FC69: 0 | FD69: 0 | FE69: 0 | FF69: 0 | FG69: 0 | FH69: 0 | FI69: 0 | FJ69: 0 | FK69: 0 | FL69: 0 | FM69: 0 | FN69: 0 | FO69: 0 | FP69: 0 | FQ69: 0 | FR69: 0 | FS69: 0 | FT69: 0 | FU69: 0 | FV69: 0 | FW69: 0 | FX69: 0 | FY69: 0 | FZ69: 0 | GA69: 0 | GB69: 0 | GC69: 0 | GD69: 0 | GE69: 0 | GF69: 0 | GG69: 0 | GH69: 0 | GI69: 0 | GJ69: 0 | GK69: 0 | GL69: 0 | GM69: 0 | GN69: 0 | GO69: 0 | GP69: 0 | GQ69: 0 | GR69: 0 | GS69: 0 | GT69: 0 | GU69: 0 | GV69: 0 | GW69: 0 | GX69: 0 | GY69: 0 | GZ69: 0 | HA69: 0 | HB69: 0 | HC69: 0 | HD69: 0 | HE69: 0 | HF69: 0 | HG69: 0 | HJ69: 1901 | HK69: =SUM(CZ$4:HI$4) -> 114 | HL69: =SUM(CZ69:HI69) -> 0 | HM69: =100*HL69/HK69 -> 0 | HO69: 0.91 | HP69: 1.07 | HQ69: 1.13
B70: New Zealand | C70: 0 | D70: 0 | E70: 0 | F70: 0 | G70: 0 | H70: 0 | I70: 0 | J70: 0 | K70: 0 | L70: 0 | M70: 0 | N70: 0 | O70: 0 | P70: 0 | Q70: 0 | R70: 0 | S70: 0 | T70: 0 | U70: 0 | V70: 0 | W70: 0 | X70: 0 | Y70: 0 | Z70: 0 | AA70: 0 | AB70: 0 | AC70: 0 | AD70: 0 | AE70: 0 | AF70: 0 | AG70: 0 | AH70: 0 | AI70: 0 | AJ70: 0 | AK70: 0 | AL70: 0 | AM70: 0 | AN70: 0 | AO70: 0 | AP70: 0 | AQ70: 0 | AR70: 0 | AS70: 0 | AT70: 0 | AU70: 0 | AV70: 0 | AW70: 0 | AX70: 0 | AY70: 0 | AZ70: 0 | BA70: 0 | BB70: 0 | BC70: 0 | BD70: 0 | BE70: 0 | BF70: 0 | BG70: 0 | BH70: 0 | BI70: 0 | BJ70: 0 | BK70: 0 | BL70: 0 | BM70: 0 | BN70: 0 | BO70: 0 | BP70: 0 | BQ70: 0 | BR70: 0 | BS70: 0 | BT70: 0 | BU70: 0 | BV70: 0 | BW70: 0 | BX70: 0 | BY70: 0 | BZ70: 0 | CA70: 0 | CB70: 0 | CC70: 0 | CD70: 0 | CE70: 0 | CF70: 0 | CG70: 0 | CH70: 0 | CI70: 0 | CJ70: 0 | CK70: 0 | CL70: 0 | CM70: 0 | CN70: 0 | CO70: 0 | CP70: 0 | CQ70: 0 | CR70: 0 | CS70: 0 | CT70: 0 | CU70: 0 | CV70: 0 | CW70: 0 | CX70: 0 | CY70: 0 | CZ70: 0 | DA70: 0 | DB70: 0 | DC70: 0 | DD70: 0 | DE70: 0 | DF70: 0 | DG70: 0 | DH70: 0 | DI70: 0 | DJ70: 0 | DK70: 0 | DL70: 0 | DM70: 0 | DN70: 0 | DO70: 0 | DP70: 0 | DQ70: 0 | DR70: 0 | DS70: 0 | DT70: 0 | DU70: 0 | DV70: 0 | DW70: 0 | DX70: 0 | DY70: 0 | DZ70: 0 | EA70: 0 | EB70: 0 | EC70: 0 | ED70: 0 | EE70: 0 | EF70: 0 | EG70: 0 | EH70: 0 | EI70: 0 | EJ70: 0 | EK70: 0 | EL70: 0 | EM70: 0 | EN70: 0 | EO70: 0 | EP70: 0 | EQ70: 0 | ER70: 0 | ES70: 0 | ET70: 0 | EU70: 0 | EV70: 0 | EW70: 0 | EX70: 0 | EY70: 0 | EZ70: 0 | FA70: 0 | FB70: 0 | FC70: 0 | FD70: 0 | FE70: 0 | FF70: 0 | FG70: 0 | FH70: 0 | FI70: 0 | FJ70: 0 | FK70: 0 | FL70: 0 | FM70: 0 | FN70: 0 | FO70: 0 | FP70: 0 | FQ70: 0 | FR70: 0 | FS70: 0 | FT70: 0 | FU70: 0 | FV70: 0 | FW70: 0 | FX70: 0 | FY70: 0 | FZ70: 0 | GA70: 0 | GB70: 0 | GC70: 0 | GD70: 0 | GE70: 0 | GF70: 0 | GG70: 0 | GH70: 0 | GI70: 0 | GJ70: 0 | GK70: 0 | GL70: 0 | GM70: 0 | GN70: 0 | GO70: 0 | GP70: 0 | GQ70: 0 | GR70: 0 | GS70: 0 | GT70: 0 | GU70: 0 | GV70: 0 | GW70: 0 | GX70: 0 | GY70: 0 | GZ70: 0 | HA70: 0 | HB70: 0 | HC70: 0 | HD70: 0 | HE70: 0 | HF70: 0 | HG70: 0 | HJ70: 1907 | HK70: =SUM(DF$4:HI$4) -> 108 | HL70: =SUM(DF70:HI70) -> 0 | HM70: =100*HL70/HK70 -> 0 | HO70: 0.21 | HP70: 0.17 | HQ70: 0.17
B71: TOTAL (in sample) | C71: =SUM(C5:C70) -> 0 | D71: =SUM(D5:D70) -> 0 | E71: =SUM(E5:E70) -> 2 | F71: =SUM(F5:F70) -> 2 | G71: =SUM(G5:G70) -> 2 | H71: =SUM(H5:H70) -> 2 | I71: =SUM(I5:I70) -> 2 | J71: =SUM(J5:J70) -> 3 | ... HI71: =SUM(HI5:HI70) -> 3 | HO71: =SUM(HO5:HO70) -> 93.04 | HP71: =SUM(HP5:HP70) -> 89.24 | HQ71: =SUM(HQ5:HQ70) -> 90.848312
A72: Share of sovereigns in default (in sample) | C72: 0 | D72: 0 | E72: 11.764706 | F72: 11.764706 | G72: 11.764706 | H72: 11.764706 | I72: 11.764706 | J72: 17.647059 | K72: 11.764706 | L72: 11.764706 | M72: 11.764706 | N72: 10.526316 | O72: 26.315789 | P72: 15.789474 | Q72: 15.789474 | R72: 5.2631579 | S72: 5 | T72: 0 | U72: 0 | V72: 0 | W72: 4.5454545 | X72: 0 | Y72: 0 | Z72: 0 | AA72: 3.3333333 | AB72: 3.2258065 | AC72: 19.354839 | AD72: 22.580645 | AE72: 45.16129 | AF72: 40.625 | AG72: 40 | AH72: 36.111111 | AI72: 36.111111 | AJ72: 38.888889 | AK72: 38.888889 | AL72: 36.111111 | AM72: 36.111111 | AN72: 41.666667 | AO72: 41.666667 | AP72: 44.444444 | AQ72: 41.666667 | AR72: 36.111111 | AS72: 30.555556 | AT72: 27.777778 | AU72: 30.555556 | AV72: 29.72973 | AW72: 24.324324 | AX72: 24.324324 | AY72: 27.027027 | AZ72: 24.324324 | BA72: 32.432432 | BB72: 27.027027 | BC72: 27.027027 | BD72: 27.027027 | BE72: 29.72973 | BF72: 29.72973 | BG72: 29.72973 | BH72: 24.324324 | BI72: 21.621622 | BJ72: 21.621622 | BK72: 21.621622 | BL72: 18.918919 | BM72: 16.216216 | BN72: 13.513514 | BO72: 13.513514 | BP72: 13.513514 | BQ72: 16.216216 | BR72: 18.421053 | BS72: 18.421053 | BT72: 18.421053 | BU72: 18.421053 | BV72: 13.157895 | BW72: 15.789474 | BX72: 21.052632 | BY72: 23.684211 | BZ72: 23.684211 | CA72: 36.842105 | CB72: 39.473684 | CC72: 38.461538 | CD72: 33.333333 | CE72: 35.897436 | CF72: 33.333333 | CG72: 28.205128 | CH72: 25.641026 | CI72: 23.076923 | CJ72: 25.641026 | CK72: 15.384615 | CL72: 15.384615 | CM72: 15.384615 | CN72: 10.25641 | CO72: 10.25641 | CP72: 10.25641 | CQ72: 17.948718 | CR72: 15.384615 | CS72: 20.512821 | CT72: 20.512821 | CU72: 15.384615 | CV72: 15.384615 | CW72: 15.384615 | CX72: 15.384615 | CY72: 17.948718 | CZ72: 20 | DA72: 17.5 | DB72: 19.512195 | DC72: 19.512195 | DD72: 14.285714 | DE72: 14.285714 | DF72: 13.953488 | DG72: 11.627907 | DH72: 11.627907 | DI72: 11.363636 | DJ72: 11.363636 | DK72: 6.8181818 | DL72: 4.5454545 | DM72: 11.363636 | DN72: 18.181818 | DO72: 15.909091 | DP72: 15.555556 | DQ72: 14.893617 | DR72: 14.893617 | DS72: 14.893617 | DT72: 19.148936 | DU72: 17.021277 | DV72: 12.765957 | DW72: 12.765957 | DX72: 8.5106383 | DY72: 6.3829787 | DZ72: 6.3829787 | EA72: 8.5106383 | EB72: 8.5106383 | EC72: 8.5106383 | ED72: 21.276596 | EE72: 42.553191 | EF72: 48.93617 | EG72: 42.553191 | EH72: 40.425532 | EI72: 42.553191 | EJ72: 38.297872 | EK72: 36.170213 | EL72: 34.042553 | EM72: 42.553191 | EN72: 44.680851 | EO72: 46.808511 | EP72: 44.680851 | EQ72: 40.425532 | ER72: 35.416667 | ES72: 34.693878 | ET72: 28 | EU72: 25 | EV72: 22.222222 | EW72: 20.37037 | EX72: 22.222222 | EY72: 18.518519 | EZ72: 11.111111 | FA72: 9.2592593 | FB72: 7.4074074 | FC72: 12.727273 | FD72: 8.9285714 | FE72: 14.285714 | FF72: 7.1428571 | FG72: 6.779661 | FH72: 10.169492 | FI72: 10 | FJ72: 13.114754 | FK72: 8.0645161 | FL72: 9.375 | FM72: 6.25 | FN72: 6.25 | FO72: 6.1538462 | FP72: 9.2307692 | FQ72: 6.1538462 | FR72: 4.6153846 | FS72: 6.1538462 | FT72: 6.1538462 | FU72: 6.1538462 | FV72: 6.0606061 | FW72: 6.0606061 | FX72: 3.030303 | FY72: 6.0606061 | FZ72: 9.0909091 | GA72: 9.0909091 | GB72: 15.151515 | GC72: 21.212121 | GD72: 34.848485 | GE72: 31.818182 | GF72: 31.818182 | GG72: 37.878788 | GH72: 36.363636 | GI72: 33.333333 | GJ72: 34.848485 | GK72: 34.848485 | GL72: 30.30303 | GM72: 28.787879 | GN72: 27.272727 | GO72: 25.757576 | GP72: 19.69697 | GQ72: 18.181818 | GR72: 16.666667 | GS72: 12.121212 | GT72: 12.121212 | GU72: 16.666667 | GV72: 12.121212 | GW72: 13.636364 | GX72: 15.151515 | GY72: 15.151515 | GZ72: 15.151515 | HA72: 7.5757576 | HB72: 7.5757576 | HC72: 9.0909091 | HD72: 9.0909091 | HE72: 7.5757576 | HF72: 6.0606061 | HG72: 7.5757576 | HH72: 4.5454545 | HI72: 4.5454545
A74: Not in Reinhart and Rogoff (2009) sample:
A75: Africa | B75: Burkina Faso | C75: 0 | D75: 0 | E75: 0 | F75: 0 | G75: 0 | H75: 0 | I75: 0 | J75: 0 | K75: 0 | L75: 0 | M75: 0 | N75: 0 | O75: 0 | P75: 0 | Q75: 0 | R75: 0 | S75: 0 | T75: 0 | U75: 0 | V75: 0 | W75: 0 | X75: 0 | Y75: 0 | Z75: 0 | AA75: 0 | AB75: 0 | AC75: 0 | AD75: 0 | AE75: 0 | AF75: 0 | AG75: 0 | AH75: 0 | AI75: 0 | AJ75: 0 | AK75: 0 | AL75: 0 | AM75: 0 | AN75: 0 | AO75: 0 | AP75: 0 | AQ75: 0 | AR75: 0 | AS75: 0 | AT75: 0 | AU75: 0 | AV75: 0 | AW75: 0 | AX75: 0 | AY75: 0 | AZ75: 0 | BA75: 0 | BB75: 0 | BC75: 0 | BD75: 0 | BE75: 0 | BF75: 0 | BG75: 0 | BH75: 0 | BI75: 0 | BJ75: 0 | BK75: 0 | BL75: 0 | BM75: 0 | BN75: 0 | BO75: 0 | BP75: 0 | BQ75: 0 | BR75: 0 | BS75: 0 | BT75: 0 | BU75: 0 | BV75: 0 | BW75: 0 | BX75: 0 | BY75: 0 | BZ75: 0 | CA75: 0 | CB75: 0 | CC75: 0 | CD75: 0 | CE75: 0 | CF75: 0 | CG75: 0 | CH75: 0 | CI75: 0 | CJ75: 0 | CK75: 0 | CL75: 0 | CM75: 0 | CN75: 0 | CO75: 0 | CP75: 0 | CQ75: 0 | CR75: 0 | CS75: 0 | CT75: 0 | CU75: 0 | CV75: 0 | CW75: 0 | CX75: 0 | CY75: 0 | CZ75: 0 | DA75: 0 | DB75: 0 | DC75: 0 | DD75: 0 | DE75: 0 | DF75: 0 | DG75: 0 | DH75: 0 | DI75: 0 | DJ75: 0 | DK75: 0 | DL75: 0 | DM75: 0 | DN75: 0 | DO75: 0 | DP75: 0 | DQ75: 0 | DR75: 0 | DS75: 0 | DT75: 0 | DU75: 0 | DV75: 0 | DW75: 0 | DX75: 0 | DY75: 0 | DZ75: 0 | EA75: 0 | EB75: 0 | EC75: 0 | ED75: 0 | EE75: 0 | EF75: 0 | EG75: 0 | EH75: 0 | EI75: 0 | EJ75: 0 | EK75: 0 | EL75: 0 | EM75: 0 | EN75: 0 | EO75: 0 | EP75: 0 | EQ75: 0 | ER75: 0 | ES75: 0 | ET75: 0 | EU75: 0 | EV75: 0 | EW75: 0 | EX75: 0 | EY75: 0 | EZ75: 0 | FA75: 0 | FB75: 0 | FC75: 0 | FD75: 0 | FE75: 0 | FF75: 0 | FG75: 0 | FH75: 0 | FI75: 0 | FJ75: 0 | FK75: 0 | FL75: 0 | FM75: 0 | FN75: 0 | FO75: 0 | FP75: 0 | FQ75: 0 | FR75: 0 | FS75: 0 | FT75: 0 | FU75: 0 | FV75: 0 | FW75: 0 | FX75: 0 | FY75: 0 | FZ75: 0 | GA75: 0 | GB75: 0 | GC75: 0 | GD75: 1 | GE75: 1 | GF75: 1 | GG75: 1 | GH75: 1 | GI75: 1 | GJ75: 1 | GK75: 1 | GL75: 1 | GM75: 1 | GN75: 1 | GO75: 1 | GP75: 1 | GQ75: 1 | GR75: 0 | GS75: 0 | GT75: 0 | GU75: 0 | GV75: 0 | GW75: 0 | GX75: 0 | GY75: 0 | GZ75: 0 | HA75: 0 | HB75: 0 | HC75: 0 | HD75: 0 | HE75: 0 | HF75: 0 | HG75: 0 | HJ75: 1958 | HK75: =SUM(FE$4:HI$4) -> 57 | HL75: =SUM(FE75:HI75) -> 14 | HM75: =100*HL75/HK75 -> 24.561404
B76: Cameroon | C76: 0 | D76: 0 | E76: 0 | F76: 0 | G76: 0 | H76: 0 | I76: 0 | J76: 0 | K76: 0 | L76: 0 | M76: 0 | N76: 0 | O76: 0 | P76: 0 | Q76: 0 | R76: 0 | S76: 0 | T76: 0 | U76: 0 | V76: 0 | W76: 0 | X76: 0 | Y76: 0 | Z76: 0 | AA76: 0 | AB76: 0 | AC76: 0 | AD76: 0 | AE76: 0 | AF76: 0 | AG76: 0 | AH76: 0 | AI76: 0 | AJ76: 0 | AK76: 0 | AL76: 0 | AM76: 0 | AN76: 0 | AO76: 0 | AP76: 0 | AQ76: 0 | AR76: 0 | AS76: 0 | AT76: 0 | AU76: 0 | AV76: 0 | AW76: 0 | AX76: 0 | AY76: 0 | AZ76: 0 | BA76: 0 | BB76: 0 | BC76: 0 | BD76: 0 | BE76: 0 | BF76: 0 | BG76: 0 | BH76: 0 | BI76: 0 | BJ76: 0 | BK76: 0 | BL76: 0 | BM76: 0 | BN76: 0 | BO76: 0 | BP76: 0 | BQ76: 0 | BR76: 0 | BS76: 0 | BT76: 0 | BU76: 0 | BV76: 0 | BW76: 0 | BX76: 0 | BY76: 0 | BZ76: 0 | CA76: 0 | CB76: 0 | CC76: 0 | CD76: 0 | CE76: 0 | CF76: 0 | CG76: 0 | CH76: 0 | CI76: 0 | CJ76: 0 | CK76: 0 | CL76: 0 | CM76: 0 | CN76: 0 | CO76: 0 | CP76: 0 | CQ76: 0 | CR76: 0 | CS76: 0 | CT76: 0 | CU76: 0 | CV76: 0 | CW76: 0 | CX76: 0 | CY76: 0 | CZ76: 0 | DA76: 0 | DB76: 0 | DC76: 0 | DD76: 0 | DE76: 0 | DF76: 0 | DG76: 0 | DH76: 0 | DI76: 0 | DJ76: 0 | DK76: 0 | DL76: 0 | DM76: 0 | DN76: 0 | DO76: 0 | DP76: 0 | DQ76: 0 | DR76: 0 | DS76: 0 | DT76: 0 | DU76: 0 | DV76: 0 | DW76: 0 | DX76: 0 | DY76: 0 | DZ76: 0 | EA76: 0 | EB76: 0 | EC76: 0 | ED76: 0 | EE76: 0 | EF76: 0 | EG76: 0 | EH76: 0 | EI76: 0 | EJ76: 0 | EK76: 0 | EL76: 0 | EM76: 0 | EN76: 0 | EO76: 0 | EP76: 0 | EQ76: 0 | ER76: 0 | ES76: 0 | ET76: 0 | EU76: 0 | EV76: 0 | EW76: 0 | EX76: 0 | EY76: 0 | EZ76: 0 | FA76: 0 | FB76: 0 | FC76: 0 | FD76: 0 | FE76: 0 | FF76: 0 | FG76: 0 | FH76: 0 | FI76: 0 | FJ76: 0 | FK76: 0 | FL76: 0 | FM76: 0 | FN76: 0 | FO76: 0 | FP76: 0 | FQ76: 0 | FR76: 0 | FS76: 0 | FT76: 0 | FU76: 0 | FV76: 0 | FW76: 0 | FX76: 0 | FY76: 0 | FZ76: 0 | GA76: 0 | GB76: 0 | GC76: 0 | GD76: 0 | GE76: 0 | GF76: 1 | GG76: 1 | GH76: 1 | GI76: 1 | GJ76: 1 | GK76: 1 | GL76: 1 | GM76: 1 | GN76: 1 | GO76: 1 | GP76: 1 | GQ76: 1 | GR76: 1 | GS76: 1 | GT76: 1 | GU76: 1 | GV76: 1 | GW76: 1 | GX76: 1 | GY76: 0 | GZ76: 0 | HA76: 0 | HB76: 0 | HC76: 0 | HD76: 0 | HE76: 0 | HF76: 0 | HG76: 0 | HJ76: 1960 | HK76: =SUM(FG$4:HI$4) -> 55 | HL76: =SUM(FG76:HI76) -> 19 | HM76: =100*HL76/HK76 -> 34.545455
B77: Cape Verde | C77: 0 | D77: 0 | E77: 0 | F77: 0 | G77: 0 | H77: 0 | I77: 0 | J77: 0 | K77: 0 | L77: 0 | M77: 0 | N77: 0 | O77: 0 | P77: 0 | Q77: 0 | R77: 0 | S77: 0 | T77: 0 | U77: 0 | V77: 0 | W77: 0 | X77: 0 | Y77: 0 | Z77: 0 | AA77: 0 | AB77: 0 | AC77: 0 | AD77: 0 | AE77: 0 | AF77: 0 | AG77: 0 | AH77: 0 | AI77: 0 | AJ77: 0 | AK77: 0 | AL77: 0 | AM77: 0 | AN77: 0 | AO77: 0 | AP77: 0 | AQ77: 0 | AR77: 0 | AS77: 0 | AT77: 0 | AU77: 0 | AV77: 0 | AW77: 0 | AX77: 0 | AY77: 0 | AZ77: 0 | BA77: 0 | BB77: 0 | BC77: 0 | BD77: 0 | BE77: 0 | BF77: 0 | BG77: 0 | BH77: 0 | BI77: 0 | BJ77: 0 | BK77: 0 | BL77: 0 | BM77: 0 | BN77: 0 | BO77: 0 | BP77: 0 | BQ77: 0 | BR77: 0 | BS77: 0 | BT77: 0 | BU77: 0 | BV77: 0 | BW77: 0 | BX77: 0 | BY77: 0 | BZ77: 0 | CA77: 0 | CB77: 0 | CC77: 0 | CD77: 0 | CE77: 0 | CF77: 0 | CG77: 0 | CH77: 0 | CI77: 0 | CJ77: 0 | CK77: 0 | CL77: 0 | CM77: 0 | CN77: 0 | CO77: 0 | CP77: 0 | CQ77: 0 | CR77: 0 | CS77: 0 | CT77: 0 | CU77: 0 | CV77: 0 | CW77: 0 | CX77: 0 | CY77: 0 | CZ77: 0 | DA77: 0 | DB77: 0 | DC77: 0 | DD77: 0 | DE77: 0 | DF77: 0 | DG77: 0 | DH77: 0 | DI77: 0 | DJ77: 0 | DK77: 0 | DL77: 0 | DM77: 0 | DN77: 0 | DO77: 0 | DP77: 0 | DQ77: 0 | DR77: 0 | DS77: 0 | DT77: 0 | DU77: 0 | DV77: 0 | DW77: 0 | DX77: 0 | DY77: 0 | DZ77: 0 | EA77: 0 | EB77: 0 | EC77: 0 | ED77: 0 | EE77: 0 | EF77: 0 | EG77: 0 | EH77: 0 | EI77: 0 | EJ77: 0 | EK77: 0 | EL77: 0 | EM77: 0 | EN77: 0 | EO77: 0 | EP77: 0 | EQ77: 0 | ER77: 0 | ES77: 0 | ET77: 0 | EU77: 0 | EV77: 0 | EW77: 0 | EX77: 0 | EY77: 0 | EZ77: 0 | FA77: 0 | FB77: 0 | FC77: 0 | FD77: 0 | FE77: 0 | FF77: 0 | FG77: 0 | FH77: 0 | FI77: 0 | FJ77: 0 | FK77: 0 | FL77: 0 | FM77: 0 | FN77: 0 | FO77: 0 | FP77: 0 | FQ77: 0 | FR77: 0 | FS77: 0 | FT77: 0 | FU77: 0 | FV77: 0 | FW77: 0 | FX77: 0 | FY77: 0 | FZ77: 0 | GA77: 0 | GB77: 1 | GC77: 1 | GD77: 1 | GE77: 1 | GF77: 1 | GG77: 1 | GH77: 1 | GI77: 1 | GJ77: 1 | GK77: 1 | GL77: 1 | GM77: 1 | GN77: 1 | GO77: 1 | GP77: 1 | GQ77: 1 | GR77: 0 | GS77: 0 | GT77: 0 | GU77: 0 | GV77: 0 | GW77: 0 | GX77: 0 | GY77: 0 | GZ77: 0 | HA77: 0 | HB77: 0 | HC77: 0 | HD77: 0 | HE77: 0 | HF77: 0 | HG77: 0 | HJ77: 1975 | HK77: =SUM(FV$4:HI$4) -> 40 | HL77: =SUM(FV77:HI77) -> 16 | HM77: =100*HL77/HK77 -> 40
B78: Congo (Brazzaville) | C78: 0 | D78: 0 | E78: 0 | F78: 0 | G78: 0 | H78: 0 | I78: 0 | J78: 0 | K78: 0 | L78: 0 | M78: 0 | N78: 0 | O78: 0 | P78: 0 | Q78: 0 | R78: 0 | S78: 0 | T78: 0 | U78: 0 | V78: 0 | W78: 0 | X78: 0 | Y78: 0 | Z78: 0 | AA78: 0 | AB78: 0 | AC78: 0 | AD78: 0 | AE78: 0 | AF78: 0 | AG78: 0 | AH78: 0 | AI78: 0 | AJ78: 0 | AK78: 0 | AL78: 0 | AM78: 0 | AN78: 0 | AO78: 0 | AP78: 0 | AQ78: 0 | AR78: 0 | AS78: 0 | AT78: 0 | AU78: 0 | AV78: 0 | AW78: 0 | AX78: 0 | AY78: 0 | AZ78: 0 | BA78: 0 | BB78: 0 | BC78: 0 | BD78: 0 | BE78: 0 | BF78: 0 | BG78: 0 | BH78: 0 | BI78: 0 | BJ78: 0 | BK78: 0 | BL78: 0 | BM78: 0 | BN78: 0 | BO78: 0 | BP78: 0 | BQ78: 0 | BR78: 0 | BS78: 0 | BT78: 0 | BU78: 0 | BV78: 0 | BW78: 0 | BX78: 0 | BY78: 0 | BZ78: 0 | CA78: 0 | CB78: 0 | CC78: 0 | CD78: 0 | CE78: 0 | CF78: 0 | CG78: 0 | CH78: 0 | CI78: 0 | CJ78: 0 | CK78: 0 | CL78: 0 | CM78: 0 | CN78: 0 | CO78: 0 | CP78: 0 | CQ78: 0 | CR78: 0 | CS78: 0 | CT78: 0 | CU78: 0 | CV78: 0 | CW78: 0 | CX78: 0 | CY78: 0 | CZ78: 0 | DA78: 0 | DB78: 0 | DC78: 0 | DD78: 0 | DE78: 0 | DF78: 0 | DG78: 0 | DH78: 0 | DI78: 0 | DJ78: 0 | DK78: 0 | DL78: 0 | DM78: 0 | DN78: 0 | DO78: 0 | DP78: 0 | DQ78: 0 | DR78: 0 | DS78: 0 | DT78: 0 | DU78: 0 | DV78: 0 | DW78: 0 | DX78: 0 | DY78: 0 | DZ78: 0 | EA78: 0 | EB78: 0 | EC78: 0 | ED78: 0 | EE78: 0 | EF78: 0 | EG78: 0 | EH78: 0 | EI78: 0 | EJ78: 0 | EK78: 0 | EL78: 0 | EM78: 0 | EN78: 0 | EO78: 0 | EP78: 0 | EQ78: 0 | ER78: 0 | ES78: 0 | ET78: 0 | EU78: 0 | EV78: 0 | EW78: 0 | EX78: 0 | EY78: 0 | EZ78: 0 | FA78: 0 | FB78: 0 | FC78: 0 | FD78: 0 | FE78: 0 | FF78: 0 | FG78: 0 | FH78: 0 | FI78: 0 | FJ78: 0 | FK78: 0 | FL78: 0 | FM78: 0 | FN78: 0 | FO78: 0 | FP78: 0 | FQ78: 0 | FR78: 0 | FS78: 0 | FT78: 0 | FU78: 0 | FV78: 0 | FW78: 0 | FX78: 0 | FY78: 0 | FZ78: 0 | GA78: 0 | GB78: 0 | GC78: 0 | GD78: 1 | GE78: 1 | GF78: 1 | GG78: 1 | GH78: 1 | GI78: 1 | GJ78: 1 | GK78: 1 | GL78: 1 | GM78: 1 | GN78: 1 | GO78: 1 | GP78: 1 | GQ78: 1 | GR78: 1 | GS78: 1 | GT78: 1 | GU78: 1 | GV78: 1 | GW78: 1 | GX78: 1 | GY78: 1 | GZ78: 1 | HA78: 1 | HB78: 1 | HC78: 0 | HD78: 0 | HE78: 0 | HF78: 0 | HG78: 0 | HJ78: 1960 | HK78: =SUM(FG$4:HI$4) -> 55 | HL78: =SUM(FG78:HI78) -> 25 | HM78: =100*HL78/HK78 -> 45.454545 | HS78: Need to check beyond 2008
