Workbook

Sheet Domestic and imported
A1: Instituto Nacional de Estadística y Geografía (INEGI).
A2: Sistema de Cuentas Nacionales de México. Matriz de Insumo Producto simétrica, Base 2018
A3: Matriz simétrica de insumo producto. Industria por industria/ Economía total / Origen doméstico e importado/ Subsector SCIAN/ Millones de pesos a precios básicos
A5: Concepto | B5: UTPB - Utilización total a precios básicos | C5: DI - Demanda intermedia | CD5: DA - Demanda agregada
C6: Total | D6: 111 - Agricultura | E6: 112 - Cría y explotación de animales | F6: 113 - Aprovechamiento forestal | G6: 114 - Pesca, caza y captura | H6: 115 - Servicios relacionados con las actividades agropecuarias y forestales | I6: 211 - Extracción de petróleo y gas | J6: 212 - Minería de minerales metálicos y no metálicos, excepto petróleo y gas | K6: 213 - Servicios relacionados con la minería | L6: 221 - Generación, transmisión, distribución y comercialización de energía eléctrica, suministro de agua y de gas natural por ductos al consumidor final | M6: 236 - Edificación | N6: 237 - Construcción de obras de ingeniería civil | O6: 238 - Trabajos especializados para la construcción | P6: 311 - Industria alimentaria | Q6: 312 - Industria de las bebidas y del tabaco | R6: 313 - Fabricación de insumos textiles y acabado de textiles | S6: 314 - Fabricación de productos textiles, excepto prendas de vestir | T6: 315 - Fabricación de prendas de vestir | U6: 316 - Curtido y acabado de cuero y piel, y fabricación de productos de cuero, piel y materiales sucedáneos | V6: 321 - Industria de la madera | W6: 322 - Industria del papel | X6: 323 - Impresión e industrias conexas | Y6: 324 - Fabricación de productos derivados del petróleo y del carbón | Z6: 325 - Industria química | AA6: 326 - Industria del plástico y del hule | AB6: 327 - Fabricación de productos a base de minerales no metálicos | AC6: 331 - Industrias metálicas básicas | AD6: 332 - Fabricación de productos metálicos | AE6: 333 - Fabricación de maquinaria y equipo | AF6: 334 - Fabricación de equipo de computación, comunicación, medición y de otros equipos, componentes y accesorios electrónicos | AG6: 335 - Fabricación de accesorios, aparatos eléctricos y equipo de generación de energía eléctrica | AH6: 336 - Fabricación de equipo de transporte | AI6: 337 - Fabricación de muebles, colchones y persianas | AJ6: 339 - Otras industrias manufactureras | AK6: 431 - Comercio al por mayor de abarrotes, alimentos, bebidas, hielo y tabaco | AL6: 461 - Comercio al por menor de abarrotes, alimentos, bebidas, hielo y tabaco | AM6: 481 - Transporte aéreo | AN6: 482 - Transporte por ferrocarril | AO6: 483 - Transporte por agua | AP6: 484 - Autotransporte de carga | AQ6: 485 - Transporte terrestre de pasajeros, excepto por ferrocarril | AR6: 486 - Transporte por ductos | AS6: 487 - Transporte turístico | AT6: 488 - Servicios relacionados con el transporte | AU6: 491 - Servicios postales | AV6: 492 - Servicios de mensajería y paquetería | AW6: 493 - Servicios de almacenamiento | AX6: 511 - Edición de periódicos, revistas, libros, software y otros materiales, y edición de estas publicaciones integrada con la impresión | AY6: 512 - Industria fílmica y del video, e industria del sonido | AZ6: 515 - Radio y televisión | BA6: 517 - Telecomunicaciones | BB6: 518 - Procesamiento electrónico de información, hospedaje y otros servicios relacionados | BC6: 519 - Otros servicios de información | BD6: 521 - Banca central | BE6: 522 - Instituciones de intermediación crediticia y financiera no bursátil | BF6: 523 - Actividades bursátiles, cambiarias y de inversión financiera | BG6: 524 - Compañías de seguros, fianzas, y administración de fondos para el retiro | BH6: 531 - Servicios inmobiliarios | BI6: 532 - Servicios de alquiler de bienes muebles | BJ6: 533 - Servicios de alquiler de marcas registradas, patentes y franquicias | BK6: 541 - Servicios profesionales, científicos y técnicos | BL6: 551 - Corporativos | BM6: 561 - Servicios de apoyo a los negocios | BN6: 562 - Manejo de residuos y servicios de remediación | BO6: 611 - Servicios educativos | BP6: 621 - Servicios médicos de consulta externa y servicios relacionados | BQ6: 622 - Hospitales | BR6: 623 - Residencias de asistencia social y para el cuidado de la salud | BS6: 624 - Otros servicios de asistencia social | BT6: 711 - Servicios artísticos, culturales y deportivos, y otros servicios relacionados | BU6: 712 - Museos, sitios históricos, zoológicos y similares | BV6: 713 - Servicios de entretenimiento en instalaciones recreativas y otros servicios recreativos | BW6: 721 - Servicios de alojamiento temporal | BX6: 722 - Servicios de preparación de alimentos y bebidas | BY6: 811 - Servicios de reparación y mantenimiento | BZ6: 812 - Servicios personales | CA6: 813 - Asociaciones y organizaciones | CB6: 814 - Hogares con empleados domésticos | CC6: 931 - Actividades legislativas, gubernamentales y de impartición de justicia | CD6: Total | CE6: CP - Consumo Privado | CF6: CG - Consumo de gobierno | CG6: P.51b - Formación bruta de capital fijo | CH6: P.52 - Variación de existencias | CI6: a P.6 - Exportaciones de bienes y servicios | CJ6: b P.7 - Importaciones de bienes y servicios | CK6: YA0 - Discrepancia estadística
A7: 111 - Agricultura | B7: 682846.43 | C7: 490741.13 | D7: 17872.458 | E7: 58727.6 | F7: 176.569 | G7: 15.594 | H7: 314.236 | I7: 0 | J7: 0 | K7: 0 | L7: 0 | M7: 39.5 | N7: 1589.433 | O7: 9.078 | P7: 320433.4 | Q7: 26560.817 | R7: 17644.121 | S7: 1015.461 | T7: 618.101 | U7: 58.905 | V7: 426.575 | W7: 5.262 | X7: 0 | Y7: 0 | Z7: 1745.046 | AA7: 4243.552 | AB7: 18.296 | AC7: 0 | AD7: 0 | AE7: 0 | AF7: 0.014 | AG7: 941.667 | AH7: 0 | AI7: 0 | AJ7: 458.171 | AK7: 0 | AL7: 0.141 | AM7: 0 | AN7: 0 | AO7: 0 | AP7: 0 | AQ7: 0 | AR7: 0 | AS7: 0 | AT7: 0 | AU7: 0 | AV7: 0 | AW7: 0 | AX7: 0 | AY7: 0 | AZ7: 0.005 | BA7: 0 | BB7: 0 | BC7: 0.001 | BD7: 0 | BE7: 0 | BF7: 0 | BG7: 0 | BH7: 0.014 | BI7: 0 | BJ7: 0 | BK7: 1.544 | BL7: 0 | BM7: 1.944 | BN7: 0 | BO7: 2.75 | BP7: 0.101 | BQ7: 572.652 | BR7: 49.174 | BS7: 265.093 | BT7: 0 | BU7: 0 | BV7: 0.085 | BW7: 10430.279 | BX7: 26189.763 | BY7: 0.001 | BZ7: 13.112 | CA7: 251.128 | CB7: 0 | CC7: 49.495 | CD7: 192105.3 | CE7: 177570.47 | CF7: 401.578 | CG7: 15150.198 | CH7: 2313.924 | CI7: 203046.56 | CJ7: -206377.43
A8: 112 - Cría y explotación de animales | B8: 495469.19 | C8: 368925.73 | D8: 5038.302 | E8: 11934.088 | F8: 0 | G8: 0 | H8: 0 | I8: 0.008 | J8: 0.001 | K8: 0.012 | L8: 0.002 | M8: 618.977 | N8: 0.01 | O8: 0.011 | P8: 348273.86 | Q8: 3.347 | R8: 666.294 | S8: 0 | T8: 0.001 | U8: 148.227 | V8: 0 | W8: 0.001 | X8: 0.001 | Y8: 0 | Z8: 379.584 | AA8: 0.002 | AB8: 0 | AC8: 0.001 | AD8: 0.001 | AE8: 0.001 | AF8: 0.002 | AG8: 0.053 | AH8: 0.021 | AI8: 0.001 | AJ8: 184.944 | AK8: 0.029 | AL8: 0.048 | AM8: 0.001 | AN8: 0 | AO8: 0 | AP8: 0 | AQ8: 0.004 | AR8: 0 | AS8: 0 | AT8: 0.001 | AU8: 0 | AV8: 0 | AW8: 0.002 | AX8: 0 | AY8: 0.014 | AZ8: 0.113 | BA8: 0.015 | BB8: 0 | BC8: 0.037 | BD8: 0 | BE8: 0.011 | BF8: 0 | BG8: 0.002 | BH8: 0.395 | BI8: 0 | BJ8: 0 | BK8: 0.004 | BL8: 0.002 | BM8: 52.522 | BN8: 0 | BO8: 0.077 | BP8: 2.77 | BQ8: 287.688 | BR8: 21.023 | BS8: 29.419 | BT8: 0 | BU8: 0 | BV8: 2.306 | BW8: 0.002 | BX8: 1274.867 | BY8: 0.046 | BZ8: 3.154 | CA8: 0.001 | CB8: 0 | CC8: 3.418 | CD8: 126543.46 | CE8: 53881.036 | CF8: 3.35 | CG8: 64919.281 | CH8: 4327.278 | CI8: 11279.802 | CJ8: -7867.282
A9: 113 - Aprovechamiento forestal | B9: 28827.855 | C9: 25766.231 | D9: 0 | E9: 0 | F9: 1262.96 | G9: 0 | H9: 0.057 | I9: 0 | J9: 0.671 | K9: 0 | L9: 0 | M9: 0 | N9: 0 | O9: 0 | P9: 766.463 | Q9: 0 | R9: 0 | S9: 4.527 | T9: 0.483 | U9: 170.383 | V9: 15512.362 | W9: 1182.954 | X9: 0.253 | Y9: 0 | Z9: 4354.616 | AA9: 783.116 | AB9: 366.077 | AC9: 0 | AD9: 22.078 | AE9: 0 | AF9: 2.596 | AG9: 4.691 | AH9: 0 | AI9: 623.412 | AJ9: 708.424 | AK9: 0 | AL9: 0 | AM9: 0 | AN9: 0 | AO9: 0 | AP9: 0 | AQ9: 0 | AR9: 0 | AS9: 0 | AT9: 0 | AU9: 0 | AV9: 0 | AW9: 0 | AX9: 0 | AY9: 0 | AZ9: 0 | BA9: 0 | BB9: 0 | BC9: 0 | BD9: 0 | BE9: 0 | BF9: 0 | BG9: 0 | BH9: 0 | BI9: 0 | BJ9: 0 | BK9: 0.008 | BL9: 0 | BM9: 0 | BN9: 0 | BO9: 0.099 | BP9: 0 | BQ9: 0 | BR9: 0 | BS9: 0 | BT9: 0 | BU9: 0 | BV9: 0 | BW9: 0 | BX9: 0 | BY9: 0 | BZ9: 0 | CA9: 0 | CB9: 0 | CC9: 0.001 | CD9: 3061.624 | CE9: 3236.816 | CF9: 0 | CG9: 0 | CH9: 6.253 | CI9: 1368.362 | CJ9: -1549.807
A10: 114 - Pesca, caza y captura | B10: 22972.495 | C10: 6172.513 | D10: 0 | E10: 0.032 | F10: 0.017 | G10: 16.199 | H10: 0.007 | I10: 2.141 | J10: 0.348 | K10: 3.202 | L10: 0.376 | M10: 5.523 | N10: 2.317 | O10: 2.529 | P10: 4864.585 | Q10: 0.15 | R10: 0.06 | S10: 0.056 | T10: 0.177 | U10: 0.043 | V10: 0.05 | W10: 8.532 | X10: 0.125 | Y10: 0.016 | Z10: 0.452 | AA10: 0.338 | AB10: 0.174 | AC10: 0.234 | AD10: 0.313 | AE10: 0.286 | AF10: 0.636 | AG10: 0.152 | AH10: 4.497 | AI10: 0.136 | AJ10: 0.343 | AK10: 4.456 | AL10: 7.068 | AM10: 0.106 | AN10: 0.042 | AO10: 0.02 | AP10: 0.066 | AQ10: 0.624 | AR10: 0.009 | AS10: 0.003 | AT10: 0.207 | AU10: 0.004 | AV10: 0.021 | AW10: 0.246 | AX10: 0.03 | AY10: 0.476 | AZ10: 0.131 | BA10: 1.953 | BB10: 0.012 | BC10: 0.013 | BD10: 0.002 | BE10: 1.71 | BF10: 0.078 | BG10: 0.23 | BH10: 0.715 | BI10: 0.089 | BJ10: 0.002 | BK10: 0.76 | BL10: 0.266 | BM10: 0.749 | BN10: 0.014 | BO10: 1.699 | BP10: 1.636 | BQ10: 0.685 | BR10: 0.028 | BS10: 0.18 | BT10: 0.078 | BU10: 0.462 | BV10: 0.346 | BW10: 658.279 | BX10: 567.994 | BY10: 0.487 | BZ10: 0.605 | CA10: 0.244 | CB10: 0 | CC10: 5.642 | CD10: 16799.982 | CE10: 12461.6 | CF10: 0.002 | CG10: 23.382 | CH10: 0.324 | CI10: 4716.085 | CJ10: -401.411
A11: 115 - Servicios relacionados con las actividades agropecuarias y forestales | B11: 10393.96 | C11: 9546.667 | D11: 3859.953 | E11: 729.703 | F11: 77.339 | G11: 19.418 | H11: 0.261 | I11: 0.02 | J11: 0.003 | K11: 0.001 | L11: 0.005 | M11: 0.225 | N11: 0.021 | O11: 0.006 | P11: 4104.789 | Q11: 0.014 | R11: 527.495 | S11: 0.002 | T11: 224.951 | U11: 0.001 | V11: 0.002 | W11: 0.01 | X11: 0.003 | Y11: 0.015 | Z11: 0.075 | AA11: 0.018 | AB11: 0.011 | AC11: 0.022 | AD11: 0.015 | AE11: 0.015 | AF11: 0.022 | AG11: 0.012 | AH11: 0.158 | AI11: 0.004 | AJ11: 0.812 | AK11: 0.07 | AL11: 0.05 | AM11: 0.004 | AN11: 0.001 | AO11: 0 | AP11: 0.015 | AQ11: 0.008 | AR11: 0 | AS11: 0 | AT11: 0.002 | AU11: 0 | AV11: 0.001 | AW11: 0 | AX11: 0.039 | AY11: 0.024 | AZ11: 0.022 | BA11: 0.006 | BB11: 0 | BC11: 0 | BD11: 0.001 | BE11: 0.133 | BF11: 0.003 | BG11: 0.001 | BH11: 0.02 | BI11: 0.002 | BJ11: 0 | BK11: 0.035 | BL11: 0.001 | BM11: 0.022 | BN11: 0 | BO11: 0.094 | BP11: 0.019 | BQ11: 0.034 | BR11: 0 | BS11: 0 | BT11: 0 | BU11: 0.001 | BV11: 0.002 | BW11: 0.005 | BX11: 0.015 | BY11: 0.005 | BZ11: 0.001 | CA11: 0.046 | CB11: 0 | CC11: 0.584 | CD11: 847.293 | CE11: 828.859 | CF11: 0.324 | CG11: 25.881 | CH11: 0 | CI11: 0.417 | CJ11: -8.188
A12: 211 - Extracción de petróleo y gas | B12: 886533.21 | C12: 392468.64 | D12: 4.417 | E12: 8.057 | F12: 0.119 | G12: 0.218 | H12: 0.084 | I12: 3.627 | J12: 1.749 | K12: 0.902 | L12: 3.243 | M12: 35.283 | N12: 4.849 | O12: 2.696 | P12: 34.101 | Q12: 3.442 | R12: 0.853 | S12: 0.674 | T12: 1.433 | U12: 0.862 | V12: 1.051 | W12: 5.021 | X12: 1.354 | Y12: 280842.23 | Z12: 111324.16 | AA12: 8.337 | AB12: 5.258 | AC12: 12.184 | AD12: 7.65 | AE12: 8.607 | AF12: 12.086 | AG12: 6.419 | AH12: 68.119 | AI12: 2 | AJ12: 3.034 | AK12: 4.18 | AL12: 1.983 | AM12: 1.943 | AN12: 0.241 | AO12: 0.154 | AP12: 4.355 | AQ12: 3.194 | AR12: 0.128 | AS12: 0.019 | AT12: 1.531 | AU12: 0.004 | AV12: 0.295 | AW12: 0.183 | AX12: 0.066 | AY12: 0.155 | AZ12: 0.206 | BA12: 2.471 | BB12: 0.035 | BC12: 0.003 | BD12: 0.139 | BE12: 1.238 | BF12: 0.044 | BG12: 0.085 | BH12: 2.346 | BI12: 0.86 | BJ12: 0.005 | BK12: 2.018 | BL12: 0.281 | BM12: 3.719 | BN12: 0.195 | BO12: 1.624 | BP12: 2.412 | BQ12: 4.474 | BR12: 0.041 | BS12: 0.301 | BT12: 0.215 | BU12: 0.066 | BV12: 0.728 | BW12: 2.338 | BX12: 4.117 | BY12: 1.979 | BZ12: 0.697 | CA12: 0.5 | CB12: 0 | CC12: 2.948 | CD12: 494064.58 | CE12: 518.713 | CF12: 0 | CG12: 95.936 | CH12: 0.007 | CI12: 493451.49 | CJ12: -1.566
A13: 212 - Minería de minerales metálicos y no metálicos, excepto petróleo y gas | B13: 421712.98 | C13: 379330.25 | D13: 514.206 | E13: 228.398 | F13: 15.74 | G13: 14.302 | H13: 2.023 | I13: 744.668 | J13: 9820.326 | K13: 393.958 | L13: 17960.148 | M13: 26384.015 | N13: 14441.717 | O13: 5003.589 | P13: 855.418 | Q13: 810.236 | R13: 1.438 | S13: 2.062 | T13: 4.457 | U13: 2.428 | V13: 2.693 | W13: 178.189 | X13: 6.279 | Y13: 831.614 | Z13: 12783.309 | AA13: 172.719 | AB13: 64801.689 | AC13: 216543.26 | AD13: 1186.204 | AE13: 44.967 | AF13: 80.355 | AG13: 363.892 | AH13: 1296.414 | AI13: 4.911 | AJ13: 1083.44 | AK13: 181.167 | AL13: 183.483 | AM13: 10.614 | AN13: 29.597 | AO13: 1.292 | AP13: 191.286 | AQ13: 360.949 | AR13: 21.934 | AS13: 1.933 | AT13: 35.047 | AU13: 0.029 | AV13: 35.044 | AW13: 4.639 | AX13: 3.137 | AY13: 14.541 | AZ13: 20.841 | BA13: 161.696 | BB13: 1.317 | BC13: 0.51 | BD13: 0.033 | BE13: 34.154 | BF13: 2.559 | BG13: 5.306 | BH13: 191.759 | BI13: 15.063 | BJ13: 0.146 | BK13: 66.78 | BL13: 3.951 | BM13: 58.367 | BN13: 1.188 | BO13: 122.067 | BP13: 282.254 | BQ13: 44.294 | BR13: 2.521 | BS13: 12.726 | BT13: 2.199 | BU13: 2.162 | BV13: 22.104 | BW13: 47.834 | BX13: 85.546 | BY13: 2.721 | BZ13: 21.431 | CA13: 19.659 | CB13: 0 | CC13: 445.305 | CD13: 42382.735 | CE13: 20.854 | CF13: 6.359 | CG13: 827.651 | CH13: 2007.874 | CI13: 96352.216 | CJ13: -56832.219
A14: 213 - Servicios relacionados con la minería | B14: 152934.19 | C14: 3485.49 | D14: 0 | E14: 0.007 | F14: 0.023 | G14: 0.011 | H14: 0.005 | I14: 3103.645 | J14: 300.167 | K14: 43.922 | L14: 0.357 | M14: 7.182 | N14: 3.089 | O14: 3.256 | P14: 0.09 | Q14: 0.016 | R14: 0.007 | S14: 0.01 | T14: 0.029 | U14: 0.007 | V14: 0.014 | W14: 0.088 | X14: 0.052 | Y14: 0.009 | Z14: 0.159 | AA14: 0.095 | AB14: 0.065 | AC14: 0.29 | AD14: 0.107 | AE14: 0.149 | AF14: 0.655 | AG14: 0.083 | AH14: 4.18 | AI14: 0.02 | AJ14: 0.036 | AK14: 1.412 | AL14: 1.395 | AM14: 0.024 | AN14: 0.038 | AO14: 0.012 | AP14: 0.012 | AQ14: 0.012 | AR14: 0.001 | AS14: 0 | AT14: 0.044 | AU14: 0 | AV14: 0.002 | AW14: 0.077 | AX14: 0.08 | AY14: 0.093 | AZ14: 0.073 | BA14: 0.034 | BB14: 0.003 | BC14: 0.006 | BD14: 0.001 | BE14: 0.657 | BF14: 0.044 | BG14: 0.079 | BH14: 0.216 | BI14: 0.015 | BJ14: 0 | BK14: 0.229 | BL14: 0.004 | BM14: 0.137 | BN14: 0.005 | BO14: 1.821 | BP14: 1.643 | BQ14: 0.712 | BR14: 0.035 | BS14: 0.2 | BT14: 0.015 | BU14: 0.018 | BV14: 0.092 | BW14: 0.073 | BX14: 0.187 | BY14: 0.026 | BZ14: 0.253 | CA14: 0.296 | CB14: 0 | CC14: 7.589 | CD14: 149448.7 | CE14: 0.344 | CF14: 0.108 | CG14: 149457.75 | CH14: 5.448 | CI14: 0.172 | CJ14: -15.128
A15: 221 - Generación, transmisión, distribución y comercialización de energía eléctrica, suministro de agua y de gas natural por ductos al consumidor final | B15: 735834.91 | C15: 452314.98 | D15: 10662.788 | E15: 5367.402 | F15: 104.655 | G15: 95.854 | H15: 166.707 | I15: 3251.582 | J15: 13961.72 | K15: 8063.642 | L15: 11879.983 | M15: 2384.52 | N15: 3662.105 | O15: 1580.792 | P15: 24813.883 | Q15: 4633.368 | R15: 6509.542 | S15: 1293.516 | T15: 4445.198 | U15: 1535.169 | V15: 1303.674 | W15: 5676.826 | X15: 1241.857 | Y15: 10862.973 | Z15: 13216.343 | AA15: 12443.23 | AB15: 8288.997 | AC15: 27654.932 | AD15: 6632.865 | AE15: 8412.439 | AF15: 15284.712 | AG15: 3840.675 | AH15: 41314.297 | AI15: 994.714 | AJ15: 2212.189 | AK15: 16710.864 | AL15: 67306.094 | AM15: 111.287 | AN15: 91.433 | AO15: 158.185 | AP15: 648.511 | AQ15: 1736.577 | AR15: 356.624 | AS15: 18.625 | AT15: 1041.017 | AU15: 15.905 | AV15: 116.23 | AW15: 1875.245 | AX15: 152.147 | AY15: 624.321 | AZ15: 1002.064 | BA15: 5046.857 | BB15: 267.333 | BC15: 26.469 | BD15: 34.136 | BE15: 3838.424 | BF15: 159.821 | BG15: 1427.316 | BH15: 18606.157 | BI15: 593.581 | BJ15: 8.607 | BK15: 4049.08 | BL15: 498.581 | BM15: 5898.381 | BN15: 117.115 | BO15: 12262.046 | BP15: 3955.492 | BQ15: 4343.692 | BR15: 147.98 | BS15: 490.628 | BT15: 343.025 | BU15: 201.272 | BV15: 2170.007 | BW15: 5143.011 | BX15: 4891.001 | BY15: 1998.961 | BZ15: 2895.453 | CA15: 1189.82 | CB15: 0 | CC15: 15952.459 | CD15: 283519.93 | CE15: 286082.97 | CF15: 17.511 | CG15: 607.812 | CH15: 0 | CI15: 4309.228 | CJ15: -7497.594
A16: 236 - Edificación | B16: 2090312.5 | C16: 27894.678 | D16: 11.804 | E16: 18.427 | F16: 1.509 | G16: 8.028 | H16: 1.254 | I16: 469.005 | J16: 357.27 | K16: 392.401 | L16: 535.833 | M16: 16227.947 | N16: 1305.87 | O16: 603.379 | P16: 177.855 | Q16: 25.936 | R16: 5.169 | S16: 4.626 | T16: 17.453 | U16: 5.29 | V16: 9.231 | W16: 43.505 | X16: 36.164 | Y16: 17.994 | Z16: 530.864 | AA16: 93.667 | AB16: 55.756 | AC16: 99.246 | AD16: 92.228 | AE16: 56.062 | AF16: 84.815 | AG16: 33.142 | AH16: 1282.241 | AI16: 21.81 | AJ16: 14.597 | AK16: 312.253 | AL16: 536.637 | AM16: 6.026 | AN16: 2.858 | AO16: 1.185 | AP16: 7.329 | AQ16: 20.654 | AR16: 189.074 | AS16: 0.103 | AT16: 11.213 | AU16: 0.128 | AV16: 1.068 | AW16: 23.398 | AX16: 2.562 | AY16: 20.312 | AZ16: 15.211 | BA16: 62.074 | BB16: 0.629 | BC16: 1.621 | BD16: 0.226 | BE16: 63.836 | BF16: 9.354 | BG16: 130.34 | BH16: 184.421 | BI16: 11.611 | BJ16: 0.157 | BK16: 1223.022 | BL16: 7.531 | BM16: 788.521 | BN16: 4.363 | BO16: 210.95 | BP16: 207.379 | BQ16: 54.182 | BR16: 2.746 | BS16: 24.422 | BT16: 9.399 | BU16: 3.118 | BV16: 66.017 | BW16: 60.982 | BX16: 148.258 | BY16: 39.833 | BZ16: 145.289 | CA16: 42.48 | CB16: 0 | CC16: 601.528 | CD16: 2062417.8 | CE16: 4232.269 | CF16: 59.437 | CG16: 2059440.1 | CH16: 0 | CI16: 2496.817 | CJ16: -3810.847
A17: 237 - Construcción de obras de ingeniería civil | B17: 568177.3 | C17: 47150.251 | D17: 8.864 | E17: 13.494 | F17: 2.649 | G17: 8.083 | H17: 1.368 | I17: 601.377 | J17: 362.267 | K17: 598.186 | L17: 525.611 | M17: 2971.287 | N17: 33829.962 | O17: 747.835 | P17: 137.379 | Q17: 20.96 | R17: 3.68 | S17: 3.605 | T17: 14.361 | U17: 4.224 | V17: 8.207 | W17: 40.616 | X17: 34.768 | Y17: 14.029 | Z17: 498.637 | AA17: 84.586 | AB17: 51.268 | AC17: 91.346 | AD17: 84.886 | AE17: 53.559 | AF17: 106.769 | AG17: 30.888 | AH17: 1382.452 | AI17: 18.366 | AJ17: 12.127 | AK17: 305.383 | AL17: 470.106 | AM17: 4.353 | AN17: 4.373 | AO17: 1.482 | AP17: 4.14 | AQ17: 6.45 | AR17: 179.873 | AS17: 0.055 | AT17: 8.814 | AU17: 0.073 | AV17: 0.577 | AW17: 22.636 | AX17: 2.972 | AY17: 13.558 | AZ17: 13.204 | BA17: 21.577 | BB17: 0.524 | BC17: 1.332 | BD17: 0.128 | BE17: 57.875 | BF17: 10.091 | BG17: 124.886 | BH17: 169.207 | BI17: 9.827 | BJ17: 0.132 | BK17: 1162.491 | BL17: 2.001 | BM17: 179.863 | BN17: 4.101 | BO17: 281.05 | BP17: 246.132 | BQ17: 81.913 | BR17: 4.416 | BS17: 24.145 | BT17: 8.267 | BU17: 3.399 | BV17: 37.257 | BW17: 55.929 | BX17: 126.78 | BY17: 28.513 | BZ17: 126.842 | CA17: 55.404 | CB17: 0 | CC17: 920.424 | CD17: 521027.05 | CE17: 1420.363 | CF17: 21666.505 | CG17: 499458.2 | CH17: 0 | CI17: 2276.05 | CJ17: -3794.062
A18: 238 - Trabajos especializados para la construcción | B18: 304773.24 | C18: 286480.84 | D18: 7.902 | E18: 21.449 | F18: 1283.715 | G18: 0.934 | H18: 12.143 | I18: 166.796 | J18: 4902.724 | K18: 1171.886 | L18: 61.171 | M18: 183463.98 | N18: 69080.584 | O18: 1353.996 | P18: 923.183 | Q18: 30.297 | R18: 2.758 | S18: 13.277 | T18: 42.151 | U18: 10.907 | V18: 4.819 | W18: 22.677 | X18: 24.604 | Y18: 137.472 | Z18: 54.824 | AA18: 24.067 | AB18: 23.286 | AC18: 33.887 | AD18: 25.503 | AE18: 30.616 | AF18: 37.492 | AG18: 14.098 | AH18: 243.285 | AI18: 9.886 | AJ18: 14.926 | AK18: 1000.265 | AL18: 1039.373 | AM18: 82.198 | AN18: 5.24 | AO18: 15.224 | AP18: 36.805 | AQ18: 124.75 | AR18: 18.06 | AS18: 1.522 | AT18: 24.045 | AU18: 0.406 | AV18: 5.741 | AW18: 33.232 | AX18: 2.594 | AY18: 8.156 | AZ18: 6.445 | BA18: 44.175 | BB18: 0.309 | BC18: 3.456 | BD18: 0.241 | BE18: 1115.346 | BF18: 1.3 | BG18: 16.628 | BH18: 92.259 | BI18: 4.8 | BJ18: 0.038 | BK18: 460.884 | BL18: 2.827 | BM18: 57.237 | BN18: 1.197 | BO18: 4401.697 | BP18: 1793.046 | BQ18: 1206.99 | BR18: 1.598 | BS18: 69.878 | BT18: 28.532 | BU18: 346.099 | BV18: 132.569 | BW18: 34.204 | BX18: 167.866 | BY18: 115.228 | BZ18: 25.247 | CA18: 8.695 | CB18: 0 | CC18: 10693.138 | CD18: 18292.402 | CE18: 969.495 | CF18: 38.329 | CG18: 17107.016 | CH18: 3.474 | CI18: 350.898 | CJ18: -176.81
... A84: 931 - Actividades legislativas, gubernamentales y de impartición de justicia | B84: 1305939.3 | C84: 499.619 | D84: 0 | E84: 0 | F84: 0 | G84: 0 | H84: 0 | I84: 0 | J84: 0 | K84: 0 | L84: 0 | M84: 0 | N84: 0 | O84: 0 | P84: 0 | Q84: 0 | R84: 0 | S84: 0 | T84: 0 | U84: 0 | V84: 0 | W84: 0 | X84: 0 | Y84: 0 | Z84: 0 | AA84: 0 | AB84: 0 | AC84: 0 | AD84: 0 | AE84: 0 | AF84: 0 | AG84: 0 | AH84: 0 | AI84: 0 | AJ84: 0 | AK84: 0 | AL84: 0 | AM84: 0 | AN84: 0 | AO84: 0 | AP84: 0 | AQ84: 0 | AR84: 0 | AS84: 0 | AT84: 0 | AU84: 0 | AV84: 0 | AW84: 0 | AX84: 0 | AY84: 0 | AZ84: 0 | BA84: 0 | BB84: 0 | BC84: 0 | BD84: 0 | BE84: 41.317 | BF84: 21.136 | BG84: 437.166 | BH84: 0 | BI84: 0 | BJ84: 0 | BK84: 0 | BL84: 0 | BM84: 0 | BN84: 0 | BO84: 0 | BP84: 0 | BQ84: 0 | BR84: 0 | BS84: 0 | BT84: 0 | BU84: 0 | BV84: 0 | BW84: 0 | BX84: 0 | BY84: 0 | BZ84: 0 | CA84: 0 | CB84: 0 | CC84: 0 | CD84: 1305439.6 | CE84: 6950.097 | CF84: 1298489.5 | CG84: 0 | CH84: 0 | CI84: 0 | CJ84: 0
A85: UETONI - Usos de la ET de origen nacional e importado | B85: 41959242 | C85: 18773096 | D85: 165184.98 | E85: 252628.64 | F85: 6080.69 | G85: 13159.222 | H85: 4448.99 | I85: 262200.12 | J85: 152354.44 | K85: 89202.819 | L85: 256368.93 | M85: 1022404.9 | N85: 350571.31 | O85: 122622.35 | P85: 1472875.4 | Q85: 222513.51 | R85: 66073.974 | S85: 29825.38 | T85: 101845.91 | U85: 52640.034 | V85: 50610.722 | W85: 187234.88 | X85: 60822.838 | Y85: 760591.51 | Z85: 750152.16 | AA85: 396752.29 | AB85: 238615.78 | AC85: 621121.8 | AD85: 340880.57 | AE85: 391587.42 | AF85: 1506816.6 | AG85: 430844.01 | AH85: 2897708.3 | AI85: 82230.259 | AJ85: 320207.19 | AK85: 611251.64 | AL85: 640062.84 | AM85: 155945.98 | AN85: 29764.341 | AO85: 12624.89 | AP85: 378990.08 | AQ85: 269178.67 | AR85: 12967.682 | AS85: 2310.229 | AT85: 79153.882 | AU85: 985.45 | AV85: 24038.16 | AW85: 35245.084 | AX85: 16026.21 | AY85: 33439.718 | AZ85: 48831.756 | BA85: 189450.38 | BB85: 5140.289 | BC85: 1345.739 | BD85: 5106.945 | BE85: 262021.01 | BF85: 14522.533 | BG85: 204263.76 | BH85: 184790.35 | BI85: 32986.73 | BJ85: 395.335 | BK85: 148287.13 | BL85: 85720.451 | BM85: 224689.44 | BN85: 10737.968 | BO85: 132736.17 | BP85: 103246.55 | BQ85: 167213.05 | BR85: 1792.189 | BS85: 16994.985 | BT85: 14493.534 | BU85: 4990.034 | BV85: 42763.679 | BW85: 143973.39 | BX85: 188900.28 | BY85: 88604.201 | BZ85: 47532.467 | CA85: 26215.995 | CB85: 0 | CC85: 394186.37 | CD85: 23186147 | CE85: 15571569 | CF85: 2714421.7 | CG85: 5533104.9 | CH85: 103964.58 | CI85: 8933758.5 | CJ85: -9670671.8 | CK85: 0
A86: P.721 - Compras directas en el exterior por residentes | B86: 0 | CD86: 0 | CE86: 270999.24 | CF86: 11557.36 | CG86: 0 | CH86: 0 | CI86: 0 | CJ86: -282556.6
A87: P.621 - Compras directas en el mercado interno por no residentes | B87: 5.8207661e-11 | CD87: 5.8207661e-11 | CE87: -501182.33 | CF87: -4581.333 | CG87: 0 | CH87: 0 | CI87: 505763.67 | CJ87: 0
A88: P.621+P.721 - Compras netas de residentes y no residentes | B88: 5.8207661e-11 | CD88: 5.8207661e-11 | CE88: -230183.09 | CF88: 6976.027 | CG88: 0 | CH88: 0 | CI88: 505763.67 | CJ88: -282556.6 | CK88: 0
A89: UONI_T - Usos de origen nacional e importado (total) | B89: 41959242 | C89: 18773096 | D89: 165184.98 | E89: 252628.64 | F89: 6080.69 | G89: 13159.222 | H89: 4448.99 | I89: 262200.12 | J89: 152354.44 | K89: 89202.819 | L89: 256368.93 | M89: 1022404.9 | N89: 350571.31 | O89: 122622.35 | P89: 1472875.4 | Q89: 222513.51 | R89: 66073.974 | S89: 29825.38 | T89: 101845.91 | U89: 52640.034 | V89: 50610.722 | W89: 187234.88 | X89: 60822.838 | Y89: 760591.51 | Z89: 750152.16 | AA89: 396752.29 | AB89: 238615.78 | AC89: 621121.8 | AD89: 340880.57 | AE89: 391587.42 | AF89: 1506816.6 | AG89: 430844.01 | AH89: 2897708.3 | AI89: 82230.259 | AJ89: 320207.19 | AK89: 611251.64 | AL89: 640062.84 | AM89: 155945.98 | AN89: 29764.341 | AO89: 12624.89 | AP89: 378990.08 | AQ89: 269178.67 | AR89: 12967.682 | AS89: 2310.229 | AT89: 79153.882 | AU89: 985.45 | AV89: 24038.16 | AW89: 35245.084 | AX89: 16026.21 | AY89: 33439.718 | AZ89: 48831.756 | BA89: 189450.38 | BB89: 5140.289 | BC89: 1345.739 | BD89: 5106.945 | BE89: 262021.01 | BF89: 14522.533 | BG89: 204263.76 | BH89: 184790.35 | BI89: 32986.73 | BJ89: 395.335 | BK89: 148287.13 | BL89: 85720.451 | BM89: 224689.44 | BN89: 10737.968 | BO89: 132736.17 | BP89: 103246.55 | BQ89: 167213.05 | BR89: 1792.189 | BS89: 16994.985 | BT89: 14493.534 | BU89: 4990.034 | BV89: 42763.679 | BW89: 143973.39 | BX89: 188900.28 | BY89: 88604.201 | BZ89: 47532.467 | CA89: 26215.995 | CB89: 0 | CC89: 394186.37 | CD89: 23186147 | CE89: 15341386 | CF89: 2721397.8 | CG89: 5533104.9 | CH89: 103964.58 | CI89: 9439522.2 | CJ89: -9953228.4 | CK89: 0
A90: D.21 - Impuestos sobre los productos | B90: 1393818.8 | C90: 316020.91 | D90: 1306.898 | E90: 312.005 | F90: 56.495 | G90: 237.708 | H90: 31.071 | I90: 2795.361 | J90: 4291.201 | K90: 2013.14 | L90: 22558.955 | M90: 2982.864 | N90: 3570.361 | O90: 349.786 | P90: 6473.307 | Q90: 1480.321 | R90: 184.55 | S90: 95.783 | T90: 378.859 | U90: 164.241 | V90: 143.733 | W90: 1068.697 | X90: 421.91 | Y90: 74266.668 | Z90: 10021.326 | AA90: 1927.139 | AB90: 1713.18 | AC90: 2309.543 | AD90: 1292.634 | AE90: 560.99 | AF90: 834.198 | AG90: 668.494 | AH90: 5283.898 | AI90: 234.804 | AJ90: 310.735 | AK90: 14821.402 | AL90: 8958.179 | AM90: 9903.702 | AN90: 1145.789 | AO90: 567.669 | AP90: 12725.16 | AQ90: 9315.629 | AR90: 200.573 | AS90: 61.499 | AT90: 504.952 | AU90: 5.294 | AV90: 604.381 | AW90: 314.129 | AX90: 68.557 | AY90: 210.515 | AZ90: 517.018 | BA90: 1225.02 | BB90: 12.37 | BC90: 28.967 | BD90: 6.356 | BE90: 340.468 | BF90: 56.386 | BG90: 82.381 | BH90: 2043.191 | BI90: 281.85 | BJ90: 4.929 | BK90: 1896.396 | BL90: 1161.267 | BM90: 1411.321 | BN90: 62.232 | BO90: 8837.619 | BP90: 6752.046 | BQ90: 8396.388 | BR90: 28.166 | BS90: 747.391 | BT90: 531.37 | BU90: 269.617 | BV90: 581.602 | BW90: 7037.411 | BX90: 6332.317 | BY90: 183.456 | BZ90: 169.508 | CA90: 89.682 | CB90: 0 | CC90: 57185.905 | CD90: 1077797.9 | CE90: 1038457.4 | CF90: 0 | CG90: 39340.29 | CH90: 0 | CI90: 0.177
A91: D.31 - Subsidios a los productos | B91: 90793.994 | C91: 3519.875 | D91: 0 | E91: 4.544 | F91: 0.115 | G91: 27.098 | H91: 0.022 | I91: 2.87 | J91: 0.213 | K91: 0.205 | L91: 0.196 | M91: 1.533 | N91: 26.393 | O91: 0.143 | P91: 1.103 | Q91: 0.105 | R91: 0.024 | S91: 0.072 | T91: 0.155 | U91: 0.028 | V91: 0.04 | W91: 0.222 | X91: 0.582 | Y91: 0.053 | Z91: 0.52 | AA91: 0.266 | AB91: 0.301 | AC91: 0.469 | AD91: 0.29 | AE91: 0.382 | AF91: 0.47 | AG91: 0.135 | AH91: 1.453 | AI91: 0.092 | AJ91: 0.116 | AK91: 10.808 | AL91: 177.251 | AM91: 2.785 | AN91: 0.159 | AO91: 28.561 | AP91: 0.37 | AQ91: 0.167 | AR91: 0.44 | AS91: 2.835 | AT91: 0.248 | AU91: 54.938 | AV91: 0.064 | AW91: 0.292 | AX91: 0.132 | AY91: 0.38 | AZ91: 416.203 | BA91: 469.294 | BB91: 0.041 | BC91: 0.204 | BD91: 54.212 | BE91: 683.368 | BF91: 15.574 | BG91: 514.985 | BH91: 5.446 | BI91: 0.218 | BJ91: 0.005 | BK91: 16.094 | BL91: 5.975 | BM91: 19.596 | BN91: 0.134 | BO91: 106.133 | BP91: 17.676 | BQ91: 20.309 | BR91: 0.022 | BS91: 1.016 | BT91: 1.178 | BU91: 3.674 | BV91: 1.782 | BW91: 5.149 | BX91: 0.594 | BY91: 0.683 | BZ91: 1.946 | CA91: 2.289 | CB91: 0 | CC91: 806.435 | CD91: 87274.119 | CE91: 86940.416 | CF91: 0 | CG91: 333.703 | CH91: 0 | CI91: 0
A92: D.21-D.31 - Impuestos sobre los productos, netos | B92: 1303024.8 | C92: 312501.04 | D92: 1306.898 | E92: 307.461 | F92: 56.38 | G92: 210.61 | H92: 31.049 | I92: 2792.491 | J92: 4290.988 | K92: 2012.935 | L92: 22558.759 | M92: 2981.331 | N92: 3543.968 | O92: 349.643 | P92: 6472.204 | Q92: 1480.216 | R92: 184.526 | S92: 95.711 | T92: 378.704 | U92: 164.213 | V92: 143.693 | W92: 1068.475 | X92: 421.328 | Y92: 74266.615 | Z92: 10020.806 | AA92: 1926.873 | AB92: 1712.879 | AC92: 2309.074 | AD92: 1292.344 | AE92: 560.608 | AF92: 833.728 | AG92: 668.359 | AH92: 5282.445 | AI92: 234.712 | AJ92: 310.619 | AK92: 14810.594 | AL92: 8780.928 | AM92: 9900.917 | AN92: 1145.63 | AO92: 539.108 | AP92: 12724.79 | AQ92: 9315.462 | AR92: 200.133 | AS92: 58.664 | AT92: 504.704 | AU92: -49.644 | AV92: 604.317 | AW92: 313.837 | AX92: 68.425 | AY92: 210.135 | AZ92: 100.815 | BA92: 755.726 | BB92: 12.329 | BC92: 28.763 | BD92: -47.856 | BE92: -342.9 | BF92: 40.812 | BG92: -432.604 | BH92: 2037.745 | BI92: 281.632 | BJ92: 4.924 | BK92: 1880.302 | BL92: 1155.292 | BM92: 1391.725 | BN92: 62.098 | BO92: 8731.486 | BP92: 6734.37 | BQ92: 8376.079 | BR92: 28.144 | BS92: 746.375 | BT92: 530.192 | BU92: 265.943 | BV92: 579.82 | BW92: 7032.262 | BX92: 6331.723 | BY92: 182.773 | BZ92: 167.562 | CA92: 87.393 | CB92: 0 | CC92: 56379.47 | CD92: 990523.79 | CE92: 951517.03 | CF92: 0 | CG92: 39006.587 | CH92: 0 | CI92: 0.177 | CJ92: 0 | CK92: 0
A93: UONI_PC - Usos de origen nacional e importado (total a precios comprador) | B93: 43262267 | C93: 19085597 | D93: 166491.88 | E93: 252936.1 | F93: 6137.07 | G93: 13369.832 | H93: 4480.039 | I93: 264992.61 | J93: 156645.43 | K93: 91215.754 | L93: 278927.69 | M93: 1025386.2 | N93: 354115.28 | O93: 122971.99 | P93: 1479347.6 | Q93: 223993.73 | R93: 66258.5 | S93: 29921.091 | T93: 102224.61 | U93: 52804.247 | V93: 50754.415 | W93: 188303.36 | X93: 61244.166 | Y93: 834858.12 | Z93: 760172.97 | AA93: 398679.16 | AB93: 240328.66 | AC93: 623430.87 | AD93: 342172.92 | AE93: 392148.03 | AF93: 1507650.4 | AG93: 431512.36 | AH93: 2902990.8 | AI93: 82464.971 | AJ93: 320517.81 | AK93: 626062.23 | AL93: 648843.77 | AM93: 165846.89 | AN93: 30909.971 | AO93: 13163.998 | AP93: 391714.87 | AQ93: 278494.13 | AR93: 13167.815 | AS93: 2368.893 | AT93: 79658.586 | AU93: 935.806 | AV93: 24642.477 | AW93: 35558.921 | AX93: 16094.635 | AY93: 33649.853 | AZ93: 48932.571 | BA93: 190206.11 | BB93: 5152.618 | BC93: 1374.502 | BD93: 5059.089 | BE93: 261678.11 | BF93: 14563.345 | BG93: 203831.15 | BH93: 186828.1 | BI93: 33268.362 | BJ93: 400.259 | BK93: 150167.43 | BL93: 86875.743 | BM93: 226081.16 | BN93: 10800.066 | BO93: 141467.66 | BP93: 109980.92 | BQ93: 175589.12 | BR93: 1820.333 | BS93: 17741.36 | BT93: 15023.726 | BU93: 5255.977 | BV93: 43343.499 | BW93: 151005.66 | BX93: 195232.01 | BY93: 88786.974 | BZ93: 47700.029 | CA93: 26303.388 | CB93: 0 | CC93: 450565.84 | CD93: 24176670 | CE93: 16292903 | CF93: 2721397.8 | CG93: 5572111.5 | CH93: 103964.58 | CI93: 9439522.4 | CJ93: -9953228.4 | CK93: 0
A94: B.1bV - Valor agregado bruto | C94: 22873646 | D94: 516354.55 | E94: 242533.1 | F94: 22690.785 | G94: 9602.663 | H94: 5913.921 | I94: 621540.6 | J94: 265067.55 | K94: 61718.433 | L94: 456907.22 | M94: 1064926.3 | N94: 214062.02 | O94: 181801.25 | P94: 911713.77 | Q94: 240174.37 | R94: 32513.579 | S94: 17328.629 | T94: 71182.811 | U94: 31436.957 | V94: 38837.812 | W94: 101611.97 | X94: 24643.809 | Y94: 164436.95 | Z94: 356405.6 | AA94: 151603.43 | AB94: 157596.1 | AC94: 257274.88 | AD94: 170712.28 | AE94: 208837.09 | AF94: 409294.66 | AG94: 178614.03 | AH94: 1168500.8 | AI94: 55539.633 | AJ94: 132857.27 | AK94: 2268261.4 | AL94: 2241444.5 | AM94: 63574.495 | AN94: 38500.664 | AO94: 18964.174 | AP94: 856330.64 | AQ94: 451171.37 | AR94: 12751.734 | AS94: 2487.176 | AT94: 154556.62 | AU94: 3961.699 | AV94: 21564.182 | AW94: 29847.125 | AX94: 16348.493 | AY94: 36940.5 | AZ94: 41617.767 | BA94: 266493.91 | BB94: 8319.393 | BC94: 1540.617 | BD94: 38078.365 | BE94: 678782.23 | BF94: 22931.666 | BG94: 146867.75 | BH94: 2036876.9 | BI94: 34210.342 | BJ94: 49572.822 | BK94: 435679.6 | BL94: 126888.46 | BM94: 778751.55 | BN94: 14765.428 | BO94: 877924.17 | BP94: 245527.75 | BQ94: 283184.08 | BR94: 2758.547 | BS94: 16206.956 | BT94: 51526.702 | BU94: 7531.426 | BV94: 56466.616 | BW94: 254701.17 | BX94: 329273.32 | BY94: 118399.89 | BZ94: 175693.32 | CA94: 56696.528 | CB94: 100065.29 | CC94: 855373.41
A95: P.1 - Producción | C95: 41959242 | D95: 682846.43 | E95: 495469.19 | F95: 28827.855 | G95: 22972.495 | H95: 10393.96 | I95: 886533.21 | J95: 421712.98 | K95: 152934.19 | L95: 735834.91 | M95: 2090312.5 | N95: 568177.3 | O95: 304773.24 | P95: 2391061.4 | Q95: 464168.1 | R95: 98772.079 | S95: 47249.72 | T95: 173407.42 | U95: 84241.204 | V95: 89592.227 | W95: 289915.33 | X95: 85887.975 | Y95: 999295.07 | Z95: 1116578.6 | AA95: 550282.59 | AB95: 397924.76 | AC95: 880705.75 | AD95: 512885.2 | AE95: 600985.12 | AF95: 1916945 | AG95: 610126.4 | AH95: 4071491.5 | AI95: 138004.6 | AJ95: 453375.08 | AK95: 2894323.7 | AL95: 2890288.2 | AM95: 229421.39 | AN95: 69410.635 | AO95: 32128.172 | AP95: 1248045.5 | AQ95: 729665.5 | AR95: 25919.549 | AS95: 4856.069 | AT95: 234215.2 | AU95: 4897.505 | AV95: 46206.659 | AW95: 65406.046 | AX95: 32443.128 | AY95: 70590.353 | AZ95: 90550.338 | BA95: 456700.01 | BB95: 13472.011 | BC95: 2915.119 | BD95: 43137.454 | BE95: 940460.33 | BF95: 37495.011 | BG95: 350698.9 | BH95: 2223705 | BI95: 67478.704 | BJ95: 49973.081 | BK95: 585847.03 | BL95: 213764.2 | BM95: 1004832.7 | BN95: 25565.494 | BO95: 1019391.8 | BP95: 355508.67 | BQ95: 458773.2 | BR95: 4578.88 | BS95: 33948.316 | BT95: 66550.428 | BU95: 12787.403 | BV95: 99810.115 | BW95: 405706.83 | BX95: 524505.33 | BY95: 207186.86 | BZ95: 223393.35 | CA95: 82999.916 | CB95: 100065.29 | CC95: 1305939.3
A96: B.1bP - Producto interno bruto | B96: 24176670 | C96: 23186147 | D96: 517661.45 | E96: 242840.56 | F96: 22747.165 | G96: 9813.273 | H96: 5944.97 | I96: 624333.09 | J96: 269358.54 | K96: 63731.368 | L96: 479465.98 | M96: 1067907.6 | N96: 217605.99 | O96: 182150.89 | P96: 918185.97 | Q96: 241654.59 | R96: 32698.105 | S96: 17424.34 | T96: 71561.515 | U96: 31601.17 | V96: 38981.505 | W96: 102680.45 | X96: 25065.137 | Y96: 238703.56 | Z96: 366426.41 | AA96: 153530.31 | AB96: 159308.98 | AC96: 259583.95 | AD96: 172004.62 | AE96: 209397.7 | AF96: 410128.39 | AG96: 179282.39 | AH96: 1173783.2 | AI96: 55774.345 | AJ96: 133167.89 | AK96: 2283072 | AL96: 2250225.4 | AM96: 73475.412 | AN96: 39646.294 | AO96: 19503.282 | AP96: 869055.43 | AQ96: 460486.83 | AR96: 12951.867 | AS96: 2545.84 | AT96: 155061.32 | AU96: 3912.055 | AV96: 22168.499 | AW96: 30160.962 | AX96: 16416.918 | AY96: 37150.635 | AZ96: 41718.582 | BA96: 267249.63 | BB96: 8331.722 | BC96: 1569.38 | BD96: 38030.509 | BE96: 678439.33 | BF96: 22972.478 | BG96: 146435.14 | BH96: 2038914.7 | BI96: 34491.974 | BJ96: 49577.746 | BK96: 437559.9 | BL96: 128043.75 | BM96: 780143.28 | BN96: 14827.526 | BO96: 886655.66 | BP96: 252262.12 | BQ96: 291560.16 | BR96: 2786.691 | BS96: 16953.331 | BT96: 52056.894 | BU96: 7797.369 | BV96: 57046.436 | BW96: 261733.43 | BX96: 335605.05 | BY96: 118582.66 | BZ96: 175860.89 | CA96: 56783.921 | CB96: 100065.29 | CC96: 911752.88 | CD96: 990523.79 | CE96: 951517.03 | CF96: 0 | CG96: 39006.587 | CH96: 0 | CI96: 0.177 | CJ96: 0 | CK96: 0
A97: __cD.1 - Remuneración de los asalariados | C97: 5974564.1 | D97: 81952.982 | E97: 43031.241 | F97: 737.32 | G97: 3298.361 | H97: 1494.103 | I97: 31707.356 | J97: 34467.606 | K97: 5404.55 | L97: 80611.858 | M97: 306662.64 | N97: 47285.398 | O97: 40442.471 | P97: 101965.91 | Q97: 22523.696 | R97: 10797.038 | S97: 6271.621 | T97: 29620.008 | U97: 14107.86 | V97: 10442.215 | W97: 20457.367 | X97: 10714.06 | Y97: 17586.133 | Z97: 60324.339 | AA97: 45326.683 | AB97: 25120.79 | AC97: 24772.187 | AD97: 53298.487 | AE97: 58863.988 | AF97: 191288.82 | AG97: 59237.737 | AH97: 170394.67 | AI97: 22042.646 | AJ97: 51567.494 | AK97: 92635.907 | AL97: 481440.27 | AM97: 14192.194 | AN97: 4005.537 | AO97: 3476.737 | AP97: 149044.31 | AQ97: 167321.96 | AR97: 2463.319 | AS97: 953.773 | AT97: 28166.273 | AU97: 3663.679 | AV97: 8213.066 | AW97: 14327.91 | AX97: 5852.123 | AY97: 5883.84 | AZ97: 2560.248 | BA97: 49401.885 | BB97: 2601.818 | BC97: 611.295 | BD97: 2586 | BE97: 163352.3 | BF97: 6203.965 | BG97: 33450.742 | BH97: 48351.87 | BI97: 5260.59 | BJ97: 94.009 | BK97: 141873.22 | BL97: 19319.039 | BM97: 489320.16 | BN97: 3815.52 | BO97: 756662.08 | BP97: 168780.85 | BQ97: 249279.04 | BR97: 2222.713 | BS97: 9365.764 | BT97: 16104.22 | BU97: 6455.413 | BV97: 10525.85 | BW97: 49994.966 | BX97: 70204.152 | BY97: 24456.583 | BZ97: 17336.449 | CA97: 25190.881 | CB97: 100065.29 | CC97: 833656.71
A98: D.11 - Sueldos y salarios | C98: 4889091.2 | D98: 81952.982 | E98: 42849.339 | F98: 737.32 | G98: 2998.863 | H98: 1285.253 | I98: 26914.038 | J98: 26518.322 | K98: 4641.092 | L98: 74736.36 | M98: 287809.38 | N98: 39374.138 | O98: 37804.952 | P98: 84080.996 | Q98: 17605.641 | R98: 8890.853 | S98: 5342.402 | T98: 24918.473 | U98: 11916.927 | V98: 9376.159 | W98: 15799.88 | X98: 8776.82 | Y98: 8632.955 | Z98: 36132.604 | AA98: 35322.325 | AB98: 18777.224 | AC98: 16575.587 | AD98: 41773.586 | AE98: 41500.406 | AF98: 145311.2 | AG98: 40696.154 | AH98: 122065.33 | AI98: 18444.418 | AJ98: 40220.072 | AK98: 77519.531 | AL98: 427135.59 | AM98: 12209.939 | AN98: 2960.594 | AO98: 2747.812 | AP98: 122553.5 | AQ98: 155578.3 | AR98: 2074.385 | AS98: 922.676 | AT98: 22181.064 | AU98: 3137.786 | AV98: 5793.328 | AW98: 11651.682 | AX98: 4693.139 | AY98: 4803.111 | AZ98: 2143.51 | BA98: 35973.282 | BB98: 2288.636 | BC98: 426.267 | BD98: 1970 | BE98: 132396.52 | BF98: 5314.071 | BG98: 28196.328 | BH98: 41978.97 | BI98: 3926.024 | BJ98: 84.395 | BK98: 119003.79 | BL98: 10740.822 | BM98: 387623.84 | BN98: 3156.154 | BO98: 638785 | BP98: 120209.57 | BQ98: 152118.75 | BR98: 1826.658 | BS98: 7058.405 | BT98: 15012.547 | BU98: 4789.237 | BV98: 8713.785 | BW98: 41367.996 | BX98: 63216.225 | BY98: 21037.554 | BZ98: 16097.381 | CA98: 23464.444 | CB98: 100065.29 | CC98: 664361.26
A99: D.11_1 - Salarios | C99: 2613160 | D99: 81952.982 | E99: 42793.47 | F99: 737.32 | G99: 2891.846 | H99: 1117.799 | I99: 8544.188 | J99: 21819.321 | K99: 3701.432 | L99: 65104.482 | M99: 264066.59 | N99: 25617.465 | O99: 33228.838 | P99: 62342.684 | Q99: 12380.845 | R99: 7456.787 | S99: 4395.376 | T99: 21321.574 | U99: 9963.979 | V99: 8380.144 | W99: 10885.649 | X99: 6307.537 | Y99: 6296.585 | Z99: 23660.273 | AA99: 25272.132 | AB99: 14587.248 | AC99: 11409.396 | AD99: 28626.519 | AE99: 30211.872 | AF99: 109410.15 | AG99: 30159.433 | AH99: 92633.5 | AI99: 14601.376 | AJ99: 32265.817 | AK99: 63329.159 | AL99: 376259.03 | AM99: 9615.798 | AN99: 1911.636 | AO99: 2323.303 | AP99: 89600.398 | AQ99: 147553.67 | AR99: 1472.71 | AS99: 794.187 | AT99: 12556.525 | AU99: 1960.272 | AV99: 3782.522 | AW99: 7239.35 | AX99: 2750.442 | AY99: 2917.824 | AZ99: 1539.305 | BA99: 26169.241 | BB99: 1706.432 | BC99: 217.394 | BD99: 0 | BE99: 0 | BF99: 0 | BG99: 0 | BH99: 39305.884 | BI99: 3063.626 | BJ99: 84.395 | BK99: 65505.138 | BL99: 276.102 | BM99: 298992.46 | BN99: 2815.676 | BO99: 41941.842 | BP99: 13016.295 | BQ99: 13552.696 | BR99: 952.232 | BS99: 3524.63 | BT99: 10863.134 | BU99: 562.085 | BV99: 6680.732 | BW99: 32316.7 | BX99: 59205.34 | BY99: 18434.807 | BZ99: 14538.441 | CA99: 19618.67 | CB99: 100065.29 | CC99: 0
A100: D.11_2 - Sueldos | C100: 2275931.2 | D100: 0 | E100: 55.869 | F100: 0 | G100: 107.017 | H100: 167.454 | I100: 18369.85 | J100: 4699.001 | K100: 939.66 | L100: 9631.878 | M100: 23742.792 | N100: 13756.673 | O100: 4576.114 | P100: 21738.312 | Q100: 5224.796 | R100: 1434.066 | S100: 947.026 | T100: 3596.899 | U100: 1952.948 | V100: 996.015 | W100: 4914.231 | X100: 2469.283 | Y100: 2336.37 | Z100: 12472.331 | AA100: 10050.193 | AB100: 4189.976 | AC100: 5166.191 | AD100: 13147.067 | AE100: 11288.534 | AF100: 35901.05 | AG100: 10536.721 | AH100: 29431.831 | AI100: 3843.042 | AJ100: 7954.255 | AK100: 14190.372 | AL100: 50876.556 | AM100: 2594.141 | AN100: 1048.958 | AO100: 424.509 | AP100: 32953.098 | AQ100: 8024.64 | AR100: 601.675 | AS100: 128.489 | AT100: 9624.539 | AU100: 1177.514 | AV100: 2010.806 | AW100: 4412.332 | AX100: 1942.697 | AY100: 1885.287 | AZ100: 604.205 | BA100: 9804.041 | BB100: 582.204 | BC100: 208.873 | BD100: 1970 | BE100: 132396.52 | BF100: 5314.071 | BG100: 28196.328 | BH100: 2673.086 | BI100: 862.398 | BJ100: 0 | BK100: 53498.656 | BL100: 10464.72 | BM100: 88631.385 | BN100: 340.478 | BO100: 596843.16 | BP100: 107193.27 | BQ100: 138566.05 | BR100: 874.426 | BS100: 3533.775 | BT100: 4149.413 | BU100: 4227.152 | BV100: 2033.053 | BW100: 9051.296 | BX100: 4010.885 | BY100: 2602.747 | BZ100: 1558.94 | CA100: 3845.774 | CB100: 0 | CC100: 664361.26
A101: D.121 - Contribuciones sociales efectivas de los empleadores | C101: 721349.29 | D101: 0 | E101: 134.578 | F101: 0 | G101: 193.424 | H101: 155.89 | I101: 0 | J101: 2683.888 | K101: 543.742 | L101: 4721.06 | M101: 13208.656 | N101: 5437.468 | O101: 1845.496 | P101: 7792.903 | Q101: 1766.207 | R101: 1249.81 | S101: 497.838 | T101: 2877.592 | U101: 1426.857 | V101: 738.924 | W101: 2369.619 | X101: 1195.505 | Y101: 187.578 | Z101: 4839.962 | AA101: 4958.94 | AB101: 2113.412 | AC101: 3395.21 | AD101: 5709.041 | AE101: 8012.015 | AF101: 20521.104 | AG101: 7357.596 | AH101: 20233.586 | AI101: 2256.041 | AJ101: 5285.875 | AK101: 8587.786 | AL101: 34489.729 | AM101: 1196.227 | AN101: 833.202 | AO101: 18.797 | AP101: 17757.158 | AQ101: 7010.961 | AR101: 21.513 | AS101: 18.019 | AT101: 3673.055 | AU101: 516.38 | AV101: 1270.936 | AW101: 1080.858 | AX101: 689.527 | AY101: 706.848 | AZ101: 256.825 | BA101: 6517.641 | BB101: 126.076 | BC101: 98.367 | BD101: 265 | BE101: 17531.329 | BF101: 670.24 | BG101: 2868.132 | BH101: 4174.307 | BI101: 456.941 | BJ101: 8.483 | BK101: 13235.111 | BL101: 2940.951 | BM101: 27795.339 | BN101: 265.859 | BO101: 109787.8 | BP101: 47694.901 | BQ101: 92886.771 | BR101: 356.27 | BS101: 2184.338 | BT101: 893.773 | BU101: 1526.242 | BV101: 1079.377 | BW101: 5894.114 | BX101: 3504.925 | BY101: 1074.921 | BZ101: 951.061 | CA101: 1056.924 | CB101: 0 | CC101: 163666.46
A102: D.122 - Contribuciones sociales imputadas de los empleadores | C102: 364123.65 | D102: 0 | E102: 47.324 | F102: 0 | G102: 106.074 | H102: 52.96 | I102: 4793.318 | J102: 5265.396 | K102: 219.716 | L102: 1154.438 | M102: 5644.603 | N102: 2473.792 | O102: 792.023 | P102: 10092.014 | Q102: 3151.848 | R102: 656.375 | S102: 431.381 | T102: 1823.943 | U102: 764.076 | V102: 327.132 | W102: 2287.868 | X102: 741.735 | Y102: 8765.6 | Z102: 19351.773 | AA102: 5045.418 | AB102: 4230.154 | AC102: 4801.39 | AD102: 5815.86 | AE102: 9351.567 | AF102: 25456.52 | AG102: 11183.987 | AH102: 28095.75 | AI102: 1342.187 | AJ102: 6061.547 | AK102: 6528.59 | AL102: 19814.947 | AM102: 786.028 | AN102: 211.741 | AO102: 710.128 | AP102: 8733.658 | AQ102: 4732.694 | AR102: 367.421 | AS102: 13.078 | AT102: 2312.154 | AU102: 9.513 | AV102: 1148.802 | AW102: 1595.37 | AX102: 469.457 | AY102: 373.881 | AZ102: 159.913 | BA102: 6910.962 | BB102: 187.106 | BC102: 86.661 | BD102: 351 | BE102: 13424.442 | BF102: 219.654 | BG102: 2386.282 | BH102: 2198.593 | BI102: 877.625 | BJ102: 1.131 | BK102: 9634.314 | BL102: 5637.266 | BM102: 73900.984 | BN102: 393.507 | BO102: 8089.274 | BP102: 876.381 | BQ102: 4273.525 | BR102: 39.785 | BS102: 123.021 | BT102: 197.9 | BU102: 139.934 | BV102: 732.688 | BW102: 2732.856 | BX102: 3483.002 | BY102: 2344.108 | BZ102: 288.007 | CA102: 669.513 | CB102: 0 | CC102: 5628.988
A103: D.29-D.39 - Impuestos netos de subsidios sobre la producción | C103: 130685.83 | D103: 14.564 | E103: 6.923 | F103: 0.675 | G103: 0.636 | H103: 0.091 | I103: 2133.83 | J103: 1039.727 | K103: 367.109 | L103: 5730.517 | M103: 5014.547 | N103: 1516.221 | O103: 733.332 | P103: 5752.415 | Q103: 1081.842 | R103: 237.352 | S103: 113.46 | T103: 416.264 | U103: 202.473 | V103: 215.581 | W103: 696.895 | X103: 176.93 | Y103: 1379.21 | Z103: 2575.061 | AA103: 1323.485 | AB103: 955.264 | AC103: 2111.198 | AD103: 1231.899 | AE103: 1401.028 | AF103: 4578.872 | AG103: 1466.233 | AH103: 9791.465 | AI103: 332.12 | AJ103: 1086.948 | AK103: 7834.146 | AL103: 10878.935 | AM103: 552.204 | AN103: 167.065 | AO103: 290.527 | AP103: 2463.883 | AQ103: -5966.328 | AR103: 62.298 | AS103: 11.676 | AT103: 563.278 | AU103: 120.278 | AV103: 111.155 | AW103: 153.308 | AX103: 78.038 | AY103: 165.827 | AZ103: 186.414 | BA103: 1098.961 | BB103: 32.423 | BC103: 10.267 | BD103: 79 | BE103: 19653.374 | BF103: 293.732 | BG103: 616.487 | BH103: 4804.923 | BI103: 162.283 | BJ103: 120.289 | BK103: 1287.869 | BL103: 1507.53 | BM103: 2416.36 | BN103: 61.524 | BO103: 3987.759 | BP103: 1185.668 | BQ103: 1368.687 | BR103: 34.09 | BS103: 37.472 | BT103: 134.243 | BU103: 118.725 | BV103: 244.576 | BW103: 1058.294 | BX103: 1324.012 | BY103: 498.664 | BZ103: 314.884 | CA103: 199.784 | CB103: 0 | CC103: 16677.081
A104: D.29_ - Impuestos que gravan la actividad | C104: 138714.61 | D104: 14.564 | E104: 6.923 | F104: 0.675 | G104: 0.636 | H104: 0.091 | I104: 2133.83 | J104: 1039.727 | K104: 367.109 | L104: 5730.517 | M104: 5014.547 | N104: 1516.221 | O104: 733.332 | P104: 5752.415 | Q104: 1081.842 | R104: 237.352 | S104: 113.46 | T104: 416.264 | U104: 202.473 | V104: 215.581 | W104: 696.895 | X104: 176.93 | Y104: 1379.21 | Z104: 2575.061 | AA104: 1323.485 | AB104: 955.264 | AC104: 2111.198 | AD104: 1231.899 | AE104: 1401.028 | AF104: 4578.872 | AG104: 1466.233 | AH104: 9791.465 | AI104: 332.12 | AJ104: 1086.948 | AK104: 7834.146 | AL104: 10878.935 | AM104: 552.204 | AN104: 167.065 | AO104: 290.527 | AP104: 2463.883 | AQ104: 1754.646 | AR104: 62.298 | AS104: 11.676 | AT104: 563.278 | AU104: 120.278 | AV104: 111.155 | AW104: 153.308 | AX104: 78.038 | AY104: 165.827 | AZ104: 186.414 | BA104: 1098.961 | BB104: 32.423 | BC104: 10.267 | BD104: 79 | BE104: 19653.374 | BF104: 293.732 | BG104: 616.487 | BH104: 4804.923 | BI104: 162.283 | BJ104: 120.289 | BK104: 1595.669 | BL104: 1507.53 | BM104: 2416.36 | BN104: 61.524 | BO104: 3987.759 | BP104: 1185.668 | BQ104: 1368.687 | BR104: 34.09 | BS104: 37.472 | BT104: 134.243 | BU104: 118.725 | BV104: 244.576 | BW104: 1058.294 | BX104: 1324.012 | BY104: 498.664 | BZ104: 314.884 | CA104: 199.784 | CB104: 0 | CC104: 16677.081
A105: D.39_ - Menos: subsidios | C105: 8028.774 | D105: 0 | E105: 0 | F105: 0 | G105: 0 | H105: 0 | I105: 0 | J105: 0 | K105: 0 | L105: 0 | M105: 0 | N105: 0 | O105: 0 | P105: 0 | Q105: 0 | R105: 0 | S105: 0 | T105: 0 | U105: 0 | V105: 0 | W105: 0 | X105: 0 | Y105: 0 | Z105: 0 | AA105: 0 | AB105: 0 | AC105: 0 | AD105: 0 | AE105: 0 | AF105: 0 | AG105: 0 | AH105: 0 | AI105: 0 | AJ105: 0 | AK105: 0 | AL105: 0 | AM105: 0 | AN105: 0 | AO105: 0 | AP105: 0 | AQ105: 7720.974 | AR105: 0 | AS105: 0 | AT105: 0 | AU105: 0 | AV105: 0 | AW105: 0 | AX105: 0 | AY105: 0 | AZ105: 0 | BA105: 0 | BB105: 0 | BC105: 0 | BD105: 0 | BE105: 0 | BF105: 0 | BG105: 0 | BH105: 0 | BI105: 0 | BJ105: 0 | BK105: 307.8 | BL105: 0 | BM105: 0 | BN105: 0 | BO105: 0 | BP105: 0 | BQ105: 0 | BR105: 0 | BS105: 0 | BT105: 0 | BU105: 0 | BV105: 0 | BW105: 0 | BX105: 0 | BY105: 0 | BZ105: 0 | CA105: 0 | CB105: 0 | CC105: 0
A106: B.2b - Excedente bruto de operación | C106: 16768396 | D106: 434387.01 | E106: 199494.93 | F106: 21952.79 | G106: 6303.666 | H106: 4419.727 | I106: 587699.41 | J106: 229560.22 | K106: 55946.774 | L106: 370564.85 | M106: 753249.07 | N106: 165260.4 | O106: 140625.45 | P106: 803995.44 | Q106: 216568.83 | R106: 21479.189 | S106: 10943.548 | T106: 41146.539 | U106: 17126.624 | V106: 28180.016 | W106: 80457.71 | X106: 13752.819 | Y106: 145471.6 | Z106: 293506.2 | AA106: 104953.26 | AB106: 131520.05 | AC106: 230391.49 | AD106: 116181.89 | AE106: 148572.08 | AF106: 213426.96 | AG106: 117910.06 | AH106: 988314.62 | AI106: 33164.867 | AJ106: 80202.828 | AK106: 2167791.4 | AL106: 1749125.3 | AM106: 48830.097 | AN106: 34328.062 | AO106: 15196.91 | AP106: 704822.45 | AQ106: 289815.74 | AR106: 10226.117 | AS106: 1521.727 | AT106: 125827.07 | AU106: 177.742 | AV106: 13239.961 | AW106: 15365.907 | AX106: 10418.332 | AY106: 30890.833 | AZ106: 38871.105 | BA106: 215993.06 | BB106: 5685.152 | BC106: 919.055 | BD106: 35413.365 | BE106: 495776.56 | BF106: 16433.969 | BG106: 112800.52 | BH106: 1983720.1 | BI106: 28787.469 | BJ106: 49358.524 | BK106: 292518.51 | BL106: 106061.89 | BM106: 287015.03 | BN106: 10888.384 | BO106: 117274.34 | BP106: 75561.234 | BQ106: 32536.35 | BR106: 501.744 | BS106: 6803.72 | BT106: 35288.239 | BU106: 957.288 | BV106: 45696.19 | BW106: 203647.91 | BX106: 257745.16 | BY106: 93444.642 | BZ106: 158041.99 | CA106: 31305.863 | CB106: 0 | CC106: 5039.62
A107: PT - Puestos de trabajo | C107: 59505022 | D107: 6412119 | E107: 1204660 | F107: 72310 | G107: 179676 | H107: 20080 | I107: 38020 | J107: 198950 | K107: 24322 | L107: 215438 | M107: 3388685 | N107: 485188 | O107: 1122289 | P107: 1728806 | Q107: 182083 | R107: 133466 | S107: 225523 | T107: 596975 | U107: 187414 | V107: 197584 | W107: 149383 | X107: 114009 | Y107: 29875 | Z107: 215415 | AA107: 279254 | AB107: 391866 | AC107: 94523 | AD107: 561602 | AE107: 318587 | AF107: 917547 | AG107: 340577 | AH107: 896614 | AI107: 374427 | AJ107: 526211 | AK107: 1594832 | AL107: 9973725 | AM107: 33574 | AN107: 11382 | AO107: 7646 | AP107: 1099711 | AQ107: 1592721 | AR107: 4097 | AS107: 19490 | AT107: 180047 | AU107: 14929 | AV107: 60933 | AW107: 152695 | AX107: 35089 | AY107: 38582 | AZ107: 22781 | BA107: 113906 | BB107: 11214 | BC107: 3843 | BD107: 3317 | BE107: 214283 | BF107: 13362 | BG107: 135021 | BH107: 610938 | BI107: 108525 | BJ107: 779 | BK107: 988290 | BL107: 41691 | BM107: 5028012 | BN107: 104238 | BO107: 2572328 | BP107: 782009 | BQ107: 614384 | BR107: 32812 | BS107: 204921 | BT107: 168594 | BU107: 17687 | BV107: 171118 | BW107: 582491 | BX107: 2627312 | BY107: 1166324 | BZ107: 1120214 | CA107: 310459 | CB107: 2374735 | CC107: 2716503
A108: PTDRS - Puestos de trabajo dependientes de la razón social | C108: 58517123 | D108: 6412119 | E108: 1204660 | F108: 72310 | G108: 179676 | H108: 19152 | I108: 38012 | J108: 197426 | K108: 23620 | L108: 214478 | M108: 3359925 | N108: 478984 | O108: 1118666 | P108: 1722825 | Q108: 179629 | R108: 132957 | S108: 225043 | T108: 594172 | U108: 184682 | V108: 196113 | W108: 148589 | X108: 112096 | Y108: 29794 | Z108: 213674 | AA108: 277855 | AB108: 387787 | AC108: 90651 | AD108: 551546 | AE108: 303835 | AF108: 897834 | AG108: 325693 | AH108: 875587 | AI108: 372105 | AJ108: 520100 | AK108: 1558759 | AL108: 9656826 | AM108: 33447 | AN108: 11361 | AO108: 7608 | AP108: 1095705 | AQ108: 1586404 | AR108: 4093 | AS108: 19010 | AT108: 176598 | AU108: 14929 | AV108: 60933 | AW108: 150853 | AX108: 32818 | AY108: 33898 | AZ108: 19632 | BA108: 106907 | BB108: 10744 | BC108: 3488 | BD108: 3317 | BE108: 204216 | BF108: 12973 | BG108: 114758 | BH108: 590784 | BI108: 105686 | BJ108: 761 | BK108: 946614 | BL108: 41505 | BM108: 4997262 | BN108: 104040 | BO108: 2430209 | BP108: 758231 | BQ108: 603900 | BR108: 31386 | BS108: 202487 | BT108: 162651 | BU108: 17096 | BV108: 162274 | BW108: 577870 | BX108: 2584814 | BY108: 1135737 | BZ108: 1095123 | CA108: 296583 | CB108: 2374735 | CC108: 2716503
... A114: PHOCSS - Personal no dependiente de la razón social, personal por honorarios o comisiones s/sueldo | C114: 987899 | D114: 0 | E114: 0 | F114: 0 | G114: 0 | H114: 928 | I114: 8 | J114: 1524 | K114: 702 | L114: 960 | M114: 28760 | N114: 6204 | O114: 3623 | P114: 5981 | Q114: 2454 | R114: 509 | S114: 480 | T114: 2803 | U114: 2732 | V114: 1471 | W114: 794 | X114: 1913 | Y114: 81 | Z114: 1741 | AA114: 1399 | AB114: 4079 | AC114: 3872 | AD114: 10056 | AE114: 14752 | AF114: 19713 | AG114: 14884 | AH114: 21027 | AI114: 2322 | AJ114: 6111 | AK114: 36073 | AL114: 316899 | AM114: 127 | AN114: 21 | AO114: 38 | AP114: 4006 | AQ114: 6317 | AR114: 4 | AS114: 480 | AT114: 3449 | AU114: 0 | AV114: 0 | AW114: 1842 | AX114: 2271 | AY114: 4684 | AZ114: 3149 | BA114: 6999 | BB114: 470 | BC114: 355 | BD114: 0 | BE114: 10067 | BF114: 389 | BG114: 20263 | BH114: 20154 | BI114: 2839 | BJ114: 18 | BK114: 41676 | BL114: 186 | BM114: 30750 | BN114: 198 | BO114: 142119 | BP114: 23778 | BQ114: 10484 | BR114: 1426 | BS114: 2434 | BT114: 5943 | BU114: 591 | BV114: 8844 | BW114: 4621 | BX114: 42498 | BY114: 30587 | BZ114: 25091 | CA114: 13876 | CB114: 0 | CC114: 0
A118: aPrecios F.O.B.
A119: bPrecios C.I.F. (Total F.O.B.)
A120: cTotal
A121: Fuente: INEGI. Sistema de Cuentas Nacionales de México. Matriz de Insumo Producto

Sheet Replicate technical coeff
A1: Instituto Nacional de Estadística y Geografía (INEGI).
A2: Sistema de Cuentas Nacionales de México. Matriz de Insumo Producto simétrica, Base 2018
A3: Matriz simétrica de insumo producto. Industria por industria/ Economía total / Origen doméstico coeficientes técnicos/ Subsector SCIAN
A5: Concepto | B5: 111 - Agricultura | C5: 112 - Cría y explotación de animales | D5: 113 - Aprovechamiento forestal | E5: 114 - Pesca, caza y captura | F5: 115 - Servicios relacionados con las actividades agropecuarias y forestales | G5: 211 - Extracción de petróleo y gas | H5: 212 - Minería de minerales metálicos y no metálicos, excepto petróleo y gas | I5: 213 - Servicios relacionados con la minería | J5: 221 - Generación, transmisión, distribución y comercialización de energía eléctrica, suministro de agua y de gas natural por ductos al consumidor final | K5: 236 - Edificación | L5: 237 - Construcción de obras de ingeniería civil | M5: 238 - Trabajos especializados para la construcción | N5: 311 - Industria alimentaria | O5: 312 - Industria de las bebidas y del tabaco | P5: 313 - Fabricación de insumos textiles y acabado de textiles | Q5: 314 - Fabricación de productos textiles, excepto prendas de vestir | R5: 315 - Fabricación de prendas de vestir | S5: 316 - Curtido y acabado de cuero y piel, y fabricación de productos de cuero, piel y materiales sucedáneos | T5: 321 - Industria de la madera | U5: 322 - Industria del papel | V5: 323 - Impresión e industrias conexas | W5: 324 - Fabricación de productos derivados del petróleo y del carbón | X5: 325 - Industria química | Y5: 326 - Industria del plástico y del hule | Z5: 327 - Fabricación de productos a base de minerales no metálicos | AA5: 331 - Industrias metálicas básicas | AB5: 332 - Fabricación de productos metálicos | AC5: 333 - Fabricación de maquinaria y equipo | AD5: 334 - Fabricación de equipo de computación, comunicación, medición y de otros equipos, componentes y accesorios electrónicos | AE5: 335 - Fabricación de accesorios, aparatos eléctricos y equipo de generación de energía eléctrica | AF5: 336 - Fabricación de equipo de transporte | AG5: 337 - Fabricación de muebles, colchones y persianas | AH5: 339 - Otras industrias manufactureras | AI5: 431 - Comercio al por mayor de abarrotes, alimentos, bebidas, hielo y tabaco | AJ5: 461 - Comercio al por menor de abarrotes, alimentos, bebidas, hielo y tabaco | AK5: 481 - Transporte aéreo | AL5: 482 - Transporte por ferrocarril | AM5: 483 - Transporte por agua | AN5: 484 - Autotransporte de carga | AO5: 485 - Transporte terrestre de pasajeros, excepto por ferrocarril | AP5: 486 - Transporte por ductos | AQ5: 487 - Transporte turístico | AR5: 488 - Servicios relacionados con el transporte | AS5: 491 - Servicios postales | AT5: 492 - Servicios de mensajería y paquetería | AU5: 493 - Servicios de almacenamiento | AV5: 511 - Edición de periódicos, revistas, libros, software y otros materiales, y edición de estas publicaciones integrada con la impresión | AW5: 512 - Industria fílmica y del video, e industria del sonido | AX5: 515 - Radio y televisión | AY5: 517 - Telecomunicaciones | AZ5: 518 - Procesamiento electrónico de información, hospedaje y otros servicios relacionados | BA5: 519 - Otros servicios de información | BB5: 521 - Banca central | BC5: 522 - Instituciones de intermediación crediticia y financiera no bursátil | BD5: 523 - Actividades bursátiles, cambiarias y de inversión financiera | BE5: 524 - Compañías de seguros, fianzas, y administración de fondos para el retiro | BF5: 531 - Servicios inmobiliarios | BG5: 532 - Servicios de alquiler de bienes muebles | BH5: 533 - Servicios de alquiler de marcas registradas, patentes y franquicias | BI5: 541 - Servicios profesionales, científicos y técnicos | BJ5: 551 - Corporativos | BK5: 561 - Servicios de apoyo a los negocios | BL5: 562 - Manejo de residuos y servicios de remediación | BM5: 611 - Servicios educativos | BN5: 621 - Servicios médicos de consulta externa y servicios relacionados | BO5: 622 - Hospitales | BP5: 623 - Residencias de asistencia social y para el cuidado de la salud | BQ5: 624 - Otros servicios de asistencia social | BR5: 711 - Servicios artísticos, culturales y deportivos, y otros servicios relacionados | BS5: 712 - Museos, sitios históricos, zoológicos y similares | BT5: 713 - Servicios de entretenimiento en instalaciones recreativas y otros servicios recreativos | BU5: 721 - Servicios de alojamiento temporal | BV5: 722 - Servicios de preparación de alimentos y bebidas | BW5: 811 - Servicios de reparación y mantenimiento | BX5: 812 - Servicios personales | BY5: 813 - Asociaciones y organizaciones | BZ5: 814 - Hogares con empleados domésticos | CA5: 931 - Actividades legislativas, gubernamentales y de impartición de justicia
A6: 111 - Agricultura | B6: =Domestic!E7/Domestic!E$96 -> 0.019041663 | C6: =Domestic!F7/Domestic!F$96 -> 0.11379988 | D6: =Domestic!G7/Domestic!G$96 -> 0.0061249441 | E6: =Domestic!H7/Domestic!H$96 -> 0.00051679193 | F6: =Domestic!I7/Domestic!I$96 -> 0.030232558 | G6: =Domestic!J7/Domestic!J$96 -> 0 | H6: =Domestic!K7/Domestic!K$96 -> 0 | I6: =Domestic!L7/Domestic!L$96 -> 0 | ... CA6: =Domestic!CD7/Domestic!CD$96 -> 3.1286294e-05
A7: 112 - Cría y explotación de animales | B7: =Domestic!E8/Domestic!E$96 -> 0.0073783822 | C7: =Domestic!F8/Domestic!F$96 -> 0.023237824 | D7: =Domestic!G8/Domestic!G$96 -> 0 | E7: =Domestic!H8/Domestic!H$96 -> 0 | F7: =Domestic!I8/Domestic!I$96 -> 0 | G7: =Domestic!J8/Domestic!J$96 -> 9.0239146e-09 | H7: =Domestic!K8/Domestic!K$96 -> 2.371281e-09 | I7: =Domestic!L8/Domestic!L$96 -> 7.8465124e-08 | ... CA7: =Domestic!CD8/Domestic!CD$96 -> 2.5261512e-06
A8: 113 - Aprovechamiento forestal | B8: =Domestic!E9/Domestic!E$96 -> 0 | C8: =Domestic!F9/Domestic!F$96 -> 0 | D8: =Domestic!G9/Domestic!G$96 -> 0.043810405 | E8: =Domestic!H9/Domestic!H$96 -> 0 | F8: =Domestic!I9/Domestic!I$96 -> 5.4839541e-06 | G8: =Domestic!J9/Domestic!J$96 -> 0 | H8: =Domestic!K9/Domestic!K$96 -> 1.5911296e-06 | I8: =Domestic!L9/Domestic!L$96 -> 0 | ... CA8: =Domestic!CD9/Domestic!CD$96 -> 0
A9: 114 - Pesca, caza y captura | B9: =Domestic!E10/Domestic!E$96 -> 0 | C9: =Domestic!F10/Domestic!F$96 -> 6.4585247e-08 | D9: =Domestic!G10/Domestic!G$96 -> 5.8970742e-07 | E9: =Domestic!H10/Domestic!H$96 -> 0.00070305816 | F9: =Domestic!I10/Domestic!I$96 -> 6.7346805e-07 | G9: =Domestic!J10/Domestic!J$96 -> 2.4138971e-06 | H9: =Domestic!K10/Domestic!K$96 -> 8.2283452e-07 | I9: =Domestic!L10/Domestic!L$96 -> 2.0937111e-05 | ... CA9: =Domestic!CD10/Domestic!CD$96 -> 4.2329687e-06
A10: 115 - Servicios relacionados con las actividades agropecuarias y forestales | B10: =Domestic!E11/Domestic!E$96 -> 0.0056527395 | C10: =Domestic!F11/Domestic!F$96 -> 0.0014727515 | D10: =Domestic!G11/Domestic!G$96 -> 0.0026827872 | E10: =Domestic!H11/Domestic!H$96 -> 0.0008452717 | F10: =Domestic!I11/Domestic!I$96 -> 2.5110737e-05 | G10: =Domestic!J11/Domestic!J$96 -> 1.8047829e-08 | H10: =Domestic!K11/Domestic!K$96 -> 7.1138431e-09 | I10: =Domestic!L11/Domestic!L$96 -> 6.5387604e-09 | ... CA10: =Domestic!CD11/Domestic!CD$96 -> 4.3263881e-07
A11: 211 - Extracción de petróleo y gas | B11: =Domestic!E12/Domestic!E$96 -> 6.4685115e-06 | C11: =Domestic!F12/Domestic!F$96 -> 1.6261354e-05 | D11: =Domestic!G12/Domestic!G$96 -> 4.1279519e-06 | E11: =Domestic!H12/Domestic!H$96 -> 9.4896092e-06 | F11: =Domestic!I12/Domestic!I$96 -> 8.0816166e-06 | G11: =Domestic!J12/Domestic!J$96 -> 4.0912173e-06 | H11: =Domestic!K12/Domestic!K$96 -> 4.1473706e-06 | I11: =Domestic!L12/Domestic!L$96 -> 5.8979618e-06 | ... CA11: =Domestic!CD12/Domestic!CD$96 -> 2.2573791e-06
A12: 212 - Minería de minerales metálicos y no metálicos, excepto petróleo y gas | B12: =Domestic!E13/Domestic!E$96 -> 0.00075139296 | C12: =Domestic!F13/Domestic!F$96 -> 0.00040295745 | D12: =Domestic!G13/Domestic!G$96 -> 0.00054599969 | E12: =Domestic!H13/Domestic!H$96 -> 0.00059423236 | F12: =Domestic!I13/Domestic!I$96 -> 0.00019434364 | G12: =Domestic!J13/Domestic!J$96 -> 0.00083997755 | H12: =Domestic!K13/Domestic!K$96 -> 0.0098084104 | I12: =Domestic!L13/Domestic!L$96 -> 0.0021631985 | ... CA12: =Domestic!CD13/Domestic!CD$96 -> 0.00033834652
A13: 213 - Servicios relacionados con la minería | B13: =Domestic!E14/Domestic!E$96 -> 0 | C13: =Domestic!F14/Domestic!F$96 -> 1.4128023e-08 | D13: =Domestic!G14/Domestic!G$96 -> 7.9783945e-07 | E13: =Domestic!H14/Domestic!H$96 -> 4.7883349e-07 | F13: =Domestic!I14/Domestic!I$96 -> 4.8104861e-07 | G13: =Domestic!J14/Domestic!J$96 -> 0.0035008784 | H13: =Domestic!K14/Domestic!K$96 -> 0.00071178032 | I13: =Domestic!L14/Domestic!L$96 -> 0.00028719543 | ... CA13: =Domestic!CD14/Domestic!CD$96 -> 5.7766852e-06
A14: 221 - Generación, transmisión, distribución y comercialización de energía eléctrica, suministro de agua y de gas natural por ductos al consumidor final | B14: =Domestic!E15/Domestic!E$96 -> 0.015589173 | C14: =Domestic!F15/Domestic!F$96 -> 0.010828849 | D14: =Domestic!G15/Domestic!G$96 -> 0.0035911101 | E14: =Domestic!H15/Domestic!H$96 -> 0.004125847 | F14: =Domestic!I15/Domestic!I$96 -> 0.015860076 | G14: =Domestic!J15/Domestic!J$96 -> 0.0036380679 | H14: =Domestic!K15/Domestic!K$96 -> 0.032504178 | I14: =Domestic!L15/Domestic!L$96 -> 0.039817225 | ... CA14: =Domestic!CD15/Domestic!CD$96 -> 0.012008737
A15: 236 - Edificación | B15: =Domestic!E16/Domestic!E$96 -> 1.7286464e-05 | C15: =Domestic!F16/Domestic!F$96 -> 3.5655093e-05 | D15: =Domestic!G16/Domestic!G$96 -> 5.2345206e-05 | E15: =Domestic!H16/Domestic!H$96 -> 0.00026657966 | F15: =Domestic!I16/Domestic!I$96 -> 9.4093108e-05 | G15: =Domestic!J16/Domestic!J$96 -> 0.00049823288 | H15: =Domestic!K16/Domestic!K$96 -> 0.00061802698 | I15: =Domestic!L16/Domestic!L$96 -> 0.0025510189 | ... CA15: =Domestic!CD16/Domestic!CD$96 -> 0.00045795775
A16: 237 - Construcción de obras de ingeniería civil | B16: =Domestic!E17/Domestic!E$96 -> 1.2980957e-05 | C16: =Domestic!F17/Domestic!F$96 -> 2.5775568e-05 | D16: =Domestic!G17/Domestic!G$96 -> 9.1890292e-05 | E16: =Domestic!H17/Domestic!H$96 -> 0.00027297862 | F16: =Domestic!I17/Domestic!I$96 -> 0.00010640795 | G16: =Domestic!J17/Domestic!J$96 -> 0.0006490349 | H16: =Domestic!K17/Domestic!K$96 -> 0.00064090273 | I16: =Domestic!L17/Domestic!L$96 -> 0.0038973496 | ... CA16: =Domestic!CD17/Domestic!CD$96 -> 0.00070322949
A17: 238 - Trabajos especializados para la construcción | B17: =Domestic!E18/Domestic!E$96 -> 1.1572148e-05 | C17: =Domestic!F18/Domestic!F$96 -> 4.3239823e-05 | D17: =Domestic!G18/Domestic!G$96 -> 0.044530368 | E17: =Domestic!H18/Domestic!H$96 -> 3.7914907e-05 | F17: =Domestic!I18/Domestic!I$96 -> 0.001167505 | G17: =Domestic!J18/Domestic!J$96 -> 0.00018711651 | H17: =Domestic!K18/Domestic!K$96 -> 0.011618068 | I17: =Domestic!L18/Domestic!L$96 -> 0.0076611582 | ... CA17: =Domestic!CD18/Domestic!CD$96 -> 0.0081878341
... A83: 931 - Actividades legislativas, gubernamentales y de impartición de justicia | B83: =Domestic!E84/Domestic!E$96 -> 0 | C83: =Domestic!F84/Domestic!F$96 -> 0 | D83: =Domestic!G84/Domestic!G$96 -> 0 | E83: =Domestic!H84/Domestic!H$96 -> 0 | F83: =Domestic!I84/Domestic!I$96 -> 0 | G83: =Domestic!J84/Domestic!J$96 -> 0 | H83: =Domestic!K84/Domestic!K$96 -> 0 | I83: =Domestic!L84/Domestic!L$96 -> 0 | ... CA83: =Domestic!CD84/Domestic!CD$96 -> 0
A84: UEION - Usos de la economía interna de origen nacional | B84: 0.15990869 | C84: 0.48692348 | D84: 0.17128853 | E84: 0.46930105 | F84: 0.32629489 | G84: 0.21244099 | H84: 0.27409875 | I84: 0.43085587 | J84: 0.20778777 | K84: 0.41286246 | L84: 0.55190895 | M84: 0.29914716 | N84: 0.49551749 | O84: 0.35462656 | P84: 0.47845236 | Q84: 0.46869857 | R84: 0.33955483 | S84: 0.423195 | T84: 0.44083545 | U84: 0.3955255 | V84: 0.4575983 | W84: 0.41083611 | X84: 0.39294854 | Y84: 0.35353193 | Z84: 0.46461329 | AA84: 0.47683715 | AB84: 0.33496909 | AC84: 0.24564226 | AD84: 0.14731724 | AE84: 0.25691242 | AF84: 0.30586577 | AG84: 0.35354492 | AH84: 0.1477901 | AI84: 0.16653809 | AJ84: 0.16062985 | AK84: 0.43111502 | AL84: 0.32246767 | AM84: 0.3000082 | AN84: 0.18801291 | AO84: 0.27313315 | AP84: 0.4056373 | AQ84: 0.36530453 | AR84: 0.21474672 | AS84: 0.16331111 | AT84: 0.4114149 | AU84: 0.36859831 | AV84: 0.33102083 | AW84: 0.43111205 | AX84: 0.40511175 | AY84: 0.30556402 | AZ84: 0.35706265 | BA84: 0.40117436 | BB84: 0.11507886 | BC84: 0.25860077 | BD84: 0.37129537 | BE84: 0.4786257 | BF84: 0.064724442 | BG84: 0.29136573 | BH84: 0.0059264907 | BI84: 0.18489233 | BJ84: 0.36450451 | BK84: 0.17980396 | BL84: 0.31798505 | BM84: 0.10376395 | BN84: 0.24427325 | BO84: 0.30386662 | BP84: 0.35571821 | BQ84: 0.45271168 | BR84: 0.16586243 | BS84: 0.32852026 | BT84: 0.31277495 | BU84: 0.30290429 | BV84: 0.30194997 | BW84: 0.32561341 | BX84: 0.15595302 | BY84: 0.27529394 | BZ84: 0 | CA84: 0.2783778
A85: IEI - Importaciones de la economía interna | B85: 0.081997792 | C85: 0.022954107 | D85: 0.039642526 | E85: 0.10352406 | F85: 0.1017412 | G85: 0.083317954 | H85: 0.087176456 | I85: 0.15241999 | J85: 0.14061773 | K85: 0.076253363 | L85: 0.065101467 | M85: 0.10319245 | N85: 0.12047481 | O85: 0.12475476 | P85: 0.19050161 | Q85: 0.16253015 | R85: 0.24776667 | S85: 0.20167777 | T85: 0.12406536 | U85: 0.25030058 | V85: 0.25056647 | W85: 0.35029194 | X85: 0.27888251 | Y85: 0.36746541 | Z85: 0.1350372 | AA85: 0.22841747 | AB85: 0.3296642 | AC85: 0.40593364 | AD85: 0.6387338 | AE85: 0.44924291 | AF85: 0.40584106 | AG85: 0.24230665 | AH85: 0.55848425 | AI85: 0.044651709 | AJ85: 0.06082309 | AK85: 0.24862097 | AL85: 0.10634761 | AM85: 0.092945686 | AN85: 0.11565396 | AO85: 0.095773794 | AP85: 0.094667774 | AQ85: 0.11043603 | AR85: 0.12320693 | AS85: 0.037903586 | AT85: 0.10881661 | AU85: 0.17026753 | AV85: 0.16295775 | AW85: 0.042603074 | AX85: 0.13416571 | AY85: 0.10926054 | AZ85: 0.024490553 | BA85: 0.060466828 | BB85: 0.0033088647 | BC85: 0.020008541 | BD85: 0.016023705 | BE85: 0.10382197 | BF85: 0.018375768 | BG85: 0.19748079 | BH85: 0.0019844684 | BI85: 0.068223449 | BJ85: 0.036500195 | BK85: 0.043804845 | BL85: 0.10203296 | BM85: 0.026447187 | BN85: 0.046145957 | BO85: 0.06061204 | BP85: 0.035685146 | BQ85: 0.047901816 | BR85: 0.051920297 | BS85: 0.061710185 | BT85: 0.1156754 | BU85: 0.051966237 | BV85: 0.058199439 | BW85: 0.10204015 | BX85: 0.056821744 | BY85: 0.04056174 | BZ85: 0 | CA85: 0.023463477
A86: IBSNS - Impuestos sobre bienes y servicios netos de subsidios | B86: 0.0019138974 | C86: 0.00062054514 | D86: 0.0019557473 | E86: 0.0091679202 | F86: 0.0029872157 | G86: 0.0031499 | H86: 0.010175139 | I86: 0.0131621 | J86: 0.030657364 | K86: 0.0014262609 | L86: 0.0062374332 | M86: 0.0011472234 | N86: 0.0027068331 | O86: 0.0031889654 | P86: 0.0018682 | Q86: 0.0020256416 | R86: 0.0021838973 | S86: 0.0019493192 | T86: 0.0016038557 | U86: 0.0036854726 | V86: 0.0049055528 | W86: 0.074319005 | X86: 0.0089745641 | Y86: 0.0035016063 | Z86: 0.0043045299 | AA86: 0.002621845 | AB86: 0.002519753 | AC86: 0.00093281511 | AD86: 0.00043492536 | AE86: 0.0010954435 | AF86: 0.0012974226 | AG86: 0.0017007549 | AH86: 0.00068512588 | AI86: 0.0051171174 | AJ86: 0.0030380804 | AK86: 0.043156033 | AL86: 0.016505108 | AM86: 0.016779915 | AN86: 0.010195774 | AO86: 0.012766757 | AP86: 0.0077213149 | AQ86: 0.012080553 | AR86: 0.0021548729 | AS86: -0.01013659 | AT86: 0.013078569 | AU86: 0.0047982873 | AV86: 0.0021090753 | AW86: 0.0029768232 | AX86: 0.0011133586 | AY86: 0.0016547536 | AZ86: 0.00091515662 | BA86: 0.0098668356 | BB86: -0.001109384 | BC86: -0.00036460868 | BD86: 0.0010884648 | BE86: -0.0012335482 | BF86: 0.00091637379 | BG86: 0.0041736427 | BH86: 9.8533048e-05 | BI86: 0.0032095443 | BJ86: 0.0054045157 | BK86: 0.0013850315 | BL86: 0.0024289771 | BM86: 0.0085653875 | BN86: 0.018942913 | BO86: 0.018257559 | BP86: 0.0061464812 | BQ86: 0.021985627 | BR86: 0.0079667707 | BS86: 0.020797264 | BT86: 0.0058092309 | BU86: 0.017333359 | BV86: 0.012071799 | BW86: 0.000882165 | BX86: 0.00075007603 | BY86: 0.0010529288 | BZ86: 0 | CA86: 0.043171587
A87: B.1bV - Valor agregado bruto | B87: 0.75617962 | C87: 0.48950187 | D87: 0.78711319 | E87: 0.41800697 | F87: 0.56897669 | G87: 0.70109116 | H87: 0.62854966 | I87: 0.40356204 | J87: 0.62093713 | K87: 0.50945792 | L87: 0.37675215 | M87: 0.59651317 | N87: 0.38130087 | O87: 0.51742972 | P87: 0.32917783 | Q87: 0.36674564 | R87: 0.41049461 | S87: 0.37317792 | T87: 0.43349533 | U87: 0.35048844 | V87: 0.28692968 | W87: 0.16455295 | X87: 0.31919438 | Y87: 0.27550105 | Z87: 0.39604498 | AA87: 0.29212354 | AB87: 0.33284696 | AC87: 0.34749129 | AD87: 0.21351403 | AE87: 0.29274923 | AF87: 0.28699575 | AG87: 0.40244768 | AH87: 0.29304052 | AI87: 0.78369308 | AJ87: 0.77550898 | AK87: 0.27710797 | AL87: 0.55467961 | AM87: 0.5902662 | AN87: 0.68613735 | AO87: 0.6183263 | AP87: 0.49197361 | AQ87: 0.51217888 | AR87: 0.65989148 | AS87: 0.80892189 | AT87: 0.46668992 | AU87: 0.45633587 | AV87: 0.50391235 | AW87: 0.52330805 | AX87: 0.45960918 | AY87: 0.58352068 | AZ87: 0.61753164 | BA87: 0.52849198 | BB87: 0.88272166 | BC87: 0.7217553 | BD87: 0.61159246 | BE87: 0.41878588 | BF87: 0.91598342 | BG87: 0.50697983 | BH87: 0.99199051 | BI87: 0.74367468 | BJ87: 0.59359078 | BK87: 0.77500617 | BL87: 0.57755301 | BM87: 0.86122347 | BN87: 0.69063787 | BO87: 0.61726378 | BP87: 0.60245016 | BQ87: 0.47740088 | BR87: 0.7742505 | BS87: 0.58897229 | BT87: 0.56574042 | BU87: 0.62779611 | BV87: 0.62777879 | BW87: 0.57146427 | BX87: 0.78647516 | BY87: 0.68309139 | BZ87: 1 | CA87: 0.65498713
A88: P.1 - Producción | B88: 1 | C88: 1 | D88: 1 | E88: 1 | F88: 1 | G88: 1 | H88: 1 | I88: 1 | J88: 1 | K88: 1 | L88: 1 | M88: 1 | N88: 1 | O88: 1 | P88: 1 | Q88: 1 | R88: 1 | S88: 1 | T88: 1 | U88: 1 | V88: 1 | W88: 1 | X88: 1 | Y88: 1 | Z88: 1 | AA88: 1 | AB88: 1 | AC88: 1 | AD88: 1 | AE88: 1 | AF88: 1 | AG88: 1 | AH88: 1 | AI88: 1 | AJ88: 1 | AK88: 1 | AL88: 1 | AM88: 1 | AN88: 1 | AO88: 1 | AP88: 1 | AQ88: 1 | AR88: 1 | AS88: 1 | AT88: 1 | AU88: 1 | AV88: 1 | AW88: 1 | AX88: 1 | AY88: 1 | AZ88: 1 | BA88: 1 | BB88: 1 | BC88: 1 | BD88: 1 | BE88: 1 | BF88: 1 | BG88: 1 | BH88: 1 | BI88: 1 | BJ88: 1 | BK88: 1 | BL88: 1 | BM88: 1 | BN88: 1 | BO88: 1 | BP88: 1 | BQ88: 1 | BR88: 1 | BS88: 1 | BT88: 1 | BU88: 1 | BV88: 1 | BW88: 1 | BX88: 1 | BY88: 1 | BZ88: 1 | CA88: 1
A92: Fuente: INEGI. Sistema de Cuentas Nacionales de México. Matriz de Insumo Producto

Sheet Domestic
A1: Instituto Nacional de Estadística y Geografía (INEGI).
A2: Sistema de Cuentas Nacionales de México. Matriz de Insumo Producto simétrica, Base 2018
A3: Matriz simétrica de insumo producto. Industria por industria/ Economía total / Origen doméstico/ Subsector SCIAN/ Millones de pesos a precios básicos
A5: Concepto | B5: UPPB - Utilización de la producción a precios básicos | D5: DI - Demanda intermedia | CE5: DF - Demanda final
C6: Total minus oil | D6: Total | E6: 111 - Agricultura | F6: 112 - Cría y explotación de animales | G6: 113 - Aprovechamiento forestal | H6: 114 - Pesca, caza y captura | I6: 115 - Servicios relacionados con las actividades agropecuarias y forestales | J6: 211 - Extracción de petróleo y gas | K6: 212 - Minería de minerales metálicos y no metálicos, excepto petróleo y gas | L6: 213 - Servicios relacionados con la minería | M6: 221 - Generación, transmisión, distribución y comercialización de energía eléctrica, suministro de agua y de gas natural por ductos al consumidor final | N6: 236 - Edificación | O6: 237 - Construcción de obras de ingeniería civil | P6: 238 - Trabajos especializados para la construcción | Q6: 311 - Industria alimentaria | R6: 312 - Industria de las bebidas y del tabaco | S6: 313 - Fabricación de insumos textiles y acabado de textiles | T6: 314 - Fabricación de productos textiles, excepto prendas de vestir | U6: 315 - Fabricación de prendas de vestir | V6: 316 - Curtido y acabado de cuero y piel, y fabricación de productos de cuero, piel y materiales sucedáneos | W6: 321 - Industria de la madera | X6: 322 - Industria del papel | Y6: 323 - Impresión e industrias conexas | Z6: 324 - Fabricación de productos derivados del petróleo y del carbón | AA6: 325 - Industria química | AB6: 326 - Industria del plástico y del hule | AC6: 327 - Fabricación de productos a base de minerales no metálicos | AD6: 331 - Industrias metálicas básicas | AE6: 332 - Fabricación de productos metálicos | AF6: 333 - Fabricación de maquinaria y equipo | AG6: 334 - Fabricación de equipo de computación, comunicación, medición y de otros equipos, componentes y accesorios electrónicos | AH6: 335 - Fabricación de accesorios, aparatos eléctricos y equipo de generación de energía eléctrica | AI6: 336 - Fabricación de equipo de transporte | AJ6: 337 - Fabricación de muebles, colchones y persianas | AK6: 339 - Otras industrias manufactureras | AL6: 431 - Comercio al por mayor de abarrotes, alimentos, bebidas, hielo y tabaco | AM6: 461 - Comercio al por menor de abarrotes, alimentos, bebidas, hielo y tabaco | AN6: 481 - Transporte aéreo | AO6: 482 - Transporte por ferrocarril | AP6: 483 - Transporte por agua | AQ6: 484 - Autotransporte de carga | AR6: 485 - Transporte terrestre de pasajeros, excepto por ferrocarril | AS6: 486 - Transporte por ductos | AT6: 487 - Transporte turístico | AU6: 488 - Servicios relacionados con el transporte | AV6: 491 - Servicios postales | AW6: 492 - Servicios de mensajería y paquetería | AX6: 493 - Servicios de almacenamiento | AY6: 511 - Edición de periódicos, revistas, libros, software y otros materiales, y edición de estas publicaciones integrada con la impresión | AZ6: 512 - Industria fílmica y del video, e industria del sonido | BA6: 515 - Radio y televisión | BB6: 517 - Telecomunicaciones | BC6: 518 - Procesamiento electrónico de información, hospedaje y otros servicios relacionados | BD6: 519 - Otros servicios de información | BE6: 521 - Banca central | BF6: 522 - Instituciones de intermediación crediticia y financiera no bursátil | BG6: 523 - Actividades bursátiles, cambiarias y de inversión financiera | BH6: 524 - Compañías de seguros, fianzas, y administración de fondos para el retiro | BI6: 531 - Servicios inmobiliarios | BJ6: 532 - Servicios de alquiler de bienes muebles | BK6: 533 - Servicios de alquiler de marcas registradas, patentes y franquicias | BL6: 541 - Servicios profesionales, científicos y técnicos | BM6: 551 - Corporativos | BN6: 561 - Servicios de apoyo a los negocios | BO6: 562 - Manejo de residuos y servicios de remediación | BP6: 611 - Servicios educativos | BQ6: 621 - Servicios médicos de consulta externa y servicios relacionados | BR6: 622 - Hospitales | BS6: 623 - Residencias de asistencia social y para el cuidado de la salud | BT6: 624 - Otros servicios de asistencia social | BU6: 711 - Servicios artísticos, culturales y deportivos, y otros servicios relacionados | BV6: 712 - Museos, sitios históricos, zoológicos y similares | BW6: 713 - Servicios de entretenimiento en instalaciones recreativas y otros servicios recreativos | BX6: 721 - Servicios de alojamiento temporal | BY6: 722 - Servicios de preparación de alimentos y bebidas | BZ6: 811 - Servicios de reparación y mantenimiento | CA6: 812 - Servicios personales | CB6: 813 - Asociaciones y organizaciones | CC6: 814 - Hogares con empleados domésticos | CD6: 931 - Actividades legislativas, gubernamentales y de impartición de justicia | CE6: Total | CF6: CPrv - Consumo privado | CG6: CG - Consumo de gobierno | CH6: P.51b - Formación bruta de capital fijo | CI6: P.52 - Variación de existencias | CJ6: a P.6 - Exportaciones de bienes y servicios | CK6: YA0 - Discrepancia estadística
A7: 111 - Agricultura | B7: 682846.43 | C7: =D7-J7 -> 320479.86 | D7: 320479.86 | E7: 13002.532 | F7: 56384.337 | G7: 176.569 | H7: 11.872 | I7: 314.236 | J7: 0 | K7: 0 | L7: 0 | M7: 0 | N7: 34.723 | O7: 1356.941 | P7: 8.241 | Q7: 176378.12 | R7: 25693.13 | S7: 11070.905 | T7: 0 | U7: 475.728 | V7: 0.151 | W7: 422.116 | X7: 5.262 | Y7: 0 | Z7: 0 | AA7: 1328.653 | AB7: 341.312 | AC7: 2.152 | AD7: 0 | AE7: 0 | AF7: 0 | AG7: 0 | AH7: 0 | AI7: 0 | AJ7: 0 | AK7: 166.334 | AL7: 0 | AM7: 0.141 | AN7: 0 | AO7: 0 | AP7: 0 | AQ7: 0 | AR7: 0 | AS7: 0 | AT7: 0 | AU7: 0 | AV7: 0 | AW7: 0 | AX7: 0 | AY7: 0 | AZ7: 0 | BA7: 0.005 | BB7: 0 | BC7: 0 | BD7: 0.001 | BE7: 0 | BF7: 0 | BG7: 0 | BH7: 0 | BI7: 0.014 | BJ7: 0 | BK7: 0 | BL7: 0.661 | BM7: 0 | BN7: 1.944 | BO7: 0 | BP7: 2.743 | BQ7: 0.101 | BR7: 566.124 | BS7: 49.114 | BT7: 261.142 | BU7: 0 | BV7: 0 | BW7: 0.085 | BX7: 10288.218 | BY7: 21879.593 | BZ7: 0.001 | CA7: 13.112 | CB7: 202.692 | CC7: 0 | CD7: 40.858 | CE7: 362366.57 | CF7: 146003.22 | CG7: 401.578 | CH7: 12915.213 | CI7: 0 | CJ7: 203046.56 | CK7: 0
A8: 112 - Cría y explotación de animales | B8: 495469.19 | C8: =D8-J8 -> 367447.1 | D8: 367447.1 | E8: 5038.302 | F8: 11513.626 | G8: 0 | H8: 0 | I8: 0 | J8: 0.008 | K8: 0.001 | L8: 0.012 | M8: 0.002 | N8: 618.977 | O8: 0.01 | P8: 0.011 | Q8: 347545.6 | R8: 3.347 | S8: 589.881 | T8: 0 | U8: 0.001 | V8: 0 | W8: 0 | X8: 0.001 | Y8: 0.001 | Z8: 0 | AA8: 287.819 | AB8: 0.002 | AC8: 0 | AD8: 0.001 | AE8: 0.001 | AF8: 0.001 | AG8: 0.002 | AH8: 0 | AI8: 0.021 | AJ8: 0.001 | AK8: 175.224 | AL8: 0.027 | AM8: 0.044 | AN8: 0.001 | AO8: 0 | AP8: 0 | AQ8: 0 | AR8: 0.004 | AS8: 0 | AT8: 0 | AU8: 0.001 | AV8: 0 | AW8: 0 | AX8: 0.002 | AY8: 0 | AZ8: 0.014 | BA8: 0.113 | BB8: 0.014 | BC8: 0 | BD8: 0.037 | BE8: 0 | BF8: 0.011 | BG8: 0 | BH8: 0.002 | BI8: 0.394 | BJ8: 0 | BK8: 0 | BL8: 0.002 | BM8: 0.002 | BN8: 52.522 | BO8: 0 | BP8: 0.077 | BQ8: 2.77 | BR8: 284.099 | BS8: 21.023 | BT8: 29.419 | BU8: 0 | BV8: 0 | BW8: 2.306 | BX8: 0.002 | BY8: 1274.867 | BZ8: 0.046 | CA8: 3.154 | CB8: 0.001 | CC8: 0 | CD8: 3.299 | CE8: 128022.09 | CF8: 53632.632 | CG8: 3.35 | CH8: 58787.773 | CI8: 4318.531 | CJ8: 11279.802 | CK8: 0
A9: 113 - Aprovechamiento forestal | B9: 28827.855 | C9: =D9-J9 -> 24233.094 | D9: 24233.094 | E9: 0 | F9: 0 | G9: 1262.96 | H9: 0 | I9: 0.057 | J9: 0 | K9: 0.671 | L9: 0 | M9: 0 | N9: 0 | O9: 0 | P9: 0 | Q9: 757.449 | R9: 0 | S9: 0 | T9: 0 | U9: 0 | V9: 117.005 | W9: 15476.057 | X9: 1172.401 | Y9: 0 | Z9: 0 | AA9: 3381.715 | AB9: 667.325 | AC9: 65.645 | AD9: 0 | AE9: 0 | AF9: 0 | AG9: 0 | AH9: 0 | AI9: 0 | AJ9: 623.412 | AK9: 708.379 | AL9: 0 | AM9: 0 | AN9: 0 | AO9: 0 | AP9: 0 | AQ9: 0 | AR9: 0 | AS9: 0 | AT9: 0 | AU9: 0 | AV9: 0 | AW9: 0 | AX9: 0 | AY9: 0 | AZ9: 0 | BA9: 0 | BB9: 0 | BC9: 0 | BD9: 0 | BE9: 0 | BF9: 0 | BG9: 0 | BH9: 0 | BI9: 0 | BJ9: 0 | BK9: 0 | BL9: 0.008 | BM9: 0 | BN9: 0 | BO9: 0 | BP9: 0.01 | BQ9: 0 | BR9: 0 | BS9: 0 | BT9: 0 | BU9: 0 | BV9: 0 | BW9: 0 | BX9: 0 | BY9: 0 | BZ9: 0 | CA9: 0 | CB9: 0 | CC9: 0 | CD9: 0 | CE9: 4594.761 | CF9: 3226.399 | CG9: 0 | CH9: 0 | CI9: 0 | CJ9: 1368.362 | CK9: 0
A10: 114 - Pesca, caza y captura | B10: 22972.495 | C10: =D10-J10 -> 6163.102 | D10: 6165.242 | E10: 0 | F10: 0.032 | G10: 0.017 | H10: 16.151 | I10: 0.007 | J10: 2.14 | K10: 0.347 | L10: 3.202 | M10: 0.376 | N10: 5.52 | O10: 2.314 | P10: 2.527 | Q10: 4860.831 | R10: 0.148 | S10: 0.06 | T10: 0.056 | U10: 0.174 | V10: 0.042 | W10: 0.049 | X10: 8.489 | Y10: 0.122 | Z10: 0.016 | AA10: 0.441 | AB10: 0.33 | AC10: 0.171 | AD10: 0.228 | AE10: 0.307 | AF10: 0.281 | AG10: 0.627 | AH10: 0.149 | AI10: 4.432 | AJ10: 0.134 | AK10: 0.131 | AL10: 4.124 | AM10: 6.486 | AN10: 0.104 | AO10: 0.041 | AP10: 0.02 | AQ10: 0.063 | AR10: 0.619 | AS10: 0.008 | AT10: 0.003 | AU10: 0.201 | AV10: 0.004 | AW10: 0.02 | AX10: 0.235 | AY10: 0.029 | AZ10: 0.463 | BA10: 0.124 | BB10: 1.873 | BC10: 0.012 | BD10: 0.013 | BE10: 0.002 | BF10: 1.71 | BG10: 0.078 | BH10: 0.23 | BI10: 0.604 | BJ10: 0.086 | BK10: 0.002 | BL10: 0.742 | BM10: 0.263 | BN10: 0.726 | BO10: 0.014 | BP10: 1.696 | BQ10: 1.634 | BR10: 0.682 | BS10: 0.028 | BT10: 0.18 | BU10: 0.078 | BV10: 0.46 | BW10: 0.342 | BX10: 657.325 | BY10: 567.208 | BZ10: 0.487 | CA10: 0.6 | CB10: 0.244 | CC10: 0 | CD10: 5.528 | CE10: 16807.253 | CF10: 12067.784 | CG10: 0.002 | CH10: 23.382 | CI10: 0 | CJ10: 4716.085 | CK10: 0
A11: 115 - Servicios relacionados con las actividades agropecuarias y forestales | B11: 10393.96 | C11: =D11-J11 -> 9546.511 | D11: 9546.527 | E11: 3859.953 | F11: 729.703 | G11: 77.339 | H11: 19.418 | I11: 0.261 | J11: 0.016 | K11: 0.003 | L11: 0.001 | M11: 0.005 | N11: 0.225 | O11: 0.021 | P11: 0.006 | Q11: 4104.789 | R11: 0.012 | S11: 527.495 | T11: 0.002 | U11: 224.951 | V11: 0.001 | W11: 0.002 | X11: 0.01 | Y11: 0.003 | Z11: 0.014 | AA11: 0.042 | AB11: 0.016 | AC11: 0.01 | AD11: 0.022 | AE11: 0.015 | AF11: 0.015 | AG11: 0.022 | AH11: 0.012 | AI11: 0.156 | AJ11: 0.004 | AK11: 0.812 | AL11: 0.07 | AM11: 0.049 | AN11: 0.004 | AO11: 0.001 | AP11: 0 | AQ11: 0.008 | AR11: 0.005 | AS11: 0 | AT11: 0 | AU11: 0.002 | AV11: 0 | AW11: 0.001 | AX11: 0 | AY11: 0 | AZ11: 0.022 | BA11: 0.001 | BB11: 0.006 | BC11: 0 | BD11: 0 | BE11: 0.001 | BF11: 0.133 | BG11: 0.003 | BH11: 0.001 | BI11: 0.017 | BJ11: 0.002 | BK11: 0 | BL11: 0.035 | BM11: 0.001 | BN11: 0.022 | BO11: 0 | BP11: 0.094 | BQ11: 0.019 | BR11: 0.034 | BS11: 0 | BT11: 0 | BU11: 0 | BV11: 0.001 | BW11: 0.002 | BX11: 0.005 | BY11: 0.015 | BZ11: 0.005 | CA11: 0.001 | CB11: 0.046 | CC11: 0 | CD11: 0.565 | CE11: 847.433 | CF11: 828.835 | CG11: 0.324 | CH11: 17.857 | CI11: 0 | CJ11: 0.417 | CK11: 0
A12: 211 - Extracción de petróleo y gas | B12: 886533.21 | C12: =D12-J12 -> 392463.45 | D12: 392467.08 | E12: 4.417 | F12: 8.057 | G12: 0.119 | H12: 0.218 | I12: 0.084 | J12: 3.627 | K12: 1.749 | L12: 0.902 | M12: 3.243 | N12: 35.283 | O12: 4.849 | P12: 2.696 | Q12: 34.101 | R12: 3.442 | S12: 0.853 | T12: 0.674 | U12: 1.433 | V12: 0.862 | W12: 1.051 | X12: 5.021 | Y12: 1.354 | Z12: 280841.52 | AA12: 111323.32 | AB12: 8.337 | AC12: 5.258 | AD12: 12.184 | AE12: 7.65 | AF12: 8.607 | AG12: 12.086 | AH12: 6.419 | AI12: 68.119 | AJ12: 2 | AK12: 3.034 | AL12: 4.18 | AM12: 1.983 | AN12: 1.943 | AO12: 0.241 | AP12: 0.154 | AQ12: 4.355 | AR12: 3.194 | AS12: 0.128 | AT12: 0.019 | AU12: 1.531 | AV12: 0.004 | AW12: 0.295 | AX12: 0.183 | AY12: 0.066 | AZ12: 0.155 | BA12: 0.206 | BB12: 2.471 | BC12: 0.035 | BD12: 0.003 | BE12: 0.139 | BF12: 1.238 | BG12: 0.044 | BH12: 0.085 | BI12: 2.346 | BJ12: 0.86 | BK12: 0.005 | BL12: 2.018 | BM12: 0.281 | BN12: 3.719 | BO12: 0.195 | BP12: 1.624 | BQ12: 2.412 | BR12: 4.474 | BS12: 0.041 | BT12: 0.301 | BU12: 0.215 | BV12: 0.066 | BW12: 0.728 | BX12: 2.338 | BY12: 4.117 | BZ12: 1.979 | CA12: 0.697 | CB12: 0.5 | CC12: 0 | CD12: 2.948 | CE12: 494066.14 | CF12: 518.713 | CG12: 0 | CH12: 95.936 | CI12: 0 | CJ12: 493451.49 | CK12: 0
A13: 212 - Minería de minerales metálicos y no metálicos, excepto petróleo y gas | B13: 421712.98 | C13: =D13-J13 -> 322518.81 | D13: 323263.48 | E13: 513.086 | F13: 199.653 | G13: 15.74 | H13: 13.651 | I13: 2.02 | J13: 744.668 | K13: 4136.334 | L13: 330.827 | M13: 10931.14 | N13: 26090.879 | O13: 14408.831 | P13: 4949.266 | Q13: 757.519 | R13: 810.151 | S13: 1.433 | T13: 2.052 | U13: 4.361 | V13: 2.315 | W13: 2.552 | X13: 176.358 | Y13: 6.193 | Z13: 788.378 | AA13: 4712.799 | AB13: 118.068 | AC13: 58284.243 | AD13: 190920.63 | AE13: 654.301 | AF13: 18.828 | AG13: 41.992 | AH13: 73.593 | AI13: 399.611 | AJ13: 2.279 | AK13: 572.233 | AL13: 180.285 | AM13: 183.113 | AN13: 10.594 | AO13: 29.542 | AP13: 1.29 | AQ13: 190.904 | AR13: 360.222 | AS13: 21.886 | AT13: 1.929 | AU13: 34.918 | AV13: 0.029 | AW13: 34.973 | AX13: 4.639 | AY13: 1.181 | AZ13: 14.432 | BA13: 19.747 | BB13: 161.374 | BC13: 1.316 | BD13: 0.51 | BE13: 0.033 | BF13: 34.147 | BG13: 2.559 | BH13: 5.305 | BI13: 191.137 | BJ13: 15.029 | BK13: 0.146 | BL13: 65.167 | BM13: 3.938 | BN13: 57.828 | BO13: 1.186 | BP13: 121.856 | BQ13: 129.501 | BR13: 44.179 | BS13: 2.52 | BT13: 12.725 | BU13: 2.195 | BV13: 2.148 | BW13: 22.066 | BX13: 47.759 | BY13: 77.551 | BZ13: 2.7 | CA13: 21.417 | CB13: 19.657 | CC13: 0 | CD13: 441.86 | CE13: 98449.503 | CF13: 20.854 | CG13: 6.359 | CH13: 441.537 | CI13: 1628.537 | CJ13: 96352.216 | CK13: 0
A14: 213 - Servicios relacionados con la minería | B14: 152934.19 | C14: =D14-J14 -> 381.674 | D14: 3485.319 | E14: 0 | F14: 0.007 | G14: 0.023 | H14: 0.011 | I14: 0.005 | J14: 3103.645 | K14: 300.167 | L14: 43.922 | M14: 0.357 | N14: 7.182 | O14: 3.089 | P14: 3.256 | Q14: 0.09 | R14: 0.016 | S14: 0.007 | T14: 0.01 | U14: 0.029 | V14: 0.007 | W14: 0.014 | X14: 0.088 | Y14: 0.052 | Z14: 0.009 | AA14: 0.159 | AB14: 0.095 | AC14: 0.065 | AD14: 0.29 | AE14: 0.107 | AF14: 0.149 | AG14: 0.655 | AH14: 0.083 | AI14: 4.18 | AJ14: 0.02 | AK14: 0.036 | AL14: 1.412 | AM14: 1.395 | AN14: 0.024 | AO14: 0.038 | AP14: 0.012 | AQ14: 0.012 | AR14: 0.012 | AS14: 0.001 | AT14: 0 | AU14: 0.044 | AV14: 0 | AW14: 0.002 | AX14: 0.077 | AY14: 0.004 | AZ14: 0.09 | BA14: 0.031 | BB14: 0.034 | BC14: 0.003 | BD14: 0.006 | BE14: 0.001 | BF14: 0.657 | BG14: 0.044 | BH14: 0.079 | BI14: 0.211 | BJ14: 0.015 | BK14: 0 | BL14: 0.229 | BM14: 0.004 | BN14: 0.137 | BO14: 0.005 | BP14: 1.821 | BQ14: 1.643 | BR14: 0.712 | BS14: 0.035 | BT14: 0.2 | BU14: 0.015 | BV14: 0.018 | BW14: 0.092 | BX14: 0.073 | BY14: 0.187 | BZ14: 0.026 | CA14: 0.253 | CB14: 0.296 | CC14: 0 | CD14: 7.544 | CE14: 149448.87 | CF14: 0.344 | CG14: 0.108 | CH14: 149442.8 | CI14: 5.448 | CJ14: 0.172 | CK14: 0
A15: 221 - Generación, transmisión, distribución y comercialización de energía eléctrica, suministro de agua y de gas natural por ductos al consumidor final | B15: 735834.91 | C15: =D15-J15 -> 441715.57 | D15: 444940.84 | E15: 10645.011 | F15: 5365.361 | G15: 103.524 | H15: 94.781 | I15: 164.849 | J15: 3225.268 | K15: 13707.434 | L15: 6089.415 | M15: 11714.333 | N15: 2369.805 | O15: 3568.871 | P15: 1575.736 | Q15: 24625.93 | R15: 4610.899 | S15: 6490.979 | T15: 1281.882 | U15: 4409.497 | V15: 1528.353 | W15: 1295.976 | X15: 5628.529 | Y15: 1230.542 | Z15: 10712.519 | AA15: 13106.267 | AB15: 12342.045 | AC15: 8180.071 | AD15: 27534.364 | AE15: 6582.532 | AF15: 8374.312 | AG15: 15245.329 | AH15: 3824.653 | AI15: 41047.321 | AJ15: 989.549 | AK15: 2203.817 | AL15: 15647.29 | AM15: 66085.609 | AN15: 110.393 | AO15: 90.412 | AP15: 157.911 | AQ15: 642.428 | AR15: 1718.521 | AS15: 351.405 | AT15: 18.461 | AU15: 1029.455 | AV15: 15.718 | AW15: 114.779 | AX15: 1854.388 | AY15: 149.714 | AZ15: 616.887 | BA15: 992.769 | BB15: 4973.86 | BC15: 266.968 | BD15: 26.086 | BE15: 33.625 | BF15: 3780.729 | BG15: 157.654 | BH15: 1412.581 | BI15: 18416.009 | BJ15: 588.675 | BK15: 8.545 | BL15: 4005.719 | BM15: 492.091 | BN15: 5859.728 | BO15: 116.496 | BP15: 12114.515 | BQ15: 3922.448 | BR15: 4302.127 | BS15: 147.46 | BT15: 487.726 | BU15: 340.983 | BV15: 199.048 | BW15: 2154.084 | BX15: 5095.537 | BY15: 4840.03 | BZ15: 1990.526 | CA15: 2878.669 | CB15: 1180.347 | CC15: 0 | CD15: 15682.681 | CE15: 290894.07 | CF15: 286082.97 | CG15: 17.511 | CH15: 484.36 | CI15: 0 | CJ15: 4309.228 | CK15: 0
A16: 236 - Edificación | B16: 2090312.5 | C16: =D16-J16 -> 23704.143 | D16: 24145.843 | E16: 11.804 | F16: 17.666 | G16: 1.509 | H16: 6.124 | I16: 0.978 | J16: 441.7 | K16: 260.63 | L16: 390.138 | M16: 449.688 | N16: 15576.753 | O16: 1144.304 | P16: 575.396 | Q16: 118.596 | R16: 16.358 | S16: 4.458 | T16: 3.725 | U16: 12.438 | V16: 4.134 | W16: 7.206 | X16: 33.906 | Y16: 26.056 | Z16: 13.001 | AA16: 429.799 | AB16: 57.198 | AC16: 34.299 | AD16: 73.618 | AE16: 67.313 | AF16: 45.234 | AG16: 76.28 | AH16: 26.893 | AI16: 958.184 | AJ16: 16.415 | AK16: 12.713 | AL16: 169.033 | AM16: 227.528 | AN16: 5.98 | AO16: 2.833 | AP16: 1.182 | AQ16: 7.238 | AR16: 20.524 | AS16: 122.11 | AT16: 0.102 | AU16: 9.8 | AV16: 0.125 | AW16: 1.007 | AX16: 18.238 | AY16: 1.561 | AZ16: 17.846 | BA16: 11.709 | BB16: 57.667 | BC16: 0.562 | BD16: 1.312 | BE16: 0.226 | BF16: 63.836 | BG16: 9.354 | BH16: 130.34 | BI16: 100.357 | BJ16: 7.32 | BK16: 0.112 | BL16: 108.98 | BM16: 7.419 | BN16: 729.54 | BO16: 3.424 | BP16: 180.197 | BQ16: 187.566 | BR16: 52.223 | BS16: 2.717 | BT16: 23.83 | BU16: 7.406 | BV16: 2.518 | BW16: 49.605 | BX16: 34.753 | BY16: 91.608 | BZ16: 27.451 | CA16: 94.401 | CB16: 41.724 | CC16: 0 | CD16: 598.065 | CE16: 2066166.6 | CF16: 4232.269 | CG16: 59.437 | CH16: 2059378.1 | CI16: 0 | CJ16: 2496.817 | CK16: 0
A17: 237 - Construcción de obras de ingeniería civil | B17: 568177.3 | C17: =D17-J17 -> 43033.247 | D17: 43608.638 | E17: 8.864 | F17: 12.771 | G17: 2.649 | H17: 6.271 | I17: 1.106 | J17: 575.391 | K17: 270.277 | L17: 596.038 | M17: 443.609 | N17: 2351.352 | O17: 33676.195 | P17: 721.237 | Q17: 81.248 | R17: 11.877 | S17: 3.013 | T17: 2.76 | U17: 9.657 | V17: 3.132 | W17: 6.298 | X17: 31.585 | Y17: 25.194 | Z17: 9.284 | AA17: 402.625 | AB17: 50.029 | AC17: 30.915 | AD17: 67.055 | AE17: 61.277 | AF17: 43.372 | AG17: 98.846 | AH17: 24.997 | AI17: 1075.234 | AJ17: 13.263 | AK17: 10.356 | AL17: 175.603 | AM17: 187.342 | AN17: 4.344 | AO17: 4.368 | AP17: 1.482 | AQ17: 4.121 | AR17: 6.427 | AS17: 116.127 | AT17: 0.055 | AU17: 7.597 | AV17: 0.073 | AW17: 0.543 | AX17: 17.949 | AY17: 1.18 | AZ17: 11.435 | BA17: 9.529 | BB17: 18.978 | BC17: 0.463 | BD17: 1.047 | BE17: 0.128 | BF17: 57.875 | BG17: 10.091 | BH17: 124.886 | BI17: 91.294 | BJ17: 5.795 | BK17: 0.092 | BL17: 102.147 | BM17: 1.956 | BN17: 124.172 | BO17: 3.209 | BP17: 251.845 | BQ17: 227.306 | BR17: 80.109 | BS17: 4.389 | BT17: 23.584 | BU17: 6.381 | BV17: 2.836 | BW17: 21.695 | BX17: 31.11 | BY17: 73.006 | BZ17: 16.732 | CA17: 78.5 | CB17: 54.685 | CC17: 0 | CD17: 918.375 | CE17: 524568.67 | CF17: 1420.363 | CG17: 21666.505 | CH17: 499205.75 | CI17: 0 | CJ17: 2276.05 | CK17: 0
A18: 238 - Trabajos especializados para la construcción | B18: 304773.24 | C18: =D18-J18 -> 286189.7 | D18: 286355.59 | E18: 7.902 | F18: 21.424 | G18: 1283.715 | H18: 0.871 | I18: 12.135 | J18: 165.885 | K18: 4899.49 | L18: 1171.653 | M18: 58.293 | N18: 183442.32 | O18: 69075.204 | P18: 1353.065 | Q18: 921.2 | R18: 29.978 | S18: 2.733 | T18: 13.246 | U18: 41.982 | V18: 10.868 | W18: 4.751 | X18: 22.354 | Y18: 24.268 | Z18: 137.294 | AA18: 51.458 | AB18: 22.85 | AC18: 22.565 | AD18: 33.026 | AE18: 24.674 | AF18: 30.254 | AG18: 37.206 | AH18: 13.891 | AI18: 232.506 | AJ18: 9.708 | AK18: 14.864 | AL18: 995.514 | AM18: 1029.166 | AN18: 82.197 | AO18: 5.24 | AP18: 15.224 | AQ18: 36.803 | AR18: 124.747 | AS18: 15.832 | AT18: 1.522 | AU18: 24.001 | AV18: 0.406 | AW18: 5.74 | AX18: 33.062 | AY18: 2.43 | AZ18: 8.071 | BA18: 6.256 | BB18: 44.046 | BC18: 0.306 | BD18: 3.446 | BE18: 0.241 | BF18: 1115.343 | BG18: 1.3 | BH18: 16.627 | BI18: 89.472 | BJ18: 4.658 | BK18: 0.037 | BL18: 423.831 | BM18: 2.824 | BN18: 55.278 | BO18: 1.166 | BP18: 4400.665 | BQ18: 1792.386 | BR18: 1206.922 | BS18: 1.597 | BT18: 69.86 | BU18: 28.465 | BV18: 346.079 | BW18: 132.024 | BX18: 33.331 | BY18: 165.98 | BZ18: 114.816 | CA18: 23.556 | CB18: 8.669 | CC18: 0 | CD18: 10692.814 | CE18: 18417.654 | CF18: 969.495 | CG18: 38.329 | CH18: 17055.458 | CI18: 3.474 | CJ18: 350.898 | CK18: 0
... A86: IET - Importaciones de la economía total | B86: 9670671.8 | C86: =D86-J86 -> 7088636.8 | D86: 7162501 | E86: 55991.9 | F86: 11373.053 | G86: 1142.809 | H86: 2378.206 | I86: 1057.494 | J86: 73864.134 | K86: 36763.443 | L86: 23310.227 | M86: 103471.44 | N86: 159393.36 | O86: 36989.176 | P86: 31450.296 | Q86: 288062.66 | R86: 57907.179 | S86: 18816.24 | T86: 7679.504 | U86: 42964.579 | V86: 16989.578 | W86: 11115.292 | X86: 72565.975 | Y86: 21520.647 | Z86: 350045.01 | AA86: 311394.24 | AB86: 202209.82 | AC86: 53734.646 | AD86: 201168.58 | AE86: 169079.89 | AF86: 243960.08 | AG86: 1224417.6 | AH86: 274094.96 | AI86: 1652378.5 | AJ86: 33439.433 | AK86: 253202.84 | AL86: 129236.5 | AM86: 175796.26 | AN86: 57038.969 | AO86: 7381.655 | AP86: 2986.175 | AQ86: 144341.41 | AR86: 69882.834 | AS86: 2453.746 | AT86: 536.285 | AU86: 28856.936 | AV86: 185.633 | AW86: 5028.052 | AX86: 11136.526 | AY86: 5286.859 | AZ86: 3007.366 | BA86: 12148.75 | BB86: 49899.289 | BC86: 329.937 | BD86: 176.268 | BE86: 142.736 | BF86: 18817.239 | BG86: 600.809 | BH86: 36410.25 | BI86: 40862.287 | BJ86: 13325.748 | BK86: 99.17 | BL86: 39968.505 | BM86: 7802.435 | BN86: 44016.541 | BO86: 2608.523 | BP86: 26960.046 | BQ86: 16405.288 | BR86: 27807.18 | BS86: 163.398 | BT86: 1626.186 | BU86: 3455.318 | BV86: 789.113 | BW86: 11545.575 | BX86: 21083.057 | BY86: 30525.916 | BZ86: 21141.379 | CA86: 12693.6 | CB86: 3366.621 | CC86: 0 | CD86: 30641.876 | CE86: 2508170.9 | CF86: 1223353.5 | CG86: 0 | CH86: 1230986.3 | CI86: 53831.01 | CJ86: 0 | CK86: 0
A87: P.721 - Compras directas en el exterior por residentes | B87: 282556.6 | C87: =D87-J87 -> #VALUE! | CE87: 282556.6 | CF87: 270999.24 | CG87: 11557.36 | CH87: 0 | CI87: 0 | CJ87: 0 | CK87: 0
A88: P.621 - Compras directas en el mercado interno por no residentes | B88: 5.8207661e-11 | C88: =D88-J88 -> #VALUE! | CE88: 5.8207661e-11 | CF88: -501182.33 | CG88: -4581.333 | CH88: 0 | CI88: 0 | CJ88: 505763.67 | CK88: 0
A89: P.621+P.721 - Compras netas de residentes y no residentes | B89: 282556.6 | C89: =D89-J89 -> #VALUE! | CE89: 282556.6 | CF89: -230183.09 | CG89: 6976.027 | CH89: 0 | CI89: 0 | CJ89: 505763.67 | CK89: 0
A90: P.7 - Importaciones de bienes y servicios | B90: 9953228.4 | C90: =D90-J90 -> 7088636.8 | D90: 7162501 | E90: 55991.9 | F90: 11373.053 | G90: 1142.809 | H90: 2378.206 | I90: 1057.494 | J90: 73864.134 | K90: 36763.443 | L90: 23310.227 | M90: 103471.44 | N90: 159393.36 | O90: 36989.176 | P90: 31450.296 | Q90: 288062.66 | R90: 57907.179 | S90: 18816.24 | T90: 7679.504 | U90: 42964.579 | V90: 16989.578 | W90: 11115.292 | X90: 72565.975 | Y90: 21520.647 | Z90: 350045.01 | AA90: 311394.24 | AB90: 202209.82 | AC90: 53734.646 | AD90: 201168.58 | AE90: 169079.89 | AF90: 243960.08 | AG90: 1224417.6 | AH90: 274094.96 | AI90: 1652378.5 | AJ90: 33439.433 | AK90: 253202.84 | AL90: 129236.5 | AM90: 175796.26 | AN90: 57038.969 | AO90: 7381.655 | AP90: 2986.175 | AQ90: 144341.41 | AR90: 69882.834 | AS90: 2453.746 | AT90: 536.285 | AU90: 28856.936 | AV90: 185.633 | AW90: 5028.052 | AX90: 11136.526 | AY90: 5286.859 | AZ90: 3007.366 | BA90: 12148.75 | BB90: 49899.289 | BC90: 329.937 | BD90: 176.268 | BE90: 142.736 | BF90: 18817.239 | BG90: 600.809 | BH90: 36410.25 | BI90: 40862.287 | BJ90: 13325.748 | BK90: 99.17 | BL90: 39968.505 | BM90: 7802.435 | BN90: 44016.541 | BO90: 2608.523 | BP90: 26960.046 | BQ90: 16405.288 | BR90: 27807.18 | BS90: 163.398 | BT90: 1626.186 | BU90: 3455.318 | BV90: 789.113 | BW90: 11545.575 | BX90: 21083.057 | BY90: 30525.916 | BZ90: 21141.379 | CA90: 12693.6 | CB90: 3366.621 | CC90: 0 | CD90: 30641.876 | CE90: 2790727.5 | CF90: 993170.44 | CG90: 6976.027 | CH90: 1230986.3 | CI90: 53831.01 | CJ90: 505763.67 | CK90: 0
A91: D.21 - Impuestos sobre los productos | B91: 1393818.8 | C91: =D91-J91 -> 313225.55 | D91: 316020.91 | E91: 1306.898 | F91: 312.005 | G91: 56.495 | H91: 237.708 | I91: 31.071 | J91: 2795.361 | K91: 4291.201 | L91: 2013.14 | M91: 22558.955 | N91: 2982.864 | O91: 3570.361 | P91: 349.786 | Q91: 6473.307 | R91: 1480.321 | S91: 184.55 | T91: 95.783 | U91: 378.859 | V91: 164.241 | W91: 143.733 | X91: 1068.697 | Y91: 421.91 | Z91: 74266.668 | AA91: 10021.326 | AB91: 1927.139 | AC91: 1713.18 | AD91: 2309.543 | AE91: 1292.634 | AF91: 560.99 | AG91: 834.198 | AH91: 668.494 | AI91: 5283.898 | AJ91: 234.804 | AK91: 310.735 | AL91: 14821.402 | AM91: 8958.179 | AN91: 9903.702 | AO91: 1145.789 | AP91: 567.669 | AQ91: 12725.16 | AR91: 9315.629 | AS91: 200.573 | AT91: 61.499 | AU91: 504.952 | AV91: 5.294 | AW91: 604.381 | AX91: 314.129 | AY91: 68.557 | AZ91: 210.515 | BA91: 517.018 | BB91: 1225.02 | BC91: 12.37 | BD91: 28.967 | BE91: 6.356 | BF91: 340.468 | BG91: 56.386 | BH91: 82.381 | BI91: 2043.191 | BJ91: 281.85 | BK91: 4.929 | BL91: 1896.396 | BM91: 1161.267 | BN91: 1411.321 | BO91: 62.232 | BP91: 8837.619 | BQ91: 6752.046 | BR91: 8396.388 | BS91: 28.166 | BT91: 747.391 | BU91: 531.37 | BV91: 269.617 | BW91: 581.602 | BX91: 7037.411 | BY91: 6332.317 | BZ91: 183.456 | CA91: 169.508 | CB91: 89.682 | CC91: 0 | CD91: 57185.905 | CE91: 1077797.9 | CF91: 1038457.4 | CG91: 0 | CH91: 39340.29 | CI91: 0 | CJ91: 0.177 | CK91: 0
A92: D.31 - Subsidios a los productos | B92: 90793.994 | C92: =D92-J92 -> 3517.005 | D92: 3519.875 | E92: 0 | F92: 4.544 | G92: 0.115 | H92: 27.098 | I92: 0.022 | J92: 2.87 | K92: 0.213 | L92: 0.205 | M92: 0.196 | N92: 1.533 | O92: 26.393 | P92: 0.143 | Q92: 1.103 | R92: 0.105 | S92: 0.024 | T92: 0.072 | U92: 0.155 | V92: 0.028 | W92: 0.04 | X92: 0.222 | Y92: 0.582 | Z92: 0.053 | AA92: 0.52 | AB92: 0.266 | AC92: 0.301 | AD92: 0.469 | AE92: 0.29 | AF92: 0.382 | AG92: 0.47 | AH92: 0.135 | AI92: 1.453 | AJ92: 0.092 | AK92: 0.116 | AL92: 10.808 | AM92: 177.251 | AN92: 2.785 | AO92: 0.159 | AP92: 28.561 | AQ92: 0.37 | AR92: 0.167 | AS92: 0.44 | AT92: 2.835 | AU92: 0.248 | AV92: 54.938 | AW92: 0.064 | AX92: 0.292 | AY92: 0.132 | AZ92: 0.38 | BA92: 416.203 | BB92: 469.294 | BC92: 0.041 | BD92: 0.204 | BE92: 54.212 | BF92: 683.368 | BG92: 15.574 | BH92: 514.985 | BI92: 5.446 | BJ92: 0.218 | BK92: 0.005 | BL92: 16.094 | BM92: 5.975 | BN92: 19.596 | BO92: 0.134 | BP92: 106.133 | BQ92: 17.676 | BR92: 20.309 | BS92: 0.022 | BT92: 1.016 | BU92: 1.178 | BV92: 3.674 | BW92: 1.782 | BX92: 5.149 | BY92: 0.594 | BZ92: 0.683 | CA92: 1.946 | CB92: 2.289 | CC92: 0 | CD92: 806.435 | CE92: 87274.119 | CF92: 86940.416 | CG92: 0 | CH92: 333.703 | CI92: 0 | CJ92: 0 | CK92: 0
A93: D.21-D.31 - Impuestos sobre los productos, netos | B93: 1303024.8 | C93: =D93-J93 -> 309708.55 | D93: 312501.04 | E93: 1306.898 | F93: 307.461 | G93: 56.38 | H93: 210.61 | I93: 31.049 | J93: 2792.491 | K93: 4290.988 | L93: 2012.935 | M93: 22558.759 | N93: 2981.331 | O93: 3543.968 | P93: 349.643 | Q93: 6472.204 | R93: 1480.216 | S93: 184.526 | T93: 95.711 | U93: 378.704 | V93: 164.213 | W93: 143.693 | X93: 1068.475 | Y93: 421.328 | Z93: 74266.615 | AA93: 10020.806 | AB93: 1926.873 | AC93: 1712.879 | AD93: 2309.074 | AE93: 1292.344 | AF93: 560.608 | AG93: 833.728 | AH93: 668.359 | AI93: 5282.445 | AJ93: 234.712 | AK93: 310.619 | AL93: 14810.594 | AM93: 8780.928 | AN93: 9900.917 | AO93: 1145.63 | AP93: 539.108 | AQ93: 12724.79 | AR93: 9315.462 | AS93: 200.133 | AT93: 58.664 | AU93: 504.704 | AV93: -49.644 | AW93: 604.317 | AX93: 313.837 | AY93: 68.425 | AZ93: 210.135 | BA93: 100.815 | BB93: 755.726 | BC93: 12.329 | BD93: 28.763 | BE93: -47.856 | BF93: -342.9 | BG93: 40.812 | BH93: -432.604 | BI93: 2037.745 | BJ93: 281.632 | BK93: 4.924 | BL93: 1880.302 | BM93: 1155.292 | BN93: 1391.725 | BO93: 62.098 | BP93: 8731.486 | BQ93: 6734.37 | BR93: 8376.079 | BS93: 28.144 | BT93: 746.375 | BU93: 530.192 | BV93: 265.943 | BW93: 579.82 | BX93: 7032.262 | BY93: 6331.723 | BZ93: 182.773 | CA93: 167.562 | CB93: 87.393 | CC93: 0 | CD93: 56379.47 | CE93: 990523.79 | CF93: 951517.03 | CG93: 0 | CH93: 39006.587 | CI93: 0 | CJ93: 0.177 | CK93: 0
A94: UPC - Usos a precios de comprador | B94: 53215495 | C94: =D94-J94 -> 18820604 | D94: 19085597 | E94: 166491.88 | F94: 252936.1 | G94: 6137.07 | H94: 13369.832 | I94: 4480.039 | J94: 264992.61 | K94: 156645.43 | L94: 91215.754 | M94: 278927.69 | N94: 1025386.2 | O94: 354115.28 | P94: 122971.99 | Q94: 1479347.6 | R94: 223993.73 | S94: 66258.5 | T94: 29921.091 | U94: 102224.61 | V94: 52804.247 | W94: 50754.415 | X94: 188303.36 | Y94: 61244.166 | Z94: 834858.12 | AA94: 760172.97 | AB94: 398679.16 | AC94: 240328.66 | AD94: 623430.87 | AE94: 342172.92 | AF94: 392148.03 | AG94: 1507650.4 | AH94: 431512.36 | AI94: 2902990.8 | AJ94: 82464.971 | AK94: 320517.81 | AL94: 626062.23 | AM94: 648843.77 | AN94: 165846.89 | AO94: 30909.971 | AP94: 13163.998 | AQ94: 391714.87 | AR94: 278494.13 | AS94: 13167.815 | AT94: 2368.893 | AU94: 79658.586 | AV94: 935.806 | AW94: 24642.477 | AX94: 35558.921 | AY94: 16094.635 | AZ94: 33649.853 | BA94: 48932.571 | BB94: 190206.11 | BC94: 5152.618 | BD94: 1374.502 | BE94: 5059.089 | BF94: 261678.11 | BG94: 14563.345 | BH94: 203831.15 | BI94: 186828.1 | BJ94: 33268.362 | BK94: 400.259 | BL94: 150167.43 | BM94: 86875.743 | BN94: 226081.16 | BO94: 10800.066 | BP94: 141467.66 | BQ94: 109980.92 | BR94: 175589.12 | BS94: 1820.333 | BT94: 17741.36 | BU94: 15023.726 | BV94: 5255.977 | BW94: 43343.499 | BX94: 151005.66 | BY94: 195232.01 | BZ94: 88786.974 | CA94: 47700.029 | CB94: 26303.388 | CC94: 0 | CD94: 450565.84 | CE94: 34129899 | CF94: 16292903 | CG94: 2721397.8 | CH94: 5572111.5 | CI94: 103964.58 | CJ94: 9439522.4 | CK94: 0
A95: B.1bV - Valor agregado bruto | C95: =D95-J95 -> 22252105 | D95: 22873646 | E95: 516354.55 | F95: 242533.1 | G95: 22690.785 | H95: 9602.663 | I95: 5913.921 | J95: 621540.6 | K95: 265067.55 | L95: 61718.433 | M95: 456907.22 | N95: 1064926.3 | O95: 214062.02 | P95: 181801.25 | Q95: 911713.77 | R95: 240174.37 | S95: 32513.579 | T95: 17328.629 | U95: 71182.811 | V95: 31436.957 | W95: 38837.812 | X95: 101611.97 | Y95: 24643.809 | Z95: 164436.95 | AA95: 356405.6 | AB95: 151603.43 | AC95: 157596.1 | AD95: 257274.88 | AE95: 170712.28 | AF95: 208837.09 | AG95: 409294.66 | AH95: 178614.03 | AI95: 1168500.8 | AJ95: 55539.633 | AK95: 132857.27 | AL95: 2268261.4 | AM95: 2241444.5 | AN95: 63574.495 | AO95: 38500.664 | AP95: 18964.174 | AQ95: 856330.64 | AR95: 451171.37 | AS95: 12751.734 | AT95: 2487.176 | AU95: 154556.62 | AV95: 3961.699 | AW95: 21564.182 | AX95: 29847.125 | AY95: 16348.493 | AZ95: 36940.5 | BA95: 41617.767 | BB95: 266493.91 | BC95: 8319.393 | BD95: 1540.617 | BE95: 38078.365 | BF95: 678782.23 | BG95: 22931.666 | BH95: 146867.75 | BI95: 2036876.9 | BJ95: 34210.342 | BK95: 49572.822 | BL95: 435679.6 | BM95: 126888.46 | BN95: 778751.55 | BO95: 14765.428 | BP95: 877924.17 | BQ95: 245527.75 | BR95: 283184.08 | BS95: 2758.547 | BT95: 16206.956 | BU95: 51526.702 | BV95: 7531.426 | BW95: 56466.616 | BX95: 254701.17 | BY95: 329273.32 | BZ95: 118399.89 | CA95: 175693.32 | CB95: 56696.528 | CC95: 100065.29 | CD95: 855373.41
A96: P.1 - Producción | C96: =D96-J96 -> 41072709 | D96: 41959242 | E96: 682846.43 | F96: 495469.19 | G96: 28827.855 | H96: 22972.495 | I96: 10393.96 | J96: 886533.21 | K96: 421712.98 | L96: 152934.19 | M96: 735834.91 | N96: 2090312.5 | O96: 568177.3 | P96: 304773.24 | Q96: 2391061.4 | R96: 464168.1 | S96: 98772.079 | T96: 47249.72 | U96: 173407.42 | V96: 84241.204 | W96: 89592.227 | X96: 289915.33 | Y96: 85887.975 | Z96: 999295.07 | AA96: 1116578.6 | AB96: 550282.59 | AC96: 397924.76 | AD96: 880705.75 | AE96: 512885.2 | AF96: 600985.12 | AG96: 1916945 | AH96: 610126.4 | AI96: 4071491.5 | AJ96: 138004.6 | AK96: 453375.08 | AL96: 2894323.7 | AM96: 2890288.2 | AN96: 229421.39 | AO96: 69410.635 | AP96: 32128.172 | AQ96: 1248045.5 | AR96: 729665.5 | AS96: 25919.549 | AT96: 4856.069 | AU96: 234215.2 | AV96: 4897.505 | AW96: 46206.659 | AX96: 65406.046 | AY96: 32443.128 | AZ96: 70590.353 | BA96: 90550.338 | BB96: 456700.01 | BC96: 13472.011 | BD96: 2915.119 | BE96: 43137.454 | BF96: 940460.33 | BG96: 37495.011 | BH96: 350698.9 | BI96: 2223705 | BJ96: 67478.704 | BK96: 49973.081 | BL96: 585847.03 | BM96: 213764.2 | BN96: 1004832.7 | BO96: 25565.494 | BP96: 1019391.8 | BQ96: 355508.67 | BR96: 458773.2 | BS96: 4578.88 | BT96: 33948.316 | BU96: 66550.428 | BV96: 12787.403 | BW96: 99810.115 | BX96: 405706.83 | BY96: 524505.33 | BZ96: 207186.86 | CA96: 223393.35 | CB96: 82999.916 | CC96: 100065.29 | CD96: 1305939.3
A97: B.1bP - Producto interno bruto | B97: 24176670 | C97: =D97-J97 -> 22561813 | D97: 23186147 | E97: 517661.45 | F97: 242840.56 | G97: 22747.165 | H97: 9813.273 | I97: 5944.97 | J97: 624333.09 | K97: 269358.54 | L97: 63731.368 | M97: 479465.98 | N97: 1067907.6 | O97: 217605.99 | P97: 182150.89 | Q97: 918185.97 | R97: 241654.59 | S97: 32698.105 | T97: 17424.34 | U97: 71561.515 | V97: 31601.17 | W97: 38981.505 | X97: 102680.45 | Y97: 25065.137 | Z97: 238703.56 | AA97: 366426.41 | AB97: 153530.31 | AC97: 159308.98 | AD97: 259583.95 | AE97: 172004.62 | AF97: 209397.7 | AG97: 410128.39 | AH97: 179282.39 | AI97: 1173783.2 | AJ97: 55774.345 | AK97: 133167.89 | AL97: 2283072 | AM97: 2250225.4 | AN97: 73475.412 | AO97: 39646.294 | AP97: 19503.282 | AQ97: 869055.43 | AR97: 460486.83 | AS97: 12951.867 | AT97: 2545.84 | AU97: 155061.32 | AV97: 3912.055 | AW97: 22168.499 | AX97: 30160.962 | AY97: 16416.918 | AZ97: 37150.635 | BA97: 41718.582 | BB97: 267249.63 | BC97: 8331.722 | BD97: 1569.38 | BE97: 38030.509 | BF97: 678439.33 | BG97: 22972.478 | BH97: 146435.14 | BI97: 2038914.7 | BJ97: 34491.974 | BK97: 49577.746 | BL97: 437559.9 | BM97: 128043.75 | BN97: 780143.28 | BO97: 14827.526 | BP97: 886655.66 | BQ97: 252262.12 | BR97: 291560.16 | BS97: 2786.691 | BT97: 16953.331 | BU97: 52056.894 | BV97: 7797.369 | BW97: 57046.436 | BX97: 261733.43 | BY97: 335605.05 | BZ97: 118582.66 | CA97: 175860.89 | CB97: 56783.921 | CC97: 100065.29 | CD97: 911752.88 | CE97: 990523.79 | CF97: 951517.03 | CG97: 0 | CH97: 39006.587 | CI97: 0 | CJ97: 0.177 | CK97: 0
A98: D.1 - Remuneración de los asalariados | C98: =D98-J98 -> 5942856.8 | D98: 5974564.1 | E98: 81952.982 | F98: 43031.241 | G98: 737.32 | H98: 3298.361 | I98: 1494.103 | J98: 31707.356 | K98: 34467.606 | L98: 5404.55 | M98: 80611.858 | N98: 306662.64 | O98: 47285.398 | P98: 40442.471 | Q98: 101965.91 | R98: 22523.696 | S98: 10797.038 | T98: 6271.621 | U98: 29620.008 | V98: 14107.86 | W98: 10442.215 | X98: 20457.367 | Y98: 10714.06 | Z98: 17586.133 | AA98: 60324.339 | AB98: 45326.683 | AC98: 25120.79 | AD98: 24772.187 | AE98: 53298.487 | AF98: 58863.988 | AG98: 191288.82 | AH98: 59237.737 | AI98: 170394.67 | AJ98: 22042.646 | AK98: 51567.494 | AL98: 92635.907 | AM98: 481440.27 | AN98: 14192.194 | AO98: 4005.537 | AP98: 3476.737 | AQ98: 149044.31 | AR98: 167321.96 | AS98: 2463.319 | AT98: 953.773 | AU98: 28166.273 | AV98: 3663.679 | AW98: 8213.066 | AX98: 14327.91 | AY98: 5852.123 | AZ98: 5883.84 | BA98: 2560.248 | BB98: 49401.885 | BC98: 2601.818 | BD98: 611.295 | BE98: 2586 | BF98: 163352.3 | BG98: 6203.965 | BH98: 33450.742 | BI98: 48351.87 | BJ98: 5260.59 | BK98: 94.009 | BL98: 141873.22 | BM98: 19319.039 | BN98: 489320.16 | BO98: 3815.52 | BP98: 756662.08 | BQ98: 168780.85 | BR98: 249279.04 | BS98: 2222.713 | BT98: 9365.764 | BU98: 16104.22 | BV98: 6455.413 | BW98: 10525.85 | BX98: 49994.966 | BY98: 70204.152 | BZ98: 24456.583 | CA98: 17336.449 | CB98: 25190.881 | CC98: 100065.29 | CD98: 833656.71
A99: D.11 - Sueldos y salarios | C99: =D99-J99 -> 4862177.2 | D99: 4889091.2 | E99: 81952.982 | F99: 42849.339 | G99: 737.32 | H99: 2998.863 | I99: 1285.253 | J99: 26914.038 | K99: 26518.322 | L99: 4641.092 | M99: 74736.36 | N99: 287809.38 | O99: 39374.138 | P99: 37804.952 | Q99: 84080.996 | R99: 17605.641 | S99: 8890.853 | T99: 5342.402 | U99: 24918.473 | V99: 11916.927 | W99: 9376.159 | X99: 15799.88 | Y99: 8776.82 | Z99: 8632.955 | AA99: 36132.604 | AB99: 35322.325 | AC99: 18777.224 | AD99: 16575.587 | AE99: 41773.586 | AF99: 41500.406 | AG99: 145311.2 | AH99: 40696.154 | AI99: 122065.33 | AJ99: 18444.418 | AK99: 40220.072 | AL99: 77519.531 | AM99: 427135.59 | AN99: 12209.939 | AO99: 2960.594 | AP99: 2747.812 | AQ99: 122553.5 | AR99: 155578.3 | AS99: 2074.385 | AT99: 922.676 | AU99: 22181.064 | AV99: 3137.786 | AW99: 5793.328 | AX99: 11651.682 | AY99: 4693.139 | AZ99: 4803.111 | BA99: 2143.51 | BB99: 35973.282 | BC99: 2288.636 | BD99: 426.267 | BE99: 1970 | BF99: 132396.52 | BG99: 5314.071 | BH99: 28196.328 | BI99: 41978.97 | BJ99: 3926.024 | BK99: 84.395 | BL99: 119003.79 | BM99: 10740.822 | BN99: 387623.84 | BO99: 3156.154 | BP99: 638785 | BQ99: 120209.57 | BR99: 152118.75 | BS99: 1826.658 | BT99: 7058.405 | BU99: 15012.547 | BV99: 4789.237 | BW99: 8713.785 | BX99: 41367.996 | BY99: 63216.225 | BZ99: 21037.554 | CA99: 16097.381 | CB99: 23464.444 | CC99: 100065.29 | CD99: 664361.26
A100: D.11_1 - Salarios | C100: =D100-J100 -> 2604615.8 | D100: 2613160 | E100: 81952.982 | F100: 42793.47 | G100: 737.32 | H100: 2891.846 | I100: 1117.799 | J100: 8544.188 | K100: 21819.321 | L100: 3701.432 | M100: 65104.482 | N100: 264066.59 | O100: 25617.465 | P100: 33228.838 | Q100: 62342.684 | R100: 12380.845 | S100: 7456.787 | T100: 4395.376 | U100: 21321.574 | V100: 9963.979 | W100: 8380.144 | X100: 10885.649 | Y100: 6307.537 | Z100: 6296.585 | AA100: 23660.273 | AB100: 25272.132 | AC100: 14587.248 | AD100: 11409.396 | AE100: 28626.519 | AF100: 30211.872 | AG100: 109410.15 | AH100: 30159.433 | AI100: 92633.5 | AJ100: 14601.376 | AK100: 32265.817 | AL100: 63329.159 | AM100: 376259.03 | AN100: 9615.798 | AO100: 1911.636 | AP100: 2323.303 | AQ100: 89600.398 | AR100: 147553.67 | AS100: 1472.71 | AT100: 794.187 | AU100: 12556.525 | AV100: 1960.272 | AW100: 3782.522 | AX100: 7239.35 | AY100: 2750.442 | AZ100: 2917.824 | BA100: 1539.305 | BB100: 26169.241 | BC100: 1706.432 | BD100: 217.394 | BE100: 0 | BF100: 0 | BG100: 0 | BH100: 0 | BI100: 39305.884 | BJ100: 3063.626 | BK100: 84.395 | BL100: 65505.138 | BM100: 276.102 | BN100: 298992.46 | BO100: 2815.676 | BP100: 41941.842 | BQ100: 13016.295 | BR100: 13552.696 | BS100: 952.232 | BT100: 3524.63 | BU100: 10863.134 | BV100: 562.085 | BW100: 6680.732 | BX100: 32316.7 | BY100: 59205.34 | BZ100: 18434.807 | CA100: 14538.441 | CB100: 19618.67 | CC100: 100065.29 | CD100: 0
A101: D.11_2 - Sueldos | C101: =D101-J101 -> 2257561.4 | D101: 2275931.2 | E101: 0 | F101: 55.869 | G101: 0 | H101: 107.017 | I101: 167.454 | J101: 18369.85 | K101: 4699.001 | L101: 939.66 | M101: 9631.878 | N101: 23742.792 | O101: 13756.673 | P101: 4576.114 | Q101: 21738.312 | R101: 5224.796 | S101: 1434.066 | T101: 947.026 | U101: 3596.899 | V101: 1952.948 | W101: 996.015 | X101: 4914.231 | Y101: 2469.283 | Z101: 2336.37 | AA101: 12472.331 | AB101: 10050.193 | AC101: 4189.976 | AD101: 5166.191 | AE101: 13147.067 | AF101: 11288.534 | AG101: 35901.05 | AH101: 10536.721 | AI101: 29431.831 | AJ101: 3843.042 | AK101: 7954.255 | AL101: 14190.372 | AM101: 50876.556 | AN101: 2594.141 | AO101: 1048.958 | AP101: 424.509 | AQ101: 32953.098 | AR101: 8024.64 | AS101: 601.675 | AT101: 128.489 | AU101: 9624.539 | AV101: 1177.514 | AW101: 2010.806 | AX101: 4412.332 | AY101: 1942.697 | AZ101: 1885.287 | BA101: 604.205 | BB101: 9804.041 | BC101: 582.204 | BD101: 208.873 | BE101: 1970 | BF101: 132396.52 | BG101: 5314.071 | BH101: 28196.328 | BI101: 2673.086 | BJ101: 862.398 | BK101: 0 | BL101: 53498.656 | BM101: 10464.72 | BN101: 88631.385 | BO101: 340.478 | BP101: 596843.16 | BQ101: 107193.27 | BR101: 138566.05 | BS101: 874.426 | BT101: 3533.775 | BU101: 4149.413 | BV101: 4227.152 | BW101: 2033.053 | BX101: 9051.296 | BY101: 4010.885 | BZ101: 2602.747 | CA101: 1558.94 | CB101: 3845.774 | CC101: 0 | CD101: 664361.26
A102: D.121 - Contribuciones sociales efectivas de los empleadores | C102: =D102-J102 -> 721349.29 | D102: 721349.29 | E102: 0 | F102: 134.578 | G102: 0 | H102: 193.424 | I102: 155.89 | J102: 0 | K102: 2683.888 | L102: 543.742 | M102: 4721.06 | N102: 13208.656 | O102: 5437.468 | P102: 1845.496 | Q102: 7792.903 | R102: 1766.207 | S102: 1249.81 | T102: 497.838 | U102: 2877.592 | V102: 1426.857 | W102: 738.924 | X102: 2369.619 | Y102: 1195.505 | Z102: 187.578 | AA102: 4839.962 | AB102: 4958.94 | AC102: 2113.412 | AD102: 3395.21 | AE102: 5709.041 | AF102: 8012.015 | AG102: 20521.104 | AH102: 7357.596 | AI102: 20233.586 | AJ102: 2256.041 | AK102: 5285.875 | AL102: 8587.786 | AM102: 34489.729 | AN102: 1196.227 | AO102: 833.202 | AP102: 18.797 | AQ102: 17757.158 | AR102: 7010.961 | AS102: 21.513 | AT102: 18.019 | AU102: 3673.055 | AV102: 516.38 | AW102: 1270.936 | AX102: 1080.858 | AY102: 689.527 | AZ102: 706.848 | BA102: 256.825 | BB102: 6517.641 | BC102: 126.076 | BD102: 98.367 | BE102: 265 | BF102: 17531.329 | BG102: 670.24 | BH102: 2868.132 | BI102: 4174.307 | BJ102: 456.941 | BK102: 8.483 | BL102: 13235.111 | BM102: 2940.951 | BN102: 27795.339 | BO102: 265.859 | BP102: 109787.8 | BQ102: 47694.901 | BR102: 92886.771 | BS102: 356.27 | BT102: 2184.338 | BU102: 893.773 | BV102: 1526.242 | BW102: 1079.377 | BX102: 5894.114 | BY102: 3504.925 | BZ102: 1074.921 | CA102: 951.061 | CB102: 1056.924 | CC102: 0 | CD102: 163666.46
A103: D.122 - Contribuciones sociales imputadas de los empleadores | C103: =D103-J103 -> 359330.33 | D103: 364123.65 | E103: 0 | F103: 47.324 | G103: 0 | H103: 106.074 | I103: 52.96 | J103: 4793.318 | K103: 5265.396 | L103: 219.716 | M103: 1154.438 | N103: 5644.603 | O103: 2473.792 | P103: 792.023 | Q103: 10092.014 | R103: 3151.848 | S103: 656.375 | T103: 431.381 | U103: 1823.943 | V103: 764.076 | W103: 327.132 | X103: 2287.868 | Y103: 741.735 | Z103: 8765.6 | AA103: 19351.773 | AB103: 5045.418 | AC103: 4230.154 | AD103: 4801.39 | AE103: 5815.86 | AF103: 9351.567 | AG103: 25456.52 | AH103: 11183.987 | AI103: 28095.75 | AJ103: 1342.187 | AK103: 6061.547 | AL103: 6528.59 | AM103: 19814.947 | AN103: 786.028 | AO103: 211.741 | AP103: 710.128 | AQ103: 8733.658 | AR103: 4732.694 | AS103: 367.421 | AT103: 13.078 | AU103: 2312.154 | AV103: 9.513 | AW103: 1148.802 | AX103: 1595.37 | AY103: 469.457 | AZ103: 373.881 | BA103: 159.913 | BB103: 6910.962 | BC103: 187.106 | BD103: 86.661 | BE103: 351 | BF103: 13424.442 | BG103: 219.654 | BH103: 2386.282 | BI103: 2198.593 | BJ103: 877.625 | BK103: 1.131 | BL103: 9634.314 | BM103: 5637.266 | BN103: 73900.984 | BO103: 393.507 | BP103: 8089.274 | BQ103: 876.381 | BR103: 4273.525 | BS103: 39.785 | BT103: 123.021 | BU103: 197.9 | BV103: 139.934 | BW103: 732.688 | BX103: 2732.856 | BY103: 3483.002 | BZ103: 2344.108 | CA103: 288.007 | CB103: 669.513 | CC103: 0 | CD103: 5628.988
A104: D.29-D.39 - Impuestos netos de subsidios sobre la producción | C104: =D104-J104 -> 128552 | D104: 130685.83 | E104: 14.564 | F104: 6.923 | G104: 0.675 | H104: 0.636 | I104: 0.091 | J104: 2133.83 | K104: 1039.727 | L104: 367.109 | M104: 5730.517 | N104: 5014.547 | O104: 1516.221 | P104: 733.332 | Q104: 5752.415 | R104: 1081.842 | S104: 237.352 | T104: 113.46 | U104: 416.264 | V104: 202.473 | W104: 215.581 | X104: 696.895 | Y104: 176.93 | Z104: 1379.21 | AA104: 2575.061 | AB104: 1323.485 | AC104: 955.264 | AD104: 2111.198 | AE104: 1231.899 | AF104: 1401.028 | AG104: 4578.872 | AH104: 1466.233 | AI104: 9791.465 | AJ104: 332.12 | AK104: 1086.948 | AL104: 7834.146 | AM104: 10878.935 | AN104: 552.204 | AO104: 167.065 | AP104: 290.527 | AQ104: 2463.883 | AR104: -5966.328 | AS104: 62.298 | AT104: 11.676 | AU104: 563.278 | AV104: 120.278 | AW104: 111.155 | AX104: 153.308 | AY104: 78.038 | AZ104: 165.827 | BA104: 186.414 | BB104: 1098.961 | BC104: 32.423 | BD104: 10.267 | BE104: 79 | BF104: 19653.374 | BG104: 293.732 | BH104: 616.487 | BI104: 4804.923 | BJ104: 162.283 | BK104: 120.289 | BL104: 1287.869 | BM104: 1507.53 | BN104: 2416.36 | BO104: 61.524 | BP104: 3987.759 | BQ104: 1185.668 | BR104: 1368.687 | BS104: 34.09 | BT104: 37.472 | BU104: 134.243 | BV104: 118.725 | BW104: 244.576 | BX104: 1058.294 | BY104: 1324.012 | BZ104: 498.664 | CA104: 314.884 | CB104: 199.784 | CC104: 0 | CD104: 16677.081
A105: D.29_ - Impuestos que gravan la actividad | C105: =D105-J105 -> 136580.78 | D105: 138714.61 | E105: 14.564 | F105: 6.923 | G105: 0.675 | H105: 0.636 | I105: 0.091 | J105: 2133.83 | K105: 1039.727 | L105: 367.109 | M105: 5730.517 | N105: 5014.547 | O105: 1516.221 | P105: 733.332 | Q105: 5752.415 | R105: 1081.842 | S105: 237.352 | T105: 113.46 | U105: 416.264 | V105: 202.473 | W105: 215.581 | X105: 696.895 | Y105: 176.93 | Z105: 1379.21 | AA105: 2575.061 | AB105: 1323.485 | AC105: 955.264 | AD105: 2111.198 | AE105: 1231.899 | AF105: 1401.028 | AG105: 4578.872 | AH105: 1466.233 | AI105: 9791.465 | AJ105: 332.12 | AK105: 1086.948 | AL105: 7834.146 | AM105: 10878.935 | AN105: 552.204 | AO105: 167.065 | AP105: 290.527 | AQ105: 2463.883 | AR105: 1754.646 | AS105: 62.298 | AT105: 11.676 | AU105: 563.278 | AV105: 120.278 | AW105: 111.155 | AX105: 153.308 | AY105: 78.038 | AZ105: 165.827 | BA105: 186.414 | BB105: 1098.961 | BC105: 32.423 | BD105: 10.267 | BE105: 79 | BF105: 19653.374 | BG105: 293.732 | BH105: 616.487 | BI105: 4804.923 | BJ105: 162.283 | BK105: 120.289 | BL105: 1595.669 | BM105: 1507.53 | BN105: 2416.36 | BO105: 61.524 | BP105: 3987.759 | BQ105: 1185.668 | BR105: 1368.687 | BS105: 34.09 | BT105: 37.472 | BU105: 134.243 | BV105: 118.725 | BW105: 244.576 | BX105: 1058.294 | BY105: 1324.012 | BZ105: 498.664 | CA105: 314.884 | CB105: 199.784 | CC105: 0 | CD105: 16677.081
A106: D.39_ - Menos: subsidios | C106: =D106-J106 -> 8028.774 | D106: 8028.774 | E106: 0 | F106: 0 | G106: 0 | H106: 0 | I106: 0 | J106: 0 | K106: 0 | L106: 0 | M106: 0 | N106: 0 | O106: 0 | P106: 0 | Q106: 0 | R106: 0 | S106: 0 | T106: 0 | U106: 0 | V106: 0 | W106: 0 | X106: 0 | Y106: 0 | Z106: 0 | AA106: 0 | AB106: 0 | AC106: 0 | AD106: 0 | AE106: 0 | AF106: 0 | AG106: 0 | AH106: 0 | AI106: 0 | AJ106: 0 | AK106: 0 | AL106: 0 | AM106: 0 | AN106: 0 | AO106: 0 | AP106: 0 | AQ106: 0 | AR106: 7720.974 | AS106: 0 | AT106: 0 | AU106: 0 | AV106: 0 | AW106: 0 | AX106: 0 | AY106: 0 | AZ106: 0 | BA106: 0 | BB106: 0 | BC106: 0 | BD106: 0 | BE106: 0 | BF106: 0 | BG106: 0 | BH106: 0 | BI106: 0 | BJ106: 0 | BK106: 0 | BL106: 307.8 | BM106: 0 | BN106: 0 | BO106: 0 | BP106: 0 | BQ106: 0 | BR106: 0 | BS106: 0 | BT106: 0 | BU106: 0 | BV106: 0 | BW106: 0 | BX106: 0 | BY106: 0 | BZ106: 0 | CA106: 0 | CB106: 0 | CC106: 0 | CD106: 0
A107: B.2b - Excedente bruto de operación | C107: =D107-J107 -> 16180696 | D107: 16768396 | E107: 434387.01 | F107: 199494.93 | G107: 21952.79 | H107: 6303.666 | I107: 4419.727 | J107: 587699.41 | K107: 229560.22 | L107: 55946.774 | M107: 370564.85 | N107: 753249.07 | O107: 165260.4 | P107: 140625.45 | Q107: 803995.44 | R107: 216568.83 | S107: 21479.189 | T107: 10943.548 | U107: 41146.539 | V107: 17126.624 | W107: 28180.016 | X107: 80457.71 | Y107: 13752.819 | Z107: 145471.6 | AA107: 293506.2 | AB107: 104953.26 | AC107: 131520.05 | AD107: 230391.49 | AE107: 116181.89 | AF107: 148572.08 | AG107: 213426.96 | AH107: 117910.06 | AI107: 988314.62 | AJ107: 33164.867 | AK107: 80202.828 | AL107: 2167791.4 | AM107: 1749125.3 | AN107: 48830.097 | AO107: 34328.062 | AP107: 15196.91 | AQ107: 704822.45 | AR107: 289815.74 | AS107: 10226.117 | AT107: 1521.727 | AU107: 125827.07 | AV107: 177.742 | AW107: 13239.961 | AX107: 15365.907 | AY107: 10418.332 | AZ107: 30890.833 | BA107: 38871.105 | BB107: 215993.06 | BC107: 5685.152 | BD107: 919.055 | BE107: 35413.365 | BF107: 495776.56 | BG107: 16433.969 | BH107: 112800.52 | BI107: 1983720.1 | BJ107: 28787.469 | BK107: 49358.524 | BL107: 292518.51 | BM107: 106061.89 | BN107: 287015.03 | BO107: 10888.384 | BP107: 117274.34 | BQ107: 75561.234 | BR107: 32536.35 | BS107: 501.744 | BT107: 6803.72 | BU107: 35288.239 | BV107: 957.288 | BW107: 45696.19 | BX107: 203647.91 | BY107: 257745.16 | BZ107: 93444.642 | CA107: 158041.99 | CB107: 31305.863 | CC107: 0 | CD107: 5039.62
A108: PT - Puestos de trabajo | C108: =D108-J108 -> 59467002 | D108: 59505022 | E108: 6412119 | F108: 1204660 | G108: 72310 | H108: 179676 | I108: 20080 | J108: 38020 | K108: 198950 | L108: 24322 | M108: 215438 | N108: 3388685 | O108: 485188 | P108: 1122289 | Q108: 1728806 | R108: 182083 | S108: 133466 | T108: 225523 | U108: 596975 | V108: 187414 | W108: 197584 | X108: 149383 | Y108: 114009 | Z108: 29875 | AA108: 215415 | AB108: 279254 | AC108: 391866 | AD108: 94523 | AE108: 561602 | AF108: 318587 | AG108: 917547 | AH108: 340577 | AI108: 896614 | AJ108: 374427 | AK108: 526211 | AL108: 1594832 | AM108: 9973725 | AN108: 33574 | AO108: 11382 | AP108: 7646 | AQ108: 1099711 | AR108: 1592721 | AS108: 4097 | AT108: 19490 | AU108: 180047 | AV108: 14929 | AW108: 60933 | AX108: 152695 | AY108: 35089 | AZ108: 38582 | BA108: 22781 | BB108: 113906 | BC108: 11214 | BD108: 3843 | BE108: 3317 | BF108: 214283 | BG108: 13362 | BH108: 135021 | BI108: 610938 | BJ108: 108525 | BK108: 779 | BL108: 988290 | BM108: 41691 | BN108: 5028012 | BO108: 104238 | BP108: 2572328 | BQ108: 782009 | BR108: 614384 | BS108: 32812 | BT108: 204921 | BU108: 168594 | BV108: 17687 | BW108: 171118 | BX108: 582491 | BY108: 2627312 | BZ108: 1166324 | CA108: 1120214 | CB108: 310459 | CC108: 2374735 | CD108: 2716503
A109: PTDRS - Puestos de trabajo dependientes de la razón social | C109: =D109-J109 -> 58479111 | D109: 58517123 | E109: 6412119 | F109: 1204660 | G109: 72310 | H109: 179676 | I109: 19152 | J109: 38012 | K109: 197426 | L109: 23620 | M109: 214478 | N109: 3359925 | O109: 478984 | P109: 1118666 | Q109: 1722825 | R109: 179629 | S109: 132957 | T109: 225043 | U109: 594172 | V109: 184682 | W109: 196113 | X109: 148589 | Y109: 112096 | Z109: 29794 | AA109: 213674 | AB109: 277855 | AC109: 387787 | AD109: 90651 | AE109: 551546 | AF109: 303835 | AG109: 897834 | AH109: 325693 | AI109: 875587 | AJ109: 372105 | AK109: 520100 | AL109: 1558759 | AM109: 9656826 | AN109: 33447 | AO109: 11361 | AP109: 7608 | AQ109: 1095705 | AR109: 1586404 | AS109: 4093 | AT109: 19010 | AU109: 176598 | AV109: 14929 | AW109: 60933 | AX109: 150853 | AY109: 32818 | AZ109: 33898 | BA109: 19632 | BB109: 106907 | BC109: 10744 | BD109: 3488 | BE109: 3317 | BF109: 204216 | BG109: 12973 | BH109: 114758 | BI109: 590784 | BJ109: 105686 | BK109: 761 | BL109: 946614 | BM109: 41505 | BN109: 4997262 | BO109: 104040 | BP109: 2430209 | BQ109: 758231 | BR109: 603900 | BS109: 31386 | BT109: 202487 | BU109: 162651 | BV109: 17096 | BW109: 162274 | BX109: 577870 | BY109: 2584814 | BZ109: 1135737 | CA109: 1095123 | CB109: 296583 | CC109: 2374735 | CD109: 2716503
... A115: PHOCSS - Personal no dependiente de la razón social, personal por honorarios o comisiones s/sueldo | C115: =D115-J115 -> 987891 | D115: 987899 | E115: 0 | F115: 0 | G115: 0 | H115: 0 | I115: 928 | J115: 8 | K115: 1524 | L115: 702 | M115: 960 | N115: 28760 | O115: 6204 | P115: 3623 | Q115: 5981 | R115: 2454 | S115: 509 | T115: 480 | U115: 2803 | V115: 2732 | W115: 1471 | X115: 794 | Y115: 1913 | Z115: 81 | AA115: 1741 | AB115: 1399 | AC115: 4079 | AD115: 3872 | AE115: 10056 | AF115: 14752 | AG115: 19713 | AH115: 14884 | AI115: 21027 | AJ115: 2322 | AK115: 6111 | AL115: 36073 | AM115: 316899 | AN115: 127 | AO115: 21 | AP115: 38 | AQ115: 4006 | AR115: 6317 | AS115: 4 | AT115: 480 | AU115: 3449 | AV115: 0 | AW115: 0 | AX115: 1842 | AY115: 2271 | AZ115: 4684 | BA115: 3149 | BB115: 6999 | BC115: 470 | BD115: 355 | BE115: 0 | BF115: 10067 | BG115: 389 | BH115: 20263 | BI115: 20154 | BJ115: 2839 | BK115: 18 | BL115: 41676 | BM115: 186 | BN115: 30750 | BO115: 198 | BP115: 142119 | BQ115: 23778 | BR115: 10484 | BS115: 1426 | BT115: 2434 | BU115: 5943 | BV115: 591 | BW115: 8844 | BX115: 4621 | BY115: 42498 | BZ115: 30587 | CA115: 25091 | CB115: 13876 | CC115: 0 | CD115: 0
A117: share of domestic materials in total materials | B117: lambda | C117: =1-C90/(C85+C90) -> 0.61705597 | D117: =1-D90/(D85+D90) -> 0.6184699 | E117: =1-E90/E94 -> 0.66369591 | F117: =1-F90/F94 -> 0.95503586 | G117: =1-G90/G94 -> 0.81378589 | H117: =1-H90/H94 -> 0.82212147 | I117: =1-I90/I94 -> 0.76395429 | J117: =1-J90/(J85+J90) -> 0.718291 | K117: =1-K90/K94 -> 0.76530791 | L117: =1-L90/L94 -> 0.74444955 | M117: =1-M90/M94 -> 0.62903849 | N117: =1-N90/N94 -> 0.84455286 | O117: =1-O90/O94 -> 0.89554482 | P117: =1-P90/P94 -> 0.74424829 | Q117: =1-Q90/Q94 -> 0.80527723 | R117: =1-R90/R94 -> 0.74147857 | ... CK117: =1-CK90/CK94 -> #DIV/0!
A118: share of intermediate goods | B118: alpha_M | C118: =C94/C96 -> 0.45822651 | D118: =D94/D96 -> 0.45486037 | E118: =E94/E96 -> 0.24382038 | F118: =F94/F96 -> 0.51049813 | G118: =G94/G96 -> 0.21288681 | H118: =H94/H96 -> 0.58199303 | I118: =I94/I96 -> 0.43102331 | J118: =J94/J96 -> 0.29890884 | ... CD118: =CD94/CD96 -> 0.34501287
A119: labor share | B119: alpha_L | C119: =C98/C96 -> 0.14469113 | D119: =D98/D96 -> 0.14238971 | E119: =E98/E96 -> 0.12001671 | F119: =F98/F96 -> 0.086849479 | G119: =G98/G96 -> 0.025576651 | H119: =H98/H96 -> 0.1435787 | I119: =I98/I96 -> 0.14374723 | J119: =J98/J96 -> 0.035765559 | ... CD119: =CD98/CD96 -> 0.63835795
A120: capital share | B120: alpha_K | C120: =1-C119-C118 -> 0.39708236 | D120: =1-D119-D118 -> 0.40274992 | E120: =1-E119-E118 -> 0.63616291 | F120: =1-F119-F118 -> 0.40265239 | G120: =1-G119-G118 -> 0.76153654 | H120: =1-H119-H118 -> 0.27442827 | I120: =1-I119-I118 -> 0.42522946 | J120: =1-J119-J118 -> 0.6653256 | ... CD120: =1-CD119-CD118 -> 0.016629182
A121: aPrecios F.O.B. | C121: =C98/C95 -> 0.26706942 | D121: =D98/D95 -> 0.2611986 | E121: =E98/E95 -> 0.15871455 | F121: =F98/F95 -> 0.1774242 | G121: =G98/G95 -> 0.032494248 | H121: =H98/H95 -> 0.34348399 | I121: =I98/I95 -> 0.25264169 | J121: =J98/J95 -> 0.051014135 | ... CD121: =CD98/CD95 -> 0.97461144
A122: Fuente: INEGI. Sistema de Cuentas Nacionales de México. Matriz de Insumo Producto
I125: PEMEX | J125: 2018 statements
I126: cash | J126: 81912409 | K126: thousands of pesos
I127: sales | J127: 1681119150 | K127: thousands of pesos
I128: debt to suppliers | J128: 149842712 | K128: thousands of pesos
I129: cost of sales | J129: 1199511561 | K129: thousands of pesos
I131: cash | J131: =J126/1000 -> 81912.409 | K131: million pesos
I132: sales | J132: =J127/1000 -> 1681119.1 | K132: million pesos
H133: 7612837 | I133: debt to suppliers | J133: =J128/1000 -> 149842.71 | K133: million pesos
H134: 60941810 | I134: cost of sales | J134: =J129/1000 -> 1199511.6 | K134: million pesos
I135: cash/GDP | J135: =J131/J97 -> 0.13119985
I136: cahs/sales | J136: =J131/J132 -> 0.048724928
G137: =H137/H139 -> 0.44343551 | H137: =H133/H134 -> 0.12491977 | I137: directly theta? | J137: =J133/J134 -> 0.12491977 | L137: 0.7 in model
H139: =(1-J117) -> 0.281709

Sheet Domestic Technical Coefficients
A1: Instituto Nacional de Estadística y Geografía (INEGI).
A2: Sistema de Cuentas Nacionales de México. Matriz de Insumo Producto simétrica, Base 2018
A3: Matriz simétrica de insumo producto. Industria por industria/ Economía total / Origen doméstico coeficientes técnicos/ Subsector SCIAN
A5: Concepto | B5: 111 - Agricultura | C5: 112 - Cría y explotación de animales | D5: 113 - Aprovechamiento forestal | E5: 114 - Pesca, caza y captura | F5: 115 - Servicios relacionados con las actividades agropecuarias y forestales | G5: 211 - Extracción de petróleo y gas | H5: 212 - Minería de minerales metálicos y no metálicos, excepto petróleo y gas | I5: 213 - Servicios relacionados con la minería | J5: 221 - Generación, transmisión, distribución y comercialización de energía eléctrica, suministro de agua y de gas natural por ductos al consumidor final | K5: 236 - Edificación | L5: 237 - Construcción de obras de ingeniería civil | M5: 238 - Trabajos especializados para la construcción | N5: 311 - Industria alimentaria | O5: 312 - Industria de las bebidas y del tabaco | P5: 313 - Fabricación de insumos textiles y acabado de textiles | Q5: 314 - Fabricación de productos textiles, excepto prendas de vestir | R5: 315 - Fabricación de prendas de vestir | S5: 316 - Curtido y acabado de cuero y piel, y fabricación de productos de cuero, piel y materiales sucedáneos | T5: 321 - Industria de la madera | U5: 322 - Industria del papel | V5: 323 - Impresión e industrias conexas | W5: 324 - Fabricación de productos derivados del petróleo y del carbón | X5: 325 - Industria química | Y5: 326 - Industria del plástico y del hule | Z5: 327 - Fabricación de productos a base de minerales no metálicos | AA5: 331 - Industrias metálicas básicas | AB5: 332 - Fabricación de productos metálicos | AC5: 333 - Fabricación de maquinaria y equipo | AD5: 334 - Fabricación de equipo de computación, comunicación, medición y de otros equipos, componentes y accesorios electrónicos | AE5: 335 - Fabricación de accesorios, aparatos eléctricos y equipo de generación de energía eléctrica | AF5: 336 - Fabricación de equipo de transporte | AG5: 337 - Fabricación de muebles, colchones y persianas | AH5: 339 - Otras industrias manufactureras | AI5: 431 - Comercio al por mayor de abarrotes, alimentos, bebidas, hielo y tabaco | AJ5: 461 - Comercio al por menor de abarrotes, alimentos, bebidas, hielo y tabaco | AK5: 481 - Transporte aéreo | AL5: 482 - Transporte por ferrocarril | AM5: 483 - Transporte por agua | AN5: 484 - Autotransporte de carga | AO5: 485 - Transporte terrestre de pasajeros, excepto por ferrocarril | AP5: 486 - Transporte por ductos | AQ5: 487 - Transporte turístico | AR5: 488 - Servicios relacionados con el transporte | AS5: 491 - Servicios postales | AT5: 492 - Servicios de mensajería y paquetería | AU5: 493 - Servicios de almacenamiento | AV5: 511 - Edición de periódicos, revistas, libros, software y otros materiales, y edición de estas publicaciones integrada con la impresión | AW5: 512 - Industria fílmica y del video, e industria del sonido | AX5: 515 - Radio y televisión | AY5: 517 - Telecomunicaciones | AZ5: 518 - Procesamiento electrónico de información, hospedaje y otros servicios relacionados | BA5: 519 - Otros servicios de información | BB5: 521 - Banca central | BC5: 522 - Instituciones de intermediación crediticia y financiera no bursátil | BD5: 523 - Actividades bursátiles, cambiarias y de inversión financiera | BE5: 524 - Compañías de seguros, fianzas, y administración de fondos para el retiro | BF5: 531 - Servicios inmobiliarios | BG5: 532 - Servicios de alquiler de bienes muebles | BH5: 533 - Servicios de alquiler de marcas registradas, patentes y franquicias | BI5: 541 - Servicios profesionales, científicos y técnicos | BJ5: 551 - Corporativos | BK5: 561 - Servicios de apoyo a los negocios | BL5: 562 - Manejo de residuos y servicios de remediación | BM5: 611 - Servicios educativos | BN5: 621 - Servicios médicos de consulta externa y servicios relacionados | BO5: 622 - Hospitales | BP5: 623 - Residencias de asistencia social y para el cuidado de la salud | BQ5: 624 - Otros servicios de asistencia social | BR5: 711 - Servicios artísticos, culturales y deportivos, y otros servicios relacionados | BS5: 712 - Museos, sitios históricos, zoológicos y similares | BT5: 713 - Servicios de entretenimiento en instalaciones recreativas y otros servicios recreativos | BU5: 721 - Servicios de alojamiento temporal | BV5: 722 - Servicios de preparación de alimentos y bebidas | BW5: 811 - Servicios de reparación y mantenimiento | BX5: 812 - Servicios personales | BY5: 813 - Asociaciones y organizaciones | BZ5: 814 - Hogares con empleados domésticos | CA5: 931 - Actividades legislativas, gubernamentales y de impartición de justicia
A6: 111 - Agricultura | B6: 0.019041663 | C6: 0.11379988 | D6: 0.0061249441 | E6: 0.00051679193 | F6: 0.030232558 | G6: 0 | H6: 0 | I6: 0 | J6: 0 | K6: 1.6611392e-05 | L6: 0.0023882351 | M6: 2.7039776e-05 | N6: 0.073765619 | O6: 0.055353071 | P6: 0.11208537 | Q6: 0 | R6: 0.002743412 | S6: 1.792472e-06 | T6: 0.0047115248 | U6: 1.8150127e-05 | V6: 0 | W6: 0 | X6: 0.0011899324 | Y6: 0.00062024859 | Z6: 5.4080576e-06 | AA6: 0 | AB6: 0 | AC6: 0 | AD6: 0 | AE6: 0 | AF6: 0 | AG6: 0 | AH6: 0.00036687945 | AI6: 0 | AJ6: 4.8784062e-08 | AK6: 0 | AL6: 0 | AM6: 0 | AN6: 0 | AO6: 0 | AP6: 0 | AQ6: 0 | AR6: 0 | AS6: 0 | AT6: 0 | AU6: 0 | AV6: 0 | AW6: 0 | AX6: 5.5217905e-08 | AY6: 0 | AZ6: 0 | BA6: 3.4303917e-07 | BB6: 0 | BC6: 0 | BD6: 0 | BE6: 0 | BF6: 6.295799e-09 | BG6: 0 | BH6: 0 | BI6: 1.1282809e-06 | BJ6: 0 | BK6: 1.9346504e-06 | BL6: 0 | BM6: 2.6908201e-06 | BN6: 2.8409996e-07 | BO6: 0.0012339953 | BP6: 0.010726204 | BQ6: 0.0076923403 | BR6: 0 | BS6: 0 | BT6: 8.5161709e-07 | BU6: 0.02535875 | BV6: 0.04171472 | BW6: 4.8265608e-09 | BX6: 5.8694674e-05 | BY6: 0.0024420748 | BZ6: 0 | CA6: 3.1286294e-05
A7: 112 - Cría y explotación de animales | B7: 0.0073783822 | C7: 0.023237824 | D7: 0 | E7: 0 | F7: 0 | G7: 9.0239146e-09 | H7: 2.371281e-09 | I7: 7.8465124e-08 | J7: 2.718001e-09 | K7: 0.00029611697 | L7: 1.760014e-08 | M7: 3.6092408e-08 | N7: 0.14535202 | O7: 7.2107497e-06 | P7: 0.0059721432 | Q7: 0 | R7: 5.7667659e-09 | S7: 0 | T7: 0 | U7: 3.449283e-09 | V7: 1.1643073e-08 | W7: 0 | X7: 0.00025776869 | Y7: 3.6344962e-09 | Z7: 0 | AA7: 1.135453e-09 | AB7: 1.9497541e-09 | AC7: 1.6639347e-09 | AD7: 1.0433267e-09 | AE7: 0 | AF7: 5.157815e-09 | AG7: 7.2461351e-09 | AH7: 0.00038648794 | AI7: 9.3286042e-09 | AJ7: 1.5223395e-08 | AK7: 4.3587915e-09 | AL7: 0 | AM7: 0 | AN7: 0 | AO7: 5.481964e-09 | AP7: 0 | AQ7: 0 | AR7: 4.2695776e-09 | AS7: 0 | AT7: 0 | AU7: 3.0578213e-08 | AV7: 0 | AW7: 1.9832738e-07 | AX7: 1.2479247e-06 | AY7: 3.0654696e-08 | AZ7: 0 | BA7: 1.2692449e-05 | BB7: 0 | BC7: 1.16964e-08 | BD7: 0 | BE7: 5.7028978e-09 | BF7: 1.7718177e-07 | BG7: 0 | BH7: 0 | BI7: 3.4138605e-09 | BJ7: 9.3561035e-09 | BK7: 5.2269397e-05 | BL7: 0 | BM7: 7.5535234e-08 | BN7: 7.7916524e-06 | BO7: 0.00061925805 | BP7: 0.0045912974 | BQ7: 0.00086658201 | BR7: 0 | BS7: 0 | BT7: 2.3103871e-05 | BU7: 4.9296681e-09 | BV7: 0.0024306083 | BW7: 2.220218e-07 | BX7: 1.4118594e-05 | BY7: 1.2048205e-08 | BZ7: 0 | CA7: 2.5261512e-06
A8: 113 - Aprovechamiento forestal | B8: 0 | C8: 0 | D8: 0.043810405 | E8: 0 | F8: 5.4839541e-06 | G8: 0 | H8: 1.5911296e-06 | I8: 0 | J8: 0 | K8: 0 | L8: 0 | M8: 0 | N8: 0.00031678359 | O8: 0 | P8: 0 | Q8: 0 | R8: 0 | S8: 0.0013889284 | T8: 0.17273884 | U8: 0.0040439428 | V8: 0 | W8: 0 | X8: 0.0030286404 | Y8: 0.0012126951 | Z8: 0.00016496837 | AA8: 0 | AB8: 0 | AC8: 0 | AD8: 0 | AE8: 0 | AF8: 0 | AG8: 0.0045173276 | AH8: 0.0015624569 | AI8: 0 | AJ8: 0 | AK8: 0 | AL8: 0 | AM8: 0 | AN8: 0 | AO8: 0 | AP8: 0 | AQ8: 0 | AR8: 0 | AS8: 0 | AT8: 0 | AU8: 0 | AV8: 0 | AW8: 0 | AX8: 0 | AY8: 0 | AZ8: 0 | BA8: 0 | BB8: 0 | BC8: 0 | BD8: 0 | BE8: 0 | BF8: 0 | BG8: 0 | BH8: 0 | BI8: 1.3655442e-08 | BJ8: 0 | BK8: 0 | BL8: 0 | BM8: 9.8097706e-09 | BN8: 0 | BO8: 0 | BP8: 0 | BQ8: 0 | BR8: 0 | BS8: 0 | BT8: 0 | BU8: 0 | BV8: 0 | BW8: 0 | BX8: 0 | BY8: 0 | BZ8: 0 | CA8: 0
A9: 114 - Pesca, caza y captura | B9: 0 | C9: 6.4585247e-08 | D9: 5.8970742e-07 | E9: 0.00070305816 | F9: 6.7346805e-07 | G9: 2.4138971e-06 | H9: 8.2283452e-07 | I9: 2.0937111e-05 | J9: 5.1098418e-07 | K9: 2.6407535e-06 | L9: 4.0726724e-06 | M9: 8.2914104e-06 | N9: 0.0020329177 | O9: 3.1885e-07 | P9: 6.0745912e-07 | Q9: 1.1851922e-06 | R9: 1.0034173e-06 | S9: 4.9856837e-07 | T9: 5.4692245e-07 | U9: 2.9280963e-05 | V9: 1.420455e-06 | W9: 1.6011287e-08 | X9: 3.9495653e-07 | Y9: 5.9969188e-07 | Z9: 4.2972948e-07 | AA9: 2.5888329e-07 | AB9: 5.985745e-07 | AC9: 4.6756565e-07 | AD9: 3.2708293e-07 | AE9: 2.4421169e-07 | AF9: 1.0885446e-06 | AG9: 9.709821e-07 | AH9: 2.8894398e-07 | AI9: 1.4248579e-06 | AJ9: 2.2440668e-06 | AK9: 4.5331432e-07 | AL9: 5.9068758e-07 | AM9: 6.2250663e-07 | AN9: 5.0478928e-08 | AO9: 8.4833392e-07 | AP9: 3.0864735e-07 | AQ9: 6.1778364e-07 | AR9: 8.5818511e-07 | AS9: 8.167424e-07 | AT9: 4.3283805e-07 | AU9: 3.59294e-06 | AV9: 8.9387189e-07 | AW9: 6.5589699e-06 | AX9: 1.3694041e-06 | AY9: 4.1011604e-06 | AZ9: 8.9073561e-07 | BA9: 4.4595092e-06 | BB9: 4.6363422e-08 | BC9: 1.8182585e-06 | BD9: 2.0802768e-06 | BE9: 6.5583325e-07 | BF9: 2.7161876e-07 | BG9: 1.2744762e-06 | BH9: 4.0021547e-08 | BI9: 1.2665422e-06 | BJ9: 1.2303276e-06 | BK9: 7.2250832e-07 | BL9: 5.4761312e-07 | BM9: 1.6637371e-06 | BN9: 4.5962311e-06 | BO9: 1.4865733e-06 | BP9: 6.1150325e-06 | BQ9: 5.3021776e-06 | BR9: 1.1720436e-06 | BS9: 3.5972902e-05 | BT9: 3.4265064e-06 | BU9: 0.001620197 | BV9: 0.0010814151 | BW9: 2.3505351e-06 | BX9: 2.6858454e-06 | BY9: 2.939762e-06 | BZ9: 0 | CA9: 4.2329687e-06
A10: 115 - Servicios relacionados con las actividades agropecuarias y forestales | B10: 0.0056527395 | C10: 0.0014727515 | D10: 0.0026827872 | E10: 0.0008452717 | F10: 2.5110737e-05 | G10: 1.8047829e-08 | H10: 7.1138431e-09 | I10: 6.5387604e-09 | J10: 6.7950024e-09 | K10: 1.0763941e-07 | L10: 3.6960294e-08 | M10: 1.9686768e-08 | N10: 0.0017167226 | O10: 2.5852703e-08 | P10: 0.0053405275 | Q10: 4.2328293e-08 | R10: 0.0012972398 | S10: 1.1870676e-08 | T10: 2.2323365e-08 | U10: 3.449283e-08 | V10: 3.492922e-08 | W10: 1.4009876e-08 | X10: 3.7614908e-08 | Y10: 2.907597e-08 | Z10: 2.5130379e-08 | AA10: 2.4979966e-08 | AB10: 2.9246311e-08 | AC10: 2.4959021e-08 | AD10: 1.1476594e-08 | AE10: 1.9668056e-08 | AF10: 3.8315197e-08 | AG10: 2.898454e-08 | AH10: 1.7910115e-06 | AI10: 2.418527e-08 | AJ10: 1.6953326e-08 | AK10: 1.7435166e-08 | AL10: 1.4407014e-08 | AM10: 0 | AN10: 6.4100226e-09 | AO10: 6.852455e-09 | AP10: 0 | AQ10: 0 | AR10: 8.5391553e-09 | AS10: 0 | AT10: 2.1641902e-08 | AU10: 0 | AV10: 0 | AW10: 3.1165732e-07 | AX10: 1.1043581e-08 | AY10: 1.3137727e-08 | AZ10: 0 | BA10: 0 | BB10: 2.3181711e-08 | BC10: 1.4142011e-07 | BD10: 8.0010645e-08 | BE10: 2.8514489e-09 | BF10: 7.6448988e-09 | BG10: 2.9638981e-08 | BH10: 0 | BI10: 5.9742558e-08 | BJ10: 4.6780517e-09 | BK10: 2.1894192e-08 | BL10: 0 | BM10: 9.2211844e-08 | BN10: 5.3444547e-08 | BO10: 7.4110693e-08 | BP10: 0 | BQ10: 0 | BR10: 0 | BS10: 7.8201962e-08 | BT10: 2.0038049e-08 | BU10: 1.232417e-08 | BV10: 2.8598375e-08 | BW10: 2.4132804e-08 | BX10: 4.4764089e-09 | BY10: 5.5421743e-07 | BZ10: 0 | CA10: 4.3263881e-07
A11: 211 - Extracción de petróleo y gas | B11: 6.4685115e-06 | C11: 1.6261354e-05 | D11: 4.1279519e-06 | E11: 9.4896092e-06 | F11: 8.0816166e-06 | G11: 4.0912173e-06 | H11: 4.1473706e-06 | I11: 5.8979618e-06 | J11: 4.4072386e-06 | K11: 1.6879294e-05 | L11: 8.5343078e-06 | M11: 8.845921e-06 | N11: 1.4261867e-05 | O11: 7.4154169e-06 | P11: 8.6360438e-06 | Q11: 1.4264635e-05 | R11: 8.2637755e-06 | S11: 1.0232522e-05 | T11: 1.1730928e-05 | U11: 1.731885e-05 | V11: 1.5764721e-05 | W11: 0.28103963 | X11: 0.099700387 | Y11: 1.5150397e-05 | Z11: 1.3213553e-05 | AA11: 1.383436e-05 | AB11: 1.4915619e-05 | AC11: 1.4321486e-05 | AD11: 6.3048235e-06 | AE11: 1.0520771e-05 | AF11: 1.6730724e-05 | AG11: 1.449227e-05 | AH11: 6.6920308e-06 | AI11: 1.4442061e-06 | AJ11: 6.8609074e-07 | AK11: 8.4691319e-06 | AL11: 3.4720904e-06 | AM11: 4.793301e-06 | AN11: 3.4894561e-06 | AO11: 4.3773482e-06 | AP11: 4.9383575e-06 | AQ11: 3.9126297e-06 | AR11: 6.5367234e-06 | AS11: 8.167424e-07 | AT11: 6.3843612e-06 | AU11: 2.7979065e-06 | AV11: 2.0343291e-06 | AW11: 2.1957675e-06 | AX11: 2.2749777e-06 | AY11: 5.4105538e-06 | AZ11: 2.5979789e-06 | BA11: 1.0291175e-06 | BB11: 3.2222579e-06 | BC11: 1.3163766e-06 | BD11: 1.1734895e-06 | BE11: 2.4237316e-07 | BF11: 1.054996e-06 | BG11: 1.2744762e-05 | BH11: 1.0005387e-07 | BI11: 3.4445852e-06 | BJ11: 1.3145325e-06 | BK11: 3.7011136e-06 | BL11: 7.6274685e-06 | BM11: 1.5931067e-06 | BN11: 6.7846446e-06 | BO11: 9.7520953e-06 | BP11: 8.9541547e-06 | BQ11: 8.8664192e-06 | BR11: 3.2306329e-06 | BS11: 5.1613295e-06 | BT11: 7.2938499e-06 | BU11: 5.762782e-06 | BV11: 7.8493006e-06 | BW11: 9.5517639e-06 | BX11: 3.120057e-06 | BY11: 6.0241025e-06 | BZ11: 0 | CA11: 2.2573791e-06
A12: 212 - Minería de minerales metálicos y no metálicos, excepto petróleo y gas | B12: 0.00075139296 | C12: 0.00040295745 | D12: 0.00054599969 | E12: 0.00059423236 | F12: 0.00019434364 | G12: 0.00083997755 | H12: 0.0098084104 | I12: 0.0021631985 | J12: 0.014855425 | K12: 0.012481808 | L12: 0.025359744 | M12: 0.016239175 | N12: 0.00031681287 | O12: 0.0017453828 | P12: 1.4508149e-05 | Q12: 4.3428829e-05 | R12: 2.5148866e-05 | S12: 2.7480614e-05 | T12: 2.8484614e-05 | U12: 0.00060830865 | V12: 7.2105554e-05 | W12: 0.00078893414 | X12: 0.00422075 | Y12: 0.00021455885 | Z12: 0.14647051 | AA12: 0.21678141 | AB12: 0.001275726 | AC12: 3.1328563e-05 | AD12: 2.1905688e-05 | AE12: 0.00012061927 | AF12: 9.8148552e-05 | AG12: 1.6513942e-05 | AH12: 0.0012621624 | AI12: 6.2289163e-05 | AJ12: 6.3354581e-05 | AK12: 4.6177037e-05 | AL12: 0.00042561201 | AM12: 4.0151677e-05 | AN12: 0.00015296237 | AO12: 0.00049368101 | AP12: 0.00084438198 | AQ12: 0.00039723488 | AR12: 0.00014908511 | AS12: 5.9213824e-06 | AT12: 0.00075688225 | AU12: 7.0926165e-05 | AV12: 3.6402162e-05 | AW12: 0.0002044472 | AX12: 0.0002180776 | AY12: 0.00035334792 | AZ12: 9.7684006e-05 | BA12: 0.00017494998 | BB12: 7.6499647e-07 | BC12: 3.6308815e-05 | BD12: 6.824908e-05 | BE12: 1.5126937e-05 | BF12: 8.5954296e-05 | BG12: 0.00022272212 | BH12: 2.9215729e-06 | BI12: 0.00011123552 | BJ12: 1.8422168e-05 | BK12: 5.7549878e-05 | BL12: 4.6390655e-05 | BM12: 0.00011953794 | BN12: 0.0003642696 | BO12: 9.6298126e-05 | BP12: 0.00055035292 | BQ12: 0.0003748345 | BR12: 3.2982508e-05 | BS12: 0.00016797781 | BT12: 0.0002210798 | BU12: 0.00011771801 | BV12: 0.0001478555 | BW12: 1.3031714e-05 | BX12: 9.587125e-05 | BY12: 0.00023683156 | BZ12: 0 | CA12: 0.00033834652
A13: 213 - Servicios relacionados con la minería | B13: 0 | C13: 1.4128023e-08 | D13: 7.9783945e-07 | E13: 4.7883349e-07 | F13: 4.8104861e-07 | G13: 0.0035008784 | H13: 0.00071178032 | I13: 0.00028719543 | J13: 4.8516317e-07 | K13: 3.4358499e-06 | L13: 5.4366832e-06 | M13: 1.0683353e-05 | N13: 3.7640189e-08 | O13: 3.447027e-08 | P13: 7.087023e-08 | Q13: 2.1164147e-07 | R13: 1.6723621e-07 | S13: 8.3094729e-08 | T13: 1.5626356e-07 | U13: 3.035369e-07 | V13: 6.0543982e-07 | W13: 9.0063488e-09 | X13: 1.4239929e-07 | Y13: 1.7263857e-07 | Z13: 1.6334746e-07 | AA13: 3.2928137e-07 | AB13: 2.0862369e-07 | AC13: 2.4792627e-07 | AD13: 3.4168951e-07 | AE13: 1.3603739e-07 | AF13: 1.0266508e-06 | AG13: 1.449227e-07 | AH13: 7.9404453e-08 | AI13: 4.8785145e-07 | AJ13: 4.8265082e-07 | AK13: 1.04611e-07 | AL13: 5.4746654e-07 | AM13: 3.7350398e-07 | AN13: 9.615034e-09 | AO13: 1.6445892e-08 | AP13: 3.8580918e-08 | AQ13: 0 | AR13: 1.8786142e-07 | AS13: 0 | AT13: 4.3283805e-08 | AU13: 1.1772612e-06 | AV13: 1.2329267e-07 | AW13: 1.2749618e-06 | AX13: 3.4235101e-07 | AY13: 7.4447118e-08 | AZ13: 2.226839e-07 | BA13: 2.058235e-06 | BB13: 2.3181711e-08 | BC13: 6.9859406e-07 | BD13: 1.1734895e-06 | BE13: 2.2526446e-07 | BF13: 9.4886686e-08 | BG13: 2.2229235e-07 | BH13: 0 | BI13: 3.9088702e-07 | BJ13: 1.8712207e-08 | BK13: 1.363411e-07 | BL13: 1.9557612e-07 | BM13: 1.7863592e-06 | BN13: 4.6215469e-06 | BO13: 1.5519651e-06 | BP13: 7.6437906e-06 | BQ13: 5.8913084e-06 | BR13: 2.2539299e-07 | BS13: 1.4076353e-06 | BT13: 9.2175027e-07 | BU13: 1.7993289e-07 | BV13: 3.565264e-07 | BW13: 1.2549058e-07 | BX13: 1.1325315e-06 | BY13: 3.5662687e-06 | BZ13: 0 | CA13: 5.7766852e-06
A14: 221 - Generación, transmisión, distribución y comercialización de energía eléctrica, suministro de agua y de gas natural por ductos al consumidor final | B14: 0.015589173 | C14: 0.010828849 | D14: 0.0035911101 | E14: 0.004125847 | F14: 0.015860076 | G14: 0.0036380679 | H14: 0.032504178 | I14: 0.039817225 | J14: 0.015919784 | K14: 0.0011337085 | L14: 0.0062812629 | M14: 0.0051701915 | N14: 0.010299163 | O14: 0.0099336835 | P14: 0.06571674 | Q14: 0.027129939 | R14: 0.025428537 | S14: 0.018142583 | T14: 0.014465273 | U14: 0.019414389 | V14: 0.014327291 | W14: 0.010720076 | X14: 0.011737882 | Y14: 0.022428558 | Z14: 0.020556828 | AA14: 0.031263977 | AB14: 0.012834319 | AC14: 0.013934308 | AD14: 0.0079529297 | AE14: 0.006268624 | AF14: 0.010081642 | AG14: 0.0071704057 | AH14: 0.0048609134 | AI14: 0.0054061991 | AJ14: 0.022864712 | AK14: 0.00048118007 | AL14: 0.001302567 | AM14: 0.0049150322 | AN14: 0.00051474725 | AO14: 0.0023552175 | AP14: 0.013557528 | AQ14: 0.0038016346 | AR14: 0.0043953381 | AS14: 0.0032093893 | AT14: 0.0024840359 | AU14: 0.028351936 | AV14: 0.0046146598 | AW14: 0.0087389703 | AX14: 0.010963725 | AY14: 0.010890869 | AZ14: 0.019816492 | BA14: 0.0089485198 | BB14: 0.00077948504 | BC14: 0.0040200834 | BD14: 0.0042046661 | BE14: 0.0040279026 | BF14: 0.008281678 | BG14: 0.0087238635 | BH14: 0.00017099206 | BI14: 0.0068374829 | BJ14: 0.0023020272 | BK14: 0.0058315458 | BL14: 0.004556767 | BM14: 0.011884061 | BN14: 0.01103334 | BO14: 0.0093774592 | BP14: 0.032204382 | BQ14: 0.014366721 | BR14: 0.0051236785 | BS14: 0.015565944 | BT14: 0.021581821 | BU14: 0.012559653 | BV14: 0.0092277994 | BW14: 0.0096073948 | BX14: 0.0128861 | BY14: 0.014221063 | BZ14: 0 | CA14: 0.012008737
A15: 236 - Edificación | B15: 1.7286464e-05 | C15: 3.5655093e-05 | D15: 5.2345206e-05 | E15: 0.00026657966 | F15: 9.4093108e-05 | G15: 0.00049823288 | H15: 0.00061802698 | I15: 0.0025510189 | J15: 0.00061112621 | K15: 0.0074518777 | L15: 0.002013991 | M15: 0.0018879479 | N15: 4.9599731e-05 | O15: 3.5241543e-05 | P15: 4.5134212e-05 | Q15: 7.8836446e-05 | R15: 7.1727034e-05 | S15: 4.9073373e-05 | T15: 8.0431085e-05 | U15: 0.00011695139 | V15: 0.00030337192 | W15: 1.3010171e-05 | X15: 0.00038492499 | Y15: 0.00010394296 | Z15: 8.6194687e-05 | AA15: 8.358978e-05 | AB15: 0.0001312438 | AC15: 7.5266423e-05 | AD15: 3.9792482e-05 | AE15: 4.4077752e-05 | AF15: 0.0002353398 | AG15: 0.00011894531 | AH15: 2.80408e-05 | AI15: 5.8401554e-05 | AJ15: 7.872156e-05 | AK15: 2.6065573e-05 | AL15: 4.0815071e-05 | AM15: 3.6790142e-05 | AN15: 5.799468e-06 | AO15: 2.8127957e-05 | AP15: 0.0047111159 | AQ15: 2.1004644e-05 | AR15: 4.1841861e-05 | AS15: 2.55232e-05 | AT15: 2.1793396e-05 | AU15: 0.00027884272 | AV15: 4.8114966e-05 | AW15: 0.00025281075 | AX15: 0.00012930929 | AY15: 0.00012626888 | AZ15: 4.1716118e-05 | BA15: 0.00045006739 | BB15: 5.2390667e-06 | BC15: 6.7877398e-05 | BD15: 0.00024947319 | BE15: 0.00037165785 | BF15: 4.5130536e-05 | BG15: 0.00010847867 | BH15: 2.2412066e-06 | BI15: 0.00018602126 | BJ15: 3.4706466e-05 | BK15: 0.0007260313 | BL15: 0.00013393052 | BM15: 0.00017676912 | BN15: 0.00052759895 | BO15: 0.00011383184 | BP15: 0.00059337655 | BQ15: 0.0007019494 | BR15: 0.00011128403 | BS15: 0.00019691254 | BT15: 0.00049699372 | BU15: 8.5660378e-05 | BV15: 0.00017465599 | BW15: 0.00013249392 | BX15: 0.00042257748 | BY15: 0.0005026993 | BZ15: 0 | CA15: 0.00045795775
A16: 237 - Construcción de obras de ingeniería civil | B16: 1.2980957e-05 | C16: 2.5775568e-05 | D16: 9.1890292e-05 | E16: 0.00027297862 | F16: 0.00010640795 | G16: 0.0006490349 | H16: 0.00064090273 | I16: 0.0038973496 | J16: 0.00060286484 | K16: 0.0011248806 | L16: 0.059270574 | M16: 0.0023664709 | N16: 3.3979889e-05 | O16: 2.5587713e-05 | P16: 3.0504572e-05 | Q16: 5.8413045e-05 | R16: 5.5689658e-05 | S16: 3.7178956e-05 | T16: 7.0296277e-05 | U16: 0.0001089456 | V16: 0.00029333559 | W16: 9.2905492e-06 | X16: 0.00036058815 | Y16: 9.0915106e-05 | Z16: 7.7690567e-05 | AA16: 7.6137802e-05 | AB16: 0.00011947508 | AC16: 7.2168176e-05 | AD16: 5.1564337e-05 | AE16: 4.0970199e-05 | AF16: 0.00026408848 | AG16: 9.6105489e-05 | AH16: 2.2842014e-05 | AI16: 6.0671514e-05 | AJ16: 6.4817757e-05 | AK16: 1.893459e-05 | AL16: 6.2929838e-05 | AM16: 4.6127741e-05 | AN16: 3.3019629e-06 | AO16: 8.8081456e-06 | AP16: 0.0044802863 | AQ16: 1.1326033e-05 | AR16: 3.2435981e-05 | AS16: 1.4905549e-05 | AT16: 1.1751553e-05 | AU16: 0.00027442417 | AV16: 3.6371339e-05 | AW16: 0.00016199097 | AX16: 0.00010523428 | AY16: 4.155463e-05 | AZ16: 3.4367549e-05 | BA16: 0.00035916201 | BB16: 2.967259e-06 | BC16: 6.1539012e-05 | BD16: 0.00026912914 | BE16: 0.00035610605 | BF16: 4.1054906e-05 | BG16: 8.5878946e-05 | BH16: 1.8409912e-06 | BI16: 0.0001743578 | BJ16: 9.1502692e-06 | BK16: 0.0001235748 | BL16: 0.00012552075 | BM16: 0.00024705417 | BN16: 0.00063938244 | BO16: 0.00017461569 | BP16: 0.00095853134 | BQ16: 0.00069470309 | BR16: 9.5882178e-05 | BS16: 0.00022178076 | BT16: 0.00021736274 | BU16: 7.6680987e-05 | BV16: 0.0001391902 | BW16: 8.0758016e-05 | BX16: 0.0003513981 | BY16: 0.00065885609 | BZ16: 0 | CA16: 0.00070322949
A17: 238 - Trabajos especializados para la construcción | B17: 1.1572148e-05 | C17: 4.3239823e-05 | D17: 0.044530368 | E17: 3.7914907e-05 | F17: 0.001167505 | G17: 0.00018711651 | H17: 0.011618068 | I17: 0.0076611582 | J17: 7.9220215e-05 | K17: 0.087758325 | L17: 0.12157333 | M17: 0.0044395794 | N17: 0.00038526824 | O17: 6.458436e-05 | P17: 2.7669763e-05 | Q17: 0.00028034029 | R17: 0.00024210037 | S17: 0.0001290105 | T17: 5.3029154e-05 | U17: 7.7105271e-05 | V17: 0.00028255411 | W17: 0.00013739085 | X17: 4.6085427e-05 | Y17: 4.1524119e-05 | Z17: 5.67067e-05 | AA17: 3.7499471e-05 | AB17: 4.8108232e-05 | AC17: 5.0340681e-05 | AD17: 1.9409007e-05 | AE17: 2.2767413e-05 | AF17: 5.7105854e-05 | AG17: 7.0345479e-05 | AH17: 3.2785216e-05 | AI17: 0.00034395393 | AJ17: 0.00035607729 | AK17: 0.00035827959 | AL17: 7.5492754e-05 | AM17: 0.00047385204 | AN17: 2.9488508e-05 | AO17: 0.00017096464 | AP17: 0.0006108131 | AQ17: 0.00031342224 | AR17: 0.00010247413 | AS17: 8.2899354e-05 | AT17: 0.00012422452 | AU17: 0.00050548844 | AV17: 7.4900299e-05 | AW17: 0.00011433574 | AX17: 6.9088643e-05 | AY17: 9.6444052e-05 | AZ17: 2.2713758e-05 | BA17: 0.001182113 | BB17: 5.5867924e-06 | BC17: 0.0011859543 | BD17: 3.4671279e-05 | BE17: 4.7411041e-05 | BF17: 4.0235552e-05 | BG17: 6.9029186e-05 | BH17: 7.4039862e-07 | BI17: 0.00072344995 | BJ17: 1.3210818e-05 | BK17: 5.5012142e-05 | BL17: 4.560835e-05 | BM17: 0.0043169514 | BN17: 0.0050417504 | BO17: 0.0026307596 | BP17: 0.00034877525 | BQ17: 0.002057834 | BR17: 0.00042772077 | BS17: 0.027064057 | BT17: 0.0013227517 | BU17: 8.2155384e-05 | BV17: 0.00031645055 | BW17: 0.00055416641 | BX17: 0.00010544629 | BY17: 0.00010444589 | BZ17: 0 | CA17: 0.0081878341
... A88: P.1 - Producción | B88: 1 | C88: 1 | D88: 1 | E88: 1 | F88: 1 | G88: 1 | H88: 1 | I88: 1 | J88: 1 | K88: 1 | L88: 1 | M88: 1 | N88: 1 | O88: 1 | P88: 1 | Q88: 1 | R88: 1 | S88: 1 | T88: 1 | U88: 1 | V88: 1 | W88: 1 | X88: 1 | Y88: 1 | Z88: 1 | AA88: 1 | AB88: 1 | AC88: 1 | AD88: 1 | AE88: 1 | AF88: 1 | AG88: 1 | AH88: 1 | AI88: 1 | AJ88: 1 | AK88: 1 | AL88: 1 | AM88: 1 | AN88: 1 | AO88: 1 | AP88: 1 | AQ88: 1 | AR88: 1 | AS88: 1 | AT88: 1 | AU88: 1 | AV88: 1 | AW88: 1 | AX88: 1 | AY88: 1 | AZ88: 1 | BA88: 1 | BB88: 1 | BC88: 1 | BD88: 1 | BE88: 1 | BF88: 1 | BG88: 1 | BH88: 1 | BI88: 1 | BJ88: 1 | BK88: 1 | BL88: 1 | BM88: 1 | BN88: 1 | BO88: 1 | BP88: 1 | BQ88: 1 | BR88: 1 | BS88: 1 | BT88: 1 | BU88: 1 | BV88: 1 | BW88: 1 | BX88: 1 | BY88: 1 | BZ88: 1 | CA88: 1
A92: Fuente: INEGI. Sistema de Cuentas Nacionales de México. Matriz de Insumo Producto
